Workbook

Sheet LEIA-ME
A1: PLANILHA MESTRA WINNET — precificação, margem e frete em um lugar só
A3: Resumo | B3: Fotografia executiva das margens (23/07, tarifas reais). Me peça pra regenerar após grandes edições no Simulador.
A4: Simulador | B4: O coração: 113 SKUs × 2 regiões, vivo. Edite preços/custos/tarifas e vereditos recalculam. Filtre a coluna Veredito pra ver a fila vermelha.
A5: Novo_Produto | B5: Produto novo? Digite dimensões da caixa, peso, custo e margem alvo → ela devolve a classe de frete e o PREÇO SUGERIDO. Depois teste seu preço na coluna P e veja a margem/veredito.
A6: Ref_Frete | B6: Tabela de apoio (53 regiões × custo real e cobrança das 3 classes). Alimenta as outras abas — só edite se os modelos WN mudarem na Amazon.
A7: Classificação_Frete | B7: Os 113 SKUs com peso cubado e classe validada por cotação. Consulta e histórico das reclassificações.
A8: Registro_Vendas / Livro_Vendas | B8: Registro: cada venda com margem real (linhas prontas até a 105 — NUNCA use "Inserir linha"; pedido multi-SKU = uma linha por SKU, frete só na 1ª). Livro: histórico pedido a pedido com origem Ads/Orgânico e resumo mensal.
A9: Arquivos externos: | B9: Plano_Implementacao_Amazon_Ads (operação do Ads, semanal) · Modelos_Frete (arquivo morto/backup — valores já na Amazon) · Simulador v2 (obsoleto, pode excluir).

Sheet Resumo
A1: RESUMO EXECUTIVO — pós-cirurgia completa (24/07)
A2: SP Interior = cenário real (maioria do volume). RS Capital = teste de estresse (região de MAIOR subsídio — abaixo da meta ali é efeito do frete competitivo escolhido, não erro de preço).
A4: CONTAGEM POR VEREDITO
A5: Veredito | B5: SP Interior (real) | C5: RS Capital (estresse)
A6: ACIMA DA META (>20%) | B6: 77 | C6: 36
A7: DENTRO DA META (15-20%) | B7: 36 | C7: 47
A8: ABAIXO DA META (10-15%) | B8: 0 | C8: 29
A9: CRÍTICO (<10%) | B9: 0 | C9: 1
A10: PREJUÍZO | B10: 0 | C10: 0
A12: SP INTERIOR — 12 MENORES MARGENS (todas ≥15%: catálogo 100% saudável no cenário real)
A13: SKU | B13: Margem SP | C13: Lucro/venda
A14: EMB-05 | B14: 0.16970192 | C14: 41.56
A15: L2025-B | B15: 0.17726948 | C15: 24.8
A16: Q2430-B | B16: 0.17918949 | C16: 49.08
A17: L1623-T | B17: 0.17927056 | C17: 22.217
A18: L1618-A | B18: 0.17988561 | C18: 18.87
A19: SP-PP | B19: 0.18358497 | C19: 47.543
A20: L2430-B | B20: 0.18379538 | C20: 36.397
A21: L1618-T | B21: 0.18413793 | C21: 21.36
A22: L2450-AML | B22: 0.18526356 | C22: 48.15
A23: L2430-AML | B23: 0.18568362 | C23: 34.604
A24: L2425-B | B24: 0.18622872 | C24: 34.132
A25: L2430-A | B25: 0.18718696 | C25: 33.411
A27: RS CAPITAL — 10 QUE MAIS SOFREM NO ESTRESSE (efeito do subsídio; reavaliar em 30 dias com vendas reais)
A28: SKU | B28: Margem RS | C28: Lucro/venda
A29: L1618-A | B29: 0.098856053 | C29: 10.37
A30: L1618 | B30: 0.10873269 | C30: 10.21
A31: L1623-T | B31: 0.11068345 | C31: 13.717
A32: L1618-T | B32: 0.11086207 | C32: 12.86
A33: L2025-B | B33: 0.11651179 | C33: 16.3
A34: L2025 | B34: 0.11722217 | C34: 13.259
A35: L2030 | B35: 0.12043281 | C35: 14.358
A36: L1623 | B36: 0.12147407 | C36: 13.35
A37: L1623-A | B37: 0.12671629 | C37: 15.32
A38: L2025-A | B38: 0.12775606 | C38: 16.34
A40: SP — TOP 12 MAIS LUCRATIVOS (prioridade Ads/promoções)
A41: SKU | B41: Margem SP | C41: Lucro/venda
A42: L2470-CZ | B42: 0.28158855 | C42: 100.33
A43: P3060 | B43: 0.28031364 | C43: 143.358
A44: Q3060-A | B44: 0.27866051 | C44: 161.768
A45: L4080-A | B45: 0.27281348 | C45: 222.092
A46: L4090-A | B46: 0.27186296 | C46: 223.697
A47: P3070ALC | B47: 0.26228781 | C47: 220.487
A48: P3070 | B48: 0.25978123 | C48: 160.072
A49: P4060 | B49: 0.25719388 | C49: 208.826
A50: P4070 | B50: 0.25702105 | C50: 211.004
A51: PG4050 | B51: 0.25364687 | C51: 116.708
A52: P4080 | B52: 0.25063588 | C52: 268.223
A53: L4080-B | B53: 0.24945732 | C53: 207.314
A55: AGUENTAM PROMOÇÃO 5% (margem SP ≥19%): 101 SKUs
A56: EGC · EMB-03 · EMB-03P · EMB-05P · EMB-08 · L1618 · L1618-B · L1623
A57: L1623-A · L1623-B · L2025 · L2025-A · L2025-T · L2030 · L2030-A · L2030-B
A58: L2030-T · L2425-A · L2425-AML · L2440-A · L2440-AML · L2440-B · L2450--CZ · L2450-A
A59: L2450-B · L2460-A · L2460-AML · L2460-B · L2460-CP · L2460-CZ · L2470-A · L2470-AML
A60: L2470-B · L2470-CZ · L3040-A · L3040-B · L3050-A · L3050-B · L3060-A · L3060-AML
A61: L3060-B · L3070-A · L3070-AML · L3070-B · L3085-B · L4050-A · L4050-B · L4060-A
A62: L4060-B · L4070-B · L4075-B · L4080-A · L4080-B · L4090-A · L4090-B · P1623
A63: P2025 · P2030 · P2425 · P2430 · P2440 · P3040 · P3050 · P3050ALC
A64: P3060 · P3060ALC · P3070 · P3070ALC · P4050 · P4050ALC · P4060 · P4060ALC
A65: P4070 · P4070ALC · P4070RA · P4075 · P4075ALC · P4080 · P4080ALC · P4090
A66: P4090ALC · PG2450 · PG2460 · PG2470 · PG3060 · PG3070 · PG4050 · PG4080
... A68: Q4070-A · Q4070-B · SP-01 · SP-FF · SP-T

Sheet Simulador
A1: SIMULADOR DE MARGEM v3 — CATÁLOGO COMPLETO (113 SKUs × SP Interior + RS Capital)
A2: Tarifa estimada automaticamente (célula H3 × (preço+frete)); sobrescreva com o valor real do extrato quando tiver. Cupom em 0 (pós-corte).
A3: Impostos (%): | B3: 0.1 | D3: Tarifa padrão Amazon (%):
A6: SKU | B6: Classe | C6: Região | D6: Preço de venda (R$) | E6: Cupom (%) | F6: Custo do produto (R$) | G6: Tarifa Amazon (R$) | H6: Receita pós-cupom (R$) | I6: Tarifa (%) | J6: Frete cobrado (R$) | K6: Frete real (R$) | L6: Resultado do frete (R$) | M6: Lucro líquido (R$) | N6: Margem (%) | O6: Veredito | P6: Observação
A7: EMB-03 | B7: Pequenos | C7: Rio Grande do Sul Capital | D7: 195.21 | E7: 0 | F7: 97.42 | G7: 25.04 | H7: =IF(D7="","",D7*(1-E7)) -> 195.21 | I7: =IF(OR(G7="",H7=""),"",G7/H7) -> 0.12827212 | J7: =IF(OR(B7="",C7=""),"",INDEX(Ref_Frete!$B$2:$G$54,MATCH(C7,Ref_Frete!$A$2:$A$54,0),IF(B7="Pequenos",2,IF(B7="Medios",4,6)))) -> 24.9 | K7: =IF(OR(B7="",C7=""),"",INDEX(Ref_Frete!$B$2:$G$54,MATCH(C7,Ref_Frete!$A$2:$A$54,0),IF(B7="Pequenos",1,IF(B7="Medios",3,5)))) -> 46.5 | L7: =IF(OR(J7="",K7=""),"",J7-K7) -> -21.6 | M7: =IF(OR(H7="",F7="",G7=""),"",H7-G7-F7-H7*$B$3+IF(L7="",0,L7)) -> 31.629 | N7: =IF(OR(M7="",H7=0,H7=""),"",M7/H7) -> 0.16202551 | O7: =IF(N7="","",IF(N7<0,"PREJUÍZO",IF(N7<0.1,"CRÍTICO (<10%)",IF(N7<0.15,"ABAIXO DA META (10-15%)",IF(N7<=0.2,"DENTRO DA META (15-20%)","ACIMA DA META (>20%)"))))) -> DENTRO DA META (15-20%)
A8: EMB-03 | B8: Pequenos | C8: São Paulo Interior | D8: 195.21 | E8: 0 | F8: 97.42 | G8: 25.04 | H8: =IF(D8="","",D8*(1-E8)) -> 195.21 | I8: =IF(OR(G8="",H8=""),"",G8/H8) -> 0.12827212 | J8: =IF(OR(B8="",C8=""),"",INDEX(Ref_Frete!$B$2:$G$54,MATCH(C8,Ref_Frete!$A$2:$A$54,0),IF(B8="Pequenos",2,IF(B8="Medios",4,6)))) -> 16.9 | K8: =IF(OR(B8="",C8=""),"",INDEX(Ref_Frete!$B$2:$G$54,MATCH(C8,Ref_Frete!$A$2:$A$54,0),IF(B8="Pequenos",1,IF(B8="Medios",3,5)))) -> 30 | L8: =IF(OR(J8="",K8=""),"",J8-K8) -> -13.1 | M8: =IF(OR(H8="",F8="",G8=""),"",H8-G8-F8-H8*$B$3+IF(L8="",0,L8)) -> 40.129 | N8: =IF(OR(M8="",H8=0,H8=""),"",M8/H8) -> 0.20556836 | O8: =IF(N8="","",IF(N8<0,"PREJUÍZO",IF(N8<0.1,"CRÍTICO (<10%)",IF(N8<0.15,"ABAIXO DA META (10-15%)",IF(N8<=0.2,"DENTRO DA META (15-20%)","ACIMA DA META (>20%)"))))) -> ACIMA DA META (>20%)
A9: EMB-03P | B9: Pequenos | C9: Rio Grande do Sul Capital | D9: 245.9 | E9: 0 | F9: 127.42 | G9: 31.41 | H9: =IF(D9="","",D9*(1-E9)) -> 245.9 | I9: =IF(OR(G9="",H9=""),"",G9/H9) -> 0.12773485 | J9: =IF(OR(B9="",C9=""),"",INDEX(Ref_Frete!$B$2:$G$54,MATCH(C9,Ref_Frete!$A$2:$A$54,0),IF(B9="Pequenos",2,IF(B9="Medios",4,6)))) -> 24.9 | K9: =IF(OR(B9="",C9=""),"",INDEX(Ref_Frete!$B$2:$G$54,MATCH(C9,Ref_Frete!$A$2:$A$54,0),IF(B9="Pequenos",1,IF(B9="Medios",3,5)))) -> 46.5 | L9: =IF(OR(J9="",K9=""),"",J9-K9) -> -21.6 | M9: =IF(OR(H9="",F9="",G9=""),"",H9-G9-F9-H9*$B$3+IF(L9="",0,L9)) -> 40.88 | N9: =IF(OR(M9="",H9=0,H9=""),"",M9/H9) -> 0.16624644 | O9: =IF(N9="","",IF(N9<0,"PREJUÍZO",IF(N9<0.1,"CRÍTICO (<10%)",IF(N9<0.15,"ABAIXO DA META (10-15%)",IF(N9<=0.2,"DENTRO DA META (15-20%)","ACIMA DA META (>20%)"))))) -> DENTRO DA META (15-20%) | P9: Preço +R$50 conforme instrução Dianna. Custo 127,42 = estimativa (+30 s/ polida) — confirmar custo REAL da pintura com produção
A10: EMB-03P | B10: Pequenos | C10: São Paulo Interior | D10: 245.9 | E10: 0 | F10: 127.42 | G10: 31.41 | H10: =IF(D10="","",D10*(1-E10)) -> 245.9 | I10: =IF(OR(G10="",H10=""),"",G10/H10) -> 0.12773485 | J10: =IF(OR(B10="",C10=""),"",INDEX(Ref_Frete!$B$2:$G$54,MATCH(C10,Ref_Frete!$A$2:$A$54,0),IF(B10="Pequenos",2,IF(B10="Medios",4,6)))) -> 16.9 | K10: =IF(OR(B10="",C10=""),"",INDEX(Ref_Frete!$B$2:$G$54,MATCH(C10,Ref_Frete!$A$2:$A$54,0),IF(B10="Pequenos",1,IF(B10="Medios",3,5)))) -> 30 | L10: =IF(OR(J10="",K10=""),"",J10-K10) -> -13.1 | M10: =IF(OR(H10="",F10="",G10=""),"",H10-G10-F10-H10*$B$3+IF(L10="",0,L10)) -> 49.38 | N10: =IF(OR(M10="",H10=0,H10=""),"",M10/H10) -> 0.20081334 | O10: =IF(N10="","",IF(N10<0,"PREJUÍZO",IF(N10<0.1,"CRÍTICO (<10%)",IF(N10<0.15,"ABAIXO DA META (10-15%)",IF(N10<=0.2,"DENTRO DA META (15-20%)","ACIMA DA META (>20%)"))))) -> ACIMA DA META (>20%) | P10: Preço +R$50 conforme instrução Dianna. Custo 127,42 = estimativa (+30 s/ polida) — confirmar custo REAL da pintura com produção
A11: EMB-05 | B11: Pequenos | C11: Rio Grande do Sul Capital | D11: 244.9 | E11: 0 | F11: 134.46 | G11: 31.29 | H11: =IF(D11="","",D11*(1-E11)) -> 244.9 | I11: =IF(OR(G11="",H11=""),"",G11/H11) -> 0.12776644 | J11: =IF(OR(B11="",C11=""),"",INDEX(Ref_Frete!$B$2:$G$54,MATCH(C11,Ref_Frete!$A$2:$A$54,0),IF(B11="Pequenos",2,IF(B11="Medios",4,6)))) -> 24.9 | K11: =IF(OR(B11="",C11=""),"",INDEX(Ref_Frete!$B$2:$G$54,MATCH(C11,Ref_Frete!$A$2:$A$54,0),IF(B11="Pequenos",1,IF(B11="Medios",3,5)))) -> 46.5 | L11: =IF(OR(J11="",K11=""),"",J11-K11) -> -21.6 | M11: =IF(OR(H11="",F11="",G11=""),"",H11-G11-F11-H11*$B$3+IF(L11="",0,L11)) -> 33.06 | N11: =IF(OR(M11="",H11=0,H11=""),"",M11/H11) -> 0.13499388 | O11: =IF(N11="","",IF(N11<0,"PREJUÍZO",IF(N11<0.1,"CRÍTICO (<10%)",IF(N11<0.15,"ABAIXO DA META (10-15%)",IF(N11<=0.2,"DENTRO DA META (15-20%)","ACIMA DA META (>20%)"))))) -> ABAIXO DA META (10-15%)
A12: EMB-05 | B12: Pequenos | C12: São Paulo Interior | D12: 244.9 | E12: 0 | F12: 134.46 | G12: 31.29 | H12: =IF(D12="","",D12*(1-E12)) -> 244.9 | I12: =IF(OR(G12="",H12=""),"",G12/H12) -> 0.12776644 | J12: =IF(OR(B12="",C12=""),"",INDEX(Ref_Frete!$B$2:$G$54,MATCH(C12,Ref_Frete!$A$2:$A$54,0),IF(B12="Pequenos",2,IF(B12="Medios",4,6)))) -> 16.9 | K12: =IF(OR(B12="",C12=""),"",INDEX(Ref_Frete!$B$2:$G$54,MATCH(C12,Ref_Frete!$A$2:$A$54,0),IF(B12="Pequenos",1,IF(B12="Medios",3,5)))) -> 30 | L12: =IF(OR(J12="",K12=""),"",J12-K12) -> -13.1 | M12: =IF(OR(H12="",F12="",G12=""),"",H12-G12-F12-H12*$B$3+IF(L12="",0,L12)) -> 41.56 | N12: =IF(OR(M12="",H12=0,H12=""),"",M12/H12) -> 0.16970192 | O12: =IF(N12="","",IF(N12<0,"PREJUÍZO",IF(N12<0.1,"CRÍTICO (<10%)",IF(N12<0.15,"ABAIXO DA META (10-15%)",IF(N12<=0.2,"DENTRO DA META (15-20%)","ACIMA DA META (>20%)"))))) -> DENTRO DA META (15-20%)
A13: EMB-05P | B13: Pequenos | C13: Rio Grande do Sul Capital | D13: 290 | E13: 0 | F13: 154.46 | G13: 36.92 | H13: =IF(D13="","",D13*(1-E13)) -> 290 | I13: =IF(OR(G13="",H13=""),"",G13/H13) -> 0.12731034 | J13: =IF(OR(B13="",C13=""),"",INDEX(Ref_Frete!$B$2:$G$54,MATCH(C13,Ref_Frete!$A$2:$A$54,0),IF(B13="Pequenos",2,IF(B13="Medios",4,6)))) -> 24.9 | K13: =IF(OR(B13="",C13=""),"",INDEX(Ref_Frete!$B$2:$G$54,MATCH(C13,Ref_Frete!$A$2:$A$54,0),IF(B13="Pequenos",1,IF(B13="Medios",3,5)))) -> 46.5 | L13: =IF(OR(J13="",K13=""),"",J13-K13) -> -21.6 | M13: =IF(OR(H13="",F13="",G13=""),"",H13-G13-F13-H13*$B$3+IF(L13="",0,L13)) -> 48.02 | N13: =IF(OR(M13="",H13=0,H13=""),"",M13/H13) -> 0.16558621 | O13: =IF(N13="","",IF(N13<0,"PREJUÍZO",IF(N13<0.1,"CRÍTICO (<10%)",IF(N13<0.15,"ABAIXO DA META (10-15%)",IF(N13<=0.2,"DENTRO DA META (15-20%)","ACIMA DA META (>20%)"))))) -> DENTRO DA META (15-20%) | P13: Preço +R$50 conforme instrução Dianna. Custo 154,46 = estimativa (+20 s/ polida) — confirmar custo REAL da pintura com produção
A14: EMB-05P | B14: Pequenos | C14: São Paulo Interior | D14: 290 | E14: 0 | F14: 154.46 | G14: 36.92 | H14: =IF(D14="","",D14*(1-E14)) -> 290 | I14: =IF(OR(G14="",H14=""),"",G14/H14) -> 0.12731034 | J14: =IF(OR(B14="",C14=""),"",INDEX(Ref_Frete!$B$2:$G$54,MATCH(C14,Ref_Frete!$A$2:$A$54,0),IF(B14="Pequenos",2,IF(B14="Medios",4,6)))) -> 16.9 | K14: =IF(OR(B14="",C14=""),"",INDEX(Ref_Frete!$B$2:$G$54,MATCH(C14,Ref_Frete!$A$2:$A$54,0),IF(B14="Pequenos",1,IF(B14="Medios",3,5)))) -> 30 | L14: =IF(OR(J14="",K14=""),"",J14-K14) -> -13.1 | M14: =IF(OR(H14="",F14="",G14=""),"",H14-G14-F14-H14*$B$3+IF(L14="",0,L14)) -> 56.52 | N14: =IF(OR(M14="",H14=0,H14=""),"",M14/H14) -> 0.19489655 | O14: =IF(N14="","",IF(N14<0,"PREJUÍZO",IF(N14<0.1,"CRÍTICO (<10%)",IF(N14<0.15,"ABAIXO DA META (10-15%)",IF(N14<=0.2,"DENTRO DA META (15-20%)","ACIMA DA META (>20%)"))))) -> DENTRO DA META (15-20%) | P14: Preço +R$50 conforme instrução Dianna. Custo 154,46 = estimativa (+20 s/ polida) — confirmar custo REAL da pintura com produção
A15: EMB-08 | B15: Pequenos | C15: Rio Grande do Sul Capital | D15: 344.76 | E15: 0 | F15: 181.23 | G15: 42.92 | H15: =IF(D15="","",D15*(1-E15)) -> 344.76 | I15: =IF(OR(G15="",H15=""),"",G15/H15) -> 0.1244924 | J15: =IF(OR(B15="",C15=""),"",INDEX(Ref_Frete!$B$2:$G$54,MATCH(C15,Ref_Frete!$A$2:$A$54,0),IF(B15="Pequenos",2,IF(B15="Medios",4,6)))) -> 24.9 | K15: =IF(OR(B15="",C15=""),"",INDEX(Ref_Frete!$B$2:$G$54,MATCH(C15,Ref_Frete!$A$2:$A$54,0),IF(B15="Pequenos",1,IF(B15="Medios",3,5)))) -> 46.5 | L15: =IF(OR(J15="",K15=""),"",J15-K15) -> -21.6 | M15: =IF(OR(H15="",F15="",G15=""),"",H15-G15-F15-H15*$B$3+IF(L15="",0,L15)) -> 64.534 | N15: =IF(OR(M15="",H15=0,H15=""),"",M15/H15) -> 0.18718529 | O15: =IF(N15="","",IF(N15<0,"PREJUÍZO",IF(N15<0.1,"CRÍTICO (<10%)",IF(N15<0.15,"ABAIXO DA META (10-15%)",IF(N15<=0.2,"DENTRO DA META (15-20%)","ACIMA DA META (>20%)"))))) -> DENTRO DA META (15-20%)
A16: EMB-08 | B16: Pequenos | C16: São Paulo Interior | D16: 344.76 | E16: 0 | F16: 181.23 | G16: 42.92 | H16: =IF(D16="","",D16*(1-E16)) -> 344.76 | I16: =IF(OR(G16="",H16=""),"",G16/H16) -> 0.1244924 | J16: =IF(OR(B16="",C16=""),"",INDEX(Ref_Frete!$B$2:$G$54,MATCH(C16,Ref_Frete!$A$2:$A$54,0),IF(B16="Pequenos",2,IF(B16="Medios",4,6)))) -> 16.9 | K16: =IF(OR(B16="",C16=""),"",INDEX(Ref_Frete!$B$2:$G$54,MATCH(C16,Ref_Frete!$A$2:$A$54,0),IF(B16="Pequenos",1,IF(B16="Medios",3,5)))) -> 30 | L16: =IF(OR(J16="",K16=""),"",J16-K16) -> -13.1 | M16: =IF(OR(H16="",F16="",G16=""),"",H16-G16-F16-H16*$B$3+IF(L16="",0,L16)) -> 73.034 | N16: =IF(OR(M16="",H16=0,H16=""),"",M16/H16) -> 0.21184012 | O16: =IF(N16="","",IF(N16<0,"PREJUÍZO",IF(N16<0.1,"CRÍTICO (<10%)",IF(N16<0.15,"ABAIXO DA META (10-15%)",IF(N16<=0.2,"DENTRO DA META (15-20%)","ACIMA DA META (>20%)"))))) -> ACIMA DA META (>20%)
A17: L1618 | B17: Pequenos | C17: Rio Grande do Sul Capital | D17: 93.9 | E17: 0 | F17: 39.8 | G17: 12.9 | H17: =IF(D17="","",D17*(1-E17)) -> 93.9 | I17: =IF(OR(G17="",H17=""),"",G17/H17) -> 0.13738019 | J17: =IF(OR(B17="",C17=""),"",INDEX(Ref_Frete!$B$2:$G$54,MATCH(C17,Ref_Frete!$A$2:$A$54,0),IF(B17="Pequenos",2,IF(B17="Medios",4,6)))) -> 24.9 | K17: =IF(OR(B17="",C17=""),"",INDEX(Ref_Frete!$B$2:$G$54,MATCH(C17,Ref_Frete!$A$2:$A$54,0),IF(B17="Pequenos",1,IF(B17="Medios",3,5)))) -> 46.5 | L17: =IF(OR(J17="",K17=""),"",J17-K17) -> -21.6 | M17: =IF(OR(H17="",F17="",G17=""),"",H17-G17-F17-H17*$B$3+IF(L17="",0,L17)) -> 10.21 | N17: =IF(OR(M17="",H17=0,H17=""),"",M17/H17) -> 0.10873269 | O17: =IF(N17="","",IF(N17<0,"PREJUÍZO",IF(N17<0.1,"CRÍTICO (<10%)",IF(N17<0.15,"ABAIXO DA META (10-15%)",IF(N17<=0.2,"DENTRO DA META (15-20%)","ACIMA DA META (>20%)"))))) -> ABAIXO DA META (10-15%)
A18: L1618 | B18: Pequenos | C18: São Paulo Interior | D18: 93.9 | E18: 0 | F18: 39.8 | G18: 12.9 | H18: =IF(D18="","",D18*(1-E18)) -> 93.9 | I18: =IF(OR(G18="",H18=""),"",G18/H18) -> 0.13738019 | J18: =IF(OR(B18="",C18=""),"",INDEX(Ref_Frete!$B$2:$G$54,MATCH(C18,Ref_Frete!$A$2:$A$54,0),IF(B18="Pequenos",2,IF(B18="Medios",4,6)))) -> 16.9 | K18: =IF(OR(B18="",C18=""),"",INDEX(Ref_Frete!$B$2:$G$54,MATCH(C18,Ref_Frete!$A$2:$A$54,0),IF(B18="Pequenos",1,IF(B18="Medios",3,5)))) -> 30 | L18: =IF(OR(J18="",K18=""),"",J18-K18) -> -13.1 | M18: =IF(OR(H18="",F18="",G18=""),"",H18-G18-F18-H18*$B$3+IF(L18="",0,L18)) -> 18.71 | N18: =IF(OR(M18="",H18=0,H18=""),"",M18/H18) -> 0.19925453 | O18: =IF(N18="","",IF(N18<0,"PREJUÍZO",IF(N18<0.1,"CRÍTICO (<10%)",IF(N18<0.15,"ABAIXO DA META (10-15%)",IF(N18<=0.2,"DENTRO DA META (15-20%)","ACIMA DA META (>20%)"))))) -> DENTRO DA META (15-20%)
A19: L1618-A | B19: Pequenos | C19: Rio Grande do Sul Capital | D19: 104.9 | E19: 0 | F19: 48.18 | G19: 14.26 | H19: =IF(D19="","",D19*(1-E19)) -> 104.9 | I19: =IF(OR(G19="",H19=""),"",G19/H19) -> 0.13593899 | J19: =IF(OR(B19="",C19=""),"",INDEX(Ref_Frete!$B$2:$G$54,MATCH(C19,Ref_Frete!$A$2:$A$54,0),IF(B19="Pequenos",2,IF(B19="Medios",4,6)))) -> 24.9 | K19: =IF(OR(B19="",C19=""),"",INDEX(Ref_Frete!$B$2:$G$54,MATCH(C19,Ref_Frete!$A$2:$A$54,0),IF(B19="Pequenos",1,IF(B19="Medios",3,5)))) -> 46.5 | L19: =IF(OR(J19="",K19=""),"",J19-K19) -> -21.6 | M19: =IF(OR(H19="",F19="",G19=""),"",H19-G19-F19-H19*$B$3+IF(L19="",0,L19)) -> 10.37 | N19: =IF(OR(M19="",H19=0,H19=""),"",M19/H19) -> 0.098856053 | O19: =IF(N19="","",IF(N19<0,"PREJUÍZO",IF(N19<0.1,"CRÍTICO (<10%)",IF(N19<0.15,"ABAIXO DA META (10-15%)",IF(N19<=0.2,"DENTRO DA META (15-20%)","ACIMA DA META (>20%)"))))) -> CRÍTICO (<10%)
A20: L1618-A | B20: Pequenos | C20: São Paulo Interior | D20: 104.9 | E20: 0 | F20: 48.18 | G20: 14.26 | H20: =IF(D20="","",D20*(1-E20)) -> 104.9 | I20: =IF(OR(G20="",H20=""),"",G20/H20) -> 0.13593899 | J20: =IF(OR(B20="",C20=""),"",INDEX(Ref_Frete!$B$2:$G$54,MATCH(C20,Ref_Frete!$A$2:$A$54,0),IF(B20="Pequenos",2,IF(B20="Medios",4,6)))) -> 16.9 | K20: =IF(OR(B20="",C20=""),"",INDEX(Ref_Frete!$B$2:$G$54,MATCH(C20,Ref_Frete!$A$2:$A$54,0),IF(B20="Pequenos",1,IF(B20="Medios",3,5)))) -> 30 | L20: =IF(OR(J20="",K20=""),"",J20-K20) -> -13.1 | M20: =IF(OR(H20="",F20="",G20=""),"",H20-G20-F20-H20*$B$3+IF(L20="",0,L20)) -> 18.87 | N20: =IF(OR(M20="",H20=0,H20=""),"",M20/H20) -> 0.17988561 | O20: =IF(N20="","",IF(N20<0,"PREJUÍZO",IF(N20<0.1,"CRÍTICO (<10%)",IF(N20<0.15,"ABAIXO DA META (10-15%)",IF(N20<=0.2,"DENTRO DA META (15-20%)","ACIMA DA META (>20%)"))))) -> DENTRO DA META (15-20%)
A21: L1618-B | B21: Pequenos | C21: Rio Grande do Sul Capital | D21: 129.9 | E21: 0 | F21: 60.62 | G21: 17.22 | H21: =IF(D21="","",D21*(1-E21)) -> 129.9 | I21: =IF(OR(G21="",H21=""),"",G21/H21) -> 0.13256351 | J21: =IF(OR(B21="",C21=""),"",INDEX(Ref_Frete!$B$2:$G$54,MATCH(C21,Ref_Frete!$A$2:$A$54,0),IF(B21="Pequenos",2,IF(B21="Medios",4,6)))) -> 24.9 | K21: =IF(OR(B21="",C21=""),"",INDEX(Ref_Frete!$B$2:$G$54,MATCH(C21,Ref_Frete!$A$2:$A$54,0),IF(B21="Pequenos",1,IF(B21="Medios",3,5)))) -> 46.5 | L21: =IF(OR(J21="",K21=""),"",J21-K21) -> -21.6 | M21: =IF(OR(H21="",F21="",G21=""),"",H21-G21-F21-H21*$B$3+IF(L21="",0,L21)) -> 17.47 | N21: =IF(OR(M21="",H21=0,H21=""),"",M21/H21) -> 0.13448807 | O21: =IF(N21="","",IF(N21<0,"PREJUÍZO",IF(N21<0.1,"CRÍTICO (<10%)",IF(N21<0.15,"ABAIXO DA META (10-15%)",IF(N21<=0.2,"DENTRO DA META (15-20%)","ACIMA DA META (>20%)"))))) -> ABAIXO DA META (10-15%)
A22: L1618-B | B22: Pequenos | C22: São Paulo Interior | D22: 129.9 | E22: 0 | F22: 60.62 | G22: 17.22 | H22: =IF(D22="","",D22*(1-E22)) -> 129.9 | I22: =IF(OR(G22="",H22=""),"",G22/H22) -> 0.13256351 | J22: =IF(OR(B22="",C22=""),"",INDEX(Ref_Frete!$B$2:$G$54,MATCH(C22,Ref_Frete!$A$2:$A$54,0),IF(B22="Pequenos",2,IF(B22="Medios",4,6)))) -> 16.9 | K22: =IF(OR(B22="",C22=""),"",INDEX(Ref_Frete!$B$2:$G$54,MATCH(C22,Ref_Frete!$A$2:$A$54,0),IF(B22="Pequenos",1,IF(B22="Medios",3,5)))) -> 30 | L22: =IF(OR(J22="",K22=""),"",J22-K22) -> -13.1 | M22: =IF(OR(H22="",F22="",G22=""),"",H22-G22-F22-H22*$B$3+IF(L22="",0,L22)) -> 25.97 | N22: =IF(OR(M22="",H22=0,H22=""),"",M22/H22) -> 0.19992302 | O22: =IF(N22="","",IF(N22<0,"PREJUÍZO",IF(N22<0.1,"CRÍTICO (<10%)",IF(N22<0.15,"ABAIXO DA META (10-15%)",IF(N22<=0.2,"DENTRO DA META (15-20%)","ACIMA DA META (>20%)"))))) -> DENTRO DA META (15-20%)
A23: L1618-T | B23: Pequenos | C23: Rio Grande do Sul Capital | D23: 116 | E23: 0 | F23: 54.47 | G23: 15.47 | H23: =IF(D23="","",D23*(1-E23)) -> 116 | I23: =IF(OR(G23="",H23=""),"",G23/H23) -> 0.13336207 | J23: =IF(OR(B23="",C23=""),"",INDEX(Ref_Frete!$B$2:$G$54,MATCH(C23,Ref_Frete!$A$2:$A$54,0),IF(B23="Pequenos",2,IF(B23="Medios",4,6)))) -> 24.9 | K23: =IF(OR(B23="",C23=""),"",INDEX(Ref_Frete!$B$2:$G$54,MATCH(C23,Ref_Frete!$A$2:$A$54,0),IF(B23="Pequenos",1,IF(B23="Medios",3,5)))) -> 46.5 | L23: =IF(OR(J23="",K23=""),"",J23-K23) -> -21.6 | M23: =IF(OR(H23="",F23="",G23=""),"",H23-G23-F23-H23*$B$3+IF(L23="",0,L23)) -> 12.86 | N23: =IF(OR(M23="",H23=0,H23=""),"",M23/H23) -> 0.11086207 | O23: =IF(N23="","",IF(N23<0,"PREJUÍZO",IF(N23<0.1,"CRÍTICO (<10%)",IF(N23<0.15,"ABAIXO DA META (10-15%)",IF(N23<=0.2,"DENTRO DA META (15-20%)","ACIMA DA META (>20%)"))))) -> ABAIXO DA META (10-15%)
A24: L1618-T | B24: Pequenos | C24: São Paulo Interior | D24: 116 | E24: 0 | F24: 54.47 | G24: 15.47 | H24: =IF(D24="","",D24*(1-E24)) -> 116 | I24: =IF(OR(G24="",H24=""),"",G24/H24) -> 0.13336207 | J24: =IF(OR(B24="",C24=""),"",INDEX(Ref_Frete!$B$2:$G$54,MATCH(C24,Ref_Frete!$A$2:$A$54,0),IF(B24="Pequenos",2,IF(B24="Medios",4,6)))) -> 16.9 | K24: =IF(OR(B24="",C24=""),"",INDEX(Ref_Frete!$B$2:$G$54,MATCH(C24,Ref_Frete!$A$2:$A$54,0),IF(B24="Pequenos",1,IF(B24="Medios",3,5)))) -> 30 | L24: =IF(OR(J24="",K24=""),"",J24-K24) -> -13.1 | M24: =IF(OR(H24="",F24="",G24=""),"",H24-G24-F24-H24*$B$3+IF(L24="",0,L24)) -> 21.36 | N24: =IF(OR(M24="",H24=0,H24=""),"",M24/H24) -> 0.18413793 | O24: =IF(N24="","",IF(N24<0,"PREJUÍZO",IF(N24<0.1,"CRÍTICO (<10%)",IF(N24<0.15,"ABAIXO DA META (10-15%)",IF(N24<=0.2,"DENTRO DA META (15-20%)","ACIMA DA META (>20%)"))))) -> DENTRO DA META (15-20%)
A25: L1623 | B25: Pequenos | C25: Rio Grande do Sul Capital | D25: 109.9 | E25: 0 | F25: 49.15 | G25: 14.81 | H25: =IF(D25="","",D25*(1-E25)) -> 109.9 | I25: =IF(OR(G25="",H25=""),"",G25/H25) -> 0.13475887 | J25: =IF(OR(B25="",C25=""),"",INDEX(Ref_Frete!$B$2:$G$54,MATCH(C25,Ref_Frete!$A$2:$A$54,0),IF(B25="Pequenos",2,IF(B25="Medios",4,6)))) -> 24.9 | K25: =IF(OR(B25="",C25=""),"",INDEX(Ref_Frete!$B$2:$G$54,MATCH(C25,Ref_Frete!$A$2:$A$54,0),IF(B25="Pequenos",1,IF(B25="Medios",3,5)))) -> 46.5 | L25: =IF(OR(J25="",K25=""),"",J25-K25) -> -21.6 | M25: =IF(OR(H25="",F25="",G25=""),"",H25-G25-F25-H25*$B$3+IF(L25="",0,L25)) -> 13.35 | N25: =IF(OR(M25="",H25=0,H25=""),"",M25/H25) -> 0.12147407 | O25: =IF(N25="","",IF(N25<0,"PREJUÍZO",IF(N25<0.1,"CRÍTICO (<10%)",IF(N25<0.15,"ABAIXO DA META (10-15%)",IF(N25<=0.2,"DENTRO DA META (15-20%)","ACIMA DA META (>20%)"))))) -> ABAIXO DA META (10-15%)
A26: L1623 | B26: Pequenos | C26: São Paulo Interior | D26: 109.9 | E26: 0 | F26: 49.15 | G26: 14.81 | H26: =IF(D26="","",D26*(1-E26)) -> 109.9 | I26: =IF(OR(G26="",H26=""),"",G26/H26) -> 0.13475887 | J26: =IF(OR(B26="",C26=""),"",INDEX(Ref_Frete!$B$2:$G$54,MATCH(C26,Ref_Frete!$A$2:$A$54,0),IF(B26="Pequenos",2,IF(B26="Medios",4,6)))) -> 16.9 | K26: =IF(OR(B26="",C26=""),"",INDEX(Ref_Frete!$B$2:$G$54,MATCH(C26,Ref_Frete!$A$2:$A$54,0),IF(B26="Pequenos",1,IF(B26="Medios",3,5)))) -> 30 | L26: =IF(OR(J26="",K26=""),"",J26-K26) -> -13.1 | M26: =IF(OR(H26="",F26="",G26=""),"",H26-G26-F26-H26*$B$3+IF(L26="",0,L26)) -> 21.85 | N26: =IF(OR(M26="",H26=0,H26=""),"",M26/H26) -> 0.19881711 | O26: =IF(N26="","",IF(N26<0,"PREJUÍZO",IF(N26<0.1,"CRÍTICO (<10%)",IF(N26<0.15,"ABAIXO DA META (10-15%)",IF(N26<=0.2,"DENTRO DA META (15-20%)","ACIMA DA META (>20%)"))))) -> DENTRO DA META (15-20%)
... A96: Q2430-B | B96: Pequenos | C96: São Paulo Interior | D96: 273.9 | E96: 0 | F96: 149.88 | G96: 34.45 | H96: =IF(D96="","",D96*(1-E96)) -> 273.9 | I96: =IF(OR(G96="",H96=""),"",G96/H96) -> 0.12577583 | J96: =IF(OR(B96="",C96=""),"",INDEX(Ref_Frete!$B$2:$G$54,MATCH(C96,Ref_Frete!$A$2:$A$54,0),IF(B96="Pequenos",2,IF(B96="Medios",4,6)))) -> 16.9 | K96: =IF(OR(B96="",C96=""),"",INDEX(Ref_Frete!$B$2:$G$54,MATCH(C96,Ref_Frete!$A$2:$A$54,0),IF(B96="Pequenos",1,IF(B96="Medios",3,5)))) -> 30 | L96: =IF(OR(J96="",K96=""),"",J96-K96) -> -13.1 | M96: =IF(OR(H96="",F96="",G96=""),"",H96-G96-F96-H96*$B$3+IF(L96="",0,L96)) -> 49.08 | N96: =IF(OR(M96="",H96=0,H96=""),"",M96/H96) -> 0.17918949 | O96: =IF(N96="","",IF(N96<0,"PREJUÍZO",IF(N96<0.1,"CRÍTICO (<10%)",IF(N96<0.15,"ABAIXO DA META (10-15%)",IF(N96<=0.2,"DENTRO DA META (15-20%)","ACIMA DA META (>20%)"))))) -> DENTRO DA META (15-20%)
A97: SP-PP | B97: Pequenos | C97: Rio Grande do Sul Capital | D97: 258.97 | E97: 0 | F97: 139.81 | G97: 32.62 | H97: =IF(D97="","",D97*(1-E97)) -> 258.97 | I97: =IF(OR(G97="",H97=""),"",G97/H97) -> 0.12596054 | J97: =IF(OR(B97="",C97=""),"",INDEX(Ref_Frete!$B$2:$G$54,MATCH(C97,Ref_Frete!$A$2:$A$54,0),IF(B97="Pequenos",2,IF(B97="Medios",4,6)))) -> 24.9 | K97: =IF(OR(B97="",C97=""),"",INDEX(Ref_Frete!$B$2:$G$54,MATCH(C97,Ref_Frete!$A$2:$A$54,0),IF(B97="Pequenos",1,IF(B97="Medios",3,5)))) -> 46.5 | L97: =IF(OR(J97="",K97=""),"",J97-K97) -> -21.6 | M97: =IF(OR(H97="",F97="",G97=""),"",H97-G97-F97-H97*$B$3+IF(L97="",0,L97)) -> 39.043 | N97: =IF(OR(M97="",H97=0,H97=""),"",M97/H97) -> 0.15076264 | O97: =IF(N97="","",IF(N97<0,"PREJUÍZO",IF(N97<0.1,"CRÍTICO (<10%)",IF(N97<0.15,"ABAIXO DA META (10-15%)",IF(N97<=0.2,"DENTRO DA META (15-20%)","ACIMA DA META (>20%)"))))) -> DENTRO DA META (15-20%) | P97: Conferir: Amazon=Pequenos, classificação v4 indicava Medios (~7,5 kg cubado)
A98: SP-PP | B98: Pequenos | C98: São Paulo Interior | D98: 258.97 | E98: 0 | F98: 139.81 | G98: 32.62 | H98: =IF(D98="","",D98*(1-E98)) -> 258.97 | I98: =IF(OR(G98="",H98=""),"",G98/H98) -> 0.12596054 | J98: =IF(OR(B98="",C98=""),"",INDEX(Ref_Frete!$B$2:$G$54,MATCH(C98,Ref_Frete!$A$2:$A$54,0),IF(B98="Pequenos",2,IF(B98="Medios",4,6)))) -> 16.9 | K98: =IF(OR(B98="",C98=""),"",INDEX(Ref_Frete!$B$2:$G$54,MATCH(C98,Ref_Frete!$A$2:$A$54,0),IF(B98="Pequenos",1,IF(B98="Medios",3,5)))) -> 30 | L98: =IF(OR(J98="",K98=""),"",J98-K98) -> -13.1 | M98: =IF(OR(H98="",F98="",G98=""),"",H98-G98-F98-H98*$B$3+IF(L98="",0,L98)) -> 47.543 | N98: =IF(OR(M98="",H98=0,H98=""),"",M98/H98) -> 0.18358497 | O98: =IF(N98="","",IF(N98<0,"PREJUÍZO",IF(N98<0.1,"CRÍTICO (<10%)",IF(N98<0.15,"ABAIXO DA META (10-15%)",IF(N98<=0.2,"DENTRO DA META (15-20%)","ACIMA DA META (>20%)"))))) -> DENTRO DA META (15-20%) | P98: Conferir: Amazon=Pequenos, classificação v4 indicava Medios (~7,5 kg cubado)
A99: EGC | B99: Medios | C99: Rio Grande do Sul Capital | D99: 674.62 | E99: 0 | F99: 365.7 | G99: 85.14 | H99: =IF(D99="","",D99*(1-E99)) -> 674.62 | I99: =IF(OR(G99="",H99=""),"",G99/H99) -> 0.12620438 | J99: =IF(OR(B99="",C99=""),"",INDEX(Ref_Frete!$B$2:$G$54,MATCH(C99,Ref_Frete!$A$2:$A$54,0),IF(B99="Pequenos",2,IF(B99="Medios",4,6)))) -> 59.9 | K99: =IF(OR(B99="",C99=""),"",INDEX(Ref_Frete!$B$2:$G$54,MATCH(C99,Ref_Frete!$A$2:$A$54,0),IF(B99="Pequenos",1,IF(B99="Medios",3,5)))) -> 89 | L99: =IF(OR(J99="",K99=""),"",J99-K99) -> -29.1 | M99: =IF(OR(H99="",F99="",G99=""),"",H99-G99-F99-H99*$B$3+IF(L99="",0,L99)) -> 127.218 | N99: =IF(OR(M99="",H99=0,H99=""),"",M99/H99) -> 0.18857727 | O99: =IF(N99="","",IF(N99<0,"PREJUÍZO",IF(N99<0.1,"CRÍTICO (<10%)",IF(N99<0.15,"ABAIXO DA META (10-15%)",IF(N99<=0.2,"DENTRO DA META (15-20%)","ACIMA DA META (>20%)"))))) -> DENTRO DA META (15-20%)
A100: EGC | B100: Medios | C100: São Paulo Interior | D100: 674.62 | E100: 0 | F100: 365.7 | G100: 85.14 | H100: =IF(D100="","",D100*(1-E100)) -> 674.62 | I100: =IF(OR(G100="",H100=""),"",G100/H100) -> 0.12620438 | J100: =IF(OR(B100="",C100=""),"",INDEX(Ref_Frete!$B$2:$G$54,MATCH(C100,Ref_Frete!$A$2:$A$54,0),IF(B100="Pequenos",2,IF(B100="Medios",4,6)))) -> 39.9 | K100: =IF(OR(B100="",C100=""),"",INDEX(Ref_Frete!$B$2:$G$54,MATCH(C100,Ref_Frete!$A$2:$A$54,0),IF(B100="Pequenos",1,IF(B100="Medios",3,5)))) -> 49 | L100: =IF(OR(J100="",K100=""),"",J100-K100) -> -9.1 | M100: =IF(OR(H100="",F100="",G100=""),"",H100-G100-F100-H100*$B$3+IF(L100="",0,L100)) -> 147.218 | N100: =IF(OR(M100="",H100=0,H100=""),"",M100/H100) -> 0.21822359 | O100: =IF(N100="","",IF(N100<0,"PREJUÍZO",IF(N100<0.1,"CRÍTICO (<10%)",IF(N100<0.15,"ABAIXO DA META (10-15%)",IF(N100<=0.2,"DENTRO DA META (15-20%)","ACIMA DA META (>20%)"))))) -> ACIMA DA META (>20%)
A101: L2460-A | B101: Medios | C101: Rio Grande do Sul Capital | D101: 272.57 | E101: 0 | F101: 136.09 | G101: 36.9 | H101: =IF(D101="","",D101*(1-E101)) -> 272.57 | I101: =IF(OR(G101="",H101=""),"",G101/H101) -> 0.13537807 | J101: =IF(OR(B101="",C101=""),"",INDEX(Ref_Frete!$B$2:$G$54,MATCH(C101,Ref_Frete!$A$2:$A$54,0),IF(B101="Pequenos",2,IF(B101="Medios",4,6)))) -> 59.9 | K101: =IF(OR(B101="",C101=""),"",INDEX(Ref_Frete!$B$2:$G$54,MATCH(C101,Ref_Frete!$A$2:$A$54,0),IF(B101="Pequenos",1,IF(B101="Medios",3,5)))) -> 89 | L101: =IF(OR(J101="",K101=""),"",J101-K101) -> -29.1 | M101: =IF(OR(H101="",F101="",G101=""),"",H101-G101-F101-H101*$B$3+IF(L101="",0,L101)) -> 43.223 | N101: =IF(OR(M101="",H101=0,H101=""),"",M101/H101) -> 0.15857578 | O101: =IF(N101="","",IF(N101<0,"PREJUÍZO",IF(N101<0.1,"CRÍTICO (<10%)",IF(N101<0.15,"ABAIXO DA META (10-15%)",IF(N101<=0.2,"DENTRO DA META (15-20%)","ACIMA DA META (>20%)"))))) -> DENTRO DA META (15-20%)
A102: L2460-A | B102: Medios | C102: São Paulo Interior | D102: 272.57 | E102: 0 | F102: 136.09 | G102: 36.9 | H102: =IF(D102="","",D102*(1-E102)) -> 272.57 | I102: =IF(OR(G102="",H102=""),"",G102/H102) -> 0.13537807 | J102: =IF(OR(B102="",C102=""),"",INDEX(Ref_Frete!$B$2:$G$54,MATCH(C102,Ref_Frete!$A$2:$A$54,0),IF(B102="Pequenos",2,IF(B102="Medios",4,6)))) -> 39.9 | K102: =IF(OR(B102="",C102=""),"",INDEX(Ref_Frete!$B$2:$G$54,MATCH(C102,Ref_Frete!$A$2:$A$54,0),IF(B102="Pequenos",1,IF(B102="Medios",3,5)))) -> 49 | L102: =IF(OR(J102="",K102=""),"",J102-K102) -> -9.1 | M102: =IF(OR(H102="",F102="",G102=""),"",H102-G102-F102-H102*$B$3+IF(L102="",0,L102)) -> 63.223 | N102: =IF(OR(M102="",H102=0,H102=""),"",M102/H102) -> 0.23195143 | O102: =IF(N102="","",IF(N102<0,"PREJUÍZO",IF(N102<0.1,"CRÍTICO (<10%)",IF(N102<0.15,"ABAIXO DA META (10-15%)",IF(N102<=0.2,"DENTRO DA META (15-20%)","ACIMA DA META (>20%)"))))) -> ACIMA DA META (>20%)
A103: L2460-AML | B103: Medios | C103: Rio Grande do Sul Capital | D103: 290.17 | E103: 0 | F103: 140.97 | G103: 39.01 | H103: =IF(D103="","",D103*(1-E103)) -> 290.17 | I103: =IF(OR(G103="",H103=""),"",G103/H103) -> 0.13443843 | J103: =IF(OR(B103="",C103=""),"",INDEX(Ref_Frete!$B$2:$G$54,MATCH(C103,Ref_Frete!$A$2:$A$54,0),IF(B103="Pequenos",2,IF(B103="Medios",4,6)))) -> 59.9 | K103: =IF(OR(B103="",C103=""),"",INDEX(Ref_Frete!$B$2:$G$54,MATCH(C103,Ref_Frete!$A$2:$A$54,0),IF(B103="Pequenos",1,IF(B103="Medios",3,5)))) -> 89 | L103: =IF(OR(J103="",K103=""),"",J103-K103) -> -29.1 | M103: =IF(OR(H103="",F103="",G103=""),"",H103-G103-F103-H103*$B$3+IF(L103="",0,L103)) -> 52.073 | N103: =IF(OR(M103="",H103=0,H103=""),"",M103/H103) -> 0.17945687 | O103: =IF(N103="","",IF(N103<0,"PREJUÍZO",IF(N103<0.1,"CRÍTICO (<10%)",IF(N103<0.15,"ABAIXO DA META (10-15%)",IF(N103<=0.2,"DENTRO DA META (15-20%)","ACIMA DA META (>20%)"))))) -> DENTRO DA META (15-20%)
A104: L2460-AML | B104: Medios | C104: São Paulo Interior | D104: 290.17 | E104: 0 | F104: 140.97 | G104: 39.01 | H104: =IF(D104="","",D104*(1-E104)) -> 290.17 | I104: =IF(OR(G104="",H104=""),"",G104/H104) -> 0.13443843 | J104: =IF(OR(B104="",C104=""),"",INDEX(Ref_Frete!$B$2:$G$54,MATCH(C104,Ref_Frete!$A$2:$A$54,0),IF(B104="Pequenos",2,IF(B104="Medios",4,6)))) -> 39.9 | K104: =IF(OR(B104="",C104=""),"",INDEX(Ref_Frete!$B$2:$G$54,MATCH(C104,Ref_Frete!$A$2:$A$54,0),IF(B104="Pequenos",1,IF(B104="Medios",3,5)))) -> 49 | L104: =IF(OR(J104="",K104=""),"",J104-K104) -> -9.1 | M104: =IF(OR(H104="",F104="",G104=""),"",H104-G104-F104-H104*$B$3+IF(L104="",0,L104)) -> 72.073 | N104: =IF(OR(M104="",H104=0,H104=""),"",M104/H104) -> 0.24838198 | O104: =IF(N104="","",IF(N104<0,"PREJUÍZO",IF(N104<0.1,"CRÍTICO (<10%)",IF(N104<0.15,"ABAIXO DA META (10-15%)",IF(N104<=0.2,"DENTRO DA META (15-20%)","ACIMA DA META (>20%)"))))) -> ACIMA DA META (>20%)
A105: L2460-B | B105: Medios | C105: Rio Grande do Sul Capital | D105: 299.31 | E105: 0 | F105: 152.83 | G105: 40.11 | H105: =IF(D105="","",D105*(1-E105)) -> 299.31 | I105: =IF(OR(G105="",H105=""),"",G105/H105) -> 0.13400822 | J105: =IF(OR(B105="",C105=""),"",INDEX(Ref_Frete!$B$2:$G$54,MATCH(C105,Ref_Frete!$A$2:$A$54,0),IF(B105="Pequenos",2,IF(B105="Medios",4,6)))) -> 59.9 | K105: =IF(OR(B105="",C105=""),"",INDEX(Ref_Frete!$B$2:$G$54,MATCH(C105,Ref_Frete!$A$2:$A$54,0),IF(B105="Pequenos",1,IF(B105="Medios",3,5)))) -> 89 | L105: =IF(OR(J105="",K105=""),"",J105-K105) -> -29.1 | M105: =IF(OR(H105="",F105="",G105=""),"",H105-G105-F105-H105*$B$3+IF(L105="",0,L105)) -> 47.339 | N105: =IF(OR(M105="",H105=0,H105=""),"",M105/H105) -> 0.15816044 | O105: =IF(N105="","",IF(N105<0,"PREJUÍZO",IF(N105<0.1,"CRÍTICO (<10%)",IF(N105<0.15,"ABAIXO DA META (10-15%)",IF(N105<=0.2,"DENTRO DA META (15-20%)","ACIMA DA META (>20%)"))))) -> DENTRO DA META (15-20%)
A106: L2460-B | B106: Medios | C106: São Paulo Interior | D106: 299.31 | E106: 0 | F106: 152.83 | G106: 40.11 | H106: =IF(D106="","",D106*(1-E106)) -> 299.31 | I106: =IF(OR(G106="",H106=""),"",G106/H106) -> 0.13400822 | J106: =IF(OR(B106="",C106=""),"",INDEX(Ref_Frete!$B$2:$G$54,MATCH(C106,Ref_Frete!$A$2:$A$54,0),IF(B106="Pequenos",2,IF(B106="Medios",4,6)))) -> 39.9 | K106: =IF(OR(B106="",C106=""),"",INDEX(Ref_Frete!$B$2:$G$54,MATCH(C106,Ref_Frete!$A$2:$A$54,0),IF(B106="Pequenos",1,IF(B106="Medios",3,5)))) -> 49 | L106: =IF(OR(J106="",K106=""),"",J106-K106) -> -9.1 | M106: =IF(OR(H106="",F106="",G106=""),"",H106-G106-F106-H106*$B$3+IF(L106="",0,L106)) -> 67.339 | N106: =IF(OR(M106="",H106=0,H106=""),"",M106/H106) -> 0.22498079 | O106: =IF(N106="","",IF(N106<0,"PREJUÍZO",IF(N106<0.1,"CRÍTICO (<10%)",IF(N106<0.15,"ABAIXO DA META (10-15%)",IF(N106<=0.2,"DENTRO DA META (15-20%)","ACIMA DA META (>20%)"))))) -> ACIMA DA META (>20%)
A107: L2460-CP | B107: Medios | C107: Rio Grande do Sul Capital | D107: 335.68 | E107: 0 | F107: 172.67 | G107: 44.47 | H107: =IF(D107="","",D107*(1-E107)) -> 335.68 | I107: =IF(OR(G107="",H107=""),"",G107/H107) -> 0.13247736 | J107: =IF(OR(B107="",C107=""),"",INDEX(Ref_Frete!$B$2:$G$54,MATCH(C107,Ref_Frete!$A$2:$A$54,0),IF(B107="Pequenos",2,IF(B107="Medios",4,6)))) -> 59.9 | K107: =IF(OR(B107="",C107=""),"",INDEX(Ref_Frete!$B$2:$G$54,MATCH(C107,Ref_Frete!$A$2:$A$54,0),IF(B107="Pequenos",1,IF(B107="Medios",3,5)))) -> 89 | L107: =IF(OR(J107="",K107=""),"",J107-K107) -> -29.1 | M107: =IF(OR(H107="",F107="",G107=""),"",H107-G107-F107-H107*$B$3+IF(L107="",0,L107)) -> 55.872 | N107: =IF(OR(M107="",H107=0,H107=""),"",M107/H107) -> 0.16644423 | O107: =IF(N107="","",IF(N107<0,"PREJUÍZO",IF(N107<0.1,"CRÍTICO (<10%)",IF(N107<0.15,"ABAIXO DA META (10-15%)",IF(N107<=0.2,"DENTRO DA META (15-20%)","ACIMA DA META (>20%)"))))) -> DENTRO DA META (15-20%)
A108: L2460-CP | B108: Medios | C108: São Paulo Interior | D108: 335.68 | E108: 0 | F108: 172.67 | G108: 44.47 | H108: =IF(D108="","",D108*(1-E108)) -> 335.68 | I108: =IF(OR(G108="",H108=""),"",G108/H108) -> 0.13247736 | J108: =IF(OR(B108="",C108=""),"",INDEX(Ref_Frete!$B$2:$G$54,MATCH(C108,Ref_Frete!$A$2:$A$54,0),IF(B108="Pequenos",2,IF(B108="Medios",4,6)))) -> 39.9 | K108: =IF(OR(B108="",C108=""),"",INDEX(Ref_Frete!$B$2:$G$54,MATCH(C108,Ref_Frete!$A$2:$A$54,0),IF(B108="Pequenos",1,IF(B108="Medios",3,5)))) -> 49 | L108: =IF(OR(J108="",K108=""),"",J108-K108) -> -9.1 | M108: =IF(OR(H108="",F108="",G108=""),"",H108-G108-F108-H108*$B$3+IF(L108="",0,L108)) -> 75.872 | N108: =IF(OR(M108="",H108=0,H108=""),"",M108/H108) -> 0.22602479 | O108: =IF(N108="","",IF(N108<0,"PREJUÍZO",IF(N108<0.1,"CRÍTICO (<10%)",IF(N108<0.15,"ABAIXO DA META (10-15%)",IF(N108<=0.2,"DENTRO DA META (15-20%)","ACIMA DA META (>20%)"))))) -> ACIMA DA META (>20%)
A109: L2460-CZ | B109: Medios | C109: Rio Grande do Sul Capital | D109: 318.56 | E109: 0 | F109: 159 | G109: 42.42 | H109: =IF(D109="","",D109*(1-E109)) -> 318.56 | I109: =IF(OR(G109="",H109=""),"",G109/H109) -> 0.13316173 | J109: =IF(OR(B109="",C109=""),"",INDEX(Ref_Frete!$B$2:$G$54,MATCH(C109,Ref_Frete!$A$2:$A$54,0),IF(B109="Pequenos",2,IF(B109="Medios",4,6)))) -> 59.9 | K109: =IF(OR(B109="",C109=""),"",INDEX(Ref_Frete!$B$2:$G$54,MATCH(C109,Ref_Frete!$A$2:$A$54,0),IF(B109="Pequenos",1,IF(B109="Medios",3,5)))) -> 89 | L109: =IF(OR(J109="",K109=""),"",J109-K109) -> -29.1 | M109: =IF(OR(H109="",F109="",G109=""),"",H109-G109-F109-H109*$B$3+IF(L109="",0,L109)) -> 56.184 | N109: =IF(OR(M109="",H109=0,H109=""),"",M109/H109) -> 0.17636866 | O109: =IF(N109="","",IF(N109<0,"PREJUÍZO",IF(N109<0.1,"CRÍTICO (<10%)",IF(N109<0.15,"ABAIXO DA META (10-15%)",IF(N109<=0.2,"DENTRO DA META (15-20%)","ACIMA DA META (>20%)"))))) -> DENTRO DA META (15-20%)
A110: L2460-CZ | B110: Medios | C110: São Paulo Interior | D110: 318.56 | E110: 0 | F110: 159 | G110: 42.42 | H110: =IF(D110="","",D110*(1-E110)) -> 318.56 | I110: =IF(OR(G110="",H110=""),"",G110/H110) -> 0.13316173 | J110: =IF(OR(B110="",C110=""),"",INDEX(Ref_Frete!$B$2:$G$54,MATCH(C110,Ref_Frete!$A$2:$A$54,0),IF(B110="Pequenos",2,IF(B110="Medios",4,6)))) -> 39.9 | K110: =IF(OR(B110="",C110=""),"",INDEX(Ref_Frete!$B$2:$G$54,MATCH(C110,Ref_Frete!$A$2:$A$54,0),IF(B110="Pequenos",1,IF(B110="Medios",3,5)))) -> 49 | L110: =IF(OR(J110="",K110=""),"",J110-K110) -> -9.1 | M110: =IF(OR(H110="",F110="",G110=""),"",H110-G110-F110-H110*$B$3+IF(L110="",0,L110)) -> 76.184 | N110: =IF(OR(M110="",H110=0,H110=""),"",M110/H110) -> 0.23915118 | O110: =IF(N110="","",IF(N110<0,"PREJUÍZO",IF(N110<0.1,"CRÍTICO (<10%)",IF(N110<0.15,"ABAIXO DA META (10-15%)",IF(N110<=0.2,"DENTRO DA META (15-20%)","ACIMA DA META (>20%)"))))) -> ACIMA DA META (>20%)
... A180: PG4050 | B180: Medios | C180: São Paulo Interior | D180: 460.12 | E180: 0 | F180: 228.9 | G180: 59.4 | H180: =IF(D180="","",D180*(1-E180)) -> 460.12 | I180: =IF(OR(G180="",H180=""),"",G180/H180) -> 0.12909676 | J180: =IF(OR(B180="",C180=""),"",INDEX(Ref_Frete!$B$2:$G$54,MATCH(C180,Ref_Frete!$A$2:$A$54,0),IF(B180="Pequenos",2,IF(B180="Medios",4,6)))) -> 39.9 | K180: =IF(OR(B180="",C180=""),"",INDEX(Ref_Frete!$B$2:$G$54,MATCH(C180,Ref_Frete!$A$2:$A$54,0),IF(B180="Pequenos",1,IF(B180="Medios",3,5)))) -> 49 | L180: =IF(OR(J180="",K180=""),"",J180-K180) -> -9.1 | M180: =IF(OR(H180="",F180="",G180=""),"",H180-G180-F180-H180*$B$3+IF(L180="",0,L180)) -> 116.708 | N180: =IF(OR(M180="",H180=0,H180=""),"",M180/H180) -> 0.25364687 | O180: =IF(N180="","",IF(N180<0,"PREJUÍZO",IF(N180<0.1,"CRÍTICO (<10%)",IF(N180<0.15,"ABAIXO DA META (10-15%)",IF(N180<=0.2,"DENTRO DA META (15-20%)","ACIMA DA META (>20%)"))))) -> ACIMA DA META (>20%)
A181: PQ-3060 | B181: Medios | C181: Rio Grande do Sul Capital | D181: 721.69 | E181: 0 | F181: 408.87 | G181: 90.8 | H181: =IF(D181="","",D181*(1-E181)) -> 721.69 | I181: =IF(OR(G181="",H181=""),"",G181/H181) -> 0.12581579 | J181: =IF(OR(B181="",C181=""),"",INDEX(Ref_Frete!$B$2:$G$54,MATCH(C181,Ref_Frete!$A$2:$A$54,0),IF(B181="Pequenos",2,IF(B181="Medios",4,6)))) -> 59.9 | K181: =IF(OR(B181="",C181=""),"",INDEX(Ref_Frete!$B$2:$G$54,MATCH(C181,Ref_Frete!$A$2:$A$54,0),IF(B181="Pequenos",1,IF(B181="Medios",3,5)))) -> 89 | L181: =IF(OR(J181="",K181=""),"",J181-K181) -> -29.1 | M181: =IF(OR(H181="",F181="",G181=""),"",H181-G181-F181-H181*$B$3+IF(L181="",0,L181)) -> 120.751 | N181: =IF(OR(M181="",H181=0,H181=""),"",M181/H181) -> 0.16731699 | O181: =IF(N181="","",IF(N181<0,"PREJUÍZO",IF(N181<0.1,"CRÍTICO (<10%)",IF(N181<0.15,"ABAIXO DA META (10-15%)",IF(N181<=0.2,"DENTRO DA META (15-20%)","ACIMA DA META (>20%)"))))) -> DENTRO DA META (15-20%) | P181: SEM ESTOQUE no momento
A182: PQ-3060 | B182: Medios | C182: São Paulo Interior | D182: 721.69 | E182: 0 | F182: 408.87 | G182: 90.8 | H182: =IF(D182="","",D182*(1-E182)) -> 721.69 | I182: =IF(OR(G182="",H182=""),"",G182/H182) -> 0.12581579 | J182: =IF(OR(B182="",C182=""),"",INDEX(Ref_Frete!$B$2:$G$54,MATCH(C182,Ref_Frete!$A$2:$A$54,0),IF(B182="Pequenos",2,IF(B182="Medios",4,6)))) -> 39.9 | K182: =IF(OR(B182="",C182=""),"",INDEX(Ref_Frete!$B$2:$G$54,MATCH(C182,Ref_Frete!$A$2:$A$54,0),IF(B182="Pequenos",1,IF(B182="Medios",3,5)))) -> 49 | L182: =IF(OR(J182="",K182=""),"",J182-K182) -> -9.1 | M182: =IF(OR(H182="",F182="",G182=""),"",H182-G182-F182-H182*$B$3+IF(L182="",0,L182)) -> 140.751 | N182: =IF(OR(M182="",H182=0,H182=""),"",M182/H182) -> 0.19502972 | O182: =IF(N182="","",IF(N182<0,"PREJUÍZO",IF(N182<0.1,"CRÍTICO (<10%)",IF(N182<0.15,"ABAIXO DA META (10-15%)",IF(N182<=0.2,"DENTRO DA META (15-20%)","ACIMA DA META (>20%)"))))) -> DENTRO DA META (15-20%) | P182: SEM ESTOQUE no momento
A183: Q2460-A | B183: Medios | C183: Rio Grande do Sul Capital | D183: 349.45 | E183: 0 | F183: 183.04 | G183: 46.12 | H183: =IF(D183="","",D183*(1-E183)) -> 349.45 | I183: =IF(OR(G183="",H183=""),"",G183/H183) -> 0.13197882 | J183: =IF(OR(B183="",C183=""),"",INDEX(Ref_Frete!$B$2:$G$54,MATCH(C183,Ref_Frete!$A$2:$A$54,0),IF(B183="Pequenos",2,IF(B183="Medios",4,6)))) -> 59.9 | K183: =IF(OR(B183="",C183=""),"",INDEX(Ref_Frete!$B$2:$G$54,MATCH(C183,Ref_Frete!$A$2:$A$54,0),IF(B183="Pequenos",1,IF(B183="Medios",3,5)))) -> 89 | L183: =IF(OR(J183="",K183=""),"",J183-K183) -> -29.1 | M183: =IF(OR(H183="",F183="",G183=""),"",H183-G183-F183-H183*$B$3+IF(L183="",0,L183)) -> 56.245 | N183: =IF(OR(M183="",H183=0,H183=""),"",M183/H183) -> 0.16095293 | O183: =IF(N183="","",IF(N183<0,"PREJUÍZO",IF(N183<0.1,"CRÍTICO (<10%)",IF(N183<0.15,"ABAIXO DA META (10-15%)",IF(N183<=0.2,"DENTRO DA META (15-20%)","ACIMA DA META (>20%)"))))) -> DENTRO DA META (15-20%)
A184: Q2460-A | B184: Medios | C184: São Paulo Interior | D184: 349.45 | E184: 0 | F184: 183.04 | G184: 46.12 | H184: =IF(D184="","",D184*(1-E184)) -> 349.45 | I184: =IF(OR(G184="",H184=""),"",G184/H184) -> 0.13197882 | J184: =IF(OR(B184="",C184=""),"",INDEX(Ref_Frete!$B$2:$G$54,MATCH(C184,Ref_Frete!$A$2:$A$54,0),IF(B184="Pequenos",2,IF(B184="Medios",4,6)))) -> 39.9 | K184: =IF(OR(B184="",C184=""),"",INDEX(Ref_Frete!$B$2:$G$54,MATCH(C184,Ref_Frete!$A$2:$A$54,0),IF(B184="Pequenos",1,IF(B184="Medios",3,5)))) -> 49 | L184: =IF(OR(J184="",K184=""),"",J184-K184) -> -9.1 | M184: =IF(OR(H184="",F184="",G184=""),"",H184-G184-F184-H184*$B$3+IF(L184="",0,L184)) -> 76.245 | N184: =IF(OR(M184="",H184=0,H184=""),"",M184/H184) -> 0.21818572 | O184: =IF(N184="","",IF(N184<0,"PREJUÍZO",IF(N184<0.1,"CRÍTICO (<10%)",IF(N184<0.15,"ABAIXO DA META (10-15%)",IF(N184<=0.2,"DENTRO DA META (15-20%)","ACIMA DA META (>20%)"))))) -> ACIMA DA META (>20%)
A185: Q2460-B | B185: Medios | C185: Rio Grande do Sul Capital | D185: 360.97 | E185: 0 | F185: 198.38 | G185: 47.5 | H185: =IF(D185="","",D185*(1-E185)) -> 360.97 | I185: =IF(OR(G185="",H185=""),"",G185/H185) -> 0.13158988 | J185: =IF(OR(B185="",C185=""),"",INDEX(Ref_Frete!$B$2:$G$54,MATCH(C185,Ref_Frete!$A$2:$A$54,0),IF(B185="Pequenos",2,IF(B185="Medios",4,6)))) -> 59.9 | K185: =IF(OR(B185="",C185=""),"",INDEX(Ref_Frete!$B$2:$G$54,MATCH(C185,Ref_Frete!$A$2:$A$54,0),IF(B185="Pequenos",1,IF(B185="Medios",3,5)))) -> 89 | L185: =IF(OR(J185="",K185=""),"",J185-K185) -> -29.1 | M185: =IF(OR(H185="",F185="",G185=""),"",H185-G185-F185-H185*$B$3+IF(L185="",0,L185)) -> 49.893 | N185: =IF(OR(M185="",H185=0,H185=""),"",M185/H185) -> 0.13821924 | O185: =IF(N185="","",IF(N185<0,"PREJUÍZO",IF(N185<0.1,"CRÍTICO (<10%)",IF(N185<0.15,"ABAIXO DA META (10-15%)",IF(N185<=0.2,"DENTRO DA META (15-20%)","ACIMA DA META (>20%)"))))) -> ABAIXO DA META (10-15%)
A186: Q2460-B | B186: Medios | C186: São Paulo Interior | D186: 360.97 | E186: 0 | F186: 198.38 | G186: 47.5 | H186: =IF(D186="","",D186*(1-E186)) -> 360.97 | I186: =IF(OR(G186="",H186=""),"",G186/H186) -> 0.13158988 | J186: =IF(OR(B186="",C186=""),"",INDEX(Ref_Frete!$B$2:$G$54,MATCH(C186,Ref_Frete!$A$2:$A$54,0),IF(B186="Pequenos",2,IF(B186="Medios",4,6)))) -> 39.9 | K186: =IF(OR(B186="",C186=""),"",INDEX(Ref_Frete!$B$2:$G$54,MATCH(C186,Ref_Frete!$A$2:$A$54,0),IF(B186="Pequenos",1,IF(B186="Medios",3,5)))) -> 49 | L186: =IF(OR(J186="",K186=""),"",J186-K186) -> -9.1 | M186: =IF(OR(H186="",F186="",G186=""),"",H186-G186-F186-H186*$B$3+IF(L186="",0,L186)) -> 69.893 | N186: =IF(OR(M186="",H186=0,H186=""),"",M186/H186) -> 0.19362551 | O186: =IF(N186="","",IF(N186<0,"PREJUÍZO",IF(N186<0.1,"CRÍTICO (<10%)",IF(N186<0.15,"ABAIXO DA META (10-15%)",IF(N186<=0.2,"DENTRO DA META (15-20%)","ACIMA DA META (>20%)"))))) -> DENTRO DA META (15-20%)
A187: Q3060-A | B187: Medios | C187: Rio Grande do Sul Capital | D187: 580.52 | E187: 0 | F187: 277.75 | G187: 73.85 | H187: =IF(D187="","",D187*(1-E187)) -> 580.52 | I187: =IF(OR(G187="",H187=""),"",G187/H187) -> 0.12721353 | J187: =IF(OR(B187="",C187=""),"",INDEX(Ref_Frete!$B$2:$G$54,MATCH(C187,Ref_Frete!$A$2:$A$54,0),IF(B187="Pequenos",2,IF(B187="Medios",4,6)))) -> 59.9 | K187: =IF(OR(B187="",C187=""),"",INDEX(Ref_Frete!$B$2:$G$54,MATCH(C187,Ref_Frete!$A$2:$A$54,0),IF(B187="Pequenos",1,IF(B187="Medios",3,5)))) -> 89 | L187: =IF(OR(J187="",K187=""),"",J187-K187) -> -29.1 | M187: =IF(OR(H187="",F187="",G187=""),"",H187-G187-F187-H187*$B$3+IF(L187="",0,L187)) -> 141.768 | N187: =IF(OR(M187="",H187=0,H187=""),"",M187/H187) -> 0.24420864 | O187: =IF(N187="","",IF(N187<0,"PREJUÍZO",IF(N187<0.1,"CRÍTICO (<10%)",IF(N187<0.15,"ABAIXO DA META (10-15%)",IF(N187<=0.2,"DENTRO DA META (15-20%)","ACIMA DA META (>20%)"))))) -> ACIMA DA META (>20%)
A188: Q3060-A | B188: Medios | C188: São Paulo Interior | D188: 580.52 | E188: 0 | F188: 277.75 | G188: 73.85 | H188: =IF(D188="","",D188*(1-E188)) -> 580.52 | I188: =IF(OR(G188="",H188=""),"",G188/H188) -> 0.12721353 | J188: =IF(OR(B188="",C188=""),"",INDEX(Ref_Frete!$B$2:$G$54,MATCH(C188,Ref_Frete!$A$2:$A$54,0),IF(B188="Pequenos",2,IF(B188="Medios",4,6)))) -> 39.9 | K188: =IF(OR(B188="",C188=""),"",INDEX(Ref_Frete!$B$2:$G$54,MATCH(C188,Ref_Frete!$A$2:$A$54,0),IF(B188="Pequenos",1,IF(B188="Medios",3,5)))) -> 49 | L188: =IF(OR(J188="",K188=""),"",J188-K188) -> -9.1 | M188: =IF(OR(H188="",F188="",G188=""),"",H188-G188-F188-H188*$B$3+IF(L188="",0,L188)) -> 161.768 | N188: =IF(OR(M188="",H188=0,H188=""),"",M188/H188) -> 0.27866051 | O188: =IF(N188="","",IF(N188<0,"PREJUÍZO",IF(N188<0.1,"CRÍTICO (<10%)",IF(N188<0.15,"ABAIXO DA META (10-15%)",IF(N188<=0.2,"DENTRO DA META (15-20%)","ACIMA DA META (>20%)"))))) -> ACIMA DA META (>20%)
A189: Q3060-B | B189: Medios | C189: Rio Grande do Sul Capital | D189: 532.93 | E189: 0 | F189: 301.03 | G189: 68.14 | H189: =IF(D189="","",D189*(1-E189)) -> 532.93 | I189: =IF(OR(G189="",H189=""),"",G189/H189) -> 0.12785919 | J189: =IF(OR(B189="",C189=""),"",INDEX(Ref_Frete!$B$2:$G$54,MATCH(C189,Ref_Frete!$A$2:$A$54,0),IF(B189="Pequenos",2,IF(B189="Medios",4,6)))) -> 59.9 | K189: =IF(OR(B189="",C189=""),"",INDEX(Ref_Frete!$B$2:$G$54,MATCH(C189,Ref_Frete!$A$2:$A$54,0),IF(B189="Pequenos",1,IF(B189="Medios",3,5)))) -> 89 | L189: =IF(OR(J189="",K189=""),"",J189-K189) -> -29.1 | M189: =IF(OR(H189="",F189="",G189=""),"",H189-G189-F189-H189*$B$3+IF(L189="",0,L189)) -> 81.367 | N189: =IF(OR(M189="",H189=0,H189=""),"",M189/H189) -> 0.15267859 | O189: =IF(N189="","",IF(N189<0,"PREJUÍZO",IF(N189<0.1,"CRÍTICO (<10%)",IF(N189<0.15,"ABAIXO DA META (10-15%)",IF(N189<=0.2,"DENTRO DA META (15-20%)","ACIMA DA META (>20%)"))))) -> DENTRO DA META (15-20%)
A190: Q3060-B | B190: Medios | C190: São Paulo Interior | D190: 532.93 | E190: 0 | F190: 301.03 | G190: 68.14 | H190: =IF(D190="","",D190*(1-E190)) -> 532.93 | I190: =IF(OR(G190="",H190=""),"",G190/H190) -> 0.12785919 | J190: =IF(OR(B190="",C190=""),"",INDEX(Ref_Frete!$B$2:$G$54,MATCH(C190,Ref_Frete!$A$2:$A$54,0),IF(B190="Pequenos",2,IF(B190="Medios",4,6)))) -> 39.9 | K190: =IF(OR(B190="",C190=""),"",INDEX(Ref_Frete!$B$2:$G$54,MATCH(C190,Ref_Frete!$A$2:$A$54,0),IF(B190="Pequenos",1,IF(B190="Medios",3,5)))) -> 49 | L190: =IF(OR(J190="",K190=""),"",J190-K190) -> -9.1 | M190: =IF(OR(H190="",F190="",G190=""),"",H190-G190-F190-H190*$B$3+IF(L190="",0,L190)) -> 101.367 | N190: =IF(OR(M190="",H190=0,H190=""),"",M190/H190) -> 0.19020697 | O190: =IF(N190="","",IF(N190<0,"PREJUÍZO",IF(N190<0.1,"CRÍTICO (<10%)",IF(N190<0.15,"ABAIXO DA META (10-15%)",IF(N190<=0.2,"DENTRO DA META (15-20%)","ACIMA DA META (>20%)"))))) -> DENTRO DA META (15-20%)
A191: SP-01 | B191: Medios | C191: Rio Grande do Sul Capital | D191: 475.31 | E191: 0 | F191: 247.86 | G191: 61.23 | H191: =IF(D191="","",D191*(1-E191)) -> 475.31 | I191: =IF(OR(G191="",H191=""),"",G191/H191) -> 0.12882119 | J191: =IF(OR(B191="",C191=""),"",INDEX(Ref_Frete!$B$2:$G$54,MATCH(C191,Ref_Frete!$A$2:$A$54,0),IF(B191="Pequenos",2,IF(B191="Medios",4,6)))) -> 59.9 | K191: =IF(OR(B191="",C191=""),"",INDEX(Ref_Frete!$B$2:$G$54,MATCH(C191,Ref_Frete!$A$2:$A$54,0),IF(B191="Pequenos",1,IF(B191="Medios",3,5)))) -> 89 | L191: =IF(OR(J191="",K191=""),"",J191-K191) -> -29.1 | M191: =IF(OR(H191="",F191="",G191=""),"",H191-G191-F191-H191*$B$3+IF(L191="",0,L191)) -> 89.589 | N191: =IF(OR(M191="",H191=0,H191=""),"",M191/H191) -> 0.18848541 | O191: =IF(N191="","",IF(N191<0,"PREJUÍZO",IF(N191<0.1,"CRÍTICO (<10%)",IF(N191<0.15,"ABAIXO DA META (10-15%)",IF(N191<=0.2,"DENTRO DA META (15-20%)","ACIMA DA META (>20%)"))))) -> DENTRO DA META (15-20%)
A192: SP-01 | B192: Medios | C192: São Paulo Interior | D192: 475.31 | E192: 0 | F192: 247.86 | G192: 61.23 | H192: =IF(D192="","",D192*(1-E192)) -> 475.31 | I192: =IF(OR(G192="",H192=""),"",G192/H192) -> 0.12882119 | J192: =IF(OR(B192="",C192=""),"",INDEX(Ref_Frete!$B$2:$G$54,MATCH(C192,Ref_Frete!$A$2:$A$54,0),IF(B192="Pequenos",2,IF(B192="Medios",4,6)))) -> 39.9 | K192: =IF(OR(B192="",C192=""),"",INDEX(Ref_Frete!$B$2:$G$54,MATCH(C192,Ref_Frete!$A$2:$A$54,0),IF(B192="Pequenos",1,IF(B192="Medios",3,5)))) -> 49 | L192: =IF(OR(J192="",K192=""),"",J192-K192) -> -9.1 | M192: =IF(OR(H192="",F192="",G192=""),"",H192-G192-F192-H192*$B$3+IF(L192="",0,L192)) -> 109.589 | N192: =IF(OR(M192="",H192=0,H192=""),"",M192/H192) -> 0.23056321 | O192: =IF(N192="","",IF(N192<0,"PREJUÍZO",IF(N192<0.1,"CRÍTICO (<10%)",IF(N192<0.15,"ABAIXO DA META (10-15%)",IF(N192<=0.2,"DENTRO DA META (15-20%)","ACIMA DA META (>20%)"))))) -> ACIMA DA META (>20%)
A193: SP-FF | B193: Medios | C193: Rio Grande do Sul Capital | D193: 457.17 | E193: 0 | F193: 236.22 | G193: 59.05 | H193: =IF(D193="","",D193*(1-E193)) -> 457.17 | I193: =IF(OR(G193="",H193=""),"",G193/H193) -> 0.12916421 | J193: =IF(OR(B193="",C193=""),"",INDEX(Ref_Frete!$B$2:$G$54,MATCH(C193,Ref_Frete!$A$2:$A$54,0),IF(B193="Pequenos",2,IF(B193="Medios",4,6)))) -> 59.9 | K193: =IF(OR(B193="",C193=""),"",INDEX(Ref_Frete!$B$2:$G$54,MATCH(C193,Ref_Frete!$A$2:$A$54,0),IF(B193="Pequenos",1,IF(B193="Medios",3,5)))) -> 89 | L193: =IF(OR(J193="",K193=""),"",J193-K193) -> -29.1 | M193: =IF(OR(H193="",F193="",G193=""),"",H193-G193-F193-H193*$B$3+IF(L193="",0,L193)) -> 87.083 | N193: =IF(OR(M193="",H193=0,H193=""),"",M193/H193) -> 0.19048275 | O193: =IF(N193="","",IF(N193<0,"PREJUÍZO",IF(N193<0.1,"CRÍTICO (<10%)",IF(N193<0.15,"ABAIXO DA META (10-15%)",IF(N193<=0.2,"DENTRO DA META (15-20%)","ACIMA DA META (>20%)"))))) -> DENTRO DA META (15-20%)
A194: SP-FF | B194: Medios | C194: São Paulo Interior | D194: 457.17 | E194: 0 | F194: 236.22 | G194: 59.05 | H194: =IF(D194="","",D194*(1-E194)) -> 457.17 | I194: =IF(OR(G194="",H194=""),"",G194/H194) -> 0.12916421 | J194: =IF(OR(B194="",C194=""),"",INDEX(Ref_Frete!$B$2:$G$54,MATCH(C194,Ref_Frete!$A$2:$A$54,0),IF(B194="Pequenos",2,IF(B194="Medios",4,6)))) -> 39.9 | K194: =IF(OR(B194="",C194=""),"",INDEX(Ref_Frete!$B$2:$G$54,MATCH(C194,Ref_Frete!$A$2:$A$54,0),IF(B194="Pequenos",1,IF(B194="Medios",3,5)))) -> 49 | L194: =IF(OR(J194="",K194=""),"",J194-K194) -> -9.1 | M194: =IF(OR(H194="",F194="",G194=""),"",H194-G194-F194-H194*$B$3+IF(L194="",0,L194)) -> 107.083 | N194: =IF(OR(M194="",H194=0,H194=""),"",M194/H194) -> 0.23423016 | O194: =IF(N194="","",IF(N194<0,"PREJUÍZO",IF(N194<0.1,"CRÍTICO (<10%)",IF(N194<0.15,"ABAIXO DA META (10-15%)",IF(N194<=0.2,"DENTRO DA META (15-20%)","ACIMA DA META (>20%)"))))) -> ACIMA DA META (>20%)
... A230: Q4070-B | B230: Grandes | C230: São Paulo Interior | D230: 1116.81 | E230: 0 | F230: 619.95 | G230: 146.74 | H230: =IF(D230="","",D230*(1-E230)) -> 1116.81 | I230: =IF(OR(G230="",H230=""),"",G230/H230) -> 0.13139209 | J230: =IF(OR(B230="",C230=""),"",INDEX(Ref_Frete!$B$2:$G$54,MATCH(C230,Ref_Frete!$A$2:$A$54,0),IF(B230="Pequenos",2,IF(B230="Medios",4,6)))) -> 120 | K230: =IF(OR(B230="",C230=""),"",INDEX(Ref_Frete!$B$2:$G$54,MATCH(C230,Ref_Frete!$A$2:$A$54,0),IF(B230="Pequenos",1,IF(B230="Medios",3,5)))) -> 120 | L230: =IF(OR(J230="",K230=""),"",J230-K230) -> 0 | M230: =IF(OR(H230="",F230="",G230=""),"",H230-G230-F230-H230*$B$3+IF(L230="",0,L230)) -> 238.439 | N230: =IF(OR(M230="",H230=0,H230=""),"",M230/H230) -> 0.21350006 | O230: =IF(N230="","",IF(N230<0,"PREJUÍZO",IF(N230<0.1,"CRÍTICO (<10%)",IF(N230<0.15,"ABAIXO DA META (10-15%)",IF(N230<=0.2,"DENTRO DA META (15-20%)","ACIMA DA META (>20%)"))))) -> ACIMA DA META (>20%)
A231: SP-T | B231: Medios | C231: Rio Grande do Sul Capital | D231: 462.37 | E231: 0 | F231: 238.66 | G231: 68.2 | H231: =IF(D231="","",D231*(1-E231)) -> 462.37 | I231: =IF(OR(G231="",H231=""),"",G231/H231) -> 0.14750092 | J231: =IF(OR(B231="",C231=""),"",INDEX(Ref_Frete!$B$2:$G$54,MATCH(C231,Ref_Frete!$A$2:$A$54,0),IF(B231="Pequenos",2,IF(B231="Medios",4,6)))) -> 59.9 | K231: =IF(OR(B231="",C231=""),"",INDEX(Ref_Frete!$B$2:$G$54,MATCH(C231,Ref_Frete!$A$2:$A$54,0),IF(B231="Pequenos",1,IF(B231="Medios",3,5)))) -> 89 | L231: =IF(OR(J231="",K231=""),"",J231-K231) -> -29.1 | M231: =IF(OR(H231="",F231="",G231=""),"",H231-G231-F231-H231*$B$3+IF(L231="",0,L231)) -> 80.173 | N231: =IF(OR(M231="",H231=0,H231=""),"",M231/H231) -> 0.17339577 | O231: =IF(N231="","",IF(N231<0,"PREJUÍZO",IF(N231<0.1,"CRÍTICO (<10%)",IF(N231<0.15,"ABAIXO DA META (10-15%)",IF(N231<=0.2,"DENTRO DA META (15-20%)","ACIMA DA META (>20%)"))))) -> DENTRO DA META (15-20%) | P231: Classe Médios validada por cotação em 13/08. Conferir no Seller Central se o SKU SP-T já está atribuído ao modelo WN - Medios; a cobrança efetiva ao cliente depende da configuração vigente na Amazon.
A232: SP-T | B232: Medios | C232: São Paulo Interior | D232: 462.37 | E232: 0 | F232: 238.66 | G232: 68.2 | H232: =IF(D232="","",D232*(1-E232)) -> 462.37 | I232: =IF(OR(G232="",H232=""),"",G232/H232) -> 0.14750092 | J232: =IF(OR(B232="",C232=""),"",INDEX(Ref_Frete!$B$2:$G$54,MATCH(C232,Ref_Frete!$A$2:$A$54,0),IF(B232="Pequenos",2,IF(B232="Medios",4,6)))) -> 39.9 | K232: =IF(OR(B232="",C232=""),"",INDEX(Ref_Frete!$B$2:$G$54,MATCH(C232,Ref_Frete!$A$2:$A$54,0),IF(B232="Pequenos",1,IF(B232="Medios",3,5)))) -> 49 | L232: =IF(OR(J232="",K232=""),"",J232-K232) -> -9.1 | M232: =IF(OR(H232="",F232="",G232=""),"",H232-G232-F232-H232*$B$3+IF(L232="",0,L232)) -> 100.173 | N232: =IF(OR(M232="",H232=0,H232=""),"",M232/H232) -> 0.21665117 | O232: =IF(N232="","",IF(N232<0,"PREJUÍZO",IF(N232<0.1,"CRÍTICO (<10%)",IF(N232<0.15,"ABAIXO DA META (10-15%)",IF(N232<=0.2,"DENTRO DA META (15-20%)","ACIMA DA META (>20%)"))))) -> ACIMA DA META (>20%) | P232: Classe Médios validada por cotação em 13/08. Conferir no Seller Central se o SKU SP-T já está atribuído ao modelo WN - Medios; a cobrança efetiva ao cliente depende da configuração vigente na Amazon.

Sheet Registro_Vendas
A1: REGISTRO DE VENDAS — lucro real venda a venda
A2: Preencha as colunas AZUIS. PEDIDO COM VÁRIOS SKUs: uma linha por SKU (mesma data e nº de pedido), frete cobrado e frete real SÓ NA 1ª LINHA — nas demais digite 0 por cima. Tarifa: estimada; sobrescreva com a real do extrato.
A3: Imposto (%): | B3: 0.1 | C3: Tarifa padrão (%): | D3: 0.135
A5: Data | B5: SKU | C5: Qtd | D5: Região destino | E5: Preço unit. (R$) | F5: Desconto/promo total (R$) | G5: Receita produtos (R$) | H5: Classe | I5: Frete cobrado do cliente (R$) | J5: Frete real pago (R$) | K5: Tarifa Amazon (R$) | L5: Custo produtos (R$) | M5: Imposto (R$) | N5: LUCRO (R$) | O5: Margem | P5: Veredito | Q5: Nº do Pedido / Obs | R5: Origem
A6: 46228 | B6: L2030-B | C6: 1 | D6: Distrito Federal | E6: =IF($B6="","",INDEX(Simulador!$D$7:$D$232,MATCH($B6,Simulador!$A$7:$A$232,0))) -> 153.72 | G6: =IF(OR($B6="",$C6=""),"",$C6*E6-IF(F6="",0,F6)) -> 153.72 | H6: =IF($B6="","",INDEX(Simulador!$B$7:$B$232,MATCH($B6,Simulador!$A$7:$A$232,0))) -> Pequenos | I6: =IF(OR(H6="",$D6=""),"",INDEX(Ref_Frete!$B$2:$G$54,MATCH($D6,Ref_Frete!$A$2:$A$54,0),IF(H6="Pequenos",2,IF(H6="Medios",4,6)))) -> 52 | J6: 19.73 | K6: 27.78 | L6: =IF(OR($B6="",$C6=""),"",$C6*INDEX(Simulador!$F$7:$F$232,MATCH($B6,Simulador!$A$7:$A$232,0))) -> 75.68 | M6: =IF(G6="","",G6*$B$3) -> 15.372 | N6: =IF(OR(G6="",J6=""),"",G6+IF(I6="",0,I6)-J6-K6-L6-M6) -> 67.158 | O6: =IF(OR(N6="",G6=0,G6=""),"",N6/G6) -> 0.43688525 | P6: =IF(O6="","",IF(O6<0,"PREJUÍZO",IF(O6<0.1,"CRÍTICO (<10%)",IF(O6<0.15,"ABAIXO DA META (10-15%)",IF(O6<=0.2,"DENTRO DA META (15-20%)","ACIMA DA META (>20%)"))))) -> ACIMA DA META (>20%) | R6: Orgânico
A7: 46236 | B7: L3070-B | C7: 1 | D7: Minas Gerais Interior | E7: =IF($B7="","",INDEX(Simulador!$D$7:$D$232,MATCH($B7,Simulador!$A$7:$A$232,0))) -> 543.85 | G7: =IF(OR($B7="",$C7=""),"",$C7*E7-IF(F7="",0,F7)) -> 543.85 | H7: =IF($B7="","",INDEX(Simulador!$B$7:$B$232,MATCH($B7,Simulador!$A$7:$A$232,0))) -> Medios | I7: =IF(OR(H7="",$D7=""),"",INDEX(Ref_Frete!$B$2:$G$54,MATCH($D7,Ref_Frete!$A$2:$A$54,0),IF(H7="Pequenos",2,IF(H7="Medios",4,6)))) -> 69.9 | J7: 80.69 | K7: =IF(G7="","",ROUND($D$3*(G7+IF(I7="",0,I7)),2)) -> 82.86 | L7: =IF(OR($B7="",$C7=""),"",$C7*INDEX(Simulador!$F$7:$F$232,MATCH($B7,Simulador!$A$7:$A$232,0))) -> 279.42 | M7: =IF(G7="","",G7*$B$3) -> 54.385 | N7: =IF(OR(G7="",J7=""),"",G7+IF(I7="",0,I7)-J7-K7-L7-M7) -> 116.395 | O7: =IF(OR(N7="",G7=0,G7=""),"",N7/G7) -> 0.21402041 | P7: =IF(O7="","",IF(O7<0,"PREJUÍZO",IF(O7<0.1,"CRÍTICO (<10%)",IF(O7<0.15,"ABAIXO DA META (10-15%)",IF(O7<=0.2,"DENTRO DA META (15-20%)","ACIMA DA META (>20%)"))))) -> ACIMA DA META (>20%) | Q7: Geral DBA | R7: Ads
A8: 46234 | B8: L2430-B | C8: 2 | D8: São Paulo Capital | E8: =IF($B8="","",INDEX(Simulador!$D$7:$D$232,MATCH($B8,Simulador!$A$7:$A$232,0))) -> 198.03 | G8: =IF(OR($B8="",$C8=""),"",$C8*E8-IF(F8="",0,F8)) -> 396.06 | H8: =IF($B8="","",INDEX(Simulador!$B$7:$B$232,MATCH($B8,Simulador!$A$7:$A$232,0))) -> Pequenos | I8: =IF(OR(H8="",$D8=""),"",INDEX(Ref_Frete!$B$2:$G$54,MATCH($D8,Ref_Frete!$A$2:$A$54,0),IF(H8="Pequenos",2,IF(H8="Medios",4,6)))) -> 12.9 | J8: 28.29 | K8: =IF(G8="","",ROUND($D$3*(G8+IF(I8="",0,I8)),2)) -> 55.21 | L8: =IF(OR($B8="",$C8=""),"",$C8*INDEX(Simulador!$F$7:$F$232,MATCH($B8,Simulador!$A$7:$A$232,0))) -> 206.84 | M8: =IF(G8="","",G8*$B$3) -> 39.606 | N8: =IF(OR(G8="",J8=""),"",G8+IF(I8="",0,I8)-J8-K8-L8-M8) -> 79.014 | O8: =IF(OR(N8="",G8=0,G8=""),"",N8/G8) -> 0.19950008 | P8: =IF(O8="","",IF(O8<0,"PREJUÍZO",IF(O8<0.1,"CRÍTICO (<10%)",IF(O8<0.15,"ABAIXO DA META (10-15%)",IF(O8<=0.2,"DENTRO DA META (15-20%)","ACIMA DA META (>20%)"))))) -> DENTRO DA META (15-20%) | Q8: Relatório Ads registra como L2425-B — conferir SKU | R8: Ads
A9: 46233 | B9: EGC | C9: 1 | D9: Rio Grande do Sul Capital | E9: =IF($B9="","",INDEX(Simulador!$D$7:$D$232,MATCH($B9,Simulador!$A$7:$A$232,0))) -> 674.62 | G9: =IF(OR($B9="",$C9=""),"",$C9*E9-IF(F9="",0,F9)) -> 674.62 | H9: =IF($B9="","",INDEX(Simulador!$B$7:$B$232,MATCH($B9,Simulador!$A$7:$A$232,0))) -> Medios | I9: =IF(OR(H9="",$D9=""),"",INDEX(Ref_Frete!$B$2:$G$54,MATCH($D9,Ref_Frete!$A$2:$A$54,0),IF(H9="Pequenos",2,IF(H9="Medios",4,6)))) -> 59.9 | J9: 53.59 | K9: =IF(G9="","",ROUND($D$3*(G9+IF(I9="",0,I9)),2)) -> 99.16 | L9: =IF(OR($B9="",$C9=""),"",$C9*INDEX(Simulador!$F$7:$F$232,MATCH($B9,Simulador!$A$7:$A$232,0))) -> 365.7 | M9: =IF(G9="","",G9*$B$3) -> 67.462 | N9: =IF(OR(G9="",J9=""),"",G9+IF(I9="",0,I9)-J9-K9-L9-M9) -> 148.608 | O9: =IF(OR(N9="",G9=0,G9=""),"",N9/G9) -> 0.22028401 | P9: =IF(O9="","",IF(O9<0,"PREJUÍZO",IF(O9<0.1,"CRÍTICO (<10%)",IF(O9<0.15,"ABAIXO DA META (10-15%)",IF(O9<=0.2,"DENTRO DA META (15-20%)","ACIMA DA META (>20%)"))))) -> ACIMA DA META (>20%) | R9: Orgânico
A10: 46186 | B10: L1618-A | C10: 1 | D10: Paraná Capital | E10: 96.63 | G10: =IF(OR($B10="",$C10=""),"",$C10*E10-IF(F10="",0,F10)) -> 96.63 | H10: =IF($B10="","",INDEX(Simulador!$B$7:$B$232,MATCH($B10,Simulador!$A$7:$A$232,0))) -> Pequenos | I10: 23.51 | J10: 15.65 | K10: 14.42 | L10: =IF(OR($B10="",$C10=""),"",$C10*INDEX(Simulador!$F$7:$F$232,MATCH($B10,Simulador!$A$7:$A$232,0))) -> 48.18 | M10: =IF(G10="","",G10*$B$3) -> 9.663 | N10: =IF(OR(G10="",J10=""),"",G10+IF(I10="",0,I10)-J10-K10-L10-M10) -> 32.227 | O10: =IF(OR(N10="",G10=0,G10=""),"",N10/G10) -> 0.33350926 | P10: =IF(O10="","",IF(O10<0,"PREJUÍZO",IF(O10<0.1,"CRÍTICO (<10%)",IF(O10<0.15,"ABAIXO DA META (10-15%)",IF(O10<=0.2,"DENTRO DA META (15-20%)","ACIMA DA META (>20%)"))))) -> ACIMA DA META (>20%) | Q10: Preço da época (pré-reajuste; atual 104,90). | R10: Orgânico
A11: 46192 | B11: L2460-CP | C11: 1 | D11: Rio de Janeiro Capital | E11: =IF($B11="","",INDEX(Simulador!$D$7:$D$232,MATCH($B11,Simulador!$A$7:$A$232,0))) -> 335.68 | G11: =IF(OR($B11="",$C11=""),"",$C11*E11-IF(F11="",0,F11)) -> 335.68 | H11: =IF($B11="","",INDEX(Simulador!$B$7:$B$232,MATCH($B11,Simulador!$A$7:$A$232,0))) -> Medios | I11: 51 | J11: 35.52 | K11: =IF(G11="","",ROUND($D$3*(G11+IF(I11="",0,I11)),2)) -> 52.2 | L11: =IF(OR($B11="",$C11=""),"",$C11*INDEX(Simulador!$F$7:$F$232,MATCH($B11,Simulador!$A$7:$A$232,0))) -> 172.67 | M11: =IF(G11="","",G11*$B$3) -> 33.568 | N11: =IF(OR(G11="",J11=""),"",G11+IF(I11="",0,I11)-J11-K11-L11-M11) -> 92.722 | O11: =IF(OR(N11="",G11=0,G11=""),"",N11/G11) -> 0.2762214 | P11: =IF(O11="","",IF(O11<0,"PREJUÍZO",IF(O11<0.1,"CRÍTICO (<10%)",IF(O11<0.15,"ABAIXO DA META (10-15%)",IF(O11<=0.2,"DENTRO DA META (15-20%)","ACIMA DA META (>20%)"))))) -> ACIMA DA META (>20%) | Q11: auto - termo "coletor de pilhas" | R11: Ads
A12: 46195 | B12: Q3060-B | C12: 1 | D12: Rio de Janeiro Capital | E12: =IF($B12="","",INDEX(Simulador!$D$7:$D$232,MATCH($B12,Simulador!$A$7:$A$232,0))) -> 532.93 | G12: =IF(OR($B12="",$C12=""),"",$C12*E12-IF(F12="",0,F12)) -> 532.93 | H12: =IF($B12="","",INDEX(Simulador!$B$7:$B$232,MATCH($B12,Simulador!$A$7:$A$232,0))) -> Medios | I12: 59.99 | J12: 42.41 | K12: =IF(G12="","",ROUND($D$3*(G12+IF(I12="",0,I12)),2)) -> 80.04 | L12: =IF(OR($B12="",$C12=""),"",$C12*INDEX(Simulador!$F$7:$F$232,MATCH($B12,Simulador!$A$7:$A$232,0))) -> 301.03 | M12: =IF(G12="","",G12*$B$3) -> 53.293 | N12: =IF(OR(G12="",J12=""),"",G12+IF(I12="",0,I12)-J12-K12-L12-M12) -> 116.147 | O12: =IF(OR(N12="",G12=0,G12=""),"",N12/G12) -> 0.21794044 | P12: =IF(O12="","",IF(O12<0,"PREJUÍZO",IF(O12<0.1,"CRÍTICO (<10%)",IF(O12<0.15,"ABAIXO DA META (10-15%)",IF(O12<=0.2,"DENTRO DA META (15-20%)","ACIMA DA META (>20%)"))))) -> ACIMA DA META (>20%) | R12: Orgânico
A13: 46195 | B13: P3070 | C13: 1 | D13: São Paulo Capital | E13: =IF($B13="","",INDEX(Simulador!$D$7:$D$232,MATCH($B13,Simulador!$A$7:$A$232,0))) -> 616.18 | G13: =IF(OR($B13="",$C13=""),"",$C13*E13-IF(F13="",0,F13)) -> 616.18 | H13: =IF($B13="","",INDEX(Simulador!$B$7:$B$232,MATCH($B13,Simulador!$A$7:$A$232,0))) -> Medios | I13: 40.01 | J13: 37.22 | K13: =IF(G13="","",ROUND($D$3*(G13+IF(I13="",0,I13)),2)) -> 88.59 | L13: =IF(OR($B13="",$C13=""),"",$C13*INDEX(Simulador!$F$7:$F$232,MATCH($B13,Simulador!$A$7:$A$232,0))) -> 307.26 | M13: =IF(G13="","",G13*$B$3) -> 61.618 | N13: =IF(OR(G13="",J13=""),"",G13+IF(I13="",0,I13)-J13-K13-L13-M13) -> 161.502 | O13: =IF(OR(N13="",G13=0,G13=""),"",N13/G13) -> 0.26210198 | P13: =IF(O13="","",IF(O13<0,"PREJUÍZO",IF(O13<0.1,"CRÍTICO (<10%)",IF(O13<0.15,"ABAIXO DA META (10-15%)",IF(O13<=0.2,"DENTRO DA META (15-20%)","ACIMA DA META (>20%)"))))) -> ACIMA DA META (>20%) | Q13: PI - ASIN B0G9B9RCMF | R13: Ads
A14: 46197 | B14: L2450-AML | C14: 1 | D14: São Paulo Interior | E14: 203.16 | G14: =IF(OR($B14="",$C14=""),"",$C14*E14-IF(F14="",0,F14)) -> 203.16 | H14: =IF($B14="","",INDEX(Simulador!$B$7:$B$232,MATCH($B14,Simulador!$A$7:$A$232,0))) -> Pequenos | I14: 16.25 | J14: 34.5 | K14: =IF(G14="","",ROUND($D$3*(G14+IF(I14="",0,I14)),2)) -> 29.62 | L14: =IF(OR($B14="",$C14=""),"",$C14*INDEX(Simulador!$F$7:$F$232,MATCH($B14,Simulador!$A$7:$A$232,0))) -> 139.49 | M14: =IF(G14="","",G14*$B$3) -> 20.316 | N14: =IF(OR(G14="",J14=""),"",G14+IF(I14="",0,I14)-J14-K14-L14-M14) -> -4.516 | O14: =IF(OR(N14="",G14=0,G14=""),"",N14/G14) -> -0.022228785 | P14: =IF(O14="","",IF(O14<0,"PREJUÍZO",IF(O14<0.1,"CRÍTICO (<10%)",IF(O14<0.15,"ABAIXO DA META (10-15%)",IF(O14<=0.2,"DENTRO DA META (15-20%)","ACIMA DA META (>20%)"))))) -> PREJUÍZO | Q14: Preço da época (pré-reajuste; atual 259,90). Relatório Ads registra como L2025 — conferir SKU | R14: Ads
A15: 46198 | B15: PG2460 | C15: 1 | D15: Paraná Capital | E15: =IF($B15="","",INDEX(Simulador!$D$7:$D$232,MATCH($B15,Simulador!$A$7:$A$232,0))) -> 248.75 | G15: =IF(OR($B15="",$C15=""),"",$C15*E15-IF(F15="",0,F15)) -> 248.75 | H15: =IF($B15="","",INDEX(Simulador!$B$7:$B$232,MATCH($B15,Simulador!$A$7:$A$232,0))) -> Medios | I15: 46.01 | J15: 37.97 | K15: =IF(G15="","",ROUND($D$3*(G15+IF(I15="",0,I15)),2)) -> 39.79 | L15: =IF(OR($B15="",$C15=""),"",$C15*INDEX(Simulador!$F$7:$F$232,MATCH($B15,Simulador!$A$7:$A$232,0))) -> 124.42 | M15: =IF(G15="","",G15*$B$3) -> 24.875 | N15: =IF(OR(G15="",J15=""),"",G15+IF(I15="",0,I15)-J15-K15-L15-M15) -> 67.705 | O15: =IF(OR(N15="",G15=0,G15=""),"",N15/G15) -> 0.2721809 | P15: =IF(O15="","",IF(O15<0,"PREJUÍZO",IF(O15<0.1,"CRÍTICO (<10%)",IF(O15<0.15,"ABAIXO DA META (10-15%)",IF(O15<=0.2,"DENTRO DA META (15-20%)","ACIMA DA META (>20%)"))))) -> ACIMA DA META (>20%) | Q15: auto - "suporte para guarda chuva" | R15: Ads
A16: 46199 | B16: PXP | C16: 2 | D16: São Paulo Capital | E16: =IF($B16="","",INDEX(Simulador!$D$7:$D$232,MATCH($B16,Simulador!$A$7:$A$232,0))) -> 167.89 | G16: =IF(OR($B16="",$C16=""),"",$C16*E16-IF(F16="",0,F16)) -> 335.78 | H16: =IF($B16="","",INDEX(Simulador!$B$7:$B$232,MATCH($B16,Simulador!$A$7:$A$232,0))) -> Pequenos | I16: =IF(OR(H16="",$D16=""),"",INDEX(Ref_Frete!$B$2:$G$54,MATCH($D16,Ref_Frete!$A$2:$A$54,0),IF(H16="Pequenos",2,IF(H16="Medios",4,6)))) -> 12.9 | J16: 15.49 | K16: =IF(G16="","",ROUND($D$3*(G16+IF(I16="",0,I16)),2)) -> 47.07 | L16: =IF(OR($B16="",$C16=""),"",$C16*INDEX(Simulador!$F$7:$F$232,MATCH($B16,Simulador!$A$7:$A$232,0))) -> 169.58 | M16: =IF(G16="","",G16*$B$3) -> 33.578 | N16: =IF(OR(G16="",J16=""),"",G16+IF(I16="",0,I16)-J16-K16-L16-M16) -> 82.962 | O16: =IF(OR(N16="",G16=0,G16=""),"",N16/G16) -> 0.24707249 | P16: =IF(O16="","",IF(O16<0,"PREJUÍZO",IF(O16<0.1,"CRÍTICO (<10%)",IF(O16<0.15,"ABAIXO DA META (10-15%)",IF(O16<=0.2,"DENTRO DA META (15-20%)","ACIMA DA META (>20%)"))))) -> ACIMA DA META (>20%) | Q16: Órfã 26/06 identificada: 2× PXP (335,78) | R16: Orgânico
A17: 46202 | B17: SP-01 | C17: 1 | D17: Rio Grande do Norte Capital | E17: =IF($B17="","",INDEX(Simulador!$D$7:$D$232,MATCH($B17,Simulador!$A$7:$A$232,0))) -> 475.31 | G17: =IF(OR($B17="",$C17=""),"",$C17*E17-IF(F17="",0,F17)) -> 475.31 | H17: =IF($B17="","",INDEX(Simulador!$B$7:$B$232,MATCH($B17,Simulador!$A$7:$A$232,0))) -> Medios | I17: 163 | J17: 81.96 | K17: =IF(G17="","",ROUND($D$3*(G17+IF(I17="",0,I17)),2)) -> 86.17 | L17: =IF(OR($B17="",$C17=""),"",$C17*INDEX(Simulador!$F$7:$F$232,MATCH($B17,Simulador!$A$7:$A$232,0))) -> 247.86 | M17: =IF(G17="","",G17*$B$3) -> 47.531 | N17: =IF(OR(G17="",J17=""),"",G17+IF(I17="",0,I17)-J17-K17-L17-M17) -> 174.789 | O17: =IF(OR(N17="",G17=0,G17=""),"",N17/G17) -> 0.36773685 | P17: =IF(O17="","",IF(O17<0,"PREJUÍZO",IF(O17<0.1,"CRÍTICO (<10%)",IF(O17<0.15,"ABAIXO DA META (10-15%)",IF(O17<=0.2,"DENTRO DA META (15-20%)","ACIMA DA META (>20%)"))))) -> ACIMA DA META (>20%) | Q17: PI - ASIN B0C5JTQBXF | R17: Ads
A18: 46202 | B18: P3050 | C18: 1 | D18: Distrito Federal | E18: =IF($B18="","",INDEX(Simulador!$D$7:$D$232,MATCH($B18,Simulador!$A$7:$A$232,0))) -> 467.67 | F18: 37.41 | G18: =IF(OR($B18="",$C18=""),"",$C18*E18-IF(F18="",0,F18)) -> 430.26 | H18: =IF($B18="","",INDEX(Simulador!$B$7:$B$232,MATCH($B18,Simulador!$A$7:$A$232,0))) -> Medios | I18: =IF(OR(H18="",$D18=""),"",INDEX(Ref_Frete!$B$2:$G$54,MATCH($D18,Ref_Frete!$A$2:$A$54,0),IF(H18="Pequenos",2,IF(H18="Medios",4,6)))) -> 122 | J18: 53.08 | K18: =IF(G18="","",ROUND($D$3*(G18+IF(I18="",0,I18)),2)) -> 74.56 | L18: =IF(OR($B18="",$C18=""),"",$C18*INDEX(Simulador!$F$7:$F$232,MATCH($B18,Simulador!$A$7:$A$232,0))) -> 240.55 | M18: =IF(G18="","",G18*$B$3) -> 43.026 | N18: =IF(OR(G18="",J18=""),"",G18+IF(I18="",0,I18)-J18-K18-L18-M18) -> 141.044 | O18: =IF(OR(N18="",G18=0,G18=""),"",N18/G18) -> 0.32781109 | P18: =IF(O18="","",IF(O18<0,"PREJUÍZO",IF(O18<0.1,"CRÍTICO (<10%)",IF(O18<0.15,"ABAIXO DA META (10-15%)",IF(O18<=0.2,"DENTRO DA META (15-20%)","ACIMA DA META (>20%)"))))) -> ACIMA DA META (>20%) | Q18: PI - ASIN B0CYWMQ93Y | R18: Ads
A19: 46205 | B19: EGC | C19: 1 | D19: São Paulo Capital | E19: =IF($B19="","",INDEX(Simulador!$D$7:$D$232,MATCH($B19,Simulador!$A$7:$A$232,0))) -> 674.62 | G19: =IF(OR($B19="",$C19=""),"",$C19*E19-IF(F19="",0,F19)) -> 674.62 | H19: =IF($B19="","",INDEX(Simulador!$B$7:$B$232,MATCH($B19,Simulador!$A$7:$A$232,0))) -> Medios | I19: =IF(OR(H19="",$D19=""),"",INDEX(Ref_Frete!$B$2:$G$54,MATCH($D19,Ref_Frete!$A$2:$A$54,0),IF(H19="Pequenos",2,IF(H19="Medios",4,6)))) -> 34.9 | J19: 44.98 | K19: =IF(G19="","",ROUND($D$3*(G19+IF(I19="",0,I19)),2)) -> 95.79 | L19: =IF(OR($B19="",$C19=""),"",$C19*INDEX(Simulador!$F$7:$F$232,MATCH($B19,Simulador!$A$7:$A$232,0))) -> 365.7 | M19: =IF(G19="","",G19*$B$3) -> 67.462 | N19: =IF(OR(G19="",J19=""),"",G19+IF(I19="",0,I19)-J19-K19-L19-M19) -> 135.588 | O19: =IF(OR(N19="",G19=0,G19=""),"",N19/G19) -> 0.20098426 | P19: =IF(O19="","",IF(O19<0,"PREJUÍZO",IF(O19<0.1,"CRÍTICO (<10%)",IF(O19<0.15,"ABAIXO DA META (10-15%)",IF(O19<=0.2,"DENTRO DA META (15-20%)","ACIMA DA META (>20%)"))))) -> ACIMA DA META (>20%) | Q19: painel indica pedido em 01/07 | R19: Orgânico
A20: 46205 | B20: PXP | C20: 1 | D20: Goiás Capital | E20: 167.89 | G20: =IF(OR($B20="",$C20=""),"",$C20*E20-IF(F20="",0,F20)) -> 167.89 | H20: =IF($B20="","",INDEX(Simulador!$B$7:$B$232,MATCH($B20,Simulador!$A$7:$A$232,0))) -> Pequenos | I20: 59.49 | J20: 27.29 | K20: =IF(G20="","",ROUND($D$3*(G20+IF(I20="",0,I20)),2)) -> 30.7 | L20: =IF(OR($B20="",$C20=""),"",$C20*INDEX(Simulador!$F$7:$F$232,MATCH($B20,Simulador!$A$7:$A$232,0))) -> 84.79 | M20: =IF(G20="","",G20*$B$3) -> 16.789 | N20: =IF(OR(G20="",J20=""),"",G20+IF(I20="",0,I20)-J20-K20-L20-M20) -> 67.811 | O20: =IF(OR(N20="",G20=0,G20=""),"",N20/G20) -> 0.40390136 | P20: =IF(O20="","",IF(O20<0,"PREJUÍZO",IF(O20<0.1,"CRÍTICO (<10%)",IF(O20<0.15,"ABAIXO DA META (10-15%)",IF(O20<=0.2,"DENTRO DA META (15-20%)","ACIMA DA META (>20%)"))))) -> ACIMA DA META (>20%) | Q20: Pedido conjunto Goiânia (PXP+PXM 02/07) — frete do pedido NESTA linha | R20: Ads
A21: 46205 | B21: PXM | C21: 1 | D21: Goiás Capital | E21: 203.54 | G21: =IF(OR($B21="",$C21=""),"",$C21*E21-IF(F21="",0,F21)) -> 203.54 | H21: =IF($B21="","",INDEX(Simulador!$B$7:$B$232,MATCH($B21,Simulador!$A$7:$A$232,0))) -> Pequenos | I21: 0 | J21: 0 | K21: =IF(G21="","",ROUND($D$3*(G21+IF(I21="",0,I21)),2)) -> 27.48 | L21: =IF(OR($B21="",$C21=""),"",$C21*INDEX(Simulador!$F$7:$F$232,MATCH($B21,Simulador!$A$7:$A$232,0))) -> 102.8 | M21: =IF(G21="","",G21*$B$3) -> 20.354 | N21: =IF(OR(G21="",J21=""),"",G21+IF(I21="",0,I21)-J21-K21-L21-M21) -> 52.906 | O21: =IF(OR(N21="",G21=0,G21=""),"",N21/G21) -> 0.25992925 | P21: =IF(O21="","",IF(O21<0,"PREJUÍZO",IF(O21<0.1,"CRÍTICO (<10%)",IF(O21<0.15,"ABAIXO DA META (10-15%)",IF(O21<=0.2,"DENTRO DA META (15-20%)","ACIMA DA META (>20%)"))))) -> ACIMA DA META (>20%) | Q21: Mesmo pedido da linha 20 — frete zerado aqui | R21: Ads
A22: 46206 | B22: L2450--CZ | C22: 1 | D22: Bahia Capital | E22: =IF($B22="","",INDEX(Simulador!$D$7:$D$232,MATCH($B22,Simulador!$A$7:$A$232,0))) -> 319.58 | G22: =IF(OR($B22="",$C22=""),"",$C22*E22-IF(F22="",0,F22)) -> 319.58 | H22: =IF($B22="","",INDEX(Simulador!$B$7:$B$232,MATCH($B22,Simulador!$A$7:$A$232,0))) -> Pequenos | I22: 82.01 | J22: 24.6 | K22: =IF(G22="","",ROUND($D$3*(G22+IF(I22="",0,I22)),2)) -> 54.21 | L22: =IF(OR($B22="",$C22=""),"",$C22*INDEX(Simulador!$F$7:$F$232,MATCH($B22,Simulador!$A$7:$A$232,0))) -> 156 | M22: =IF(G22="","",G22*$B$3) -> 31.958 | N22: =IF(OR(G22="",J22=""),"",G22+IF(I22="",0,I22)-J22-K22-L22-M22) -> 134.822 | O22: =IF(OR(N22="",G22=0,G22=""),"",N22/G22) -> 0.42187246 | P22: =IF(O22="","",IF(O22<0,"PREJUÍZO",IF(O22<0.1,"CRÍTICO (<10%)",IF(O22<0.15,"ABAIXO DA META (10-15%)",IF(O22<=0.2,"DENTRO DA META (15-20%)","ACIMA DA META (>20%)"))))) -> ACIMA DA META (>20%) | Q22: Código do catálogo é L2450--CZ (hífen duplo). Preencher região e frete real | R22: Orgânico
A23: 46207 | B23: PXM | C23: 1 | D23: São Paulo Capital | E23: =IF($B23="","",INDEX(Simulador!$D$7:$D$232,MATCH($B23,Simulador!$A$7:$A$232,0))) -> 203.54 | G23: =IF(OR($B23="",$C23=""),"",$C23*E23-IF(F23="",0,F23)) -> 203.54 | H23: =IF($B23="","",INDEX(Simulador!$B$7:$B$232,MATCH($B23,Simulador!$A$7:$A$232,0))) -> Pequenos | I23: =IF(OR(H23="",$D23=""),"",INDEX(Ref_Frete!$B$2:$G$54,MATCH($D23,Ref_Frete!$A$2:$A$54,0),IF(H23="Pequenos",2,IF(H23="Medios",4,6)))) -> 12.9 | J23: 15.49 | K23: =IF(G23="","",ROUND($D$3*(G23+IF(I23="",0,I23)),2)) -> 29.22 | L23: =IF(OR($B23="",$C23=""),"",$C23*INDEX(Simulador!$F$7:$F$232,MATCH($B23,Simulador!$A$7:$A$232,0))) -> 102.8 | M23: =IF(G23="","",G23*$B$3) -> 20.354 | N23: =IF(OR(G23="",J23=""),"",G23+IF(I23="",0,I23)-J23-K23-L23-M23) -> 48.576 | O23: =IF(OR(N23="",G23=0,G23=""),"",N23/G23) -> 0.23865579 | P23: =IF(O23="","",IF(O23<0,"PREJUÍZO",IF(O23<0.1,"CRÍTICO (<10%)",IF(O23<0.15,"ABAIXO DA META (10-15%)",IF(O23<=0.2,"DENTRO DA META (15-20%)","ACIMA DA META (>20%)"))))) -> ACIMA DA META (>20%) | Q23: Preencher região e frete real | R23: Orgânico
A24: 46211 | B24: PXM | C24: 3 | D24: Ceará Capital | E24: =IF($B24="","",INDEX(Simulador!$D$7:$D$232,MATCH($B24,Simulador!$A$7:$A$232,0))) -> 203.54 | G24: =IF(OR($B24="",$C24=""),"",$C24*E24-IF(F24="",0,F24)) -> 610.62 | H24: =IF($B24="","",INDEX(Simulador!$B$7:$B$232,MATCH($B24,Simulador!$A$7:$A$232,0))) -> Pequenos | I24: 159.96 | J24: 80.55 | K24: =IF(G24="","",ROUND($D$3*(G24+IF(I24="",0,I24)),2)) -> 104.03 | L24: =IF(OR($B24="",$C24=""),"",$C24*INDEX(Simulador!$F$7:$F$232,MATCH($B24,Simulador!$A$7:$A$232,0))) -> 308.4 | M24: =IF(G24="","",G24*$B$3) -> 61.062 | N24: =IF(OR(G24="",J24=""),"",G24+IF(I24="",0,I24)-J24-K24-L24-M24) -> 216.538 | O24: =IF(OR(N24="",G24=0,G24=""),"",N24/G24) -> 0.35461989 | P24: =IF(O24="","",IF(O24<0,"PREJUÍZO",IF(O24<0.1,"CRÍTICO (<10%)",IF(O24<0.15,"ABAIXO DA META (10-15%)",IF(O24<=0.2,"DENTRO DA META (15-20%)","ACIMA DA META (>20%)"))))) -> ACIMA DA META (>20%) | Q24: auto — "suporte p/ extintor de 6 kg" · região/frete a preencher | R24: Ads
A25: 46212 | B25: L1618-T | C25: 1 | D25: São Paulo Interior | E25: =IF($B25="","",INDEX(Simulador!$D$7:$D$232,MATCH($B25,Simulador!$A$7:$A$232,0))) -> 116 | G25: =IF(OR($B25="",$C25=""),"",$C25*E25-IF(F25="",0,F25)) -> 116 | H25: =IF($B25="","",INDEX(Simulador!$B$7:$B$232,MATCH($B25,Simulador!$A$7:$A$232,0))) -> Pequenos | I25: =IF(OR(H25="",$D25=""),"",INDEX(Ref_Frete!$B$2:$G$54,MATCH($D25,Ref_Frete!$A$2:$A$54,0),IF(H25="Pequenos",2,IF(H25="Medios",4,6)))) -> 16.9 | J25: 16.64 | K25: =IF(G25="","",ROUND($D$3*(G25+IF(I25="",0,I25)),2)) -> 17.94 | L25: =IF(OR($B25="",$C25=""),"",$C25*INDEX(Simulador!$F$7:$F$232,MATCH($B25,Simulador!$A$7:$A$232,0))) -> 54.47 | M25: =IF(G25="","",G25*$B$3) -> 11.6 | N25: =IF(OR(G25="",J25=""),"",G25+IF(I25="",0,I25)-J25-K25-L25-M25) -> 32.25 | O25: =IF(OR(N25="",G25=0,G25=""),"",N25/G25) -> 0.27801724 | P25: =IF(O25="","",IF(O25<0,"PREJUÍZO",IF(O25<0.1,"CRÍTICO (<10%)",IF(O25<0.15,"ABAIXO DA META (10-15%)",IF(O25<=0.2,"DENTRO DA META (15-20%)","ACIMA DA META (>20%)"))))) -> ACIMA DA META (>20%) | Q25: Venda do termo "lixeira pia" (ACOS 48% — caso da O1) | R25: Ads
A26: 46212 | B26: P3050 | C26: 1 | D26: Minas Gerais Interior | E26: =IF($B26="","",INDEX(Simulador!$D$7:$D$232,MATCH($B26,Simulador!$A$7:$A$232,0))) -> 467.67 | G26: =IF(OR($B26="",$C26=""),"",$C26*E26-IF(F26="",0,F26)) -> 467.67 | H26: =IF($B26="","",INDEX(Simulador!$B$7:$B$232,MATCH($B26,Simulador!$A$7:$A$232,0))) -> Medios | I26: =IF(OR(H26="",$D26=""),"",INDEX(Ref_Frete!$B$2:$G$54,MATCH($D26,Ref_Frete!$A$2:$A$54,0),IF(H26="Pequenos",2,IF(H26="Medios",4,6)))) -> 69.9 | J26: 57.77 | K26: =IF(G26="","",ROUND($D$3*(G26+IF(I26="",0,I26)),2)) -> 72.57 | L26: =IF(OR($B26="",$C26=""),"",$C26*INDEX(Simulador!$F$7:$F$232,MATCH($B26,Simulador!$A$7:$A$232,0))) -> 240.55 | M26: =IF(G26="","",G26*$B$3) -> 46.767 | N26: =IF(OR(G26="",J26=""),"",G26+IF(I26="",0,I26)-J26-K26-L26-M26) -> 119.913 | O26: =IF(OR(N26="",G26=0,G26=""),"",N26/G26) -> 0.25640516 | P26: =IF(O26="","",IF(O26<0,"PREJUÍZO",IF(O26<0.1,"CRÍTICO (<10%)",IF(O26<0.15,"ABAIXO DA META (10-15%)",IF(O26<=0.2,"DENTRO DA META (15-20%)","ACIMA DA META (>20%)"))))) -> ACIMA DA META (>20%) | Q26: 2ª venda do P3050 via Ads | R26: Ads
A27: 46223 | B27: PXM | C27: 1 | D27: Goiás Capital | E27: =IF($B27="","",INDEX(Simulador!$D$7:$D$232,MATCH($B27,Simulador!$A$7:$A$232,0))) -> 203.54 | F27: 10.18 | G27: =IF(OR($B27="",$C27=""),"",$C27*E27-IF(F27="",0,F27)) -> 193.36 | H27: =IF($B27="","",INDEX(Simulador!$B$7:$B$232,MATCH($B27,Simulador!$A$7:$A$232,0))) -> Pequenos | I27: 37.49 | J27: 20.94 | K27: =IF(G27="","",ROUND($D$3*(G27+IF(I27="",0,I27)),2)) -> 31.16 | L27: =IF(OR($B27="",$C27=""),"",$C27*INDEX(Simulador!$F$7:$F$232,MATCH($B27,Simulador!$A$7:$A$232,0))) -> 102.8 | M27: =IF(G27="","",G27*$B$3) -> 19.336 | N27: =IF(OR(G27="",J27=""),"",G27+IF(I27="",0,I27)-J27-K27-L27-M27) -> 56.614 | O27: =IF(OR(N27="",G27=0,G27=""),"",N27/G27) -> 0.29279065 | P27: =IF(O27="","",IF(O27<0,"PREJUÍZO",IF(O27<0.1,"CRÍTICO (<10%)",IF(O27<0.15,"ABAIXO DA META (10-15%)",IF(O27<=0.2,"DENTRO DA META (15-20%)","ACIMA DA META (>20%)"))))) -> ACIMA DA META (>20%) | Q27: PI PXM · região/frete a preencher | R27: Ads
A28: 46224 | B28: PXP | C28: 1 | D28: Rio Grande do Sul Capital | E28: =IF($B28="","",INDEX(Simulador!$D$7:$D$232,MATCH($B28,Simulador!$A$7:$A$232,0))) -> 167.89 | F28: 8.39 | G28: =IF(OR($B28="",$C28=""),"",$C28*E28-IF(F28="",0,F28)) -> 159.5 | H28: =IF($B28="","",INDEX(Simulador!$B$7:$B$232,MATCH($B28,Simulador!$A$7:$A$232,0))) -> Pequenos | I28: =IF(OR(H28="",$D28=""),"",INDEX(Ref_Frete!$B$2:$G$54,MATCH($D28,Ref_Frete!$A$2:$A$54,0),IF(H28="Pequenos",2,IF(H28="Medios",4,6)))) -> 24.9 | J28: 21.19 | K28: =IF(G28="","",ROUND($D$3*(G28+IF(I28="",0,I28)),2)) -> 24.89 | L28: =IF(OR($B28="",$C28=""),"",$C28*INDEX(Simulador!$F$7:$F$232,MATCH($B28,Simulador!$A$7:$A$232,0))) -> 84.79 | M28: =IF(G28="","",G28*$B$3) -> 15.95 | N28: =IF(OR(G28="",J28=""),"",G28+IF(I28="",0,I28)-J28-K28-L28-M28) -> 37.58 | O28: =IF(OR(N28="",G28=0,G28=""),"",N28/G28) -> 0.23561129 | P28: =IF(O28="","",IF(O28<0,"PREJUÍZO",IF(O28<0.1,"CRÍTICO (<10%)",IF(O28<0.15,"ABAIXO DA META (10-15%)",IF(O28<=0.2,"DENTRO DA META (15-20%)","ACIMA DA META (>20%)"))))) -> ACIMA DA META (>20%) | Q28: auto · região/frete a preencher | R28: Ads
A29: 46225 | B29: L2025-B | C29: 1 | D29: São Paulo Interior | E29: 127.66 | F29: 1.53 | G29: =IF(OR($B29="",$C29=""),"",$C29*E29-IF(F29="",0,F29)) -> 126.13 | H29: =IF($B29="","",INDEX(Simulador!$B$7:$B$232,MATCH($B29,Simulador!$A$7:$A$232,0))) -> Pequenos | I29: =IF(OR(H29="",$D29=""),"",INDEX(Ref_Frete!$B$2:$G$54,MATCH($D29,Ref_Frete!$A$2:$A$54,0),IF(H29="Pequenos",2,IF(H29="Medios",4,6)))) -> 16.9 | J29: 40.18 | K29: =IF(G29="","",ROUND($D$3*(G29+IF(I29="",0,I29)),2)) -> 19.31 | L29: =IF(OR($B29="",$C29=""),"",$C29*INDEX(Simulador!$F$7:$F$232,MATCH($B29,Simulador!$A$7:$A$232,0))) -> 69.52 | M29: =IF(G29="","",G29*$B$3) -> 12.613 | N29: =IF(OR(G29="",J29=""),"",G29+IF(I29="",0,I29)-J29-K29-L29-M29) -> 1.407 | O29: =IF(OR(N29="",G29=0,G29=""),"",N29/G29) -> 0.011155157 | P29: =IF(O29="","",IF(O29<0,"PREJUÍZO",IF(O29<0.1,"CRÍTICO (<10%)",IF(O29<0.15,"ABAIXO DA META (10-15%)",IF(O29<=0.2,"DENTRO DA META (15-20%)","ACIMA DA META (>20%)"))))) -> CRÍTICO (<10%) | Q29: Pedido Franca 701-0789914-6289838 · frete SÓ nesta linha (real a preencher) | R29: Ads
A30: 46225 | B30: L1623-B | C30: 1 | D30: São Paulo Interior | E30: 131.24 | F30: 1.58 | G30: =IF(OR($B30="",$C30=""),"",$C30*E30-IF(F30="",0,F30)) -> 129.66 | H30: =IF($B30="","",INDEX(Simulador!$B$7:$B$232,MATCH($B30,Simulador!$A$7:$A$232,0))) -> Pequenos | I30: 0 | J30: 0 | K30: =IF(G30="","",ROUND($D$3*(G30+IF(I30="",0,I30)),2)) -> 17.5 | L30: =IF(OR($B30="",$C30=""),"",$C30*INDEX(Simulador!$F$7:$F$232,MATCH($B30,Simulador!$A$7:$A$232,0))) -> 65.95 | M30: =IF(G30="","",G30*$B$3) -> 12.966 | N30: =IF(OR(G30="",J30=""),"",G30+IF(I30="",0,I30)-J30-K30-L30-M30) -> 33.244 | O30: =IF(OR(N30="",G30=0,G30=""),"",N30/G30) -> 0.25639364 | P30: =IF(O30="","",IF(O30<0,"PREJUÍZO",IF(O30<0.1,"CRÍTICO (<10%)",IF(O30<0.15,"ABAIXO DA META (10-15%)",IF(O30<=0.2,"DENTRO DA META (15-20%)","ACIMA DA META (>20%)"))))) -> ACIMA DA META (>20%) | Q30: Pedido Franca — frete zerado (está na 1ª linha) | R30: Ads
A31: 46225 | B31: L2030 | C31: 2 | D31: São Paulo Interior | E31: 119.22 | F31: 2.85 | G31: =IF(OR($B31="",$C31=""),"",$C31*E31-IF(F31="",0,F31)) -> 235.59 | H31: =IF($B31="","",INDEX(Simulador!$B$7:$B$232,MATCH($B31,Simulador!$A$7:$A$232,0))) -> Pequenos | I31: 0 | J31: 0 | K31: =IF(G31="","",ROUND($D$3*(G31+IF(I31="",0,I31)),2)) -> 31.8 | L31: =IF(OR($B31="",$C31=""),"",$C31*INDEX(Simulador!$F$7:$F$232,MATCH($B31,Simulador!$A$7:$A$232,0))) -> 110.98 | M31: =IF(G31="","",G31*$B$3) -> 23.559 | N31: =IF(OR(G31="",J31=""),"",G31+IF(I31="",0,I31)-J31-K31-L31-M31) -> 69.251 | O31: =IF(OR(N31="",G31=0,G31=""),"",N31/G31) -> 0.29394711 | P31: =IF(O31="","",IF(O31<0,"PREJUÍZO",IF(O31<0.1,"CRÍTICO (<10%)",IF(O31<0.15,"ABAIXO DA META (10-15%)",IF(O31<=0.2,"DENTRO DA META (15-20%)","ACIMA DA META (>20%)"))))) -> ACIMA DA META (>20%) | Q31: Pedido Franca — frete zerado (está na 1ª linha) | R31: Ads
A32: 46238 | B32: PXP | C32: 3 | D32: Pernambuco Capital | E32: =IF($B32="","",INDEX(Simulador!$D$7:$D$232,MATCH($B32,Simulador!$A$7:$A$232,0))) -> 167.89 | F32: 25.18 | G32: =IF(OR($B32="",$C32=""),"",$C32*E32-IF(F32="",0,F32)) -> 478.49 | H32: =IF($B32="","",INDEX(Simulador!$B$7:$B$232,MATCH($B32,Simulador!$A$7:$A$232,0))) -> Pequenos | I32: =IF(OR(H32="",$D32=""),"",INDEX(Ref_Frete!$B$2:$G$54,MATCH($D32,Ref_Frete!$A$2:$A$54,0),IF(H32="Pequenos",2,IF(H32="Medios",4,6)))) -> 70 | J32: 87.96 | K32: =IF(G32="","",ROUND($D$3*(G32+IF(I32="",0,I32)),2)) -> 74.05 | L32: =IF(OR($B32="",$C32=""),"",$C32*INDEX(Simulador!$F$7:$F$232,MATCH($B32,Simulador!$A$7:$A$232,0))) -> 254.37 | M32: =IF(G32="","",G32*$B$3) -> 47.849 | N32: =IF(OR(G32="",J32=""),"",G32+IF(I32="",0,I32)-J32-K32-L32-M32) -> 84.261 | O32: =IF(OR(N32="",G32=0,G32=""),"",N32/G32) -> 0.17609772 | P32: =IF(O32="","",IF(O32<0,"PREJUÍZO",IF(O32<0.1,"CRÍTICO (<10%)",IF(O32<0.15,"ABAIXO DA META (10-15%)",IF(O32<=0.2,"DENTRO DA META (15-20%)","ACIMA DA META (>20%)"))))) -> DENTRO DA META (15-20%) | Q32: PROMOÇÃO 5% — 1º resgate · região/frete a preencher | R32: Ads
A33: 46239 | B33: L1618-T | C33: 1 | D33: Rio de Janeiro Interior | E33: =IF($B33="","",INDEX(Simulador!$D$7:$D$232,MATCH($B33,Simulador!$A$7:$A$232,0))) -> 116 | G33: =IF(OR($B33="",$C33=""),"",$C33*E33-IF(F33="",0,F33)) -> 116 | H33: =IF($B33="","",INDEX(Simulador!$B$7:$B$232,MATCH($B33,Simulador!$A$7:$A$232,0))) -> Pequenos | I33: =IF(OR(H33="",$D33=""),"",INDEX(Ref_Frete!$B$2:$G$54,MATCH($D33,Ref_Frete!$A$2:$A$54,0),IF(H33="Pequenos",2,IF(H33="Medios",4,6)))) -> 29.9 | J33: 19.08 | K33: =IF(G33="","",ROUND($D$3*(G33+IF(I33="",0,I33)),2)) -> 19.7 | L33: =IF(OR($B33="",$C33=""),"",$C33*INDEX(Simulador!$F$7:$F$232,MATCH($B33,Simulador!$A$7:$A$232,0))) -> 54.47 | M33: =IF(G33="","",G33*$B$3) -> 11.6 | N33: =IF(OR(G33="",J33=""),"",G33+IF(I33="",0,I33)-J33-K33-L33-M33) -> 41.05 | O33: =IF(OR(N33="",G33=0,G33=""),"",N33/G33) -> 0.35387931 | P33: =IF(O33="","",IF(O33<0,"PREJUÍZO",IF(O33<0.1,"CRÍTICO (<10%)",IF(O33<0.15,"ABAIXO DA META (10-15%)",IF(O33<=0.2,"DENTRO DA META (15-20%)","ACIMA DA META (>20%)"))))) -> ACIMA DA META (>20%) | Q33: Relatório Ads atribui apenas 1 das 2 vendas de R$116 (a de 09/07); esta é orgânica | R33: Orgânico
A34: 46240 | B34: L2025-T | C34: 1 | D34: Paraná Capital | E34: =IF($B34="","",INDEX(Simulador!$D$7:$D$232,MATCH($B34,Simulador!$A$7:$A$232,0))) -> 132.9 | G34: =IF(OR($B34="",$C34=""),"",$C34*E34-IF(F34="",0,F34)) -> 132.9 | H34: =IF($B34="","",INDEX(Simulador!$B$7:$B$232,MATCH($B34,Simulador!$A$7:$A$232,0))) -> Pequenos | I34: =IF(OR(H34="",$D34=""),"",INDEX(Ref_Frete!$B$2:$G$54,MATCH($D34,Ref_Frete!$A$2:$A$54,0),IF(H34="Pequenos",2,IF(H34="Medios",4,6)))) -> 24.9 | J34: 18.6 | K34: =IF(G34="","",ROUND($D$3*(G34+IF(I34="",0,I34)),2)) -> 21.3 | L34: =IF(OR($B34="",$C34=""),"",$C34*INDEX(Simulador!$F$7:$F$232,MATCH($B34,Simulador!$A$7:$A$232,0))) -> 63.11 | M34: =IF(G34="","",G34*$B$3) -> 13.29 | N34: =IF(OR(G34="",J34=""),"",G34+IF(I34="",0,I34)-J34-K34-L34-M34) -> 41.5 | O34: =IF(OR(N34="",G34=0,G34=""),"",N34/G34) -> 0.31226486 | P34: =IF(O34="","",IF(O34<0,"PREJUÍZO",IF(O34<0.1,"CRÍTICO (<10%)",IF(O34<0.15,"ABAIXO DA META (10-15%)",IF(O34<=0.2,"DENTRO DA META (15-20%)","ACIMA DA META (>20%)"))))) -> ACIMA DA META (>20%) | Q34: 1º de 2 pedidos do dia · região/frete a preencher | R34: Ads
A35: 46240 | B35: L2025-T | C35: 2 | D35: Rio Grande do Sul Capital | E35: =IF($B35="","",INDEX(Simulador!$D$7:$D$232,MATCH($B35,Simulador!$A$7:$A$232,0))) -> 132.9 | G35: =IF(OR($B35="",$C35=""),"",$C35*E35-IF(F35="",0,F35)) -> 265.8 | H35: =IF($B35="","",INDEX(Simulador!$B$7:$B$232,MATCH($B35,Simulador!$A$7:$A$232,0))) -> Pequenos | I35: =IF(OR(H35="",$D35=""),"",INDEX(Ref_Frete!$B$2:$G$54,MATCH($D35,Ref_Frete!$A$2:$A$54,0),IF(H35="Pequenos",2,IF(H35="Medios",4,6)))) -> 24.9 | J35: 25.56 | K35: =IF(G35="","",ROUND($D$3*(G35+IF(I35="",0,I35)),2)) -> 39.24 | L35: =IF(OR($B35="",$C35=""),"",$C35*INDEX(Simulador!$F$7:$F$232,MATCH($B35,Simulador!$A$7:$A$232,0))) -> 126.22 | M35: =IF(G35="","",G35*$B$3) -> 26.58 | N35: =IF(OR(G35="",J35=""),"",G35+IF(I35="",0,I35)-J35-K35-L35-M35) -> 73.1 | O35: =IF(OR(N35="",G35=0,G35=""),"",N35/G35) -> 0.27501881 | P35: =IF(O35="","",IF(O35<0,"PREJUÍZO",IF(O35<0.1,"CRÍTICO (<10%)",IF(O35<0.15,"ABAIXO DA META (10-15%)",IF(O35<=0.2,"DENTRO DA META (15-20%)","ACIMA DA META (>20%)"))))) -> ACIMA DA META (>20%) | Q35: 2º pedido — divisão 1u/2u estimada · região/frete a preencher | R35: Ads
A36: 46241 | B36: Q4070-A | C36: 4 | D36: São Paulo Capital | E36: =IF($B36="","",INDEX(Simulador!$D$7:$D$232,MATCH($B36,Simulador!$A$7:$A$232,0))) -> 1053.17 | F36: 210.63 | G36: =IF(OR($B36="",$C36=""),"",$C36*E36-IF(F36="",0,F36)) -> 4002.05 | H36: =IF($B36="","",INDEX(Simulador!$B$7:$B$232,MATCH($B36,Simulador!$A$7:$A$232,0))) -> Grandes | I36: =IF(OR(H36="",$D36=""),"",INDEX(Ref_Frete!$B$2:$G$54,MATCH($D36,Ref_Frete!$A$2:$A$54,0),IF(H36="Pequenos",2,IF(H36="Medios",4,6)))) -> 106 | J36: 300 | K36: =IF(G36="","",ROUND($D$3*(G36+IF(I36="",0,I36)),2)) -> 554.59 | L36: =IF(OR($B36="",$C36=""),"",$C36*INDEX(Simulador!$F$7:$F$232,MATCH($B36,Simulador!$A$7:$A$232,0))) -> 2320.52 | M36: =IF(G36="","",G36*$B$3) -> 400.205 | N36: =IF(OR(G36="",J36=""),"",G36+IF(I36="",0,I36)-J36-K36-L36-M36) -> 532.735 | O36: =IF(OR(N36="",G36=0,G36=""),"",N36/G36) -> 0.13311553 | P36: =IF(O36="","",IF(O36<0,"PREJUÍZO",IF(O36<0.1,"CRÍTICO (<10%)",IF(O36<0.15,"ABAIXO DA META (10-15%)",IF(O36<=0.2,"DENTRO DA META (15-20%)","ACIMA DA META (>20%)"))))) -> ABAIXO DA META (10-15%)
A37: 46242 | B37: P3060 | C37: 2 | D37: São Paulo Capital | E37: =IF($B37="","",INDEX(Simulador!$D$7:$D$232,MATCH($B37,Simulador!$A$7:$A$232,0))) -> 511.42 | G37: =IF(OR($B37="",$C37=""),"",$C37*E37-IF(F37="",0,F37)) -> 1022.84 | H37: =IF($B37="","",INDEX(Simulador!$B$7:$B$232,MATCH($B37,Simulador!$A$7:$A$232,0))) -> Medios | I37: =IF(OR(H37="",$D37=""),"",INDEX(Ref_Frete!$B$2:$G$54,MATCH($D37,Ref_Frete!$A$2:$A$54,0),IF(H37="Pequenos",2,IF(H37="Medios",4,6)))) -> 34.9 | J37: 75.23 | K37: =IF(G37="","",ROUND($D$3*(G37+IF(I37="",0,I37)),2)) -> 142.79 | L37: =IF(OR($B37="",$C37=""),"",$C37*INDEX(Simulador!$F$7:$F$232,MATCH($B37,Simulador!$A$7:$A$232,0))) -> 484.52 | M37: =IF(G37="","",G37*$B$3) -> 102.284 | N37: =IF(OR(G37="",J37=""),"",G37+IF(I37="",0,I37)-J37-K37-L37-M37) -> 252.916 | O37: =IF(OR(N37="",G37=0,G37=""),"",N37/G37) -> 0.24726839 | P37: =IF(O37="","",IF(O37<0,"PREJUÍZO",IF(O37<0.1,"CRÍTICO (<10%)",IF(O37<0.15,"ABAIXO DA META (10-15%)",IF(O37<=0.2,"DENTRO DA META (15-20%)","ACIMA DA META (>20%)"))))) -> ACIMA DA META (>20%)
A38: 46242 | B38: L1618-T | C38: 1 | D38: São Paulo Capital | E38: =IF($B38="","",INDEX(Simulador!$D$7:$D$232,MATCH($B38,Simulador!$A$7:$A$232,0))) -> 116 | G38: =IF(OR($B38="",$C38=""),"",$C38*E38-IF(F38="",0,F38)) -> 116 | H38: =IF($B38="","",INDEX(Simulador!$B$7:$B$232,MATCH($B38,Simulador!$A$7:$A$232,0))) -> Pequenos | I38: =IF(OR(H38="",$D38=""),"",INDEX(Ref_Frete!$B$2:$G$54,MATCH($D38,Ref_Frete!$A$2:$A$54,0),IF(H38="Pequenos",2,IF(H38="Medios",4,6)))) -> 12.9 | J38: 11.68 | K38: =IF(G38="","",ROUND($D$3*(G38+IF(I38="",0,I38)),2)) -> 17.4 | L38: =IF(OR($B38="",$C38=""),"",$C38*INDEX(Simulador!$F$7:$F$232,MATCH($B38,Simulador!$A$7:$A$232,0))) -> 54.47 | M38: =IF(G38="","",G38*$B$3) -> 11.6 | N38: =IF(OR(G38="",J38=""),"",G38+IF(I38="",0,I38)-J38-K38-L38-M38) -> 33.75 | O38: =IF(OR(N38="",G38=0,G38=""),"",N38/G38) -> 0.29094828 | P38: =IF(O38="","",IF(O38<0,"PREJUÍZO",IF(O38<0.1,"CRÍTICO (<10%)",IF(O38<0.15,"ABAIXO DA META (10-15%)",IF(O38<=0.2,"DENTRO DA META (15-20%)","ACIMA DA META (>20%)"))))) -> ACIMA DA META (>20%)
A39: 46245 | B39: L2460-AML | C39: 3 | D39: Alagoas Interior | E39: =IF($B39="","",INDEX(Simulador!$D$7:$D$232,MATCH($B39,Simulador!$A$7:$A$232,0))) -> 290.17 | F39: 43.53 | G39: =IF(OR($B39="",$C39=""),"",$C39*E39-IF(F39="",0,F39)) -> 826.98 | H39: =IF($B39="","",INDEX(Simulador!$B$7:$B$232,MATCH($B39,Simulador!$A$7:$A$232,0))) -> Medios | I39: =IF(OR(H39="",$D39=""),"",INDEX(Ref_Frete!$B$2:$G$54,MATCH($D39,Ref_Frete!$A$2:$A$54,0),IF(H39="Pequenos",2,IF(H39="Medios",4,6)))) -> 340 | J39: 131.91 | K39: =IF(G39="","",ROUND($D$3*(G39+IF(I39="",0,I39)),2)) -> 157.54 | L39: =IF(OR($B39="",$C39=""),"",$C39*INDEX(Simulador!$F$7:$F$232,MATCH($B39,Simulador!$A$7:$A$232,0))) -> 422.91 | M39: =IF(G39="","",G39*$B$3) -> 82.698 | N39: =IF(OR(G39="",J39=""),"",G39+IF(I39="",0,I39)-J39-K39-L39-M39) -> 371.922 | O39: =IF(OR(N39="",G39=0,G39=""),"",N39/G39) -> 0.44973518 | P39: =IF(O39="","",IF(O39<0,"PREJUÍZO",IF(O39<0.1,"CRÍTICO (<10%)",IF(O39<0.15,"ABAIXO DA META (10-15%)",IF(O39<=0.2,"DENTRO DA META (15-20%)","ACIMA DA META (>20%)"))))) -> ACIMA DA META (>20%)
A40: 46245 | B40: P4080 | C40: 1 | D40: Rio de Janeiro Capital | E40: =IF($B40="","",INDEX(Simulador!$D$7:$D$232,MATCH($B40,Simulador!$A$7:$A$232,0))) -> 1070.17 | G40: =IF(OR($B40="",$C40=""),"",$C40*E40-IF(F40="",0,F40)) -> 1070.17 | H40: =IF($B40="","",INDEX(Simulador!$B$7:$B$232,MATCH($B40,Simulador!$A$7:$A$232,0))) -> Grandes | I40: =IF(OR(H40="",$D40=""),"",INDEX(Ref_Frete!$B$2:$G$54,MATCH($D40,Ref_Frete!$A$2:$A$54,0),IF(H40="Pequenos",2,IF(H40="Medios",4,6)))) -> 178 | J40: 119.13 | K40: =IF(G40="","",ROUND($D$3*(G40+IF(I40="",0,I40)),2)) -> 168.5 | L40: =IF(OR($B40="",$C40=""),"",$C40*INDEX(Simulador!$F$7:$F$232,MATCH($B40,Simulador!$A$7:$A$232,0))) -> 553.79 | M40: =IF(G40="","",G40*$B$3) -> 107.017 | N40: =IF(OR(G40="",J40=""),"",G40+IF(I40="",0,I40)-J40-K40-L40-M40) -> 299.733 | O40: =IF(OR(N40="",G40=0,G40=""),"",N40/G40) -> 0.2800798 | P40: =IF(O40="","",IF(O40<0,"PREJUÍZO",IF(O40<0.1,"CRÍTICO (<10%)",IF(O40<0.15,"ABAIXO DA META (10-15%)",IF(O40<=0.2,"DENTRO DA META (15-20%)","ACIMA DA META (>20%)"))))) -> ACIMA DA META (>20%)
A41: 46246 | B41: PXM | C41: 2 | D41: Paraíba Capital | E41: =IF($B41="","",INDEX(Simulador!$D$7:$D$232,MATCH($B41,Simulador!$A$7:$A$232,0))) -> 203.54 | G41: =IF(OR($B41="",$C41=""),"",$C41*E41-IF(F41="",0,F41)) -> 407.08 | H41: =IF($B41="","",INDEX(Simulador!$B$7:$B$232,MATCH($B41,Simulador!$A$7:$A$232,0))) -> Pequenos | I41: =IF(OR(H41="",$D41=""),"",INDEX(Ref_Frete!$B$2:$G$54,MATCH($D41,Ref_Frete!$A$2:$A$54,0),IF(H41="Pequenos",2,IF(H41="Medios",4,6)))) -> 70 | J41: 57.33 | K41: 59.64 | L41: =IF(OR($B41="",$C41=""),"",$C41*INDEX(Simulador!$F$7:$F$232,MATCH($B41,Simulador!$A$7:$A$232,0))) -> 205.6 | M41: =IF(G41="","",G41*$B$3) -> 40.708 | N41: =IF(OR(G41="",J41=""),"",G41+IF(I41="",0,I41)-J41-K41-L41-M41) -> 113.802 | O41: =IF(OR(N41="",G41=0,G41=""),"",N41/G41) -> 0.27955684 | P41: =IF(O41="","",IF(O41<0,"PREJUÍZO",IF(O41<0.1,"CRÍTICO (<10%)",IF(O41<0.15,"ABAIXO DA META (10-15%)",IF(O41<=0.2,"DENTRO DA META (15-20%)","ACIMA DA META (>20%)"))))) -> ACIMA DA META (>20%)
A42: 46246 | B42: L2025-T | C42: 1 | D42: São Paulo Capital | E42: =IF($B42="","",INDEX(Simulador!$D$7:$D$232,MATCH($B42,Simulador!$A$7:$A$232,0))) -> 132.9 | G42: =IF(OR($B42="",$C42=""),"",$C42*E42-IF(F42="",0,F42)) -> 132.9 | H42: =IF($B42="","",INDEX(Simulador!$B$7:$B$232,MATCH($B42,Simulador!$A$7:$A$232,0))) -> Pequenos | I42: =IF(OR(H42="",$D42=""),"",INDEX(Ref_Frete!$B$2:$G$54,MATCH($D42,Ref_Frete!$A$2:$A$54,0),IF(H42="Pequenos",2,IF(H42="Medios",4,6)))) -> 12.9 | J42: 14.23 | K42: =IF(G42="","",ROUND($D$3*(G42+IF(I42="",0,I42)),2)) -> 19.68 | L42: =IF(OR($B42="",$C42=""),"",$C42*INDEX(Simulador!$F$7:$F$232,MATCH($B42,Simulador!$A$7:$A$232,0))) -> 63.11 | M42: =IF(G42="","",G42*$B$3) -> 13.29 | N42: =IF(OR(G42="",J42=""),"",G42+IF(I42="",0,I42)-J42-K42-L42-M42) -> 35.49 | O42: =IF(OR(N42="",G42=0,G42=""),"",N42/G42) -> 0.26704289 | P42: =IF(O42="","",IF(O42<0,"PREJUÍZO",IF(O42<0.1,"CRÍTICO (<10%)",IF(O42<0.15,"ABAIXO DA META (10-15%)",IF(O42<=0.2,"DENTRO DA META (15-20%)","ACIMA DA META (>20%)"))))) -> ACIMA DA META (>20%)
A43: 46248 | B43: L3085-B | C43: 1 | D43: Rio de Janeiro Interior | E43: =IF($B43="","",INDEX(Simulador!$D$7:$D$232,MATCH($B43,Simulador!$A$7:$A$232,0))) -> 642.24 | G43: =IF(OR($B43="",$C43=""),"",$C43*E43-IF(F43="",0,F43)) -> 642.24 | H43: =IF($B43="","",INDEX(Simulador!$B$7:$B$232,MATCH($B43,Simulador!$A$7:$A$232,0))) -> Medios | I43: =IF(OR(H43="",$D43=""),"",INDEX(Ref_Frete!$B$2:$G$54,MATCH($D43,Ref_Frete!$A$2:$A$54,0),IF(H43="Pequenos",2,IF(H43="Medios",4,6)))) -> 69.9 | J43: 84.49 | K43: =IF(G43="","",ROUND($D$3*(G43+IF(I43="",0,I43)),2)) -> 96.14 | L43: =IF(OR($B43="",$C43=""),"",$C43*INDEX(Simulador!$F$7:$F$232,MATCH($B43,Simulador!$A$7:$A$232,0))) -> 341.01 | M43: =IF(G43="","",G43*$B$3) -> 64.224 | N43: =IF(OR(G43="",J43=""),"",G43+IF(I43="",0,I43)-J43-K43-L43-M43) -> 126.276 | O43: =IF(OR(N43="",G43=0,G43=""),"",N43/G43) -> 0.19661809 | P43: =IF(O43="","",IF(O43<0,"PREJUÍZO",IF(O43<0.1,"CRÍTICO (<10%)",IF(O43<0.15,"ABAIXO DA META (10-15%)",IF(O43<=0.2,"DENTRO DA META (15-20%)","ACIMA DA META (>20%)"))))) -> DENTRO DA META (15-20%)
A44: 46250 | B44: L2030 | C44: 1 | D44: Pernambuco Capital | E44: =IF($B44="","",INDEX(Simulador!$D$7:$D$232,MATCH($B44,Simulador!$A$7:$A$232,0))) -> 119.22 | G44: =IF(OR($B44="",$C44=""),"",$C44*E44-IF(F44="",0,F44)) -> 119.22 | H44: =IF($B44="","",INDEX(Simulador!$B$7:$B$232,MATCH($B44,Simulador!$A$7:$A$232,0))) -> Pequenos | I44: =IF(OR(H44="",$D44=""),"",INDEX(Ref_Frete!$B$2:$G$54,MATCH($D44,Ref_Frete!$A$2:$A$54,0),IF(H44="Pequenos",2,IF(H44="Medios",4,6)))) -> 70 | J44: 19.95 | K44: =IF(G44="","",ROUND($D$3*(G44+IF(I44="",0,I44)),2)) -> 25.54 | L44: =IF(OR($B44="",$C44=""),"",$C44*INDEX(Simulador!$F$7:$F$232,MATCH($B44,Simulador!$A$7:$A$232,0))) -> 55.49 | M44: =IF(G44="","",G44*$B$3) -> 11.922 | N44: =IF(OR(G44="",J44=""),"",G44+IF(I44="",0,I44)-J44-K44-L44-M44) -> 76.318 | O44: =IF(OR(N44="",G44=0,G44=""),"",N44/G44) -> 0.64014427 | P44: =IF(O44="","",IF(O44<0,"PREJUÍZO",IF(O44<0.1,"CRÍTICO (<10%)",IF(O44<0.15,"ABAIXO DA META (10-15%)",IF(O44<=0.2,"DENTRO DA META (15-20%)","ACIMA DA META (>20%)"))))) -> ACIMA DA META (>20%)
A45: 46253 | B45: L2460-CP | C45: 1 | D45: Ceará Capital | E45: =IF($B45="","",INDEX(Simulador!$D$7:$D$232,MATCH($B45,Simulador!$A$7:$A$232,0))) -> 335.68 | G45: =IF(OR($B45="",$C45=""),"",$C45*E45-IF(F45="",0,F45)) -> 335.68 | H45: =IF($B45="","",INDEX(Simulador!$B$7:$B$232,MATCH($B45,Simulador!$A$7:$A$232,0))) -> Medios | I45: =IF(OR(H45="",$D45=""),"",INDEX(Ref_Frete!$B$2:$G$54,MATCH($D45,Ref_Frete!$A$2:$A$54,0),IF(H45="Pequenos",2,IF(H45="Medios",4,6)))) -> 158 | J45: 61.25 | K45: =IF(G45="","",ROUND($D$3*(G45+IF(I45="",0,I45)),2)) -> 66.65 | L45: =IF(OR($B45="",$C45=""),"",$C45*INDEX(Simulador!$F$7:$F$232,MATCH($B45,Simulador!$A$7:$A$232,0))) -> 172.67 | M45: =IF(G45="","",G45*$B$3) -> 33.568 | N45: =IF(OR(G45="",J45=""),"",G45+IF(I45="",0,I45)-J45-K45-L45-M45) -> 159.542 | O45: =IF(OR(N45="",G45=0,G45=""),"",N45/G45) -> 0.47528003 | P45: =IF(O45="","",IF(O45<0,"PREJUÍZO",IF(O45<0.1,"CRÍTICO (<10%)",IF(O45<0.15,"ABAIXO DA META (10-15%)",IF(O45<=0.2,"DENTRO DA META (15-20%)","ACIMA DA META (>20%)"))))) -> ACIMA DA META (>20%)
A46: 46254 | B46: Q3060-A | C46: 3 | D46: São Paulo Capital | E46: =IF($B46="","",INDEX(Simulador!$D$7:$D$232,MATCH($B46,Simulador!$A$7:$A$232,0))) -> 580.52 | F46: 87.08 | G46: =IF(OR($B46="",$C46=""),"",$C46*E46-IF(F46="",0,F46)) -> 1654.48 | H46: =IF($B46="","",INDEX(Simulador!$B$7:$B$232,MATCH($B46,Simulador!$A$7:$A$232,0))) -> Medios | I46: =IF(OR(H46="",$D46=""),"",INDEX(Ref_Frete!$B$2:$G$54,MATCH($D46,Ref_Frete!$A$2:$A$54,0),IF(H46="Pequenos",2,IF(H46="Medios",4,6)))) -> 34.9 | J46: 0 | K46: =IF(G46="","",ROUND($D$3*(G46+IF(I46="",0,I46)),2)) -> 228.07 | L46: =IF(OR($B46="",$C46=""),"",$C46*INDEX(Simulador!$F$7:$F$232,MATCH($B46,Simulador!$A$7:$A$232,0))) -> 833.25 | M46: =IF(G46="","",G46*$B$3) -> 165.448 | N46: =IF(OR(G46="",J46=""),"",G46+IF(I46="",0,I46)-J46-K46-L46-M46) -> 462.612 | O46: =IF(OR(N46="",G46=0,G46=""),"",N46/G46) -> 0.27961172 | P46: =IF(O46="","",IF(O46<0,"PREJUÍZO",IF(O46<0.1,"CRÍTICO (<10%)",IF(O46<0.15,"ABAIXO DA META (10-15%)",IF(O46<=0.2,"DENTRO DA META (15-20%)","ACIMA DA META (>20%)"))))) -> ACIMA DA META (>20%)
A47: 46260 | B47: PXM | C47: 1 | D47: Minas Gerais Capital | E47: =IF($B47="","",INDEX(Simulador!$D$7:$D$232,MATCH($B47,Simulador!$A$7:$A$232,0))) -> 203.54 | G47: =IF(OR($B47="",$C47=""),"",$C47*E47-IF(F47="",0,F47)) -> 203.54 | H47: =IF($B47="","",INDEX(Simulador!$B$7:$B$232,MATCH($B47,Simulador!$A$7:$A$232,0))) -> Pequenos | I47: =IF(OR(H47="",$D47=""),"",INDEX(Ref_Frete!$B$2:$G$54,MATCH($D47,Ref_Frete!$A$2:$A$54,0),IF(H47="Pequenos",2,IF(H47="Medios",4,6)))) -> 24.9 | J47: 18.08 | K47: =IF(G47="","",ROUND($D$3*(G47+IF(I47="",0,I47)),2)) -> 30.84 | L47: =IF(OR($B47="",$C47=""),"",$C47*INDEX(Simulador!$F$7:$F$232,MATCH($B47,Simulador!$A$7:$A$232,0))) -> 102.8 | M47: =IF(G47="","",G47*$B$3) -> 20.354 | N47: =IF(OR(G47="",J47=""),"",G47+IF(I47="",0,I47)-J47-K47-L47-M47) -> 56.366 | O47: =IF(OR(N47="",G47=0,G47=""),"",N47/G47) -> 0.27692837 | P47: =IF(O47="","",IF(O47<0,"PREJUÍZO",IF(O47<0.1,"CRÍTICO (<10%)",IF(O47<0.15,"ABAIXO DA META (10-15%)",IF(O47<=0.2,"DENTRO DA META (15-20%)","ACIMA DA META (>20%)"))))) -> ACIMA DA META (>20%)
A48: 46263 | B48: PXP | C48: 1 | D48: Minas Gerais Capital | E48: =IF($B48="","",INDEX(Simulador!$D$7:$D$232,MATCH($B48,Simulador!$A$7:$A$232,0))) -> 167.89 | G48: =IF(OR($B48="",$C48=""),"",$C48*E48-IF(F48="",0,F48)) -> 167.89 | H48: =IF($B48="","",INDEX(Simulador!$B$7:$B$232,MATCH($B48,Simulador!$A$7:$A$232,0))) -> Pequenos | I48: =IF(OR(H48="",$D48=""),"",INDEX(Ref_Frete!$B$2:$G$54,MATCH($D48,Ref_Frete!$A$2:$A$54,0),IF(H48="Pequenos",2,IF(H48="Medios",4,6)))) -> 24.9 | J48: 14.69 | K48: =IF(G48="","",ROUND($D$3*(G48+IF(I48="",0,I48)),2)) -> 26.03 | L48: =IF(OR($B48="",$C48=""),"",$C48*INDEX(Simulador!$F$7:$F$232,MATCH($B48,Simulador!$A$7:$A$232,0))) -> 84.79 | M48: =IF(G48="","",G48*$B$3) -> 16.789 | N48: =IF(OR(G48="",J48=""),"",G48+IF(I48="",0,I48)-J48-K48-L48-M48) -> 50.491 | O48: =IF(OR(N48="",G48=0,G48=""),"",N48/G48) -> 0.30073858 | P48: =IF(O48="","",IF(O48<0,"PREJUÍZO",IF(O48<0.1,"CRÍTICO (<10%)",IF(O48<0.15,"ABAIXO DA META (10-15%)",IF(O48<=0.2,"DENTRO DA META (15-20%)","ACIMA DA META (>20%)"))))) -> ACIMA DA META (>20%)
A49: 46264 | B49: L2025-T | C49: 1 | D49: Paraná Capital | E49: =IF($B49="","",INDEX(Simulador!$D$7:$D$232,MATCH($B49,Simulador!$A$7:$A$232,0))) -> 132.9 | G49: =IF(OR($B49="",$C49=""),"",$C49*E49-IF(F49="",0,F49)) -> 132.9 | H49: =IF($B49="","",INDEX(Simulador!$B$7:$B$232,MATCH($B49,Simulador!$A$7:$A$232,0))) -> Pequenos | I49: =IF(OR(H49="",$D49=""),"",INDEX(Ref_Frete!$B$2:$G$54,MATCH($D49,Ref_Frete!$A$2:$A$54,0),IF(H49="Pequenos",2,IF(H49="Medios",4,6)))) -> 24.9 | J49: 15.65 | K49: =IF(G49="","",ROUND($D$3*(G49+IF(I49="",0,I49)),2)) -> 21.3 | L49: =IF(OR($B49="",$C49=""),"",$C49*INDEX(Simulador!$F$7:$F$232,MATCH($B49,Simulador!$A$7:$A$232,0))) -> 63.11 | M49: =IF(G49="","",G49*$B$3) -> 13.29 | N49: =IF(OR(G49="",J49=""),"",G49+IF(I49="",0,I49)-J49-K49-L49-M49) -> 44.45 | O49: =IF(OR(N49="",G49=0,G49=""),"",N49/G49) -> 0.334462 | P49: =IF(O49="","",IF(O49<0,"PREJUÍZO",IF(O49<0.1,"CRÍTICO (<10%)",IF(O49<0.15,"ABAIXO DA META (10-15%)",IF(O49<=0.2,"DENTRO DA META (15-20%)","ACIMA DA META (>20%)"))))) -> ACIMA DA META (>20%)
A50: 46265 | B50: L2025-T | C50: 2 | D50: Mato Grosso do Sul Capital | E50: =IF($B50="","",INDEX(Simulador!$D$7:$D$232,MATCH($B50,Simulador!$A$7:$A$232,0))) -> 132.9 | G50: =IF(OR($B50="",$C50=""),"",$C50*E50-IF(F50="",0,F50)) -> 265.8 | H50: =IF($B50="","",INDEX(Simulador!$B$7:$B$232,MATCH($B50,Simulador!$A$7:$A$232,0))) -> Pequenos | I50: =IF(OR(H50="",$D50=""),"",INDEX(Ref_Frete!$B$2:$G$54,MATCH($D50,Ref_Frete!$A$2:$A$54,0),IF(H50="Pequenos",2,IF(H50="Medios",4,6)))) -> 43 | J50: 20.98 | K50: =IF(G50="","",ROUND($D$3*(G50+IF(I50="",0,I50)),2)) -> 41.69 | L50: =IF(OR($B50="",$C50=""),"",$C50*INDEX(Simulador!$F$7:$F$232,MATCH($B50,Simulador!$A$7:$A$232,0))) -> 126.22 | M50: =IF(G50="","",G50*$B$3) -> 26.58 | N50: =IF(OR(G50="",J50=""),"",G50+IF(I50="",0,I50)-J50-K50-L50-M50) -> 93.33 | O50: =IF(OR(N50="",G50=0,G50=""),"",N50/G50) -> 0.35112867 | P50: =IF(O50="","",IF(O50<0,"PREJUÍZO",IF(O50<0.1,"CRÍTICO (<10%)",IF(O50<0.15,"ABAIXO DA META (10-15%)",IF(O50<=0.2,"DENTRO DA META (15-20%)","ACIMA DA META (>20%)"))))) -> ACIMA DA META (>20%)
A51: 46265 | B51: L2450-AML | C51: 3 | D51: Pernambuco Capital | E51: =IF($B51="","",INDEX(Simulador!$D$7:$D$232,MATCH($B51,Simulador!$A$7:$A$232,0))) -> 259.9 | G51: =IF(OR($B51="",$C51=""),"",$C51*E51-IF(F51="",0,F51)) -> 779.7 | H51: =IF($B51="","",INDEX(Simulador!$B$7:$B$232,MATCH($B51,Simulador!$A$7:$A$232,0))) -> Pequenos | I51: =IF(OR(H51="",$D51=""),"",INDEX(Ref_Frete!$B$2:$G$54,MATCH($D51,Ref_Frete!$A$2:$A$54,0),IF(H51="Pequenos",2,IF(H51="Medios",4,6)))) -> 70 | J51: 102.9 | K51: =IF(G51="","",ROUND($D$3*(G51+IF(I51="",0,I51)),2)) -> 114.71 | L51: =IF(OR($B51="",$C51=""),"",$C51*INDEX(Simulador!$F$7:$F$232,MATCH($B51,Simulador!$A$7:$A$232,0))) -> 418.47 | M51: =IF(G51="","",G51*$B$3) -> 77.97 | N51: =IF(OR(G51="",J51=""),"",G51+IF(I51="",0,I51)-J51-K51-L51-M51) -> 135.65 | O51: =IF(OR(N51="",G51=0,G51=""),"",N51/G51) -> 0.17397717 | P51: =IF(O51="","",IF(O51<0,"PREJUÍZO",IF(O51<0.1,"CRÍTICO (<10%)",IF(O51<0.15,"ABAIXO DA META (10-15%)",IF(O51<=0.2,"DENTRO DA META (15-20%)","ACIMA DA META (>20%)"))))) -> DENTRO DA META (15-20%)
A52: 46265 | B52: L2025-T | C52: 1 | D52: Minas Gerais Capital | E52: =IF($B52="","",INDEX(Simulador!$D$7:$D$232,MATCH($B52,Simulador!$A$7:$A$232,0))) -> 132.9 | G52: =IF(OR($B52="",$C52=""),"",$C52*E52-IF(F52="",0,F52)) -> 132.9 | H52: =IF($B52="","",INDEX(Simulador!$B$7:$B$232,MATCH($B52,Simulador!$A$7:$A$232,0))) -> Pequenos | I52: =IF(OR(H52="",$D52=""),"",INDEX(Ref_Frete!$B$2:$G$54,MATCH($D52,Ref_Frete!$A$2:$A$54,0),IF(H52="Pequenos",2,IF(H52="Medios",4,6)))) -> 24.9 | J52: 14.3 | K52: =IF(G52="","",ROUND($D$3*(G52+IF(I52="",0,I52)),2)) -> 21.3 | L52: =IF(OR($B52="",$C52=""),"",$C52*INDEX(Simulador!$F$7:$F$232,MATCH($B52,Simulador!$A$7:$A$232,0))) -> 63.11 | M52: =IF(G52="","",G52*$B$3) -> 13.29 | N52: =IF(OR(G52="",J52=""),"",G52+IF(I52="",0,I52)-J52-K52-L52-M52) -> 45.8 | O52: =IF(OR(N52="",G52=0,G52=""),"",N52/G52) -> 0.34462002 | P52: =IF(O52="","",IF(O52<0,"PREJUÍZO",IF(O52<0.1,"CRÍTICO (<10%)",IF(O52<0.15,"ABAIXO DA META (10-15%)",IF(O52<=0.2,"DENTRO DA META (15-20%)","ACIMA DA META (>20%)"))))) -> ACIMA DA META (>20%)
A53: 46266 | B53: L2030-T | C53: 1 | D53: Goiás Capital | E53: =IF($B53="","",INDEX(Simulador!$D$7:$D$232,MATCH($B53,Simulador!$A$7:$A$232,0))) -> 143.13 | G53: =IF(OR($B53="",$C53=""),"",$C53*E53-IF(F53="",0,F53)) -> 143.13 | H53: =IF($B53="","",INDEX(Simulador!$B$7:$B$232,MATCH($B53,Simulador!$A$7:$A$232,0))) -> Pequenos | I53: =IF(OR(H53="",$D53=""),"",INDEX(Ref_Frete!$B$2:$G$54,MATCH($D53,Ref_Frete!$A$2:$A$54,0),IF(H53="Pequenos",2,IF(H53="Medios",4,6)))) -> 42 | J53: 19.45 | K53: =IF(G53="","",ROUND($D$3*(G53+IF(I53="",0,I53)),2)) -> 24.99 | L53: =IF(OR($B53="",$C53=""),"",$C53*INDEX(Simulador!$F$7:$F$232,MATCH($B53,Simulador!$A$7:$A$232,0))) -> 69.27 | M53: =IF(G53="","",G53*$B$3) -> 14.313 | N53: =IF(OR(G53="",J53=""),"",G53+IF(I53="",0,I53)-J53-K53-L53-M53) -> 57.107 | O53: =IF(OR(N53="",G53=0,G53=""),"",N53/G53) -> 0.39898693 | P53: =IF(O53="","",IF(O53<0,"PREJUÍZO",IF(O53<0.1,"CRÍTICO (<10%)",IF(O53<0.15,"ABAIXO DA META (10-15%)",IF(O53<=0.2,"DENTRO DA META (15-20%)","ACIMA DA META (>20%)"))))) -> ACIMA DA META (>20%)
E54: =IF($B54="","",INDEX(Simulador!$D$7:$D$232,MATCH($B54,Simulador!$A$7:$A$232,0))) | G54: =IF(OR($B54="",$C54=""),"",$C54*E54-IF(F54="",0,F54)) | H54: =IF($B54="","",INDEX(Simulador!$B$7:$B$232,MATCH($B54,Simulador!$A$7:$A$232,0))) | I54: =IF(OR(H54="",$D54=""),"",INDEX(Ref_Frete!$B$2:$G$54,MATCH($D54,Ref_Frete!$A$2:$A$54,0),IF(H54="Pequenos",2,IF(H54="Medios",4,6)))) | K54: =IF(G54="","",ROUND($D$3*(G54+IF(I54="",0,I54)),2)) | L54: =IF(OR($B54="",$C54=""),"",$C54*INDEX(Simulador!$F$7:$F$232,MATCH($B54,Simulador!$A$7:$A$232,0))) | M54: =IF(G54="","",G54*$B$3) | N54: =IF(OR(G54="",J54=""),"",G54+IF(I54="",0,I54)-J54-K54-L54-M54) | O54: =IF(OR(N54="",G54=0,G54=""),"",N54/G54) | P54: =IF(O54="","",IF(O54<0,"PREJUÍZO",IF(O54<0.1,"CRÍTICO (<10%)",IF(O54<0.15,"ABAIXO DA META (10-15%)",IF(O54<=0.2,"DENTRO DA META (15-20%)","ACIMA DA META (>20%)")))))
E55: =IF($B55="","",INDEX(Simulador!$D$7:$D$232,MATCH($B55,Simulador!$A$7:$A$232,0))) | G55: =IF(OR($B55="",$C55=""),"",$C55*E55-IF(F55="",0,F55)) | H55: =IF($B55="","",INDEX(Simulador!$B$7:$B$232,MATCH($B55,Simulador!$A$7:$A$232,0))) | I55: =IF(OR(H55="",$D55=""),"",INDEX(Ref_Frete!$B$2:$G$54,MATCH($D55,Ref_Frete!$A$2:$A$54,0),IF(H55="Pequenos",2,IF(H55="Medios",4,6)))) | K55: =IF(G55="","",ROUND($D$3*(G55+IF(I55="",0,I55)),2)) | L55: =IF(OR($B55="",$C55=""),"",$C55*INDEX(Simulador!$F$7:$F$232,MATCH($B55,Simulador!$A$7:$A$232,0))) | M55: =IF(G55="","",G55*$B$3) | N55: =IF(OR(G55="",J55=""),"",G55+IF(I55="",0,I55)-J55-K55-L55-M55) | O55: =IF(OR(N55="",G55=0,G55=""),"",N55/G55) | P55: =IF(O55="","",IF(O55<0,"PREJUÍZO",IF(O55<0.1,"CRÍTICO (<10%)",IF(O55<0.15,"ABAIXO DA META (10-15%)",IF(O55<=0.2,"DENTRO DA META (15-20%)","ACIMA DA META (>20%)")))))
E56: =IF($B56="","",INDEX(Simulador!$D$7:$D$232,MATCH($B56,Simulador!$A$7:$A$232,0))) | G56: =IF(OR($B56="",$C56=""),"",$C56*E56-IF(F56="",0,F56)) | H56: =IF($B56="","",INDEX(Simulador!$B$7:$B$232,MATCH($B56,Simulador!$A$7:$A$232,0))) | I56: =IF(OR(H56="",$D56=""),"",INDEX(Ref_Frete!$B$2:$G$54,MATCH($D56,Ref_Frete!$A$2:$A$54,0),IF(H56="Pequenos",2,IF(H56="Medios",4,6)))) | K56: =IF(G56="","",ROUND($D$3*(G56+IF(I56="",0,I56)),2)) | L56: =IF(OR($B56="",$C56=""),"",$C56*INDEX(Simulador!$F$7:$F$232,MATCH($B56,Simulador!$A$7:$A$232,0))) | M56: =IF(G56="","",G56*$B$3) | N56: =IF(OR(G56="",J56=""),"",G56+IF(I56="",0,I56)-J56-K56-L56-M56) | O56: =IF(OR(N56="",G56=0,G56=""),"",N56/G56) | P56: =IF(O56="","",IF(O56<0,"PREJUÍZO",IF(O56<0.1,"CRÍTICO (<10%)",IF(O56<0.15,"ABAIXO DA META (10-15%)",IF(O56<=0.2,"DENTRO DA META (15-20%)","ACIMA DA META (>20%)")))))
E57: =IF($B57="","",INDEX(Simulador!$D$7:$D$232,MATCH($B57,Simulador!$A$7:$A$232,0))) | G57: =IF(OR($B57="",$C57=""),"",$C57*E57-IF(F57="",0,F57)) | H57: =IF($B57="","",INDEX(Simulador!$B$7:$B$232,MATCH($B57,Simulador!$A$7:$A$232,0))) | I57: =IF(OR(H57="",$D57=""),"",INDEX(Ref_Frete!$B$2:$G$54,MATCH($D57,Ref_Frete!$A$2:$A$54,0),IF(H57="Pequenos",2,IF(H57="Medios",4,6)))) | K57: =IF(G57="","",ROUND($D$3*(G57+IF(I57="",0,I57)),2)) | L57: =IF(OR($B57="",$C57=""),"",$C57*INDEX(Simulador!$F$7:$F$232,MATCH($B57,Simulador!$A$7:$A$232,0))) | M57: =IF(G57="","",G57*$B$3) | N57: =IF(OR(G57="",J57=""),"",G57+IF(I57="",0,I57)-J57-K57-L57-M57) | O57: =IF(OR(N57="",G57=0,G57=""),"",N57/G57) | P57: =IF(O57="","",IF(O57<0,"PREJUÍZO",IF(O57<0.1,"CRÍTICO (<10%)",IF(O57<0.15,"ABAIXO DA META (10-15%)",IF(O57<=0.2,"DENTRO DA META (15-20%)","ACIMA DA META (>20%)")))))
E58: =IF($B58="","",INDEX(Simulador!$D$7:$D$232,MATCH($B58,Simulador!$A$7:$A$232,0))) | G58: =IF(OR($B58="",$C58=""),"",$C58*E58-IF(F58="",0,F58)) | H58: =IF($B58="","",INDEX(Simulador!$B$7:$B$232,MATCH($B58,Simulador!$A$7:$A$232,0))) | I58: =IF(OR(H58="",$D58=""),"",INDEX(Ref_Frete!$B$2:$G$54,MATCH($D58,Ref_Frete!$A$2:$A$54,0),IF(H58="Pequenos",2,IF(H58="Medios",4,6)))) | K58: =IF(G58="","",ROUND($D$3*(G58+IF(I58="",0,I58)),2)) | L58: =IF(OR($B58="",$C58=""),"",$C58*INDEX(Simulador!$F$7:$F$232,MATCH($B58,Simulador!$A$7:$A$232,0))) | M58: =IF(G58="","",G58*$B$3) | N58: =IF(OR(G58="",J58=""),"",G58+IF(I58="",0,I58)-J58-K58-L58-M58) | O58: =IF(OR(N58="",G58=0,G58=""),"",N58/G58) | P58: =IF(O58="","",IF(O58<0,"PREJUÍZO",IF(O58<0.1,"CRÍTICO (<10%)",IF(O58<0.15,"ABAIXO DA META (10-15%)",IF(O58<=0.2,"DENTRO DA META (15-20%)","ACIMA DA META (>20%)")))))
E59: =IF($B59="","",INDEX(Simulador!$D$7:$D$232,MATCH($B59,Simulador!$A$7:$A$232,0))) | G59: =IF(OR($B59="",$C59=""),"",$C59*E59-IF(F59="",0,F59)) | H59: =IF($B59="","",INDEX(Simulador!$B$7:$B$232,MATCH($B59,Simulador!$A$7:$A$232,0))) | I59: =IF(OR(H59="",$D59=""),"",INDEX(Ref_Frete!$B$2:$G$54,MATCH($D59,Ref_Frete!$A$2:$A$54,0),IF(H59="Pequenos",2,IF(H59="Medios",4,6)))) | K59: =IF(G59="","",ROUND($D$3*(G59+IF(I59="",0,I59)),2)) | L59: =IF(OR($B59="",$C59=""),"",$C59*INDEX(Simulador!$F$7:$F$232,MATCH($B59,Simulador!$A$7:$A$232,0))) | M59: =IF(G59="","",G59*$B$3) | N59: =IF(OR(G59="",J59=""),"",G59+IF(I59="",0,I59)-J59-K59-L59-M59) | O59: =IF(OR(N59="",G59=0,G59=""),"",N59/G59) | P59: =IF(O59="","",IF(O59<0,"PREJUÍZO",IF(O59<0.1,"CRÍTICO (<10%)",IF(O59<0.15,"ABAIXO DA META (10-15%)",IF(O59<=0.2,"DENTRO DA META (15-20%)","ACIMA DA META (>20%)")))))
E60: =IF($B60="","",INDEX(Simulador!$D$7:$D$232,MATCH($B60,Simulador!$A$7:$A$232,0))) | G60: =IF(OR($B60="",$C60=""),"",$C60*E60-IF(F60="",0,F60)) | H60: =IF($B60="","",INDEX(Simulador!$B$7:$B$232,MATCH($B60,Simulador!$A$7:$A$232,0))) | I60: =IF(OR(H60="",$D60=""),"",INDEX(Ref_Frete!$B$2:$G$54,MATCH($D60,Ref_Frete!$A$2:$A$54,0),IF(H60="Pequenos",2,IF(H60="Medios",4,6)))) | K60: =IF(G60="","",ROUND($D$3*(G60+IF(I60="",0,I60)),2)) | L60: =IF(OR($B60="",$C60=""),"",$C60*INDEX(Simulador!$F$7:$F$232,MATCH($B60,Simulador!$A$7:$A$232,0))) | M60: =IF(G60="","",G60*$B$3) | N60: =IF(OR(G60="",J60=""),"",G60+IF(I60="",0,I60)-J60-K60-L60-M60) | O60: =IF(OR(N60="",G60=0,G60=""),"",N60/G60) | P60: =IF(O60="","",IF(O60<0,"PREJUÍZO",IF(O60<0.1,"CRÍTICO (<10%)",IF(O60<0.15,"ABAIXO DA META (10-15%)",IF(O60<=0.2,"DENTRO DA META (15-20%)","ACIMA DA META (>20%)")))))
E61: =IF($B61="","",INDEX(Simulador!$D$7:$D$232,MATCH($B61,Simulador!$A$7:$A$232,0))) | G61: =IF(OR($B61="",$C61=""),"",$C61*E61-IF(F61="",0,F61)) | H61: =IF($B61="","",INDEX(Simulador!$B$7:$B$232,MATCH($B61,Simulador!$A$7:$A$232,0))) | I61: =IF(OR(H61="",$D61=""),"",INDEX(Ref_Frete!$B$2:$G$54,MATCH($D61,Ref_Frete!$A$2:$A$54,0),IF(H61="Pequenos",2,IF(H61="Medios",4,6)))) | K61: =IF(G61="","",ROUND($D$3*(G61+IF(I61="",0,I61)),2)) | L61: =IF(OR($B61="",$C61=""),"",$C61*INDEX(Simulador!$F$7:$F$232,MATCH($B61,Simulador!$A$7:$A$232,0))) | M61: =IF(G61="","",G61*$B$3) | N61: =IF(OR(G61="",J61=""),"",G61+IF(I61="",0,I61)-J61-K61-L61-M61) | O61: =IF(OR(N61="",G61=0,G61=""),"",N61/G61) | P61: =IF(O61="","",IF(O61<0,"PREJUÍZO",IF(O61<0.1,"CRÍTICO (<10%)",IF(O61<0.15,"ABAIXO DA META (10-15%)",IF(O61<=0.2,"DENTRO DA META (15-20%)","ACIMA DA META (>20%)")))))
E62: =IF($B62="","",INDEX(Simulador!$D$7:$D$232,MATCH($B62,Simulador!$A$7:$A$232,0))) | G62: =IF(OR($B62="",$C62=""),"",$C62*E62-IF(F62="",0,F62)) | H62: =IF($B62="","",INDEX(Simulador!$B$7:$B$232,MATCH($B62,Simulador!$A$7:$A$232,0))) | I62: =IF(OR(H62="",$D62=""),"",INDEX(Ref_Frete!$B$2:$G$54,MATCH($D62,Ref_Frete!$A$2:$A$54,0),IF(H62="Pequenos",2,IF(H62="Medios",4,6)))) | K62: =IF(G62="","",ROUND($D$3*(G62+IF(I62="",0,I62)),2)) | L62: =IF(OR($B62="",$C62=""),"",$C62*INDEX(Simulador!$F$7:$F$232,MATCH($B62,Simulador!$A$7:$A$232,0))) | M62: =IF(G62="","",G62*$B$3) | N62: =IF(OR(G62="",J62=""),"",G62+IF(I62="",0,I62)-J62-K62-L62-M62) | O62: =IF(OR(N62="",G62=0,G62=""),"",N62/G62) | P62: =IF(O62="","",IF(O62<0,"PREJUÍZO",IF(O62<0.1,"CRÍTICO (<10%)",IF(O62<0.15,"ABAIXO DA META (10-15%)",IF(O62<=0.2,"DENTRO DA META (15-20%)","ACIMA DA META (>20%)")))))
E63: =IF($B63="","",INDEX(Simulador!$D$7:$D$232,MATCH($B63,Simulador!$A$7:$A$232,0))) | G63: =IF(OR($B63="",$C63=""),"",$C63*E63-IF(F63="",0,F63)) | H63: =IF($B63="","",INDEX(Simulador!$B$7:$B$232,MATCH($B63,Simulador!$A$7:$A$232,0))) | I63: =IF(OR(H63="",$D63=""),"",INDEX(Ref_Frete!$B$2:$G$54,MATCH($D63,Ref_Frete!$A$2:$A$54,0),IF(H63="Pequenos",2,IF(H63="Medios",4,6)))) | K63: =IF(G63="","",ROUND($D$3*(G63+IF(I63="",0,I63)),2)) | L63: =IF(OR($B63="",$C63=""),"",$C63*INDEX(Simulador!$F$7:$F$232,MATCH($B63,Simulador!$A$7:$A$232,0))) | M63: =IF(G63="","",G63*$B$3) | N63: =IF(OR(G63="",J63=""),"",G63+IF(I63="",0,I63)-J63-K63-L63-M63) | O63: =IF(OR(N63="",G63=0,G63=""),"",N63/G63) | P63: =IF(O63="","",IF(O63<0,"PREJUÍZO",IF(O63<0.1,"CRÍTICO (<10%)",IF(O63<0.15,"ABAIXO DA META (10-15%)",IF(O63<=0.2,"DENTRO DA META (15-20%)","ACIMA DA META (>20%)")))))
E64: =IF($B64="","",INDEX(Simulador!$D$7:$D$232,MATCH($B64,Simulador!$A$7:$A$232,0))) | G64: =IF(OR($B64="",$C64=""),"",$C64*E64-IF(F64="",0,F64)) | H64: =IF($B64="","",INDEX(Simulador!$B$7:$B$232,MATCH($B64,Simulador!$A$7:$A$232,0))) | I64: =IF(OR(H64="",$D64=""),"",INDEX(Ref_Frete!$B$2:$G$54,MATCH($D64,Ref_Frete!$A$2:$A$54,0),IF(H64="Pequenos",2,IF(H64="Medios",4,6)))) | K64: =IF(G64="","",ROUND($D$3*(G64+IF(I64="",0,I64)),2)) | L64: =IF(OR($B64="",$C64=""),"",$C64*INDEX(Simulador!$F$7:$F$232,MATCH($B64,Simulador!$A$7:$A$232,0))) | M64: =IF(G64="","",G64*$B$3) | N64: =IF(OR(G64="",J64=""),"",G64+IF(I64="",0,I64)-J64-K64-L64-M64) | O64: =IF(OR(N64="",G64=0,G64=""),"",N64/G64) | P64: =IF(O64="","",IF(O64<0,"PREJUÍZO",IF(O64<0.1,"CRÍTICO (<10%)",IF(O64<0.15,"ABAIXO DA META (10-15%)",IF(O64<=0.2,"DENTRO DA META (15-20%)","ACIMA DA META (>20%)")))))
E65: =IF($B65="","",INDEX(Simulador!$D$7:$D$232,MATCH($B65,Simulador!$A$7:$A$232,0))) | G65: =IF(OR($B65="",$C65=""),"",$C65*E65-IF(F65="",0,F65)) | H65: =IF($B65="","",INDEX(Simulador!$B$7:$B$232,MATCH($B65,Simulador!$A$7:$A$232,0))) | I65: =IF(OR(H65="",$D65=""),"",INDEX(Ref_Frete!$B$2:$G$54,MATCH($D65,Ref_Frete!$A$2:$A$54,0),IF(H65="Pequenos",2,IF(H65="Medios",4,6)))) | K65: =IF(G65="","",ROUND($D$3*(G65+IF(I65="",0,I65)),2)) | L65: =IF(OR($B65="",$C65=""),"",$C65*INDEX(Simulador!$F$7:$F$232,MATCH($B65,Simulador!$A$7:$A$232,0))) | M65: =IF(G65="","",G65*$B$3) | N65: =IF(OR(G65="",J65=""),"",G65+IF(I65="",0,I65)-J65-K65-L65-M65) | O65: =IF(OR(N65="",G65=0,G65=""),"",N65/G65) | P65: =IF(O65="","",IF(O65<0,"PREJUÍZO",IF(O65<0.1,"CRÍTICO (<10%)",IF(O65<0.15,"ABAIXO DA META (10-15%)",IF(O65<=0.2,"DENTRO DA META (15-20%)","ACIMA DA META (>20%)")))))
... E107: =IF($B107="","",INDEX(Simulador!$D$7:$D$232,MATCH($B107,Simulador!$A$7:$A$232,0))) | G107: =IF(OR($B107="",$C107=""),"",$C107*E107-IF(F107="",0,F107)) | H107: =IF($B107="","",INDEX(Simulador!$B$7:$B$232,MATCH($B107,Simulador!$A$7:$A$232,0))) | I107: =IF(OR(H107="",$D107=""),"",INDEX(Ref_Frete!$B$2:$G$54,MATCH($D107,Ref_Frete!$A$2:$A$54,0),IF(H107="Pequenos",2,IF(H107="Medios",4,6)))) | K107: =IF(G107="","",ROUND($D$3*(G107+IF(I107="",0,I107)),2)) | L107: =IF(OR($B107="",$C107=""),"",$C107*INDEX(Simulador!$F$7:$F$232,MATCH($B107,Simulador!$A$7:$A$232,0))) | M107: =IF(G107="","",G107*$B$3) | N107: =IF(OR(G107="",J107=""),"",G107+IF(I107="",0,I107)-J107-K107-L107-M107) | O107: =IF(OR(N107="",G107=0,G107=""),"",N107/G107) | P107: =IF(O107="","",IF(O107<0,"PREJUÍZO",IF(O107<0.1,"CRÍTICO (<10%)",IF(O107<0.15,"ABAIXO DA META (10-15%)",IF(O107<=0.2,"DENTRO DA META (15-20%)","ACIMA DA META (>20%)")))))
A108: TOTAIS | G108: =SUM(G6:G107) -> 21799.32 | K108: =SUM(K6:K107) -> 3305.76 | L108: =SUM(L6:L107) -> 11461.51 | M108: =SUM(M6:M107) -> 2179.932 | N108: =SUM(N6:N107) -> 5470.458 | O108: =IF(G108=0,"",N108/G108) -> 0.25094627

Sheet Livro_Vendas
A1: LIVRO DE VENDAS — 08/06 a 31/08 · Orgânico vs Ads
A2: Fonte: painel de vendas (total do site, por dia de PEDIDO) × relatório de produtos anunciados (vendas ATRIBUÍDAS ao Ads, por clique). Atribuição tem zona cinzenta: pedido com clique em anúncio até 14 dias antes conta como Ads. Datas de clique e pedido podem divergir.
A4: Data | B4: Valor (R$) | C4: Unid. | D4: SKU(s) | E4: Origem | F4: Campanha / termo (quando conhecido)
A5: 13/06 | B5: 96.63 | C5: 1 | D5: L1618-A | E5: Orgânico
A6: 18/06 | B6: 335.68 | C6: 1 | D6: L2460-CP | E6: Ads | F6: auto — "coletor de pilhas"
A7: 20/06 | B7: 532.93 | C7: 1 | D7: Q3060-B | E7: Orgânico
A8: 21/06 | B8: 616.18 | C8: 1 | D8: P3070 | E8: Ads | F8: PI — ASIN B0G9B9RCMF
A9: 23/06 | B9: 203.16 | C9: 1 | D9: L2025 (rel.) / L2450-AML (registro) | E9: Ads | F9: auto — "lixeira banheiro 30l sem tampa inox" · conferir SKU
A10: 24/06 | B10: 248.75 | C10: 1 | D10: PG2460 | E10: Ads | F10: auto — "suporte para guarda chuva"
A11: 26/06 | B11: 335.78 | C11: 2 | D11: PXP ×2 | E11: Orgânico | F11: órfã identificada: 2 unidades do PXP
A12: 29/06 | B12: 942.98 | C12: 2 | D12: SP-01 + P3050 | E12: Ads | F12: PIs — B0C5JTQBXF / B0CYWMQ93Y
A13: 01/07 | B13: 674.62 | C13: 1 | D13: EGC | E13: Orgânico
A14: 02/07 | B14: 371.43 | C14: 2 | D14: PXP + PXM | E14: Ads | F14: auto PXP + PXM
A15: 03/07 | B15: 319.58 | C15: 1 | D15: L2450--CZ | E15: Orgânico | F15: cinzeiro vendendo sozinho!
A16: 04/07 | B16: 203.54 | C16: 1 | D16: PXM | E16: Orgânico | F16: provável (sem atribuição p/ esta data)
A17: 08/07 | B17: 610.62 | C17: 3 | D17: PXM ×3 | E17: Ads | F17: auto — "suporte para extintor de 6 kg"
A18: 09/07 | B18: 583.67 | C18: 2 | D18: L1618-T + P3050 | E18: Ads | F18: "lixeira pia" (48% ACOS) + 2ª venda P3050
A19: 20/07 | B19: 203.54 | C19: 1 | D19: PXM | E19: Ads | F19: PI PXM
A20: 21/07 | B20: 167.89 | C20: 1 | D20: PXP | E20: Ads | F20: auto
A21: 22/07 | B21: 497.34 | C21: 4 | D21: L2025-B + L1623-B + 2× L2030 (Franca) | E21: Ads | F21: PI L2030-B — ASIN B0DZV82N4P
A22: 25/07 | B22: 153.72 | C22: 1 | D22: L2030-B (DF) | E22: Orgânico | F22: margem 43,7% registrada
A23: 30/07 | B23: 674.62 | C23: 1 | D23: EGC (RS) | E23: Orgânico | F23: 2ª venda orgânica do EGC
A24: 31/07 | B24: 396.06 | C24: 2 | D24: L2425-B ×2 | E24: Ads | F24: atribuída pelo relatório (você supunha orgânica) — conferir
A25: 02/08 | B25: 543.85 | C25: 1 | D25: L3070-B | E25: Ads | F25: Geral DBA — mineradora
... A29: 07/08 | B29: 4212.68 | C29: 4 | D29: Q4070-A ×4 | E29: Orgânico | F29: maior venda do mês — resgate promo 5% (receita real R$ 4.002,05 no Registro)
A30: 08/08 | B30: 1022.84 | C30: 2 | D30: P3060 ×2 | E30: Orgânico
A31: 08/08 | B31: 116 | C31: 1 | D31: L1618-T | E31: Orgânico | F31: 3ª venda de 116
A32: 11/08 | B32: 870.51 | C32: 3 | D32: L2460-AML ×3 | E32: Orgânico | F32: resgate promo 5% (receita real R$ 826,98)
A33: 11/08 | B33: 1070.17 | C33: 1 | D33: P4080 | E33: Orgânico | F33: 1ª venda do P4080
A34: 12/08 | B34: 407.08 | C34: 2 | D34: PXM ×2 | E34: Orgânico | F34: sem atribuição nos 2 relatórios (Extintor atribui só a de 26/08)
A35: 12/08 | B35: 132.9 | C35: 1 | D35: L2025-T | E35: Ads | F35: Geral DBA
A36: 14/08 | B36: 642.24 | C36: 1 | D36: L3085-B | E36: Orgânico
A37: 16/08 | B37: 119.22 | C37: 1 | D37: L2030 | E37: Orgânico
A38: 19/08 | B38: 335.68 | C38: 1 | D38: L2460-CP | E38: Ads | F38: Geral DBA
A39: 20/08 | B39: 1741.56 | C39: 3 | D39: Q3060-A ×3 | E39: Ads | F39: Geral DBA — halo via Q2430-A (B0H7XXH5GV) CONFIRMADO; receita real R$ 1.654,48
A40: 26/08 | B40: 203.54 | C40: 1 | D40: PXM | E40: Ads | F40: Manual Extintor — exata
A41: 29/08 | B41: 167.89 | C41: 1 | D41: PXP | E41: Orgânico
A42: 30/08 | B42: 132.9 | C42: 1 | D42: L2025-T | E42: Ads | F42: Geral DBA
A43: 31/08 | B43: 265.8 | C43: 2 | D43: L2025-T ×2 | E43: Ads | F43: 6B (piloto dinâmico) — 1ª venda da manual 6B
A44: 31/08 | B44: 779.7 | C44: 3 | D44: L2450-AML ×3 | E44: Orgânico | F44: resgate promo 5%; preço atual 259,90
A45: 31/08 | B45: 132.9 | C45: 1 | D45: L2025-T | E45: Ads | F45: Geral DBA
A47: RESUMO MENSAL
A48: Mês | B48: Total (R$) | C48: Ads (R$) | D48: Orgânico (R$) | E48: % Orgânico
A49: Junho (08-30) | B49: 3312.09 | C49: 2346.75 | D49: 965.34 | E49: 0.29145947
A50: Julho | B50: 4856.63 | C50: 2830.55 | D50: 2026.08 | E50: 0.41717817
A51: Agosto | B51: 13915.83 | C51: 4391.5 | D51: 9524.33 | E51: 0.68442414
A52: TOTAL | B52: 22084.55 | C52: 9568.8 | D52: 12515.75 | E52: 0.56671972
A54: Nota de reconciliação (até 06/08): mapeamento pedido a pedido soma R$ 6.623,52 em Ads vs R$ 6.455,63 do relatório (diferença de ~R$ 168 = zona cinzenta do par PXP+PXM de 02/07). Fechamento Agosto (08/09/26): valores a preço de tabela (convenção do painel); 3 pedidos com promo 5% somam −R$ 341,24 vs receita real (Registro_Vendas preserva a real). Atribuição cruzada com Produtos Anunciados 25/07–23/08 + 08/08–06/09; sanidade fechada com Campaign export (Geral 9 compras = R$ 3.561,62, bijeção exata). Halo Q2430-A→Q3060-A confirmado. Atribuição valoriza a preço de tabela (MEMORIA 31/08).

Sheet Novo_Produto
A1: CALCULADORA DE PRODUTO NOVO — classe de frete + preço mínimo para a margem alvo
A2: Preencha as colunas AZUIS. A planilha calcula: peso cubado, classe de frete, fretes da região escolhida e o PREÇO SUGERIDO para bater a margem. Depois teste um preço à sua escolha na coluna P.
A3: Imposto (%): | B3: 0.1 | C3: Tarifa Amazon estimada (%): | E3: 0.135 | F3: ← média real do catálogo (11,7-14,8%)
A4: Fronteiras de classe validadas por cotação (17/07): Pequenos ≤ 5,5 kg cubado · Médios ≤ 18 kg · Grandes > 18 kg (ex.: caixa 25×25×50 = 5,21 → Pequeno; 42×42×60 = 17,64 → Médio).
A5: Nome / SKU | B5: Compr. caixa (cm) | C5: Larg. (cm) | D5: Alt. (cm) | E5: Peso real (kg) | F5: Peso cubado (kg) | G5: Peso considerado (kg) | H5: Classe de frete | I5: Região de referência | J5: Custo do produto (R$) | K5: Margem alvo (%) | L5: Frete cobrado (R$) | M5: Frete real (R$) | N5: PREÇO SUGERIDO (R$) | P5: Preço escolhido (R$) | Q5: Margem no preço escolhido | R5: Veredito
A6: Lixeira nova 25x40 (exemplo) | B6: 45 | C6: 26 | D6: 26 | E6: 3 | F6: =IF(OR(B6="",C6="",D6=""),"",ROUND(B6*C6*D6/6000,2)) -> 5.07 | G6: =IF(F6="","",MAX(F6,IF(E6="",0,E6))) -> 5.07 | H6: =IF(G6="","",IF(G6<=5.5,"Pequenos",IF(G6<=18,"Medios","Grandes"))) -> Pequenos | I6: São Paulo Interior | J6: 80 | K6: 0.175 | L6: =IF(OR(H6="",I6=""),"",INDEX(Ref_Frete!$B$2:$G$54,MATCH(I6,Ref_Frete!$A$2:$A$54,0),IF(H6="Pequenos",2,IF(H6="Medios",4,6)))) -> 16.9 | M6: =IF(OR(H6="",I6=""),"",INDEX(Ref_Frete!$B$2:$G$54,MATCH(I6,Ref_Frete!$A$2:$A$54,0),IF(H6="Pequenos",1,IF(H6="Medios",3,5)))) -> 30 | N6: =IF(OR(J6="",K6="",L6="",M6=""),"",ROUND((J6+M6-L6*(1-$E$3))/(1-$E$3-$B$3-K6),2)) -> 161.66 | P6: 220 | Q6: =IF(OR(P6="",J6="",L6="",M6=""),"",(P6-$E$3*(P6+L6)-J6-$B$3*P6+L6-M6)/P6) -> 0.33144773 | R6: =IF(Q6="","",IF(Q6<0,"PREJUÍZO",IF(Q6<0.1,"CRÍTICO (<10%)",IF(Q6<0.15,"ABAIXO DA META (10-15%)",IF(Q6<=0.2,"DENTRO DA META (15-20%)","ACIMA DA META (>20%)"))))) -> ACIMA DA META (>20%)
H7: =IF(G7="","",IF(G7<=5.5,"Pequenos",IF(G7<=18,"Medios","Grandes")))
H8: =IF(G8="","",IF(G8<=5.5,"Pequenos",IF(G8<=18,"Medios","Grandes")))
H9: =IF(G9="","",IF(G9<=5.5,"Pequenos",IF(G9<=18,"Medios","Grandes")))
H10: =IF(G10="","",IF(G10<=5.5,"Pequenos",IF(G10<=18,"Medios","Grandes")))
H11: =IF(G11="","",IF(G11<=5.5,"Pequenos",IF(G11<=18,"Medios","Grandes")))
H12: =IF(G12="","",IF(G12<=5.5,"Pequenos",IF(G12<=18,"Medios","Grandes")))
H13: =IF(G13="","",IF(G13<=5.5,"Pequenos",IF(G13<=18,"Medios","Grandes")))
H14: =IF(G14="","",IF(G14<=5.5,"Pequenos",IF(G14<=18,"Medios","Grandes")))
H15: =IF(G15="","",IF(G15<=5.5,"Pequenos",IF(G15<=18,"Medios","Grandes")))
H16: =IF(G16="","",IF(G16<=5.5,"Pequenos",IF(G16<=18,"Medios","Grandes")))
H17: =IF(G17="","",IF(G17<=5.5,"Pequenos",IF(G17<=18,"Medios","Grandes")))
H18: =IF(G18="","",IF(G18<=5.5,"Pequenos",IF(G18<=18,"Medios","Grandes")))
F19: =IF(OR(B19="",C19="",D19=""),"",ROUND(B19*C19*D19/6000,2)) | G19: =IF(F19="","",MAX(F19,IF(E19="",0,E19))) | H19: =IF(G19="","",IF(G19<=5.5,"Pequenos",IF(G19<=18,"Medios","Grandes"))) | L19: =IF(OR(H19="",I19=""),"",INDEX(Ref_Frete!$B$2:$G$54,MATCH(I19,Ref_Frete!$A$2:$A$54,0),IF(H19="Pequenos",2,IF(H19="Medios",4,6)))) | M19: =IF(OR(H19="",I19=""),"",INDEX(Ref_Frete!$B$2:$G$54,MATCH(I19,Ref_Frete!$A$2:$A$54,0),IF(H19="Pequenos",1,IF(H19="Medios",3,5)))) | N19: =IF(OR(J19="",K19="",L19="",M19=""),"",ROUND((J19+M19-L19*(1-$E$3))/(1-$E$3-$B$3-K19),2)) | Q19: =IF(OR(P19="",J19="",L19="",M19=""),"",(P19-$E$3*(P19+L19)-J19-$B$3*P19+L19-M19)/P19) | R19: =IF(Q19="","",IF(Q19<0,"PREJUÍZO",IF(Q19<0.1,"CRÍTICO (<10%)",IF(Q19<0.15,"ABAIXO DA META (10-15%)",IF(Q19<=0.2,"DENTRO DA META (15-20%)","ACIMA DA META (>20%)")))))
F20: =IF(OR(B20="",C20="",D20=""),"",ROUND(B20*C20*D20/6000,2)) | G20: =IF(F20="","",MAX(F20,IF(E20="",0,E20))) | H20: =IF(G20="","",IF(G20<=5.5,"Pequenos",IF(G20<=18,"Medios","Grandes"))) | L20: =IF(OR(H20="",I20=""),"",INDEX(Ref_Frete!$B$2:$G$54,MATCH(I20,Ref_Frete!$A$2:$A$54,0),IF(H20="Pequenos",2,IF(H20="Medios",4,6)))) | M20: =IF(OR(H20="",I20=""),"",INDEX(Ref_Frete!$B$2:$G$54,MATCH(I20,Ref_Frete!$A$2:$A$54,0),IF(H20="Pequenos",1,IF(H20="Medios",3,5)))) | N20: =IF(OR(J20="",K20="",L20="",M20=""),"",ROUND((J20+M20-L20*(1-$E$3))/(1-$E$3-$B$3-K20),2)) | Q20: =IF(OR(P20="",J20="",L20="",M20=""),"",(P20-$E$3*(P20+L20)-J20-$B$3*P20+L20-M20)/P20) | R20: =IF(Q20="","",IF(Q20<0,"PREJUÍZO",IF(Q20<0.1,"CRÍTICO (<10%)",IF(Q20<0.15,"ABAIXO DA META (10-15%)",IF(Q20<=0.2,"DENTRO DA META (15-20%)","ACIMA DA META (>20%)")))))
F21: =IF(OR(B21="",C21="",D21=""),"",ROUND(B21*C21*D21/6000,2)) | G21: =IF(F21="","",MAX(F21,IF(E21="",0,E21))) | H21: =IF(G21="","",IF(G21<=5.5,"Pequenos",IF(G21<=18,"Medios","Grandes"))) | L21: =IF(OR(H21="",I21=""),"",INDEX(Ref_Frete!$B$2:$G$54,MATCH(I21,Ref_Frete!$A$2:$A$54,0),IF(H21="Pequenos",2,IF(H21="Medios",4,6)))) | M21: =IF(OR(H21="",I21=""),"",INDEX(Ref_Frete!$B$2:$G$54,MATCH(I21,Ref_Frete!$A$2:$A$54,0),IF(H21="Pequenos",1,IF(H21="Medios",3,5)))) | N21: =IF(OR(J21="",K21="",L21="",M21=""),"",ROUND((J21+M21-L21*(1-$E$3))/(1-$E$3-$B$3-K21),2)) | Q21: =IF(OR(P21="",J21="",L21="",M21=""),"",(P21-$E$3*(P21+L21)-J21-$B$3*P21+L21-M21)/P21) | R21: =IF(Q21="","",IF(Q21<0,"PREJUÍZO",IF(Q21<0.1,"CRÍTICO (<10%)",IF(Q21<0.15,"ABAIXO DA META (10-15%)",IF(Q21<=0.2,"DENTRO DA META (15-20%)","ACIMA DA META (>20%)")))))
F22: =IF(OR(B22="",C22="",D22=""),"",ROUND(B22*C22*D22/6000,2)) | G22: =IF(F22="","",MAX(F22,IF(E22="",0,E22))) | H22: =IF(G22="","",IF(G22<=5.5,"Pequenos",IF(G22<=18,"Medios","Grandes"))) | L22: =IF(OR(H22="",I22=""),"",INDEX(Ref_Frete!$B$2:$G$54,MATCH(I22,Ref_Frete!$A$2:$A$54,0),IF(H22="Pequenos",2,IF(H22="Medios",4,6)))) | M22: =IF(OR(H22="",I22=""),"",INDEX(Ref_Frete!$B$2:$G$54,MATCH(I22,Ref_Frete!$A$2:$A$54,0),IF(H22="Pequenos",1,IF(H22="Medios",3,5)))) | N22: =IF(OR(J22="",K22="",L22="",M22=""),"",ROUND((J22+M22-L22*(1-$E$3))/(1-$E$3-$B$3-K22),2)) | Q22: =IF(OR(P22="",J22="",L22="",M22=""),"",(P22-$E$3*(P22+L22)-J22-$B$3*P22+L22-M22)/P22) | R22: =IF(Q22="","",IF(Q22<0,"PREJUÍZO",IF(Q22<0.1,"CRÍTICO (<10%)",IF(Q22<0.15,"ABAIXO DA META (10-15%)",IF(Q22<=0.2,"DENTRO DA META (15-20%)","ACIMA DA META (>20%)")))))
F23: =IF(OR(B23="",C23="",D23=""),"",ROUND(B23*C23*D23/6000,2)) | G23: =IF(F23="","",MAX(F23,IF(E23="",0,E23))) | H23: =IF(G23="","",IF(G23<=5.5,"Pequenos",IF(G23<=18,"Medios","Grandes"))) | L23: =IF(OR(H23="",I23=""),"",INDEX(Ref_Frete!$B$2:$G$54,MATCH(I23,Ref_Frete!$A$2:$A$54,0),IF(H23="Pequenos",2,IF(H23="Medios",4,6)))) | M23: =IF(OR(H23="",I23=""),"",INDEX(Ref_Frete!$B$2:$G$54,MATCH(I23,Ref_Frete!$A$2:$A$54,0),IF(H23="Pequenos",1,IF(H23="Medios",3,5)))) | N23: =IF(OR(J23="",K23="",L23="",M23=""),"",ROUND((J23+M23-L23*(1-$E$3))/(1-$E$3-$B$3-K23),2)) | Q23: =IF(OR(P23="",J23="",L23="",M23=""),"",(P23-$E$3*(P23+L23)-J23-$B$3*P23+L23-M23)/P23) | R23: =IF(Q23="","",IF(Q23<0,"PREJUÍZO",IF(Q23<0.1,"CRÍTICO (<10%)",IF(Q23<0.15,"ABAIXO DA META (10-15%)",IF(Q23<=0.2,"DENTRO DA META (15-20%)","ACIMA DA META (>20%)")))))
F24: =IF(OR(B24="",C24="",D24=""),"",ROUND(B24*C24*D24/6000,2)) | G24: =IF(F24="","",MAX(F24,IF(E24="",0,E24))) | H24: =IF(G24="","",IF(G24<=5.5,"Pequenos",IF(G24<=18,"Medios","Grandes"))) | L24: =IF(OR(H24="",I24=""),"",INDEX(Ref_Frete!$B$2:$G$54,MATCH(I24,Ref_Frete!$A$2:$A$54,0),IF(H24="Pequenos",2,IF(H24="Medios",4,6)))) | M24: =IF(OR(H24="",I24=""),"",INDEX(Ref_Frete!$B$2:$G$54,MATCH(I24,Ref_Frete!$A$2:$A$54,0),IF(H24="Pequenos",1,IF(H24="Medios",3,5)))) | N24: =IF(OR(J24="",K24="",L24="",M24=""),"",ROUND((J24+M24-L24*(1-$E$3))/(1-$E$3-$B$3-K24),2)) | Q24: =IF(OR(P24="",J24="",L24="",M24=""),"",(P24-$E$3*(P24+L24)-J24-$B$3*P24+L24-M24)/P24) | R24: =IF(Q24="","",IF(Q24<0,"PREJUÍZO",IF(Q24<0.1,"CRÍTICO (<10%)",IF(Q24<0.15,"ABAIXO DA META (10-15%)",IF(Q24<=0.2,"DENTRO DA META (15-20%)","ACIMA DA META (>20%)")))))
F25: =IF(OR(B25="",C25="",D25=""),"",ROUND(B25*C25*D25/6000,2)) | G25: =IF(F25="","",MAX(F25,IF(E25="",0,E25))) | H25: =IF(G25="","",IF(G25<=5.5,"Pequenos",IF(G25<=18,"Medios","Grandes"))) | L25: =IF(OR(H25="",I25=""),"",INDEX(Ref_Frete!$B$2:$G$54,MATCH(I25,Ref_Frete!$A$2:$A$54,0),IF(H25="Pequenos",2,IF(H25="Medios",4,6)))) | M25: =IF(OR(H25="",I25=""),"",INDEX(Ref_Frete!$B$2:$G$54,MATCH(I25,Ref_Frete!$A$2:$A$54,0),IF(H25="Pequenos",1,IF(H25="Medios",3,5)))) | N25: =IF(OR(J25="",K25="",L25="",M25=""),"",ROUND((J25+M25-L25*(1-$E$3))/(1-$E$3-$B$3-K25),2)) | Q25: =IF(OR(P25="",J25="",L25="",M25=""),"",(P25-$E$3*(P25+L25)-J25-$B$3*P25+L25-M25)/P25) | R25: =IF(Q25="","",IF(Q25<0,"PREJUÍZO",IF(Q25<0.1,"CRÍTICO (<10%)",IF(Q25<0.15,"ABAIXO DA META (10-15%)",IF(Q25<=0.2,"DENTRO DA META (15-20%)","ACIMA DA META (>20%)")))))

Sheet Ref_Frete
A1: Região | B1: Custo real Pequenos | C1: Cobrança Pequenos | D1: Custo real Medios | E1: Cobrança Medios | F1: Custo real Grandes | G1: Cobrança Grandes
A2: Distrito Federal | B2: 52 | C2: 52 | D2: 122 | E2: 122 | F2: 320 | G2: 320
A3: Goiás Capital | B3: 42 | C3: 42 | D3: 85 | E3: 85 | F3: 233 | G3: 233
A4: Goiás Interior | B4: 52 | C4: 52 | D4: 110 | E4: 110 | F4: 298 | G4: 298
A5: Mato Grosso do Sul Capital | B5: 43 | C5: 43 | D5: 90 | E5: 90 | F5: 232 | G5: 232
A6: Mato Grosso do Sul Interior | B6: 68 | C6: 68 | D6: 157 | E6: 157 | F6: 455 | G6: 455
A7: Mato Grosso Capital | B7: 80 | C7: 80 | D7: 160 | E7: 160 | F7: 645 | G7: 645
A8: Mato Grosso Interior | B8: 115 | C8: 115 | D8: 240 | E8: 240 | F8: 740 | G8: 740
A9: Acre Capital | B9: 90 | C9: 90 | D9: 215 | E9: 215 | F9: 562 | G9: 562
A10: Acre Interior | B10: 185 | C10: 185 | D10: 425 | E10: 425 | F10: 1120 | G10: 1120
A11: Amazonas Capital | B11: 100 | C11: 100 | D11: 260 | E11: 260 | F11: 705 | G11: 705
A12: Amazonas Interior | B12: 200 | C12: 200 | D12: 450 | E12: 450 | F12: 1280 | G12: 1280
A13: Amapá Capital | B13: 132 | C13: 132 | D13: 328 | E13: 328 | F13: 845 | G13: 845
... A54: São Paulo Interior | B54: 30 | C54: 16.9 | D54: 49 | E54: 39.9 | F54: 120 | G54: 120

Sheet Classificação_Frete
A1: CLASSIFICAÇÃO DE FRETE — CATÁLOGO COMPLETO WINNET
A2: Peso cubado = (C×L×A em cm) ÷ 6.000. Peso considerado = maior entre real e cubado. Classes (fronteiras validadas por cotação em 17/07): Pequenos ≤ 5,5 kg · Médios ≤ 18 kg · Grandes > 18 kg. Exceções operacionais documentadas na coluna Observação.
A4: SKU | B4: Produto | C4: Caixa (cm) | D4: Peso real (kg) | E4: Peso cubado (kg) | F4: Peso considerado (kg) | G4: Modelo de envio | H4: Observação
A5: L2440-A | B5: Lixeira de Aço inox 24x40 20 litros c/Aro | C5: 25×25×50 | D5: 3 | E5: 5.21 | F5: 5.21 | G5: WN - Pequenos | H5: Reclassificada Médio→Pequeno em 17/07 (cotações Campinas R$27-31 · Salvador R$55-62 · Cuiabá R$40-55)
A6: L2440-AML | B6: LIXEIRA EM AÇO INOX 24X40 20 LITROS C/ARO MEIA LUA | C6: 25×25×50 | D6: 3 | E6: 5.21 | F6: 5.21 | G6: WN - Pequenos | H6: Reclassificada Médio→Pequeno em 17/07 (cotações Campinas R$27-31 · Salvador R$55-62 · Cuiabá R$40-55)
A7: L2440-B | B7: Lixeira de Aço inox 24x40 20 litros c/Aro basculante | C7: 25×25×50 | D7: 3 | E7: 5.21 | F7: 5.21 | G7: WN - Pequenos | H7: Reclassificada Médio→Pequeno em 17/07 (cotações Campinas R$27-31 · Salvador R$55-62 · Cuiabá R$40-55)
A8: L2450-A | B8: Lixeira de Aço inox 24x50 25 litros c/Aro | C8: 25×25×50 | D8: 3 | E8: 5.21 | F8: 5.21 | G8: WN - Pequenos | H8: Reclassificada Médio→Pequeno em 17/07 (cotações Campinas R$27-31 · Salvador R$55-62 · Cuiabá R$40-55)
A9: L2450-AML | B9: LIXEIRA EM AÇO INOX 24X50 25 LITROS C/ARO MEIA LUA | C9: 25×25×50 | D9: 3 | E9: 5.21 | F9: 5.21 | G9: WN - Pequenos | H9: Reclassificada Médio→Pequeno em 17/07 (cotações Campinas R$27-31 · Salvador R$55-62 · Cuiabá R$40-55)
A10: L2450-B | B10: Lixeira de Aço inox 24x50 25 litros c/Aro basculante | C10: 25×25×50 | D10: 3 | E10: 5.21 | F10: 5.21 | G10: WN - Pequenos | H10: Reclassificada Médio→Pequeno em 17/07 (cotações Campinas R$27-31 · Salvador R$55-62 · Cuiabá R$40-55)
A11: L2450--CZ | B11: LIXEIRA CINZEIRO EM AÇO INOX 24X50 25 LITROS | C11: 25×25×50 | D11: 3 | E11: 5.21 | F11: 5.21 | G11: WN - Pequenos | H11: Reclassificada Médio→Pequeno em 17/07 (cotações Campinas R$27-31 · Salvador R$55-62 · Cuiabá R$40-55)
A12: P2440 | B12: Lixeira com Tampa Pedal de Aço inox 24x40 20 litros | C12: 25×25×50 | D12: 3 | E12: 5.21 | F12: 5.21 | G12: WN - Pequenos | H12: Reclassificada Médio→Pequeno em 17/07 (cotações Campinas R$27-31 · Salvador R$55-62 · Cuiabá R$40-55)
A13: PG2450 | B13: Porta guarda chuvas 24x50 | C13: 25×25×50 | D13: 3 | E13: 5.21 | F13: 5.21 | G13: WN - Pequenos | H13: Reclassificada Médio→Pequeno em 17/07 (cotações Campinas R$27-31 · Salvador R$55-62 · Cuiabá R$40-55)
A14: EMB-08 | B14: Lixeira de embutir de Pia em Aço inox 8 litros c/Balde de Alumínio | C14: 32×32×27 | D14: 3 | E14: 4.61 | F14: 4.61 | G14: WN - Pequenos
A15: PXM | B15: PORTA EXTINTOR 200X495 | C15: 20,5×20,5×50 (assumido) | D15: 2.5 | E15: 3.5 | F15: 3.5 | G15: WN - Pequenos | H15: Dimensão '205X205X50' parece erro de digitação (alt. 50 mm?). Assumi 205X205X500 → confirmar
A16: L2030 | B16: Lixeira de Aço inox sem Tampa 20x30 10 litros | C16: 25×25×30 | D16: 2 | E16: 3.12 | F16: 3.12 | G16: WN - Pequenos
A17: L2030-A | B17: Lixeira de Aço inox 20x30 10 litros c/Aro | C17: 25×25×30 | D17: 2 | E17: 3.12 | F17: 3.12 | G17: WN - Pequenos
A18: L2030-B | B18: Lixeira de Aço inox 20x30 10 litros c/Aro basculante | C18: 25×25×30 | D18: 2 | E18: 3.12 | F18: 3.12 | G18: WN - Pequenos
A19: L2030-T | B19: Lixeira de Aço inox 20x30 10 litros com tampa | C19: 25×25×30 | D19: 2 | E19: 3.12 | F19: 3.12 | G19: WN - Pequenos
A20: L2425-A | B20: Lixeira de Aço inox 24x25 13 litros c/Aro | C20: 25×25×30 | D20: 2 | E20: 3.12 | F20: 3.12 | G20: WN - Pequenos
A21: L2425-AML | B21: LIXEIRA EM AÇO INOX 24X25 13 LITROS C/ARO MEIA LUA | C21: 25×25×30 | D21: 2 | E21: 3.12 | F21: 3.12 | G21: WN - Pequenos
A22: L2425-B | B22: Lixeira de Aço inox 24x25 13 litros c/Aro basculante | C22: 25×25×30 | D22: 2 | E22: 3.12 | F22: 3.12 | G22: WN - Pequenos
A23: L2430-A | B23: Lixeira de Aço inox 24x30 15 litros c/Aro | C23: 25×25×30 | D23: 2 | E23: 3.12 | F23: 3.12 | G23: WN - Pequenos
A24: L2430-AML | B24: LIXEIRA EM AÇO INOX 24X30 15 LITROS C/ARO MEIA LUA | C24: 25×25×30 | D24: 2 | E24: 3.12 | F24: 3.12 | G24: WN - Pequenos
A25: L2430-B | B25: Lixeira de Aço inox 24x30 15 litros c/Aro basculante | C25: 25×25×30 | D25: 2 | E25: 3.12 | F25: 3.12 | G25: WN - Pequenos
A26: P2030 | B26: Lixeira com Tampa Pedal de Aço inox 20x30 10 litros | C26: 25×25×30 | D26: 2 | E26: 3.12 | F26: 3.12 | G26: WN - Pequenos
A27: P2425 | B27: Lixeira com Tampa Pedal de Aço inox 24x25 12 litros | C27: 25×25×30 | D27: 2 | E27: 3.12 | F27: 3.12 | G27: WN - Pequenos
... A49: P2025 | B49: Lixeira com Tampa Pedal de Aço inox 20x25 07 litros | C49: 21×21×27 | D49: 1.5 | E49: 1.98 | F49: 1.98 | G49: WN - Pequenos
A50: SP-PP | B50: Coletor de cigarros SPACE PAREDE ø 0,76 X 50 Alt. AÇO INOX | C50: 10×10×52 | D50: 1 | E50: 0.87 | F50: 1 | G50: WN - Pequenos | H50: Dimensões interpretadas em cm (padrão diferente do resto da planilha) — confirmar
A51: L4050-A | B51: Lixeira de Aço inox 40x50 62 litros c/Aro | C51: 42×42×60 | D51: 6 | E51: 17.64 | F51: 17.64 | G51: WN - Medios | H51: Reclassificada Grande→Médio em 17/07 (cotações Campinas R$64-68 · Salvador R$135-142 · Cuiabá R$111-142)
A52: L4050-B | B52: Lixeira de Aço inox 40x50 62 litros c/Aro basculante | C52: 42×42×60 | D52: 6 | E52: 17.64 | F52: 17.64 | G52: WN - Medios | H52: Reclassificada Grande→Médio em 17/07 (cotações Campinas R$64-68 · Salvador R$135-142 · Cuiabá R$111-142)
A53: L4060-A | B53: Lixeira de Aço inox 40x60 75 litros c/Aro | C53: 42×42×60 | D53: 6 | E53: 17.64 | F53: 17.64 | G53: WN - Medios | H53: Reclassificada Grande→Médio em 17/07 (cotações Campinas R$64-68 · Salvador R$135-142 · Cuiabá R$111-142)
A54: L4060-B | B54: Lixeira de Aço inox 40x60 75 litros c/Aro basculante | C54: 42×42×60 | D54: 6 | E54: 17.64 | F54: 17.64 | G54: WN - Medios | H54: Reclassificada Grande→Médio em 17/07 (cotações Campinas R$64-68 · Salvador R$135-142 · Cuiabá R$111-142)
A55: P4050 | B55: Lixeira com Tampa Pedal de Aço inox 40x50 65 litros | C55: 42×42×60 | D55: 6 | E55: 17.64 | F55: 17.64 | G55: WN - Medios | H55: Reclassificada Grande→Médio em 17/07 (cotações Campinas R$64-68 · Salvador R$135-142 · Cuiabá R$111-142)
A56: P4050ALC | B56: Lixeira com Tampa Pedal de Aço inox 40x50 65 litros C/ALÇAS | C56: 42×42×60 | D56: 6 | E56: 17.64 | F56: 17.64 | G56: WN - Medios | H56: Reclassificada Grande→Médio em 17/07 (cotações Campinas R$64-68 · Salvador R$135-142 · Cuiabá R$111-142)
A57: P4060 | B57: Lixeira com Tampa Pedal de Aço inox 40x60 75 litros | C57: 42×42×60 | D57: 6 | E57: 17.64 | F57: 17.64 | G57: WN - Medios | H57: Reclassificada Grande→Médio em 17/07 (cotações Campinas R$64-68 · Salvador R$135-142 · Cuiabá R$111-142)
A58: P4060ALC | B58: Lixeira com Tampa Pedal de Aço inox 40x60 75 litros C/ALÇAS | C58: 42×42×60 | D58: 6 | E58: 17.64 | F58: 17.64 | G58: WN - Medios | H58: Reclassificada Grande→Médio em 17/07 (cotações Campinas R$64-68 · Salvador R$135-142 · Cuiabá R$111-142)
A59: PG4050 | B59: Porta guarda chuvas 40x50 | C59: 42×42×60 | D59: 6 | E59: 17.64 | F59: 17.64 | G59: WN - Medios | H59: Reclassificada Grande→Médio em 17/07 (cotações Campinas R$64-68 · Salvador R$135-142 · Cuiabá R$111-142)
A60: SP-T | B60: Coletor de cigarros SPACE TORRE 28 X 92 Alt. AÇO INOX | C60: 33×33×93 | D60: 5 | E60: 16.88 | F60: 16.88 | G60: WN - Medios | H60: Médio CONFIRMADO por cotação em 13/08 (33×33×93, 5kg): Campinas R$ 65,45 · Salvador R$ 103,94 · Cuiabá R$ 126,93 — todos na faixa das caixas Médias validadas. Encerra a pendência da extrapolação de 17/07.
A61: L3085-B | B61: Lixeira de Aço inox 30x85 60 litros c/Aro basculante | C61: 31×31×78 | D61: 6.5 | E61: 12.57 | F61: 12.57 | G61: WN - Medios
A62: SP-01 | B62: Coletor de cigarros SPACE 27 X 92 Alt. AÇO INOX | C62: 28×28×92 | D62: 7 | E62: 11.53 | F62: 11.53 | G62: WN - Medios
A63: SP-FF | B63: Coletor de cigarros SPACE FIXO 21 X 92 Alt. AÇO INOX | C63: 28×28×92 | D63: 7 | E63: 11.53 | F63: 11.53 | G63: WN - Medios
A64: L3070-A | B64: Lixeira de Aço inox 30x70 50 litros c/Aro | C64: 31×31×70 | D64: 6 | E64: 11.21 | F64: 11.21 | G64: WN - Medios
A65: L3070-AML | B65: LIXEIRA EM AÇO INOX 30X70 50 LITROS C/ARO MEIA LUA | C65: 31×31×70 | D65: 6 | E65: 11.21 | F65: 11.21 | G65: WN - Medios
A66: L3070-B | B66: Lixeira de Aço inox 30x70 50 litros c/Aro basculante | C66: 31×31×70 | D66: 6 | E66: 11.21 | F66: 11.21 | G66: WN - Medios
A67: P3070 | B67: Lixeira com Tampa Pedal de Aço inox 30x70 60 litros | C67: 31×31×70 | D67: 6 | E67: 11.21 | F67: 11.21 | G67: WN - Medios
A68: P3070ALC | B68: Lixeira com Tampa Pedal de Aço inox 30x70 60 litros C/ALÇAS | C68: 31×31×70 | D68: 6 | E68: 11.21 | F68: 11.21 | G68: WN - Medios
A69: PG3070 | B69: Porta guarda chuvas 30x70 | C69: 31×31×70 | D69: 6 | E69: 11.21 | F69: 11.21 | G69: WN - Medios
A70: EGC | B70: Ensacador de Guarda-chuvas Aço inox c/150 saquinhos 26 x 17 x 77 | C70: 28×28×78 | D70: 8 | E70: 9.83 | F70: 9.83 | G70: WN - Medios
A71: L3050-A | B71: Lixeira de Aço inox 30x50 35 litros c/Aro | C71: 31×31×60 | D71: 5 | E71: 9.61 | F71: 9.61 | G71: WN - Medios
A72: L3050-B | B72: Lixeira de Aço inox 30x50 35 litros c/Aro basculante | C72: 31×31×60 | D72: 5 | E72: 9.61 | F72: 9.61 | G72: WN - Medios
... A117: Q4070-B | B117: Lixeira de Aço inox Quadrada 40x70 Com Aro BASCULANTE 100 litros | C117: 42×42×80 | D117: 7 | E117: 23.52 | F117: 23.52 | G117: WN - Grandes
A119: RESUMO: 46 Pequenos · 49 Médios · 18 Grandes · Total 113 SKUs

Sheet Listas
A1: SKUs
A2: EGC
A3: EMB-03
A4: EMB-03P
A5: EMB-05
A6: EMB-05P
A7: EMB-08
A8: L1618
A9: L1618-A
A10: L1618-B
A11: L1618-T
A12: L1623
... A114: SP-T
