Workbook

Sheet Legenda
A1: LEGENDA — Precificação por Marketplace · Winnet Metais · v1.0 (09/10/2026)
A3: COMO A PLANILHA FUNCIONA
A4: Parâmetros | B4: Imposto, ADS, margem mínima e custo fixo por marketplace (bloco 1) e comissão por categoria × marketplace (bloco 2). Toda taxa vive aqui — nenhuma está escondida em fórmula.
A5: Produtos | B5: Base única: código, nome, categoria e custo (Vl. Revenda 6%). As seis abas de marketplace e o Comparativo leem desta aba pela mesma linha.
A6: ML Clássico / ML Premium / Amazon / Via (Casas Bahia) / MadeiraMadeira / Magalu | B6: Uma aba por canal, mesma estrutura da Precificação ML original. Nelas você preenche só Frete, Comissão manual (opcional), Preço Manual, % Desc. Promo, Atualizado em e Observação.
A7: Comparativo | B7: Preço usado e margem de cada produto em todos os canais, lado a lado, com menor/maior margem. Somente leitura.
A8: CORES
A9: Texto AZUL | B9: Entrada manual (custo, frete, comissão manual, preço manual, % promo, taxas).
A10: Fundo AMARELO | B10: Entrada que mais pesa no resultado (custo, frete, taxas).
A11: Texto VERDE | B11: Vem de outra aba (Produtos ou Parâmetros). Não edite — edite na origem.
A12: Fundo DOURADO (✅ usado) | B12: Valor que alimenta os cálculos: o manual se preenchido, senão o automático (vale para comissão e para preço).
A13: VERMELHO | B13: Lucro ou margem negativos — prejuízo. Também sinaliza '⚠ categoria' (produto sem categoria válida) e 'INVALIDO' (taxas somadas ≥ 100%).
A14: LARANJA | B14: Margem abaixo da margem mínima do canal (aba Parâmetros).
A15: COLUNAS DAS ABAS DE MARKETPLACE
A16: Código / Produto / Categoria / Custo (A–D) | B16: Lidos de Produtos. A Categoria escolhe a comissão na aba Parâmetros.
A17: Frete (E) | B17: Só se aplica ao Mercado Livre: custo de envio que fica com a Winnet, por produto. Amazon, Via, MadeiraMadeira e Magalu ficam com 0 por decisão do LEO (09/10/2026).
A18: Comissão categoria (F) | B18: Procurada em Parâmetros pela categoria do produto e pelo canal da aba.
A19: ✏ Comissão manual (G) | B19: Opcional. Digite como fração (0,12 = 12%) quando o anúncio tiver comissão diferente da categoria. Nas abas ML já traz as taxas que estavam embutidas linha a linha na planilha original.
A20: ✅ Comissão usada (H) | B20: G se preenchida, senão F.
A21: ⚙ Preço Sugerido (I) | B21: Preço = (Custo + Frete + Custo fixo) ÷ (1 − Comissão usada − Imposto − ADS − Margem mínima). Mesma lógica da Precificação ML, agora com as taxas vindas de Parâmetros.
A22: ✏ Preço Manual (J) | B22: Digite o preço praticado no canal. Vazio ou 0 = usa o sugerido.
A23: ✅ Preço Usado (K) | B23: J se preenchido, senão I. Base de tudo.
A24: Comissão / Imposto / ADS / Custo fixo (L–O) | B24: Valores em R$ sobre o Preço Usado (custo fixo é por unidade).
A25: Lucro Líq (P) / Margem (Q) | B25: Preço Usado − Custo − Frete − L − M − N − O, e a margem sobre o Preço Usado.
A26: % Desc. Promo (R) e colunas S–X | B26: Digite o desconto como fração (0,10 = 10%). S–X recalculam tudo para o preço promocional.
A27: Atualizado em (Y) / Observação (Z) | B27: Controle livre. Nas abas ML, Y recebeu a data que estava anexada ao nome do produto na planilha original (ex.: '09/10').
A28: FONTES E PREMISSAS DESTA VERSÃO
A29: Produtos e custos | B29: Precificacao_ML_Winnet_Metais_.xlsx (LEO, 09/10/2026): 294 produtos, nomes limpos do sufixo de data. Custos conferidos contra a Planilha Mestra v4.3.5: 108 SKUs em comum, nenhuma divergência. EMB-03P e EMB-05P vieram só da Mestra.
A30: ML Clássico e ML Premium | B30: Frete, Preço Manual e comissão por linha copiados das abas originais; Preço Usado, Lucro e Margem idênticos aos da origem em todas as linhas. Diferença proposital: o Preço Sugerido agora usa a comissão da própria linha (a original usava sempre 13%/18% no divisor, mesmo nas linhas com 12%, 10,5%, 15% etc.). Preço Manual = 0 na origem foi tratado como vazio (usa o sugerido).
A31: Amazon | B31: Preço Manual = 'Preço de venda' do Simulador da Mestra v4.3.5, cenário São Paulo Interior (Livro set/26 fechado em 05/10). Frete = 0 por decisão do LEO (09/10/2026). Grafias Amazon: L2450--CZ, SP-PP, SP-FF (coluna F de Produtos). Para decisão Amazon, a Mestra continua sendo a fonte oficial.
A32: Comissões | B32: Tabela enviada pelo LEO em 09/10/2026 (print). Onde havia faixa, usado o limite superior (conservador); a faixa está anotada em Parâmetros. ML Clássico 13% e Premium 18% vieram do título da planilha original. Amazon 13% em todas as categorias por decisão do LEO (09/10/2026).
A33: Taxas ainda não confirmadas | B33: ADS e custo fixo por unidade de Via, MadeiraMadeira e Magalu (e ADS da Amazon) estão com os valores da planilha ML (3% e R$ 0). Amazon está em 13% por decisão do LEO (09/10/2026), em linha com a tarifa efetiva média da Mestra (13,0%, que incide sobre preço + frete cobrado); aqui ela incide só sobre o preço.
A34: Categoria 'Acessórios (aros e tampas)' | B34: Não consta no print. Recebeu as mesmas comissões de 'Lixeiras em inox' como premissa — confirmar.
A35: COMO INCLUIR PRODUTO
A36: Passo único | B36: Em Produtos, preencha a próxima linha vazia (código, nome, categoria, custo). As abas de canal e o Comparativo já têm fórmulas até a linha 349; depois disso, copie a última linha de fórmulas para baixo.

Sheet Parâmetros
A1: PARÂMETROS — taxas por marketplace e comissão por categoria
A2: Células AZUIS em fundo amarelo são entradas. Tudo o que está nas abas dos marketplaces lê daqui.
A3: Marketplace | B3: Imposto (%) | C3: ADS (%) | D3: Margem mín. (%) | E3: Custo fixo por unidade (R$) | F3: Observação
A4: ML Clássico | B4: 0.1 | C4: 0.03 | D4: 0.2 | E4: 0 | F4: Imposto, ADS e margem herdados da Precificação ML (LEO, 09/10/2026).
A5: ML Premium | B5: 0.1 | C5: 0.03 | D5: 0.2 | E5: 0 | F5: Idem Clássico.
A6: Amazon | B6: 0.1 | C6: 0.03 | D6: 0.2 | E6: 0 | F6: ADS 3% é o valor da planilha ML — confirmar o % real de Amazon Ads sobre a venda.
A7: Via (Casas Bahia) | B7: 0.1 | C7: 0.03 | D7: 0.2 | E7: 0 | F7: ADS e custo fixo não confirmados para este canal.
A8: MadeiraMadeira | B8: 0.1 | C8: 0.03 | D8: 0.2 | E8: 0 | F8: ADS e custo fixo não confirmados para este canal.
A9: Magalu | B9: 0.1 | C9: 0.03 | D9: 0.2 | E9: 0 | F9: ADS e custo fixo não confirmados para este canal.
A11: COMISSÃO POR CATEGORIA × MARKETPLACE (fonte: tabela enviada pelo LEO em 09/10/2026 · faixas → usado o limite superior · confirmar no painel de cada canal · uma linha pode sobrepor com 'Comissão manual' na aba do canal)
A12: Categoria | B12: ML Clássico | C12: ML Premium | D12: Amazon | E12: Via (Casas Bahia) | F12: MadeiraMadeira | G12: Magalu | H12: Faixa informada / observação
A13: Bituqueiras e cinzeiros | B13: 0.13 | C13: 0.18 | D13: 0.13 | E13: 0.21 | F13: 0.19 | G13: 0.18
A14: Lixeiras em inox | B14: 0.13 | C14: 0.18 | D14: 0.13 | E14: 0.21 | F14: 0.19 | G14: 0.18
A15: Lixeiras com pedal | B15: 0.13 | C15: 0.18 | D15: 0.13 | E15: 0.21 | F15: 0.19 | G15: 0.18
A16: Lixeiras de coleta seletiva | B16: 0.13 | C16: 0.18 | D16: 0.13 | E16: 0.21 | F16: 0.19 | G16: 0.18 | H16: Via 20%–21%
A17: Porta-extintores | B17: 0.13 | C17: 0.18 | D17: 0.13 | E17: 0.21 | F17: 0.19 | G17: 0.18 | H17: MadeiraMadeira 15%–19% · Amazon 11%–12% no print, 13% por decisão do LEO · Via 20%–21%
A18: Porta-guarda-chuvas | B18: 0.13 | C18: 0.18 | D18: 0.13 | E18: 0.21 | F18: 0.19 | G18: 0.199 | H18: Magalu 18%–19,9%
A19: Coletores de pilhas | B19: 0.13 | C19: 0.18 | D19: 0.13 | E19: 0.21 | F19: 0.19 | G19: 0.18 | H19: Via 20%–21%
A20: Placas de piso molhado | B20: 0.13 | C20: 0.18 | D20: 0.13 | E20: 0.21 | F20: 0.19 | G20: 0.18 | H20: MadeiraMadeira 15%–19% · Amazon 11%–12% no print, 13% por decisão do LEO · Via 20%–21%
A21: Ensacadores | B21: 0.13 | C21: 0.18 | D21: 0.13 | E21: 0.21 | F21: 0.19 | G21: 0.18 | H21: MadeiraMadeira 15%–19% · Amazon 11%–12% no print, 13% por decisão do LEO · Via 20%–21% (no print: 'Ensacadores de lixeira'; no catálogo é o Ensacador de guarda-chuvas EGC/REGC)
A22: Acessórios (aros e tampas) | B22: 0.13 | C22: 0.18 | D22: 0.13 | E22: 0.21 | F22: 0.19 | G22: 0.18 | H22: PREMISSA: não consta no print — copiado de 'Lixeiras em inox'. Confirmar.

Sheet Produtos
A1: PRODUTOS — base única de código, nome, categoria e custo (as abas dos marketplaces leem daqui)
A2: Entradas em AZUL. Para incluir produto: use a próxima linha vazia (as abas já têm fórmulas até a linha 349). Categoria define a comissão (aba Parâmetros).
A3: Código | B3: Produto | C3: Categoria (comissão) | D3: Vl. Revenda 6% = Custo (R$) | E3: Vl. Nota (R$) opcional | F3: SKU na Amazon (se diferente) | G3: Observação
A4: L1618 | B4: Lixeira Aço Inox s/Tampa 16x18 03L | C4: Lixeiras em inox | D4: 39.8
A5: L1623 | B5: Lixeira Aço Inox s/Tampa 16x23 05L | C5: Lixeiras em inox | D5: 49.15
A6: L2025 | B6: Lixeira Aço Inox s/Tampa 20x25 07L | C6: Lixeiras em inox | D6: 51.82
A7: L2030 | B7: Lixeira Aço Inox s/Tampa 20x30 10L | C7: Lixeiras em inox | D7: 55.49
A8: L2425 | B8: Lixeira Aço Inox s/Tampa 24x25 13L | C8: Lixeiras em inox | D8: 62.2
A9: L2430 | B9: Lixeira Aço Inox s/Tampa 24x30 15L | C9: Lixeiras em inox | D9: 69.93
A10: L2440 | B10: Lixeira Aço Inox s/Tampa 24x40 20L | C10: Lixeiras em inox | D10: 85.92
A11: L2450 | B11: Lixeira Aço Inox s/Tampa 24x50 25L | C11: Lixeiras em inox | D11: 116.34
A12: L2460 | B12: Lixeira Aço Inox s/Tampa 24x60 27L | C12: Lixeiras em inox | D12: 117.84
A13: L2470 | B13: Lixeira Aço Inox s/Tampa 24x70 30L | C13: Lixeiras em inox | D13: 186.46
A14: L3040 | B14: Lixeira Aço Inox s/Tampa 30x40 30L | C14: Lixeiras em inox | D14: 116.77
A15: L3050 | B15: Lixeira Aço Inox s/Tampa 30x50 35L | C15: Lixeiras em inox | D15: 159.84
... A174: EMB-08 | B174: Lixeira Embutir Pia 8L c/Balde Alumínio | C174: Lixeiras em inox | D174: 181.23
A175: EMB-03P | B175: Lixeira Embutir Pia 3L c/Balde Alumínio e Tampa Preta | C175: Lixeiras em inox | D175: 127.42 | G175: Só na Amazon — custo da Mestra v4.3.5
A176: EMB-05P | B176: Lixeira Embutir Pia 5L c/Balde Alumínio e Tampa Preta | C176: Lixeiras em inox | D176: 154.46 | G176: Só na Amazon — custo da Mestra v4.3.5
A177: Q2430-A | B177: Lixeira Quadrada c/Aro 24x30 15L | C177: Lixeiras em inox | D177: 121.07
A178: Q2460-A | B178: Lixeira Quadrada c/Aro 24x60 30L | C178: Lixeiras em inox | D178: 183.04
A179: Q3060-A | B179: Lixeira Quadrada c/Aro 30x60 50L | C179: Lixeiras em inox | D179: 277.75
A180: Q4070-A | B180: Lixeira Quadrada c/Aro 40x70 100L | C180: Lixeiras em inox | D180: 580.13
A181: Q2430-B | B181: Lixeira Quadrada c/Aro Basculante 24x30 15L | C181: Lixeiras em inox | D181: 149.88
A182: Q2460-B | B182: Lixeira Quadrada c/Aro Basculante 24x60 30L | C182: Lixeiras em inox | D182: 198.38
A183: Q3060-B | B183: Lixeira Quadrada c/Aro Basculante 30x60 50L | C183: Lixeiras em inox | D183: 301.03
A184: Q4070-B | B184: Lixeira Quadrada c/Aro Basculante 40x70 100L | C184: Lixeiras em inox | D184: 619.95
A185: PQ-2430 | B185: Lixeira quadrada com Tampa Pedal de Aço inox 24x30 15L | C185: Lixeiras com pedal | D185: 220.94
A186: PQ-2460 | B186: Lixeira quadrada com Tampa Pedal de Aço inox 24x60 30L | C186: Lixeiras com pedal | D186: 303.74
A187: PQ-3060 | B187: Lixeira quadrada com Tampa Pedal de Aço inox 30x60 50L | C187: Lixeiras com pedal | D187: 408.87
A188: PQ-4070 | B188: Lixeira quadrada com Tampa Pedal de Aço inox 40x70 100L | C188: Lixeiras com pedal | D188: 905.26
... A208: L2030-T | B208: Lixeira de Aço inox 20x30 10L com tampa | C208: Lixeiras em inox | D208: 69.27
A209: A24 | B209: Aro 24cm Aço Inox | C209: Acessórios (aros e tampas) | D209: 38.11 | G209: Categoria assumida — confirmar
A210: A30 | B210: Aro 30cm Aço Inox | C210: Acessórios (aros e tampas) | D210: 44.27 | G210: Categoria assumida — confirmar
A211: A40 | B211: Aro 40cm Aço Inox | C211: Acessórios (aros e tampas) | D211: 94.36 | G211: Categoria assumida — confirmar
A212: A24B | B212: Aro 24cm c/Basculante Aço Inox | C212: Acessórios (aros e tampas) | D212: 52.34 | G212: Categoria assumida — confirmar
A213: A30B | B213: Aro 30cm c/Basculante Aço Inox | C213: Acessórios (aros e tampas) | D213: 68.24 | G213: Categoria assumida — confirmar
A214: A40B | B214: Aro 40cm c/Basculante Aço Inox | C214: Acessórios (aros e tampas) | D214: 136.51 | G214: Categoria assumida — confirmar
A215: A24C | B215: Aro 24cm Pintado | C215: Acessórios (aros e tampas) | D215: 50.43 | G215: Categoria assumida — confirmar
A216: A30C | B216: Aro 30cm Pintado | C216: Acessórios (aros e tampas) | D216: 64.43 | G216: Categoria assumida — confirmar
A217: A40BP | B217: Aro 40cm Pintado | C217: Acessórios (aros e tampas) | D217: 118.62 | G217: Categoria assumida — confirmar
A218: A24BC | B218: Aro 24cm c/Basculante Pintado | C218: Acessórios (aros e tampas) | D218: 76.56 | G218: Categoria assumida — confirmar
A219: A30BC | B219: Aro 30cm c/Basculante Pintado | C219: Acessórios (aros e tampas) | D219: 90.73 | G219: Categoria assumida — confirmar
A220: A40BC | B220: Aro 40cm c/Basculante Pintado | C220: Acessórios (aros e tampas) | D220: 170.07 | G220: Categoria assumida — confirmar
A221: T24-PILHAS | B221: Tampa 24cm Coletor de Pilhas e Baterias | C221: Coletores de pilhas | D221: 57.21
A222: T30-PILHAS | B222: Tampa 30cm Coletor de Pilhas e Baterias | C222: Coletores de pilhas | D222: 46.19
A223: T40-PILHAS | B223: Tampa 40cm Coletor de Pilhas e Baterias | C223: Coletores de pilhas | D223: 98.64
A224: A24ML | B224: Aro 24cm Meia Lua Aço Inox | C224: Acessórios (aros e tampas) | D224: 60.74 | G224: Categoria assumida — confirmar
A225: A30ML | B225: Aro 30cm Meia Lua Aço Inox | C225: Acessórios (aros e tampas) | D225: 76.36 | G225: Categoria assumida — confirmar
A226: A40ML | B226: Aro 40cm Meia Lua Aço Inox | C226: Acessórios (aros e tampas) | D226: 116.98 | G226: Categoria assumida — confirmar
A227: AQ-24 | B227: Aro Quadrado 24cm Aço Inox | C227: Acessórios (aros e tampas) | D227: 39.22 | G227: Categoria assumida — confirmar
A228: AQ-30 | B228: Aro Quadrado 30cm Aço Inox | C228: Acessórios (aros e tampas) | D228: 45.58 | G228: Categoria assumida — confirmar
A229: AQ-40 | B229: Aro Quadrado 40cm Aço Inox | C229: Acessórios (aros e tampas) | D229: 96.46 | G229: Categoria assumida — confirmar
A230: AQ-24B | B230: Aro Quadrado 24cm c/Basculante | C230: Acessórios (aros e tampas) | D230: 54.06 | G230: Categoria assumida — confirmar
A231: AQ-30B | B231: Aro Quadrado 30cm c/Basculante | C231: Acessórios (aros e tampas) | D231: 69.96 | G231: Categoria assumida — confirmar
A232: AQ-40B | B232: Aro Quadrado 40cm c/Basculante | C232: Acessórios (aros e tampas) | D232: 121.9 | G232: Categoria assumida — confirmar
A233: AQ-24C | B233: Aro Quadrado 24cm Pintado | C233: Acessórios (aros e tampas) | D233: 45.58 | G233: Categoria assumida — confirmar
A234: AQ-30C | B234: Aro Quadrado 30cm Pintado | C234: Acessórios (aros e tampas) | D234: 53 | G234: Categoria assumida — confirmar
A235: AQ-40C | B235: Aro Quadrado 40cm Pintado | C235: Acessórios (aros e tampas) | D235: 104.94 | G235: Categoria assumida — confirmar
... A238: AQ-40BC | B238: Aro Quadrado 40cm c/Basculante Pintado | C238: Acessórios (aros e tampas) | D238: 132.5 | G238: Categoria assumida — confirmar
A239: PXP | B239: Porta Extintor 160x310 | C239: Porta-extintores | D239: 84.79
A240: PXM | B240: Porta Extintor 200x495 | C240: Porta-extintores | D240: 102.8
A241: PL-SD | B241: Placa Sinalizadora Piso Molhado Aço Inox 430 | C241: Placas de piso molhado | D241: 242.68
A242: SP-01 | B242: Coletor Cigarros SPACE 27x92 Aço Inox | C242: Bituqueiras e cinzeiros | D242: 247.86
A243: SP-F | B243: Coletor Cigarros SPACE FIXO 21x92 Aço Inox | C243: Bituqueiras e cinzeiros | D243: 236.22 | F243: SP-FF
A244: SP-T | B244: Coletor Cigarros SPACE TORRE 28x92 Aço Inox | C244: Bituqueiras e cinzeiros | D244: 238.66
A245: SP-P | B245: Coletor Cigarros SPACE PAREDE ø0,76x50 Aço Inox | C245: Bituqueiras e cinzeiros | D245: 139.81 | F245: SP-PP
A246: SP-FT | B246: Tampa Space Fixa | C246: Bituqueiras e cinzeiros | D246: 75
A247: L2450-CZ | B247: Lixeira Cinzeiro Aço Inox 24x50 25L | C247: Bituqueiras e cinzeiros | D247: 156 | F247: L2450--CZ
A248: L2460-CZ | B248: Lixeira Cinzeiro Aço Inox 24x60 27L | C248: Bituqueiras e cinzeiros | D248: 159
A249: L2470-CZ | B249: Lixeira Cinzeiro Aço Inox 24x70 30L | C249: Bituqueiras e cinzeiros | D249: 164.3
A250: L4045-P | B250: Lixeira de Parede c/Aro 40x19x45 20L | C250: Lixeiras em inox | D250: 277.43
A251: L4055-P | B251: Lixeira de Parede c/Aro 40x19x55 25L | C251: Lixeiras em inox | D251: 288.65
A252: L4060-P | B252: Lixeira de Parede c/Aro 40x19x60 30L | C252: Lixeiras em inox | D252: 297.96
A253: L4065-P | B253: Lixeira de Parede c/Aro 40x19x65 35L | C253: Lixeiras em inox | D253: 388.44
A254: L4070-P | B254: Lixeira de Parede c/Aro 40x19x70 40L | C254: Lixeiras em inox | D254: 394.64
A255: L4080-P | B255: Lixeira de Parede c/Aro 40x19x80 50L | C255: Lixeiras em inox | D255: 401
A256: L4045-PC | B256: Lixeira de Parede c/Aro Colorido 40x19x45 20L | C256: Lixeiras em inox | D256: 291.85
A257: L4055-PC | B257: Lixeira de Parede c/Aro Colorido 40x19x55 25L | C257: Lixeiras em inox | D257: 301.44
A258: L4060-PC | B258: Lixeira de Parede c/Aro Colorido 40x19x60 30L | C258: Lixeiras em inox | D258: 314.8
A259: L4065-PC | B259: Lixeira de Parede c/Aro Colorido 40x19x65 35L | C259: Lixeiras em inox | D259: 405.46
... A299: P4090ALC | B299: Lixeira c/Tampa Pedal 40x90 120L c/Alças | C299: Lixeiras com pedal | D299: 828.46

Sheet ML Clássico
A1: ="MERCADO LIVRE — CLÁSSICO | Comissão por categoria (aba Parâmetros) ou manual por linha | Imposto "&TEXT(Parâmetros!$B$4,"0%")&" | ADS "&TEXT(Parâmetros!$C$4,"0.0%")&" | Margem mín. "&TEXT(Parâmetros!$D$4,"0%")&" | Custo fixo/un. R$ "&TEXT(Parâmetros!$E$4,"0.00") -> MERCADO LIVRE — CLÁSSICO | Comissão por categoria (aba Parâmetros) ou manual por linha | Imposto 10% | ADS 3.0% | Margem mín. 20% | Custo fixo/un. R$ 0.00
A2: PRODUTO | D2: ENTRADAS | F2: COMISSÃO | I2: PREÇO SUGERIDO | J2: PREÇO MANUAL | K2: PREÇO USADO | L2: COMPOSIÇÃO DO PREÇO | R2: PROMOÇÃO | Y2: CONTROLE
A3: Código | B3: Produto | C3: Categoria | D3: Vl. Revenda 6% = Custo (R$) | E3: Frete (R$) | F3: Comissão categoria (%) | G3: ✏ Comissão manual (%) | H3: ✅ Comissão usada (%) | I3: ⚙ Preço Sugerido | J3: ✏ Preço Manual | K3: ✅ Preço Usado | L3: Comissão (R$) | M3: Imposto (R$) | N3: ADS (R$) | O3: Custo fixo (R$) | P3: Lucro Líq (R$) | Q3: Margem (%) | R3: % Desc. Promo | S3: Preço Promo (R$) | T3: Comissão Promo (R$) | U3: Imposto Promo (R$) | V3: ADS Promo (R$) | W3: Lucro Promo (R$) | X3: Margem Promo (%) | Y3: Atualizado em | Z3: Observação
A4: =IF(Produtos!$A4="","",Produtos!$A4) -> L1618 | B4: =IF(Produtos!$A4="","",Produtos!$B4) -> Lixeira Aço Inox s/Tampa 16x18 03L | C4: =IF(Produtos!$A4="","",Produtos!$C4) -> Lixeiras em inox | D4: =IF(Produtos!$A4="","",IF(Produtos!$D4="","",Produtos!$D4)) -> 39.8 | E4: 14.15 | F4: =IF($A4="","",IF($C4="","⚠ categoria",IFERROR(INDEX(Parâmetros!$B$13:$B$22,MATCH($C4,Parâmetros!$A$13:$A$22,0)),"⚠ categoria"))) -> 0.13 | H4: =IF($A4="","",IF(ISNUMBER($G4),$G4,IF(ISNUMBER($F4),$F4,""))) -> 0.13 | I4: =IF(OR($A4="",NOT(ISNUMBER($D4)),NOT(ISNUMBER($H4))),"",IF((1-$H4-Parâmetros!$B$4-Parâmetros!$C$4-Parâmetros!$D$4)<=0,"INVALIDO",($D4+IF(ISNUMBER($E4),$E4,0)+IF(ISNUMBER(Parâmetros!$E$4),Parâmetros!$E$4,0))/(1-$H4-Parâmetros!$B$4-Parâmetros!$C$4-Parâmetros!$D$4))) -> 99.907407 | J4: 80.4 | K4: =IF(OR($A4="",NOT(ISNUMBER($D4)),NOT(ISNUMBER($H4))),"",IF(AND(ISNUMBER($J4),$J4>0),$J4,IF(ISNUMBER($I4),$I4,""))) -> 80.4 | L4: =IF(ISNUMBER($K4),$K4*$H4,"") -> 10.452 | M4: =IF(ISNUMBER($K4),$K4*Parâmetros!$B$4,"") -> 8.04 | N4: =IF(ISNUMBER($K4),$K4*Parâmetros!$C$4,"") -> 2.412 | O4: =IF(ISNUMBER($K4),IF(ISNUMBER(Parâmetros!$E$4),Parâmetros!$E$4,0),"") -> 0 | P4: =IF(ISNUMBER($K4),$K4-$D4-IF(ISNUMBER($E4),$E4,0)-$L4-$M4-$N4-$O4,"") -> 5.546 | Q4: =IF(AND(ISNUMBER($K4),$K4>0),$P4/$K4,"") -> 0.0689801 | S4: =IF(OR(NOT(ISNUMBER($R4)),$R4=0,NOT(ISNUMBER($K4))),"",$K4*(1-$R4)) | T4: =IF(ISNUMBER($S4),$S4*$H4,"") | U4: =IF(ISNUMBER($S4),$S4*Parâmetros!$B$4,"") | V4: =IF(ISNUMBER($S4),$S4*Parâmetros!$C$4,"") | W4: =IF(ISNUMBER($S4),$S4-$D4-IF(ISNUMBER($E4),$E4,0)-$O4-$T4-$U4-$V4,"") | X4: =IF(AND(ISNUMBER($S4),$S4>0),$W4/$S4,"")
A5: =IF(Produtos!$A5="","",Produtos!$A5) -> L1623 | B5: =IF(Produtos!$A5="","",Produtos!$B5) -> Lixeira Aço Inox s/Tampa 16x23 05L | C5: =IF(Produtos!$A5="","",Produtos!$C5) -> Lixeiras em inox | D5: =IF(Produtos!$A5="","",IF(Produtos!$D5="","",Produtos!$D5)) -> 49.15 | E5: 14.15 | F5: =IF($A5="","",IF($C5="","⚠ categoria",IFERROR(INDEX(Parâmetros!$B$13:$B$22,MATCH($C5,Parâmetros!$A$13:$A$22,0)),"⚠ categoria"))) -> 0.13 | H5: =IF($A5="","",IF(ISNUMBER($G5),$G5,IF(ISNUMBER($F5),$F5,""))) -> 0.13 | I5: =IF(OR($A5="",NOT(ISNUMBER($D5)),NOT(ISNUMBER($H5))),"",IF((1-$H5-Parâmetros!$B$4-Parâmetros!$C$4-Parâmetros!$D$4)<=0,"INVALIDO",($D5+IF(ISNUMBER($E5),$E5,0)+IF(ISNUMBER(Parâmetros!$E$4),Parâmetros!$E$4,0))/(1-$H5-Parâmetros!$B$4-Parâmetros!$C$4-Parâmetros!$D$4))) -> 117.22222 | J5: 97.96 | K5: =IF(OR($A5="",NOT(ISNUMBER($D5)),NOT(ISNUMBER($H5))),"",IF(AND(ISNUMBER($J5),$J5>0),$J5,IF(ISNUMBER($I5),$I5,""))) -> 97.96 | L5: =IF(ISNUMBER($K5),$K5*$H5,"") -> 12.7348 | M5: =IF(ISNUMBER($K5),$K5*Parâmetros!$B$4,"") -> 9.796 | N5: =IF(ISNUMBER($K5),$K5*Parâmetros!$C$4,"") -> 2.9388 | O5: =IF(ISNUMBER($K5),IF(ISNUMBER(Parâmetros!$E$4),Parâmetros!$E$4,0),"") -> 0 | P5: =IF(ISNUMBER($K5),$K5-$D5-IF(ISNUMBER($E5),$E5,0)-$L5-$M5-$N5-$O5,"") -> 9.1904 | Q5: =IF(AND(ISNUMBER($K5),$K5>0),$P5/$K5,"") -> 0.093817885 | S5: =IF(OR(NOT(ISNUMBER($R5)),$R5=0,NOT(ISNUMBER($K5))),"",$K5*(1-$R5)) | T5: =IF(ISNUMBER($S5),$S5*$H5,"") | U5: =IF(ISNUMBER($S5),$S5*Parâmetros!$B$4,"") | V5: =IF(ISNUMBER($S5),$S5*Parâmetros!$C$4,"") | W5: =IF(ISNUMBER($S5),$S5-$D5-IF(ISNUMBER($E5),$E5,0)-$O5-$T5-$U5-$V5,"") | X5: =IF(AND(ISNUMBER($S5),$S5>0),$W5/$S5,"")
A6: =IF(Produtos!$A6="","",Produtos!$A6) -> L2025 | B6: =IF(Produtos!$A6="","",Produtos!$B6) -> Lixeira Aço Inox s/Tampa 20x25 07L | C6: =IF(Produtos!$A6="","",Produtos!$C6) -> Lixeiras em inox | D6: =IF(Produtos!$A6="","",IF(Produtos!$D6="","",Produtos!$D6)) -> 51.82 | E6: 16.85 | F6: =IF($A6="","",IF($C6="","⚠ categoria",IFERROR(INDEX(Parâmetros!$B$13:$B$22,MATCH($C6,Parâmetros!$A$13:$A$22,0)),"⚠ categoria"))) -> 0.13 | H6: =IF($A6="","",IF(ISNUMBER($G6),$G6,IF(ISNUMBER($F6),$F6,""))) -> 0.13 | I6: =IF(OR($A6="",NOT(ISNUMBER($D6)),NOT(ISNUMBER($H6))),"",IF((1-$H6-Parâmetros!$B$4-Parâmetros!$C$4-Parâmetros!$D$4)<=0,"INVALIDO",($D6+IF(ISNUMBER($E6),$E6,0)+IF(ISNUMBER(Parâmetros!$E$4),Parâmetros!$E$4,0))/(1-$H6-Parâmetros!$B$4-Parâmetros!$C$4-Parâmetros!$D$4))) -> 127.16667 | J6: 102.62 | K6: =IF(OR($A6="",NOT(ISNUMBER($D6)),NOT(ISNUMBER($H6))),"",IF(AND(ISNUMBER($J6),$J6>0),$J6,IF(ISNUMBER($I6),$I6,""))) -> 102.62 | L6: =IF(ISNUMBER($K6),$K6*$H6,"") -> 13.3406 | M6: =IF(ISNUMBER($K6),$K6*Parâmetros!$B$4,"") -> 10.262 | N6: =IF(ISNUMBER($K6),$K6*Parâmetros!$C$4,"") -> 3.0786 | O6: =IF(ISNUMBER($K6),IF(ISNUMBER(Parâmetros!$E$4),Parâmetros!$E$4,0),"") -> 0 | P6: =IF(ISNUMBER($K6),$K6-$D6-IF(ISNUMBER($E6),$E6,0)-$L6-$M6-$N6-$O6,"") -> 7.2688 | Q6: =IF(AND(ISNUMBER($K6),$K6>0),$P6/$K6,"") -> 0.070832196 | S6: =IF(OR(NOT(ISNUMBER($R6)),$R6=0,NOT(ISNUMBER($K6))),"",$K6*(1-$R6)) | T6: =IF(ISNUMBER($S6),$S6*$H6,"") | U6: =IF(ISNUMBER($S6),$S6*Parâmetros!$B$4,"") | V6: =IF(ISNUMBER($S6),$S6*Parâmetros!$C$4,"") | W6: =IF(ISNUMBER($S6),$S6-$D6-IF(ISNUMBER($E6),$E6,0)-$O6-$T6-$U6-$V6,"") | X6: =IF(AND(ISNUMBER($S6),$S6>0),$W6/$S6,"")
A7: =IF(Produtos!$A7="","",Produtos!$A7) -> L2030 | B7: =IF(Produtos!$A7="","",Produtos!$B7) -> Lixeira Aço Inox s/Tampa 20x30 10L | C7: =IF(Produtos!$A7="","",Produtos!$C7) -> Lixeiras em inox | D7: =IF(Produtos!$A7="","",IF(Produtos!$D7="","",Produtos!$D7)) -> 55.49 | E7: 16.85 | F7: =IF($A7="","",IF($C7="","⚠ categoria",IFERROR(INDEX(Parâmetros!$B$13:$B$22,MATCH($C7,Parâmetros!$A$13:$A$22,0)),"⚠ categoria"))) -> 0.13 | H7: =IF($A7="","",IF(ISNUMBER($G7),$G7,IF(ISNUMBER($F7),$F7,""))) -> 0.13 | I7: =IF(OR($A7="",NOT(ISNUMBER($D7)),NOT(ISNUMBER($H7))),"",IF((1-$H7-Parâmetros!$B$4-Parâmetros!$C$4-Parâmetros!$D$4)<=0,"INVALIDO",($D7+IF(ISNUMBER($E7),$E7,0)+IF(ISNUMBER(Parâmetros!$E$4),Parâmetros!$E$4,0))/(1-$H7-Parâmetros!$B$4-Parâmetros!$C$4-Parâmetros!$D$4))) -> 133.96296 | J7: 108.36 | K7: =IF(OR($A7="",NOT(ISNUMBER($D7)),NOT(ISNUMBER($H7))),"",IF(AND(ISNUMBER($J7),$J7>0),$J7,IF(ISNUMBER($I7),$I7,""))) -> 108.36 | L7: =IF(ISNUMBER($K7),$K7*$H7,"") -> 14.0868 | M7: =IF(ISNUMBER($K7),$K7*Parâmetros!$B$4,"") -> 10.836 | N7: =IF(ISNUMBER($K7),$K7*Parâmetros!$C$4,"") -> 3.2508 | O7: =IF(ISNUMBER($K7),IF(ISNUMBER(Parâmetros!$E$4),Parâmetros!$E$4,0),"") -> 0 | P7: =IF(ISNUMBER($K7),$K7-$D7-IF(ISNUMBER($E7),$E7,0)-$L7-$M7-$N7-$O7,"") -> 7.8464 | Q7: =IF(AND(ISNUMBER($K7),$K7>0),$P7/$K7,"") -> 0.072410484 | S7: =IF(OR(NOT(ISNUMBER($R7)),$R7=0,NOT(ISNUMBER($K7))),"",$K7*(1-$R7)) | T7: =IF(ISNUMBER($S7),$S7*$H7,"") | U7: =IF(ISNUMBER($S7),$S7*Parâmetros!$B$4,"") | V7: =IF(ISNUMBER($S7),$S7*Parâmetros!$C$4,"") | W7: =IF(ISNUMBER($S7),$S7-$D7-IF(ISNUMBER($E7),$E7,0)-$O7-$T7-$U7-$V7,"") | X7: =IF(AND(ISNUMBER($S7),$S7>0),$W7/$S7,"")
A8: =IF(Produtos!$A8="","",Produtos!$A8) -> L2425 | B8: =IF(Produtos!$A8="","",Produtos!$B8) -> Lixeira Aço Inox s/Tampa 24x25 13L | C8: =IF(Produtos!$A8="","",Produtos!$C8) -> Lixeiras em inox | D8: =IF(Produtos!$A8="","",IF(Produtos!$D8="","",Produtos!$D8)) -> 62.2 | F8: =IF($A8="","",IF($C8="","⚠ categoria",IFERROR(INDEX(Parâmetros!$B$13:$B$22,MATCH($C8,Parâmetros!$A$13:$A$22,0)),"⚠ categoria"))) -> 0.13 | H8: =IF($A8="","",IF(ISNUMBER($G8),$G8,IF(ISNUMBER($F8),$F8,""))) -> 0.13 | I8: =IF(OR($A8="",NOT(ISNUMBER($D8)),NOT(ISNUMBER($H8))),"",IF((1-$H8-Parâmetros!$B$4-Parâmetros!$C$4-Parâmetros!$D$4)<=0,"INVALIDO",($D8+IF(ISNUMBER($E8),$E8,0)+IF(ISNUMBER(Parâmetros!$E$4),Parâmetros!$E$4,0))/(1-$H8-Parâmetros!$B$4-Parâmetros!$C$4-Parâmetros!$D$4))) -> 115.18519 | K8: =IF(OR($A8="",NOT(ISNUMBER($D8)),NOT(ISNUMBER($H8))),"",IF(AND(ISNUMBER($J8),$J8>0),$J8,IF(ISNUMBER($I8),$I8,""))) -> 115.18519 | L8: =IF(ISNUMBER($K8),$K8*$H8,"") -> 14.974074 | M8: =IF(ISNUMBER($K8),$K8*Parâmetros!$B$4,"") -> 11.518519 | N8: =IF(ISNUMBER($K8),$K8*Parâmetros!$C$4,"") -> 3.4555556 | O8: =IF(ISNUMBER($K8),IF(ISNUMBER(Parâmetros!$E$4),Parâmetros!$E$4,0),"") -> 0 | P8: =IF(ISNUMBER($K8),$K8-$D8-IF(ISNUMBER($E8),$E8,0)-$L8-$M8-$N8-$O8,"") -> 23.037037 | Q8: =IF(AND(ISNUMBER($K8),$K8>0),$P8/$K8,"") -> 0.2 | S8: =IF(OR(NOT(ISNUMBER($R8)),$R8=0,NOT(ISNUMBER($K8))),"",$K8*(1-$R8)) | T8: =IF(ISNUMBER($S8),$S8*$H8,"") | U8: =IF(ISNUMBER($S8),$S8*Parâmetros!$B$4,"") | V8: =IF(ISNUMBER($S8),$S8*Parâmetros!$C$4,"") | W8: =IF(ISNUMBER($S8),$S8-$D8-IF(ISNUMBER($E8),$E8,0)-$O8-$T8-$U8-$V8,"") | X8: =IF(AND(ISNUMBER($S8),$S8>0),$W8/$S8,"")
A9: =IF(Produtos!$A9="","",Produtos!$A9) -> L2430 | B9: =IF(Produtos!$A9="","",Produtos!$B9) -> Lixeira Aço Inox s/Tampa 24x30 15L | C9: =IF(Produtos!$A9="","",Produtos!$C9) -> Lixeiras em inox | D9: =IF(Produtos!$A9="","",IF(Produtos!$D9="","",Produtos!$D9)) -> 69.93 | F9: =IF($A9="","",IF($C9="","⚠ categoria",IFERROR(INDEX(Parâmetros!$B$13:$B$22,MATCH($C9,Parâmetros!$A$13:$A$22,0)),"⚠ categoria"))) -> 0.13 | H9: =IF($A9="","",IF(ISNUMBER($G9),$G9,IF(ISNUMBER($F9),$F9,""))) -> 0.13 | I9: =IF(OR($A9="",NOT(ISNUMBER($D9)),NOT(ISNUMBER($H9))),"",IF((1-$H9-Parâmetros!$B$4-Parâmetros!$C$4-Parâmetros!$D$4)<=0,"INVALIDO",($D9+IF(ISNUMBER($E9),$E9,0)+IF(ISNUMBER(Parâmetros!$E$4),Parâmetros!$E$4,0))/(1-$H9-Parâmetros!$B$4-Parâmetros!$C$4-Parâmetros!$D$4))) -> 129.5 | K9: =IF(OR($A9="",NOT(ISNUMBER($D9)),NOT(ISNUMBER($H9))),"",IF(AND(ISNUMBER($J9),$J9>0),$J9,IF(ISNUMBER($I9),$I9,""))) -> 129.5 | L9: =IF(ISNUMBER($K9),$K9*$H9,"") -> 16.835 | M9: =IF(ISNUMBER($K9),$K9*Parâmetros!$B$4,"") -> 12.95 | N9: =IF(ISNUMBER($K9),$K9*Parâmetros!$C$4,"") -> 3.885 | O9: =IF(ISNUMBER($K9),IF(ISNUMBER(Parâmetros!$E$4),Parâmetros!$E$4,0),"") -> 0 | P9: =IF(ISNUMBER($K9),$K9-$D9-IF(ISNUMBER($E9),$E9,0)-$L9-$M9-$N9-$O9,"") -> 25.9 | Q9: =IF(AND(ISNUMBER($K9),$K9>0),$P9/$K9,"") -> 0.2 | S9: =IF(OR(NOT(ISNUMBER($R9)),$R9=0,NOT(ISNUMBER($K9))),"",$K9*(1-$R9)) | T9: =IF(ISNUMBER($S9),$S9*$H9,"") | U9: =IF(ISNUMBER($S9),$S9*Parâmetros!$B$4,"") | V9: =IF(ISNUMBER($S9),$S9*Parâmetros!$C$4,"") | W9: =IF(ISNUMBER($S9),$S9-$D9-IF(ISNUMBER($E9),$E9,0)-$O9-$T9-$U9-$V9,"") | X9: =IF(AND(ISNUMBER($S9),$S9>0),$W9/$S9,"")
A10: =IF(Produtos!$A10="","",Produtos!$A10) -> L2440 | B10: =IF(Produtos!$A10="","",Produtos!$B10) -> Lixeira Aço Inox s/Tampa 24x40 20L | C10: =IF(Produtos!$A10="","",Produtos!$C10) -> Lixeiras em inox | D10: =IF(Produtos!$A10="","",IF(Produtos!$D10="","",Produtos!$D10)) -> 85.92 | F10: =IF($A10="","",IF($C10="","⚠ categoria",IFERROR(INDEX(Parâmetros!$B$13:$B$22,MATCH($C10,Parâmetros!$A$13:$A$22,0)),"⚠ categoria"))) -> 0.13 | H10: =IF($A10="","",IF(ISNUMBER($G10),$G10,IF(ISNUMBER($F10),$F10,""))) -> 0.13 | I10: =IF(OR($A10="",NOT(ISNUMBER($D10)),NOT(ISNUMBER($H10))),"",IF((1-$H10-Parâmetros!$B$4-Parâmetros!$C$4-Parâmetros!$D$4)<=0,"INVALIDO",($D10+IF(ISNUMBER($E10),$E10,0)+IF(ISNUMBER(Parâmetros!$E$4),Parâmetros!$E$4,0))/(1-$H10-Parâmetros!$B$4-Parâmetros!$C$4-Parâmetros!$D$4))) -> 159.11111 | K10: =IF(OR($A10="",NOT(ISNUMBER($D10)),NOT(ISNUMBER($H10))),"",IF(AND(ISNUMBER($J10),$J10>0),$J10,IF(ISNUMBER($I10),$I10,""))) -> 159.11111 | L10: =IF(ISNUMBER($K10),$K10*$H10,"") -> 20.684444 | M10: =IF(ISNUMBER($K10),$K10*Parâmetros!$B$4,"") -> 15.911111 | N10: =IF(ISNUMBER($K10),$K10*Parâmetros!$C$4,"") -> 4.7733333 | O10: =IF(ISNUMBER($K10),IF(ISNUMBER(Parâmetros!$E$4),Parâmetros!$E$4,0),"") -> 0 | P10: =IF(ISNUMBER($K10),$K10-$D10-IF(ISNUMBER($E10),$E10,0)-$L10-$M10-$N10-$O10,"") -> 31.822222 | Q10: =IF(AND(ISNUMBER($K10),$K10>0),$P10/$K10,"") -> 0.2 | S10: =IF(OR(NOT(ISNUMBER($R10)),$R10=0,NOT(ISNUMBER($K10))),"",$K10*(1-$R10)) | T10: =IF(ISNUMBER($S10),$S10*$H10,"") | U10: =IF(ISNUMBER($S10),$S10*Parâmetros!$B$4,"") | V10: =IF(ISNUMBER($S10),$S10*Parâmetros!$C$4,"") | W10: =IF(ISNUMBER($S10),$S10-$D10-IF(ISNUMBER($E10),$E10,0)-$O10-$T10-$U10-$V10,"") | X10: =IF(AND(ISNUMBER($S10),$S10>0),$W10/$S10,"")
A11: =IF(Produtos!$A11="","",Produtos!$A11) -> L2450 | B11: =IF(Produtos!$A11="","",Produtos!$B11) -> Lixeira Aço Inox s/Tampa 24x50 25L | C11: =IF(Produtos!$A11="","",Produtos!$C11) -> Lixeiras em inox | D11: =IF(Produtos!$A11="","",IF(Produtos!$D11="","",Produtos!$D11)) -> 116.34 | F11: =IF($A11="","",IF($C11="","⚠ categoria",IFERROR(INDEX(Parâmetros!$B$13:$B$22,MATCH($C11,Parâmetros!$A$13:$A$22,0)),"⚠ categoria"))) -> 0.13 | H11: =IF($A11="","",IF(ISNUMBER($G11),$G11,IF(ISNUMBER($F11),$F11,""))) -> 0.13 | I11: =IF(OR($A11="",NOT(ISNUMBER($D11)),NOT(ISNUMBER($H11))),"",IF((1-$H11-Parâmetros!$B$4-Parâmetros!$C$4-Parâmetros!$D$4)<=0,"INVALIDO",($D11+IF(ISNUMBER($E11),$E11,0)+IF(ISNUMBER(Parâmetros!$E$4),Parâmetros!$E$4,0))/(1-$H11-Parâmetros!$B$4-Parâmetros!$C$4-Parâmetros!$D$4))) -> 215.44444 | K11: =IF(OR($A11="",NOT(ISNUMBER($D11)),NOT(ISNUMBER($H11))),"",IF(AND(ISNUMBER($J11),$J11>0),$J11,IF(ISNUMBER($I11),$I11,""))) -> 215.44444 | L11: =IF(ISNUMBER($K11),$K11*$H11,"") -> 28.007778 | M11: =IF(ISNUMBER($K11),$K11*Parâmetros!$B$4,"") -> 21.544444 | N11: =IF(ISNUMBER($K11),$K11*Parâmetros!$C$4,"") -> 6.4633333 | O11: =IF(ISNUMBER($K11),IF(ISNUMBER(Parâmetros!$E$4),Parâmetros!$E$4,0),"") -> 0 | P11: =IF(ISNUMBER($K11),$K11-$D11-IF(ISNUMBER($E11),$E11,0)-$L11-$M11-$N11-$O11,"") -> 43.088889 | Q11: =IF(AND(ISNUMBER($K11),$K11>0),$P11/$K11,"") -> 0.2 | S11: =IF(OR(NOT(ISNUMBER($R11)),$R11=0,NOT(ISNUMBER($K11))),"",$K11*(1-$R11)) | T11: =IF(ISNUMBER($S11),$S11*$H11,"") | U11: =IF(ISNUMBER($S11),$S11*Parâmetros!$B$4,"") | V11: =IF(ISNUMBER($S11),$S11*Parâmetros!$C$4,"") | W11: =IF(ISNUMBER($S11),$S11-$D11-IF(ISNUMBER($E11),$E11,0)-$O11-$T11-$U11-$V11,"") | X11: =IF(AND(ISNUMBER($S11),$S11>0),$W11/$S11,"")
A12: =IF(Produtos!$A12="","",Produtos!$A12) -> L2460 | B12: =IF(Produtos!$A12="","",Produtos!$B12) -> Lixeira Aço Inox s/Tampa 24x60 27L | C12: =IF(Produtos!$A12="","",Produtos!$C12) -> Lixeiras em inox | D12: =IF(Produtos!$A12="","",IF(Produtos!$D12="","",Produtos!$D12)) -> 117.84 | F12: =IF($A12="","",IF($C12="","⚠ categoria",IFERROR(INDEX(Parâmetros!$B$13:$B$22,MATCH($C12,Parâmetros!$A$13:$A$22,0)),"⚠ categoria"))) -> 0.13 | H12: =IF($A12="","",IF(ISNUMBER($G12),$G12,IF(ISNUMBER($F12),$F12,""))) -> 0.13 | I12: =IF(OR($A12="",NOT(ISNUMBER($D12)),NOT(ISNUMBER($H12))),"",IF((1-$H12-Parâmetros!$B$4-Parâmetros!$C$4-Parâmetros!$D$4)<=0,"INVALIDO",($D12+IF(ISNUMBER($E12),$E12,0)+IF(ISNUMBER(Parâmetros!$E$4),Parâmetros!$E$4,0))/(1-$H12-Parâmetros!$B$4-Parâmetros!$C$4-Parâmetros!$D$4))) -> 218.22222 | K12: =IF(OR($A12="",NOT(ISNUMBER($D12)),NOT(ISNUMBER($H12))),"",IF(AND(ISNUMBER($J12),$J12>0),$J12,IF(ISNUMBER($I12),$I12,""))) -> 218.22222 | L12: =IF(ISNUMBER($K12),$K12*$H12,"") -> 28.368889 | M12: =IF(ISNUMBER($K12),$K12*Parâmetros!$B$4,"") -> 21.822222 | N12: =IF(ISNUMBER($K12),$K12*Parâmetros!$C$4,"") -> 6.5466667 | O12: =IF(ISNUMBER($K12),IF(ISNUMBER(Parâmetros!$E$4),Parâmetros!$E$4,0),"") -> 0 | P12: =IF(ISNUMBER($K12),$K12-$D12-IF(ISNUMBER($E12),$E12,0)-$L12-$M12-$N12-$O12,"") -> 43.644444 | Q12: =IF(AND(ISNUMBER($K12),$K12>0),$P12/$K12,"") -> 0.2 | S12: =IF(OR(NOT(ISNUMBER($R12)),$R12=0,NOT(ISNUMBER($K12))),"",$K12*(1-$R12)) | T12: =IF(ISNUMBER($S12),$S12*$H12,"") | U12: =IF(ISNUMBER($S12),$S12*Parâmetros!$B$4,"") | V12: =IF(ISNUMBER($S12),$S12*Parâmetros!$C$4,"") | W12: =IF(ISNUMBER($S12),$S12-$D12-IF(ISNUMBER($E12),$E12,0)-$O12-$T12-$U12-$V12,"") | X12: =IF(AND(ISNUMBER($S12),$S12>0),$W12/$S12,"")
A13: =IF(Produtos!$A13="","",Produtos!$A13) -> L2470 | B13: =IF(Produtos!$A13="","",Produtos!$B13) -> Lixeira Aço Inox s/Tampa 24x70 30L | C13: =IF(Produtos!$A13="","",Produtos!$C13) -> Lixeiras em inox | D13: =IF(Produtos!$A13="","",IF(Produtos!$D13="","",Produtos!$D13)) -> 186.46 | F13: =IF($A13="","",IF($C13="","⚠ categoria",IFERROR(INDEX(Parâmetros!$B$13:$B$22,MATCH($C13,Parâmetros!$A$13:$A$22,0)),"⚠ categoria"))) -> 0.13 | H13: =IF($A13="","",IF(ISNUMBER($G13),$G13,IF(ISNUMBER($F13),$F13,""))) -> 0.13 | I13: =IF(OR($A13="",NOT(ISNUMBER($D13)),NOT(ISNUMBER($H13))),"",IF((1-$H13-Parâmetros!$B$4-Parâmetros!$C$4-Parâmetros!$D$4)<=0,"INVALIDO",($D13+IF(ISNUMBER($E13),$E13,0)+IF(ISNUMBER(Parâmetros!$E$4),Parâmetros!$E$4,0))/(1-$H13-Parâmetros!$B$4-Parâmetros!$C$4-Parâmetros!$D$4))) -> 345.2963 | K13: =IF(OR($A13="",NOT(ISNUMBER($D13)),NOT(ISNUMBER($H13))),"",IF(AND(ISNUMBER($J13),$J13>0),$J13,IF(ISNUMBER($I13),$I13,""))) -> 345.2963 | L13: =IF(ISNUMBER($K13),$K13*$H13,"") -> 44.888519 | M13: =IF(ISNUMBER($K13),$K13*Parâmetros!$B$4,"") -> 34.52963 | N13: =IF(ISNUMBER($K13),$K13*Parâmetros!$C$4,"") -> 10.358889 | O13: =IF(ISNUMBER($K13),IF(ISNUMBER(Parâmetros!$E$4),Parâmetros!$E$4,0),"") -> 0 | P13: =IF(ISNUMBER($K13),$K13-$D13-IF(ISNUMBER($E13),$E13,0)-$L13-$M13-$N13-$O13,"") -> 69.059259 | Q13: =IF(AND(ISNUMBER($K13),$K13>0),$P13/$K13,"") -> 0.2 | S13: =IF(OR(NOT(ISNUMBER($R13)),$R13=0,NOT(ISNUMBER($K13))),"",$K13*(1-$R13)) | T13: =IF(ISNUMBER($S13),$S13*$H13,"") | U13: =IF(ISNUMBER($S13),$S13*Parâmetros!$B$4,"") | V13: =IF(ISNUMBER($S13),$S13*Parâmetros!$C$4,"") | W13: =IF(ISNUMBER($S13),$S13-$D13-IF(ISNUMBER($E13),$E13,0)-$O13-$T13-$U13-$V13,"") | X13: =IF(AND(ISNUMBER($S13),$S13>0),$W13/$S13,"")
A14: =IF(Produtos!$A14="","",Produtos!$A14) -> L3040 | B14: =IF(Produtos!$A14="","",Produtos!$B14) -> Lixeira Aço Inox s/Tampa 30x40 30L | C14: =IF(Produtos!$A14="","",Produtos!$C14) -> Lixeiras em inox | D14: =IF(Produtos!$A14="","",IF(Produtos!$D14="","",Produtos!$D14)) -> 116.77 | F14: =IF($A14="","",IF($C14="","⚠ categoria",IFERROR(INDEX(Parâmetros!$B$13:$B$22,MATCH($C14,Parâmetros!$A$13:$A$22,0)),"⚠ categoria"))) -> 0.13 | H14: =IF($A14="","",IF(ISNUMBER($G14),$G14,IF(ISNUMBER($F14),$F14,""))) -> 0.13 | I14: =IF(OR($A14="",NOT(ISNUMBER($D14)),NOT(ISNUMBER($H14))),"",IF((1-$H14-Parâmetros!$B$4-Parâmetros!$C$4-Parâmetros!$D$4)<=0,"INVALIDO",($D14+IF(ISNUMBER($E14),$E14,0)+IF(ISNUMBER(Parâmetros!$E$4),Parâmetros!$E$4,0))/(1-$H14-Parâmetros!$B$4-Parâmetros!$C$4-Parâmetros!$D$4))) -> 216.24074 | K14: =IF(OR($A14="",NOT(ISNUMBER($D14)),NOT(ISNUMBER($H14))),"",IF(AND(ISNUMBER($J14),$J14>0),$J14,IF(ISNUMBER($I14),$I14,""))) -> 216.24074 | L14: =IF(ISNUMBER($K14),$K14*$H14,"") -> 28.111296 | M14: =IF(ISNUMBER($K14),$K14*Parâmetros!$B$4,"") -> 21.624074 | N14: =IF(ISNUMBER($K14),$K14*Parâmetros!$C$4,"") -> 6.4872222 | O14: =IF(ISNUMBER($K14),IF(ISNUMBER(Parâmetros!$E$4),Parâmetros!$E$4,0),"") -> 0 | P14: =IF(ISNUMBER($K14),$K14-$D14-IF(ISNUMBER($E14),$E14,0)-$L14-$M14-$N14-$O14,"") -> 43.248148 | Q14: =IF(AND(ISNUMBER($K14),$K14>0),$P14/$K14,"") -> 0.2 | S14: =IF(OR(NOT(ISNUMBER($R14)),$R14=0,NOT(ISNUMBER($K14))),"",$K14*(1-$R14)) | T14: =IF(ISNUMBER($S14),$S14*$H14,"") | U14: =IF(ISNUMBER($S14),$S14*Parâmetros!$B$4,"") | V14: =IF(ISNUMBER($S14),$S14*Parâmetros!$C$4,"") | W14: =IF(ISNUMBER($S14),$S14-$D14-IF(ISNUMBER($E14),$E14,0)-$O14-$T14-$U14-$V14,"") | X14: =IF(AND(ISNUMBER($S14),$S14>0),$W14/$S14,"")
A15: =IF(Produtos!$A15="","",Produtos!$A15) -> L3050 | B15: =IF(Produtos!$A15="","",Produtos!$B15) -> Lixeira Aço Inox s/Tampa 30x50 35L | C15: =IF(Produtos!$A15="","",Produtos!$C15) -> Lixeiras em inox | D15: =IF(Produtos!$A15="","",IF(Produtos!$D15="","",Produtos!$D15)) -> 159.84 | F15: =IF($A15="","",IF($C15="","⚠ categoria",IFERROR(INDEX(Parâmetros!$B$13:$B$22,MATCH($C15,Parâmetros!$A$13:$A$22,0)),"⚠ categoria"))) -> 0.13 | H15: =IF($A15="","",IF(ISNUMBER($G15),$G15,IF(ISNUMBER($F15),$F15,""))) -> 0.13 | I15: =IF(OR($A15="",NOT(ISNUMBER($D15)),NOT(ISNUMBER($H15))),"",IF((1-$H15-Parâmetros!$B$4-Parâmetros!$C$4-Parâmetros!$D$4)<=0,"INVALIDO",($D15+IF(ISNUMBER($E15),$E15,0)+IF(ISNUMBER(Parâmetros!$E$4),Parâmetros!$E$4,0))/(1-$H15-Parâmetros!$B$4-Parâmetros!$C$4-Parâmetros!$D$4))) -> 296 | K15: =IF(OR($A15="",NOT(ISNUMBER($D15)),NOT(ISNUMBER($H15))),"",IF(AND(ISNUMBER($J15),$J15>0),$J15,IF(ISNUMBER($I15),$I15,""))) -> 296 | L15: =IF(ISNUMBER($K15),$K15*$H15,"") -> 38.48 | M15: =IF(ISNUMBER($K15),$K15*Parâmetros!$B$4,"") -> 29.6 | N15: =IF(ISNUMBER($K15),$K15*Parâmetros!$C$4,"") -> 8.88 | O15: =IF(ISNUMBER($K15),IF(ISNUMBER(Parâmetros!$E$4),Parâmetros!$E$4,0),"") -> 0 | P15: =IF(ISNUMBER($K15),$K15-$D15-IF(ISNUMBER($E15),$E15,0)-$L15-$M15-$N15-$O15,"") -> 59.2 | Q15: =IF(AND(ISNUMBER($K15),$K15>0),$P15/$K15,"") -> 0.2 | S15: =IF(OR(NOT(ISNUMBER($R15)),$R15=0,NOT(ISNUMBER($K15))),"",$K15*(1-$R15)) | T15: =IF(ISNUMBER($S15),$S15*$H15,"") | U15: =IF(ISNUMBER($S15),$S15*Parâmetros!$B$4,"") | V15: =IF(ISNUMBER($S15),$S15*Parâmetros!$C$4,"") | W15: =IF(ISNUMBER($S15),$S15-$D15-IF(ISNUMBER($E15),$E15,0)-$O15-$T15-$U15-$V15,"") | X15: =IF(AND(ISNUMBER($S15),$S15>0),$W15/$S15,"")
A16: =IF(Produtos!$A16="","",Produtos!$A16) -> L3060 | B16: =IF(Produtos!$A16="","",Produtos!$B16) -> Lixeira Aço Inox s/Tampa 30x60 40L | C16: =IF(Produtos!$A16="","",Produtos!$C16) -> Lixeiras em inox | D16: =IF(Produtos!$A16="","",IF(Produtos!$D16="","",Produtos!$D16)) -> 164.99 | F16: =IF($A16="","",IF($C16="","⚠ categoria",IFERROR(INDEX(Parâmetros!$B$13:$B$22,MATCH($C16,Parâmetros!$A$13:$A$22,0)),"⚠ categoria"))) -> 0.13 | H16: =IF($A16="","",IF(ISNUMBER($G16),$G16,IF(ISNUMBER($F16),$F16,""))) -> 0.13 | I16: =IF(OR($A16="",NOT(ISNUMBER($D16)),NOT(ISNUMBER($H16))),"",IF((1-$H16-Parâmetros!$B$4-Parâmetros!$C$4-Parâmetros!$D$4)<=0,"INVALIDO",($D16+IF(ISNUMBER($E16),$E16,0)+IF(ISNUMBER(Parâmetros!$E$4),Parâmetros!$E$4,0))/(1-$H16-Parâmetros!$B$4-Parâmetros!$C$4-Parâmetros!$D$4))) -> 305.53704 | K16: =IF(OR($A16="",NOT(ISNUMBER($D16)),NOT(ISNUMBER($H16))),"",IF(AND(ISNUMBER($J16),$J16>0),$J16,IF(ISNUMBER($I16),$I16,""))) -> 305.53704 | L16: =IF(ISNUMBER($K16),$K16*$H16,"") -> 39.719815 | M16: =IF(ISNUMBER($K16),$K16*Parâmetros!$B$4,"") -> 30.553704 | N16: =IF(ISNUMBER($K16),$K16*Parâmetros!$C$4,"") -> 9.1661111 | O16: =IF(ISNUMBER($K16),IF(ISNUMBER(Parâmetros!$E$4),Parâmetros!$E$4,0),"") -> 0 | P16: =IF(ISNUMBER($K16),$K16-$D16-IF(ISNUMBER($E16),$E16,0)-$L16-$M16-$N16-$O16,"") -> 61.107407 | Q16: =IF(AND(ISNUMBER($K16),$K16>0),$P16/$K16,"") -> 0.2 | S16: =IF(OR(NOT(ISNUMBER($R16)),$R16=0,NOT(ISNUMBER($K16))),"",$K16*(1-$R16)) | T16: =IF(ISNUMBER($S16),$S16*$H16,"") | U16: =IF(ISNUMBER($S16),$S16*Parâmetros!$B$4,"") | V16: =IF(ISNUMBER($S16),$S16*Parâmetros!$C$4,"") | W16: =IF(ISNUMBER($S16),$S16-$D16-IF(ISNUMBER($E16),$E16,0)-$O16-$T16-$U16-$V16,"") | X16: =IF(AND(ISNUMBER($S16),$S16>0),$W16/$S16,"")
A17: =IF(Produtos!$A17="","",Produtos!$A17) -> L3070 | B17: =IF(Produtos!$A17="","",Produtos!$B17) -> Lixeira Aço Inox s/Tampa 30x70 50L | C17: =IF(Produtos!$A17="","",Produtos!$C17) -> Lixeiras em inox | D17: =IF(Produtos!$A17="","",IF(Produtos!$D17="","",Produtos!$D17)) -> 210.17 | F17: =IF($A17="","",IF($C17="","⚠ categoria",IFERROR(INDEX(Parâmetros!$B$13:$B$22,MATCH($C17,Parâmetros!$A$13:$A$22,0)),"⚠ categoria"))) -> 0.13 | H17: =IF($A17="","",IF(ISNUMBER($G17),$G17,IF(ISNUMBER($F17),$F17,""))) -> 0.13 | I17: =IF(OR($A17="",NOT(ISNUMBER($D17)),NOT(ISNUMBER($H17))),"",IF((1-$H17-Parâmetros!$B$4-Parâmetros!$C$4-Parâmetros!$D$4)<=0,"INVALIDO",($D17+IF(ISNUMBER($E17),$E17,0)+IF(ISNUMBER(Parâmetros!$E$4),Parâmetros!$E$4,0))/(1-$H17-Parâmetros!$B$4-Parâmetros!$C$4-Parâmetros!$D$4))) -> 389.2037 | K17: =IF(OR($A17="",NOT(ISNUMBER($D17)),NOT(ISNUMBER($H17))),"",IF(AND(ISNUMBER($J17),$J17>0),$J17,IF(ISNUMBER($I17),$I17,""))) -> 389.2037 | L17: =IF(ISNUMBER($K17),$K17*$H17,"") -> 50.596481 | M17: =IF(ISNUMBER($K17),$K17*Parâmetros!$B$4,"") -> 38.92037 | N17: =IF(ISNUMBER($K17),$K17*Parâmetros!$C$4,"") -> 11.676111 | O17: =IF(ISNUMBER($K17),IF(ISNUMBER(Parâmetros!$E$4),Parâmetros!$E$4,0),"") -> 0 | P17: =IF(ISNUMBER($K17),$K17-$D17-IF(ISNUMBER($E17),$E17,0)-$L17-$M17-$N17-$O17,"") -> 77.840741 | Q17: =IF(AND(ISNUMBER($K17),$K17>0),$P17/$K17,"") -> 0.2 | S17: =IF(OR(NOT(ISNUMBER($R17)),$R17=0,NOT(ISNUMBER($K17))),"",$K17*(1-$R17)) | T17: =IF(ISNUMBER($S17),$S17*$H17,"") | U17: =IF(ISNUMBER($S17),$S17*Parâmetros!$B$4,"") | V17: =IF(ISNUMBER($S17),$S17*Parâmetros!$C$4,"") | W17: =IF(ISNUMBER($S17),$S17-$D17-IF(ISNUMBER($E17),$E17,0)-$O17-$T17-$U17-$V17,"") | X17: =IF(AND(ISNUMBER($S17),$S17>0),$W17/$S17,"")
A18: =IF(Produtos!$A18="","",Produtos!$A18) -> L3085 | B18: =IF(Produtos!$A18="","",Produtos!$B18) -> Lixeira Aço Inox s/Tampa 30x85 60L | C18: =IF(Produtos!$A18="","",Produtos!$C18) -> Lixeiras em inox | D18: =IF(Produtos!$A18="","",IF(Produtos!$D18="","",Produtos!$D18)) -> 266.36 | F18: =IF($A18="","",IF($C18="","⚠ categoria",IFERROR(INDEX(Parâmetros!$B$13:$B$22,MATCH($C18,Parâmetros!$A$13:$A$22,0)),"⚠ categoria"))) -> 0.13 | H18: =IF($A18="","",IF(ISNUMBER($G18),$G18,IF(ISNUMBER($F18),$F18,""))) -> 0.13 | I18: =IF(OR($A18="",NOT(ISNUMBER($D18)),NOT(ISNUMBER($H18))),"",IF((1-$H18-Parâmetros!$B$4-Parâmetros!$C$4-Parâmetros!$D$4)<=0,"INVALIDO",($D18+IF(ISNUMBER($E18),$E18,0)+IF(ISNUMBER(Parâmetros!$E$4),Parâmetros!$E$4,0))/(1-$H18-Parâmetros!$B$4-Parâmetros!$C$4-Parâmetros!$D$4))) -> 493.25926 | K18: =IF(OR($A18="",NOT(ISNUMBER($D18)),NOT(ISNUMBER($H18))),"",IF(AND(ISNUMBER($J18),$J18>0),$J18,IF(ISNUMBER($I18),$I18,""))) -> 493.25926 | L18: =IF(ISNUMBER($K18),$K18*$H18,"") -> 64.123704 | M18: =IF(ISNUMBER($K18),$K18*Parâmetros!$B$4,"") -> 49.325926 | N18: =IF(ISNUMBER($K18),$K18*Parâmetros!$C$4,"") -> 14.797778 | O18: =IF(ISNUMBER($K18),IF(ISNUMBER(Parâmetros!$E$4),Parâmetros!$E$4,0),"") -> 0 | P18: =IF(ISNUMBER($K18),$K18-$D18-IF(ISNUMBER($E18),$E18,0)-$L18-$M18-$N18-$O18,"") -> 98.651852 | Q18: =IF(AND(ISNUMBER($K18),$K18>0),$P18/$K18,"") -> 0.2 | S18: =IF(OR(NOT(ISNUMBER($R18)),$R18=0,NOT(ISNUMBER($K18))),"",$K18*(1-$R18)) | T18: =IF(ISNUMBER($S18),$S18*$H18,"") | U18: =IF(ISNUMBER($S18),$S18*Parâmetros!$B$4,"") | V18: =IF(ISNUMBER($S18),$S18*Parâmetros!$C$4,"") | W18: =IF(ISNUMBER($S18),$S18-$D18-IF(ISNUMBER($E18),$E18,0)-$O18-$T18-$U18-$V18,"") | X18: =IF(AND(ISNUMBER($S18),$S18>0),$W18/$S18,"")
A19: =IF(Produtos!$A19="","",Produtos!$A19) -> L4050 | B19: =IF(Produtos!$A19="","",Produtos!$B19) -> Lixeira Aço Inox s/Tampa 40x50 62L | C19: =IF(Produtos!$A19="","",Produtos!$C19) -> Lixeiras em inox | D19: =IF(Produtos!$A19="","",IF(Produtos!$D19="","",Produtos!$D19)) -> 221.01 | F19: =IF($A19="","",IF($C19="","⚠ categoria",IFERROR(INDEX(Parâmetros!$B$13:$B$22,MATCH($C19,Parâmetros!$A$13:$A$22,0)),"⚠ categoria"))) -> 0.13 | H19: =IF($A19="","",IF(ISNUMBER($G19),$G19,IF(ISNUMBER($F19),$F19,""))) -> 0.13 | I19: =IF(OR($A19="",NOT(ISNUMBER($D19)),NOT(ISNUMBER($H19))),"",IF((1-$H19-Parâmetros!$B$4-Parâmetros!$C$4-Parâmetros!$D$4)<=0,"INVALIDO",($D19+IF(ISNUMBER($E19),$E19,0)+IF(ISNUMBER(Parâmetros!$E$4),Parâmetros!$E$4,0))/(1-$H19-Parâmetros!$B$4-Parâmetros!$C$4-Parâmetros!$D$4))) -> 409.27778 | K19: =IF(OR($A19="",NOT(ISNUMBER($D19)),NOT(ISNUMBER($H19))),"",IF(AND(ISNUMBER($J19),$J19>0),$J19,IF(ISNUMBER($I19),$I19,""))) -> 409.27778 | L19: =IF(ISNUMBER($K19),$K19*$H19,"") -> 53.206111 | M19: =IF(ISNUMBER($K19),$K19*Parâmetros!$B$4,"") -> 40.927778 | N19: =IF(ISNUMBER($K19),$K19*Parâmetros!$C$4,"") -> 12.278333 | O19: =IF(ISNUMBER($K19),IF(ISNUMBER(Parâmetros!$E$4),Parâmetros!$E$4,0),"") -> 0 | P19: =IF(ISNUMBER($K19),$K19-$D19-IF(ISNUMBER($E19),$E19,0)-$L19-$M19-$N19-$O19,"") -> 81.855556 | Q19: =IF(AND(ISNUMBER($K19),$K19>0),$P19/$K19,"") -> 0.2 | S19: =IF(OR(NOT(ISNUMBER($R19)),$R19=0,NOT(ISNUMBER($K19))),"",$K19*(1-$R19)) | T19: =IF(ISNUMBER($S19),$S19*$H19,"") | U19: =IF(ISNUMBER($S19),$S19*Parâmetros!$B$4,"") | V19: =IF(ISNUMBER($S19),$S19*Parâmetros!$C$4,"") | W19: =IF(ISNUMBER($S19),$S19-$D19-IF(ISNUMBER($E19),$E19,0)-$O19-$T19-$U19-$V19,"") | X19: =IF(AND(ISNUMBER($S19),$S19>0),$W19/$S19,"")
... A24: =IF(Produtos!$A24="","",Produtos!$A24) -> L4090 | B24: =IF(Produtos!$A24="","",Produtos!$B24) -> Lixeira Aço Inox s/Tampa 40x90 120L | C24: =IF(Produtos!$A24="","",Produtos!$C24) -> Lixeiras em inox | D24: =IF(Produtos!$A24="","",IF(Produtos!$D24="","",Produtos!$D24)) -> 378.85 | F24: =IF($A24="","",IF($C24="","⚠ categoria",IFERROR(INDEX(Parâmetros!$B$13:$B$22,MATCH($C24,Parâmetros!$A$13:$A$22,0)),"⚠ categoria"))) -> 0.13 | H24: =IF($A24="","",IF(ISNUMBER($G24),$G24,IF(ISNUMBER($F24),$F24,""))) -> 0.13 | I24: =IF(OR($A24="",NOT(ISNUMBER($D24)),NOT(ISNUMBER($H24))),"",IF((1-$H24-Parâmetros!$B$4-Parâmetros!$C$4-Parâmetros!$D$4)<=0,"INVALIDO",($D24+IF(ISNUMBER($E24),$E24,0)+IF(ISNUMBER(Parâmetros!$E$4),Parâmetros!$E$4,0))/(1-$H24-Parâmetros!$B$4-Parâmetros!$C$4-Parâmetros!$D$4))) -> 701.57407 | K24: =IF(OR($A24="",NOT(ISNUMBER($D24)),NOT(ISNUMBER($H24))),"",IF(AND(ISNUMBER($J24),$J24>0),$J24,IF(ISNUMBER($I24),$I24,""))) -> 701.57407 | L24: =IF(ISNUMBER($K24),$K24*$H24,"") -> 91.20463 | M24: =IF(ISNUMBER($K24),$K24*Parâmetros!$B$4,"") -> 70.157407 | N24: =IF(ISNUMBER($K24),$K24*Parâmetros!$C$4,"") -> 21.047222 | O24: =IF(ISNUMBER($K24),IF(ISNUMBER(Parâmetros!$E$4),Parâmetros!$E$4,0),"") -> 0 | P24: =IF(ISNUMBER($K24),$K24-$D24-IF(ISNUMBER($E24),$E24,0)-$L24-$M24-$N24-$O24,"") -> 140.31481 | Q24: =IF(AND(ISNUMBER($K24),$K24>0),$P24/$K24,"") -> 0.2 | S24: =IF(OR(NOT(ISNUMBER($R24)),$R24=0,NOT(ISNUMBER($K24))),"",$K24*(1-$R24)) | T24: =IF(ISNUMBER($S24),$S24*$H24,"") | U24: =IF(ISNUMBER($S24),$S24*Parâmetros!$B$4,"") | V24: =IF(ISNUMBER($S24),$S24*Parâmetros!$C$4,"") | W24: =IF(ISNUMBER($S24),$S24-$D24-IF(ISNUMBER($E24),$E24,0)-$O24-$T24-$U24-$V24,"") | X24: =IF(AND(ISNUMBER($S24),$S24>0),$W24/$S24,"")
A25: =IF(Produtos!$A25="","",Produtos!$A25) -> L1618-A | B25: =IF(Produtos!$A25="","",Produtos!$B25) -> Lixeira Aço Inox c/Aro 16x18 03L | C25: =IF(Produtos!$A25="","",Produtos!$C25) -> Lixeiras em inox | D25: =IF(Produtos!$A25="","",IF(Produtos!$D25="","",Produtos!$D25)) -> 48.18 | E25: 14.15 | F25: =IF($A25="","",IF($C25="","⚠ categoria",IFERROR(INDEX(Parâmetros!$B$13:$B$22,MATCH($C25,Parâmetros!$A$13:$A$22,0)),"⚠ categoria"))) -> 0.13 | H25: =IF($A25="","",IF(ISNUMBER($G25),$G25,IF(ISNUMBER($F25),$F25,""))) -> 0.13 | I25: =IF(OR($A25="",NOT(ISNUMBER($D25)),NOT(ISNUMBER($H25))),"",IF((1-$H25-Parâmetros!$B$4-Parâmetros!$C$4-Parâmetros!$D$4)<=0,"INVALIDO",($D25+IF(ISNUMBER($E25),$E25,0)+IF(ISNUMBER(Parâmetros!$E$4),Parâmetros!$E$4,0))/(1-$H25-Parâmetros!$B$4-Parâmetros!$C$4-Parâmetros!$D$4))) -> 115.42593 | J25: 90.35 | K25: =IF(OR($A25="",NOT(ISNUMBER($D25)),NOT(ISNUMBER($H25))),"",IF(AND(ISNUMBER($J25),$J25>0),$J25,IF(ISNUMBER($I25),$I25,""))) -> 90.35 | L25: =IF(ISNUMBER($K25),$K25*$H25,"") -> 11.7455 | M25: =IF(ISNUMBER($K25),$K25*Parâmetros!$B$4,"") -> 9.035 | N25: =IF(ISNUMBER($K25),$K25*Parâmetros!$C$4,"") -> 2.7105 | O25: =IF(ISNUMBER($K25),IF(ISNUMBER(Parâmetros!$E$4),Parâmetros!$E$4,0),"") -> 0 | P25: =IF(ISNUMBER($K25),$K25-$D25-IF(ISNUMBER($E25),$E25,0)-$L25-$M25-$N25-$O25,"") -> 4.529 | Q25: =IF(AND(ISNUMBER($K25),$K25>0),$P25/$K25,"") -> 0.050127283 | S25: =IF(OR(NOT(ISNUMBER($R25)),$R25=0,NOT(ISNUMBER($K25))),"",$K25*(1-$R25)) | T25: =IF(ISNUMBER($S25),$S25*$H25,"") | U25: =IF(ISNUMBER($S25),$S25*Parâmetros!$B$4,"") | V25: =IF(ISNUMBER($S25),$S25*Parâmetros!$C$4,"") | W25: =IF(ISNUMBER($S25),$S25-$D25-IF(ISNUMBER($E25),$E25,0)-$O25-$T25-$U25-$V25,"") | X25: =IF(AND(ISNUMBER($S25),$S25>0),$W25/$S25,"")
A26: =IF(Produtos!$A26="","",Produtos!$A26) -> L1623-A | B26: =IF(Produtos!$A26="","",Produtos!$B26) -> Lixeira Aço Inox c/Aro 16x23 05L | C26: =IF(Produtos!$A26="","",Produtos!$C26) -> Lixeiras em inox | D26: =IF(Produtos!$A26="","",IF(Produtos!$D26="","",Produtos!$D26)) -> 55.75 | E26: 16.45 | F26: =IF($A26="","",IF($C26="","⚠ categoria",IFERROR(INDEX(Parâmetros!$B$13:$B$22,MATCH($C26,Parâmetros!$A$13:$A$22,0)),"⚠ categoria"))) -> 0.13 | H26: =IF($A26="","",IF(ISNUMBER($G26),$G26,IF(ISNUMBER($F26),$F26,""))) -> 0.13 | I26: =IF(OR($A26="",NOT(ISNUMBER($D26)),NOT(ISNUMBER($H26))),"",IF((1-$H26-Parâmetros!$B$4-Parâmetros!$C$4-Parâmetros!$D$4)<=0,"INVALIDO",($D26+IF(ISNUMBER($E26),$E26,0)+IF(ISNUMBER(Parâmetros!$E$4),Parâmetros!$E$4,0))/(1-$H26-Parâmetros!$B$4-Parâmetros!$C$4-Parâmetros!$D$4))) -> 133.7037 | J26: 104.62 | K26: =IF(OR($A26="",NOT(ISNUMBER($D26)),NOT(ISNUMBER($H26))),"",IF(AND(ISNUMBER($J26),$J26>0),$J26,IF(ISNUMBER($I26),$I26,""))) -> 104.62 | L26: =IF(ISNUMBER($K26),$K26*$H26,"") -> 13.6006 | M26: =IF(ISNUMBER($K26),$K26*Parâmetros!$B$4,"") -> 10.462 | N26: =IF(ISNUMBER($K26),$K26*Parâmetros!$C$4,"") -> 3.1386 | O26: =IF(ISNUMBER($K26),IF(ISNUMBER(Parâmetros!$E$4),Parâmetros!$E$4,0),"") -> 0 | P26: =IF(ISNUMBER($K26),$K26-$D26-IF(ISNUMBER($E26),$E26,0)-$L26-$M26-$N26-$O26,"") -> 5.2188 | Q26: =IF(AND(ISNUMBER($K26),$K26>0),$P26/$K26,"") -> 0.049883387 | S26: =IF(OR(NOT(ISNUMBER($R26)),$R26=0,NOT(ISNUMBER($K26))),"",$K26*(1-$R26)) | T26: =IF(ISNUMBER($S26),$S26*$H26,"") | U26: =IF(ISNUMBER($S26),$S26*Parâmetros!$B$4,"") | V26: =IF(ISNUMBER($S26),$S26*Parâmetros!$C$4,"") | W26: =IF(ISNUMBER($S26),$S26-$D26-IF(ISNUMBER($E26),$E26,0)-$O26-$T26-$U26-$V26,"") | X26: =IF(AND(ISNUMBER($S26),$S26>0),$W26/$S26,"")
A27: =IF(Produtos!$A27="","",Produtos!$A27) -> L2025-A | B27: =IF(Produtos!$A27="","",Produtos!$B27) -> Lixeira Aço Inox c/Aro 20x25 07L | C27: =IF(Produtos!$A27="","",Produtos!$C27) -> Lixeiras em inox | D27: =IF(Produtos!$A27="","",IF(Produtos!$D27="","",Produtos!$D27)) -> 60.21 | E27: 16.85 | F27: =IF($A27="","",IF($C27="","⚠ categoria",IFERROR(INDEX(Parâmetros!$B$13:$B$22,MATCH($C27,Parâmetros!$A$13:$A$22,0)),"⚠ categoria"))) -> 0.13 | H27: =IF($A27="","",IF(ISNUMBER($G27),$G27,IF(ISNUMBER($F27),$F27,""))) -> 0.13 | I27: =IF(OR($A27="",NOT(ISNUMBER($D27)),NOT(ISNUMBER($H27))),"",IF((1-$H27-Parâmetros!$B$4-Parâmetros!$C$4-Parâmetros!$D$4)<=0,"INVALIDO",($D27+IF(ISNUMBER($E27),$E27,0)+IF(ISNUMBER(Parâmetros!$E$4),Parâmetros!$E$4,0))/(1-$H27-Parâmetros!$B$4-Parâmetros!$C$4-Parâmetros!$D$4))) -> 142.7037 | J27: 111.81 | K27: =IF(OR($A27="",NOT(ISNUMBER($D27)),NOT(ISNUMBER($H27))),"",IF(AND(ISNUMBER($J27),$J27>0),$J27,IF(ISNUMBER($I27),$I27,""))) -> 111.81 | L27: =IF(ISNUMBER($K27),$K27*$H27,"") -> 14.5353 | M27: =IF(ISNUMBER($K27),$K27*Parâmetros!$B$4,"") -> 11.181 | N27: =IF(ISNUMBER($K27),$K27*Parâmetros!$C$4,"") -> 3.3543 | O27: =IF(ISNUMBER($K27),IF(ISNUMBER(Parâmetros!$E$4),Parâmetros!$E$4,0),"") -> 0 | P27: =IF(ISNUMBER($K27),$K27-$D27-IF(ISNUMBER($E27),$E27,0)-$L27-$M27-$N27-$O27,"") -> 5.6794 | Q27: =IF(AND(ISNUMBER($K27),$K27>0),$P27/$K27,"") -> 0.050795099 | S27: =IF(OR(NOT(ISNUMBER($R27)),$R27=0,NOT(ISNUMBER($K27))),"",$K27*(1-$R27)) | T27: =IF(ISNUMBER($S27),$S27*$H27,"") | U27: =IF(ISNUMBER($S27),$S27*Parâmetros!$B$4,"") | V27: =IF(ISNUMBER($S27),$S27*Parâmetros!$C$4,"") | W27: =IF(ISNUMBER($S27),$S27-$D27-IF(ISNUMBER($E27),$E27,0)-$O27-$T27-$U27-$V27,"") | X27: =IF(AND(ISNUMBER($S27),$S27>0),$W27/$S27,"")
A28: =IF(Produtos!$A28="","",Produtos!$A28) -> L2030-A | B28: =IF(Produtos!$A28="","",Produtos!$B28) -> Lixeira Aço Inox c/Aro 20x30 10L | C28: =IF(Produtos!$A28="","",Produtos!$C28) -> Lixeiras em inox | D28: =IF(Produtos!$A28="","",IF(Produtos!$D28="","",Produtos!$D28)) -> 68.57 | E28: 24.35 | F28: =IF($A28="","",IF($C28="","⚠ categoria",IFERROR(INDEX(Parâmetros!$B$13:$B$22,MATCH($C28,Parâmetros!$A$13:$A$22,0)),"⚠ categoria"))) -> 0.13 | G28: 0.12 | H28: =IF($A28="","",IF(ISNUMBER($G28),$G28,IF(ISNUMBER($F28),$F28,""))) -> 0.12 | I28: =IF(OR($A28="",NOT(ISNUMBER($D28)),NOT(ISNUMBER($H28))),"",IF((1-$H28-Parâmetros!$B$4-Parâmetros!$C$4-Parâmetros!$D$4)<=0,"INVALIDO",($D28+IF(ISNUMBER($E28),$E28,0)+IF(ISNUMBER(Parâmetros!$E$4),Parâmetros!$E$4,0))/(1-$H28-Parâmetros!$B$4-Parâmetros!$C$4-Parâmetros!$D$4))) -> 168.94545 | J28: 169.467 | K28: =IF(OR($A28="",NOT(ISNUMBER($D28)),NOT(ISNUMBER($H28))),"",IF(AND(ISNUMBER($J28),$J28>0),$J28,IF(ISNUMBER($I28),$I28,""))) -> 169.467 | L28: =IF(ISNUMBER($K28),$K28*$H28,"") -> 20.33604 | M28: =IF(ISNUMBER($K28),$K28*Parâmetros!$B$4,"") -> 16.9467 | N28: =IF(ISNUMBER($K28),$K28*Parâmetros!$C$4,"") -> 5.08401 | O28: =IF(ISNUMBER($K28),IF(ISNUMBER(Parâmetros!$E$4),Parâmetros!$E$4,0),"") -> 0 | P28: =IF(ISNUMBER($K28),$K28-$D28-IF(ISNUMBER($E28),$E28,0)-$L28-$M28-$N28-$O28,"") -> 34.18025 | Q28: =IF(AND(ISNUMBER($K28),$K28>0),$P28/$K28,"") -> 0.20169266 | S28: =IF(OR(NOT(ISNUMBER($R28)),$R28=0,NOT(ISNUMBER($K28))),"",$K28*(1-$R28)) | T28: =IF(ISNUMBER($S28),$S28*$H28,"") | U28: =IF(ISNUMBER($S28),$S28*Parâmetros!$B$4,"") | V28: =IF(ISNUMBER($S28),$S28*Parâmetros!$C$4,"") | W28: =IF(ISNUMBER($S28),$S28-$D28-IF(ISNUMBER($E28),$E28,0)-$O28-$T28-$U28-$V28,"") | X28: =IF(AND(ISNUMBER($S28),$S28>0),$W28/$S28,"") | Y28: 02/10
A29: =IF(Produtos!$A29="","",Produtos!$A29) -> L2425-A | B29: =IF(Produtos!$A29="","",Produtos!$B29) -> Lixeira Aço Inox c/Aro 24x25 13L | C29: =IF(Produtos!$A29="","",Produtos!$C29) -> Lixeiras em inox | D29: =IF(Produtos!$A29="","",IF(Produtos!$D29="","",Produtos!$D29)) -> 79.66 | E29: 24.35 | F29: =IF($A29="","",IF($C29="","⚠ categoria",IFERROR(INDEX(Parâmetros!$B$13:$B$22,MATCH($C29,Parâmetros!$A$13:$A$22,0)),"⚠ categoria"))) -> 0.13 | G29: 0.12 | H29: =IF($A29="","",IF(ISNUMBER($G29),$G29,IF(ISNUMBER($F29),$F29,""))) -> 0.12 | I29: =IF(OR($A29="",NOT(ISNUMBER($D29)),NOT(ISNUMBER($H29))),"",IF((1-$H29-Parâmetros!$B$4-Parâmetros!$C$4-Parâmetros!$D$4)<=0,"INVALIDO",($D29+IF(ISNUMBER($E29),$E29,0)+IF(ISNUMBER(Parâmetros!$E$4),Parâmetros!$E$4,0))/(1-$H29-Parâmetros!$B$4-Parâmetros!$C$4-Parâmetros!$D$4))) -> 189.10909 | J29: 189.85618 | K29: =IF(OR($A29="",NOT(ISNUMBER($D29)),NOT(ISNUMBER($H29))),"",IF(AND(ISNUMBER($J29),$J29>0),$J29,IF(ISNUMBER($I29),$I29,""))) -> 189.85618 | L29: =IF(ISNUMBER($K29),$K29*$H29,"") -> 22.782741 | M29: =IF(ISNUMBER($K29),$K29*Parâmetros!$B$4,"") -> 18.985618 | N29: =IF(ISNUMBER($K29),$K29*Parâmetros!$C$4,"") -> 5.6956853 | O29: =IF(ISNUMBER($K29),IF(ISNUMBER(Parâmetros!$E$4),Parâmetros!$E$4,0),"") -> 0 | P29: =IF(ISNUMBER($K29),$K29-$D29-IF(ISNUMBER($E29),$E29,0)-$L29-$M29-$N29-$O29,"") -> 38.382131 | Q29: =IF(AND(ISNUMBER($K29),$K29>0),$P29/$K29,"") -> 0.20216425 | S29: =IF(OR(NOT(ISNUMBER($R29)),$R29=0,NOT(ISNUMBER($K29))),"",$K29*(1-$R29)) | T29: =IF(ISNUMBER($S29),$S29*$H29,"") | U29: =IF(ISNUMBER($S29),$S29*Parâmetros!$B$4,"") | V29: =IF(ISNUMBER($S29),$S29*Parâmetros!$C$4,"") | W29: =IF(ISNUMBER($S29),$S29-$D29-IF(ISNUMBER($E29),$E29,0)-$O29-$T29-$U29-$V29,"") | X29: =IF(AND(ISNUMBER($S29),$S29>0),$W29/$S29,"") | Y29: 02/10
A30: =IF(Produtos!$A30="","",Produtos!$A30) -> L2430-A | B30: =IF(Produtos!$A30="","",Produtos!$B30) -> Lixeira Aço Inox c/Aro 24x30 15L | C30: =IF(Produtos!$A30="","",Produtos!$C30) -> Lixeiras em inox | D30: =IF(Produtos!$A30="","",IF(Produtos!$D30="","",Produtos!$D30)) -> 91.16 | E30: 27.05 | F30: =IF($A30="","",IF($C30="","⚠ categoria",IFERROR(INDEX(Parâmetros!$B$13:$B$22,MATCH($C30,Parâmetros!$A$13:$A$22,0)),"⚠ categoria"))) -> 0.13 | G30: 0.12 | H30: =IF($A30="","",IF(ISNUMBER($G30),$G30,IF(ISNUMBER($F30),$F30,""))) -> 0.12 | I30: =IF(OR($A30="",NOT(ISNUMBER($D30)),NOT(ISNUMBER($H30))),"",IF((1-$H30-Parâmetros!$B$4-Parâmetros!$C$4-Parâmetros!$D$4)<=0,"INVALIDO",($D30+IF(ISNUMBER($E30),$E30,0)+IF(ISNUMBER(Parâmetros!$E$4),Parâmetros!$E$4,0))/(1-$H30-Parâmetros!$B$4-Parâmetros!$C$4-Parâmetros!$D$4))) -> 214.92727 | J30: 216.407 | K30: =IF(OR($A30="",NOT(ISNUMBER($D30)),NOT(ISNUMBER($H30))),"",IF(AND(ISNUMBER($J30),$J30>0),$J30,IF(ISNUMBER($I30),$I30,""))) -> 216.407 | L30: =IF(ISNUMBER($K30),$K30*$H30,"") -> 25.96884 | M30: =IF(ISNUMBER($K30),$K30*Parâmetros!$B$4,"") -> 21.6407 | N30: =IF(ISNUMBER($K30),$K30*Parâmetros!$C$4,"") -> 6.49221 | O30: =IF(ISNUMBER($K30),IF(ISNUMBER(Parâmetros!$E$4),Parâmetros!$E$4,0),"") -> 0 | P30: =IF(ISNUMBER($K30),$K30-$D30-IF(ISNUMBER($E30),$E30,0)-$L30-$M30-$N30-$O30,"") -> 44.09525 | Q30: =IF(AND(ISNUMBER($K30),$K30>0),$P30/$K30,"") -> 0.20376074 | S30: =IF(OR(NOT(ISNUMBER($R30)),$R30=0,NOT(ISNUMBER($K30))),"",$K30*(1-$R30)) | T30: =IF(ISNUMBER($S30),$S30*$H30,"") | U30: =IF(ISNUMBER($S30),$S30*Parâmetros!$B$4,"") | V30: =IF(ISNUMBER($S30),$S30*Parâmetros!$C$4,"") | W30: =IF(ISNUMBER($S30),$S30-$D30-IF(ISNUMBER($E30),$E30,0)-$O30-$T30-$U30-$V30,"") | X30: =IF(AND(ISNUMBER($S30),$S30>0),$W30/$S30,"") | Y30: 09/10
A31: =IF(Produtos!$A31="","",Produtos!$A31) -> L2440-A | B31: =IF(Produtos!$A31="","",Produtos!$B31) -> Lixeira Aço Inox c/Aro 24x40 20L | C31: =IF(Produtos!$A31="","",Produtos!$C31) -> Lixeiras em inox | D31: =IF(Produtos!$A31="","",IF(Produtos!$D31="","",Produtos!$D31)) -> 102.19 | E31: 29.25 | F31: =IF($A31="","",IF($C31="","⚠ categoria",IFERROR(INDEX(Parâmetros!$B$13:$B$22,MATCH($C31,Parâmetros!$A$13:$A$22,0)),"⚠ categoria"))) -> 0.13 | G31: 0.12 | H31: =IF($A31="","",IF(ISNUMBER($G31),$G31,IF(ISNUMBER($F31),$F31,""))) -> 0.12 | I31: =IF(OR($A31="",NOT(ISNUMBER($D31)),NOT(ISNUMBER($H31))),"",IF((1-$H31-Parâmetros!$B$4-Parâmetros!$C$4-Parâmetros!$D$4)<=0,"INVALIDO",($D31+IF(ISNUMBER($E31),$E31,0)+IF(ISNUMBER(Parâmetros!$E$4),Parâmetros!$E$4,0))/(1-$H31-Parâmetros!$B$4-Parâmetros!$C$4-Parâmetros!$D$4))) -> 238.98182 | J31: 240.24192 | K31: =IF(OR($A31="",NOT(ISNUMBER($D31)),NOT(ISNUMBER($H31))),"",IF(AND(ISNUMBER($J31),$J31>0),$J31,IF(ISNUMBER($I31),$I31,""))) -> 240.24192 | L31: =IF(ISNUMBER($K31),$K31*$H31,"") -> 28.82903 | M31: =IF(ISNUMBER($K31),$K31*Parâmetros!$B$4,"") -> 24.024192 | N31: =IF(ISNUMBER($K31),$K31*Parâmetros!$C$4,"") -> 7.2072575 | O31: =IF(ISNUMBER($K31),IF(ISNUMBER(Parâmetros!$E$4),Parâmetros!$E$4,0),"") -> 0 | P31: =IF(ISNUMBER($K31),$K31-$D31-IF(ISNUMBER($E31),$E31,0)-$L31-$M31-$N31-$O31,"") -> 48.741437 | Q31: =IF(AND(ISNUMBER($K31),$K31>0),$P31/$K31,"") -> 0.20288482 | S31: =IF(OR(NOT(ISNUMBER($R31)),$R31=0,NOT(ISNUMBER($K31))),"",$K31*(1-$R31)) | T31: =IF(ISNUMBER($S31),$S31*$H31,"") | U31: =IF(ISNUMBER($S31),$S31*Parâmetros!$B$4,"") | V31: =IF(ISNUMBER($S31),$S31*Parâmetros!$C$4,"") | W31: =IF(ISNUMBER($S31),$S31-$D31-IF(ISNUMBER($E31),$E31,0)-$O31-$T31-$U31-$V31,"") | X31: =IF(AND(ISNUMBER($S31),$S31>0),$W31/$S31,"") | Y31: 02/10
A32: =IF(Produtos!$A32="","",Produtos!$A32) -> L2450-A | B32: =IF(Produtos!$A32="","",Produtos!$B32) -> Lixeira Aço Inox c/Aro 24x50 25L | C32: =IF(Produtos!$A32="","",Produtos!$C32) -> Lixeiras em inox | D32: =IF(Produtos!$A32="","",IF(Produtos!$D32="","",Produtos!$D32)) -> 132.03 | E32: 45.25 | F32: =IF($A32="","",IF($C32="","⚠ categoria",IFERROR(INDEX(Parâmetros!$B$13:$B$22,MATCH($C32,Parâmetros!$A$13:$A$22,0)),"⚠ categoria"))) -> 0.13 | G32: 0.12 | H32: =IF($A32="","",IF(ISNUMBER($G32),$G32,IF(ISNUMBER($F32),$F32,""))) -> 0.12 | I32: =IF(OR($A32="",NOT(ISNUMBER($D32)),NOT(ISNUMBER($H32))),"",IF((1-$H32-Parâmetros!$B$4-Parâmetros!$C$4-Parâmetros!$D$4)<=0,"INVALIDO",($D32+IF(ISNUMBER($E32),$E32,0)+IF(ISNUMBER(Parâmetros!$E$4),Parâmetros!$E$4,0))/(1-$H32-Parâmetros!$B$4-Parâmetros!$C$4-Parâmetros!$D$4))) -> 322.32727 | J32: 325.6 | K32: =IF(OR($A32="",NOT(ISNUMBER($D32)),NOT(ISNUMBER($H32))),"",IF(AND(ISNUMBER($J32),$J32>0),$J32,IF(ISNUMBER($I32),$I32,""))) -> 325.6 | L32: =IF(ISNUMBER($K32),$K32*$H32,"") -> 39.072 | M32: =IF(ISNUMBER($K32),$K32*Parâmetros!$B$4,"") -> 32.56 | N32: =IF(ISNUMBER($K32),$K32*Parâmetros!$C$4,"") -> 9.768 | O32: =IF(ISNUMBER($K32),IF(ISNUMBER(Parâmetros!$E$4),Parâmetros!$E$4,0),"") -> 0 | P32: =IF(ISNUMBER($K32),$K32-$D32-IF(ISNUMBER($E32),$E32,0)-$L32-$M32-$N32-$O32,"") -> 66.92 | Q32: =IF(AND(ISNUMBER($K32),$K32>0),$P32/$K32,"") -> 0.20552826 | S32: =IF(OR(NOT(ISNUMBER($R32)),$R32=0,NOT(ISNUMBER($K32))),"",$K32*(1-$R32)) | T32: =IF(ISNUMBER($S32),$S32*$H32,"") | U32: =IF(ISNUMBER($S32),$S32*Parâmetros!$B$4,"") | V32: =IF(ISNUMBER($S32),$S32*Parâmetros!$C$4,"") | W32: =IF(ISNUMBER($S32),$S32-$D32-IF(ISNUMBER($E32),$E32,0)-$O32-$T32-$U32-$V32,"") | X32: =IF(AND(ISNUMBER($S32),$S32>0),$W32/$S32,"") | Y32: 09/10
A33: =IF(Produtos!$A33="","",Produtos!$A33) -> L2460-A | B33: =IF(Produtos!$A33="","",Produtos!$B33) -> Lixeira Aço Inox c/Aro 24x60 27L | C33: =IF(Produtos!$A33="","",Produtos!$C33) -> Lixeiras em inox | D33: =IF(Produtos!$A33="","",IF(Produtos!$D33="","",Produtos!$D33)) -> 136.09 | E33: 40.85 | F33: =IF($A33="","",IF($C33="","⚠ categoria",IFERROR(INDEX(Parâmetros!$B$13:$B$22,MATCH($C33,Parâmetros!$A$13:$A$22,0)),"⚠ categoria"))) -> 0.13 | G33: 0.12 | H33: =IF($A33="","",IF(ISNUMBER($G33),$G33,IF(ISNUMBER($F33),$F33,""))) -> 0.12 | I33: =IF(OR($A33="",NOT(ISNUMBER($D33)),NOT(ISNUMBER($H33))),"",IF((1-$H33-Parâmetros!$B$4-Parâmetros!$C$4-Parâmetros!$D$4)<=0,"INVALIDO",($D33+IF(ISNUMBER($E33),$E33,0)+IF(ISNUMBER(Parâmetros!$E$4),Parâmetros!$E$4,0))/(1-$H33-Parâmetros!$B$4-Parâmetros!$C$4-Parâmetros!$D$4))) -> 321.70909 | J33: 321.882 | K33: =IF(OR($A33="",NOT(ISNUMBER($D33)),NOT(ISNUMBER($H33))),"",IF(AND(ISNUMBER($J33),$J33>0),$J33,IF(ISNUMBER($I33),$I33,""))) -> 321.882 | L33: =IF(ISNUMBER($K33),$K33*$H33,"") -> 38.62584 | M33: =IF(ISNUMBER($K33),$K33*Parâmetros!$B$4,"") -> 32.1882 | N33: =IF(ISNUMBER($K33),$K33*Parâmetros!$C$4,"") -> 9.65646 | O33: =IF(ISNUMBER($K33),IF(ISNUMBER(Parâmetros!$E$4),Parâmetros!$E$4,0),"") -> 0 | P33: =IF(ISNUMBER($K33),$K33-$D33-IF(ISNUMBER($E33),$E33,0)-$L33-$M33-$N33-$O33,"") -> 64.4715 | Q33: =IF(AND(ISNUMBER($K33),$K33>0),$P33/$K33,"") -> 0.20029545 | S33: =IF(OR(NOT(ISNUMBER($R33)),$R33=0,NOT(ISNUMBER($K33))),"",$K33*(1-$R33)) | T33: =IF(ISNUMBER($S33),$S33*$H33,"") | U33: =IF(ISNUMBER($S33),$S33*Parâmetros!$B$4,"") | V33: =IF(ISNUMBER($S33),$S33*Parâmetros!$C$4,"") | W33: =IF(ISNUMBER($S33),$S33-$D33-IF(ISNUMBER($E33),$E33,0)-$O33-$T33-$U33-$V33,"") | X33: =IF(AND(ISNUMBER($S33),$S33>0),$W33/$S33,"") | Y33: 02/10
A34: =IF(Produtos!$A34="","",Produtos!$A34) -> L2470-A | B34: =IF(Produtos!$A34="","",Produtos!$B34) -> Lixeira Aço Inox c/Aro 24x70 30L | C34: =IF(Produtos!$A34="","",Produtos!$C34) -> Lixeiras em inox | D34: =IF(Produtos!$A34="","",IF(Produtos!$D34="","",Produtos!$D34)) -> 203.27 | E34: 45.25 | F34: =IF($A34="","",IF($C34="","⚠ categoria",IFERROR(INDEX(Parâmetros!$B$13:$B$22,MATCH($C34,Parâmetros!$A$13:$A$22,0)),"⚠ categoria"))) -> 0.13 | G34: 0.105 | H34: =IF($A34="","",IF(ISNUMBER($G34),$G34,IF(ISNUMBER($F34),$F34,""))) -> 0.105 | I34: =IF(OR($A34="",NOT(ISNUMBER($D34)),NOT(ISNUMBER($H34))),"",IF((1-$H34-Parâmetros!$B$4-Parâmetros!$C$4-Parâmetros!$D$4)<=0,"INVALIDO",($D34+IF(ISNUMBER($E34),$E34,0)+IF(ISNUMBER(Parâmetros!$E$4),Parâmetros!$E$4,0))/(1-$H34-Parâmetros!$B$4-Parâmetros!$C$4-Parâmetros!$D$4))) -> 439.85841 | J34: 440.83518 | K34: =IF(OR($A34="",NOT(ISNUMBER($D34)),NOT(ISNUMBER($H34))),"",IF(AND(ISNUMBER($J34),$J34>0),$J34,IF(ISNUMBER($I34),$I34,""))) -> 440.83518 | L34: =IF(ISNUMBER($K34),$K34*$H34,"") -> 46.287694 | M34: =IF(ISNUMBER($K34),$K34*Parâmetros!$B$4,"") -> 44.083518 | N34: =IF(ISNUMBER($K34),$K34*Parâmetros!$C$4,"") -> 13.225055 | O34: =IF(ISNUMBER($K34),IF(ISNUMBER(Parâmetros!$E$4),Parâmetros!$E$4,0),"") -> 0 | P34: =IF(ISNUMBER($K34),$K34-$D34-IF(ISNUMBER($E34),$E34,0)-$L34-$M34-$N34-$O34,"") -> 88.71891 | Q34: =IF(AND(ISNUMBER($K34),$K34>0),$P34/$K34,"") -> 0.20125188 | S34: =IF(OR(NOT(ISNUMBER($R34)),$R34=0,NOT(ISNUMBER($K34))),"",$K34*(1-$R34)) | T34: =IF(ISNUMBER($S34),$S34*$H34,"") | U34: =IF(ISNUMBER($S34),$S34*Parâmetros!$B$4,"") | V34: =IF(ISNUMBER($S34),$S34*Parâmetros!$C$4,"") | W34: =IF(ISNUMBER($S34),$S34-$D34-IF(ISNUMBER($E34),$E34,0)-$O34-$T34-$U34-$V34,"") | X34: =IF(AND(ISNUMBER($S34),$S34>0),$W34/$S34,"") | Y34: 02/10
A35: =IF(Produtos!$A35="","",Produtos!$A35) -> L3040-A | B35: =IF(Produtos!$A35="","",Produtos!$B35) -> Lixeira Aço Inox c/Aro 30x40 30L | C35: =IF(Produtos!$A35="","",Produtos!$C35) -> Lixeiras em inox | D35: =IF(Produtos!$A35="","",IF(Produtos!$D35="","",Produtos!$D35)) -> 151.33 | E35: 49.35 | F35: =IF($A35="","",IF($C35="","⚠ categoria",IFERROR(INDEX(Parâmetros!$B$13:$B$22,MATCH($C35,Parâmetros!$A$13:$A$22,0)),"⚠ categoria"))) -> 0.13 | G35: 0.12 | H35: =IF($A35="","",IF(ISNUMBER($G35),$G35,IF(ISNUMBER($F35),$F35,""))) -> 0.12 | I35: =IF(OR($A35="",NOT(ISNUMBER($D35)),NOT(ISNUMBER($H35))),"",IF((1-$H35-Parâmetros!$B$4-Parâmetros!$C$4-Parâmetros!$D$4)<=0,"INVALIDO",($D35+IF(ISNUMBER($E35),$E35,0)+IF(ISNUMBER(Parâmetros!$E$4),Parâmetros!$E$4,0))/(1-$H35-Parâmetros!$B$4-Parâmetros!$C$4-Parâmetros!$D$4))) -> 364.87273 | J35: 365.87244 | K35: =IF(OR($A35="",NOT(ISNUMBER($D35)),NOT(ISNUMBER($H35))),"",IF(AND(ISNUMBER($J35),$J35>0),$J35,IF(ISNUMBER($I35),$I35,""))) -> 365.87244 | L35: =IF(ISNUMBER($K35),$K35*$H35,"") -> 43.904693 | M35: =IF(ISNUMBER($K35),$K35*Parâmetros!$B$4,"") -> 36.587244 | N35: =IF(ISNUMBER($K35),$K35*Parâmetros!$C$4,"") -> 10.976173 | O35: =IF(ISNUMBER($K35),IF(ISNUMBER(Parâmetros!$E$4),Parâmetros!$E$4,0),"") -> 0 | P35: =IF(ISNUMBER($K35),$K35-$D35-IF(ISNUMBER($E35),$E35,0)-$L35-$M35-$N35-$O35,"") -> 73.724333 | Q35: =IF(AND(ISNUMBER($K35),$K35>0),$P35/$K35,"") -> 0.20150283 | S35: =IF(OR(NOT(ISNUMBER($R35)),$R35=0,NOT(ISNUMBER($K35))),"",$K35*(1-$R35)) | T35: =IF(ISNUMBER($S35),$S35*$H35,"") | U35: =IF(ISNUMBER($S35),$S35*Parâmetros!$B$4,"") | V35: =IF(ISNUMBER($S35),$S35*Parâmetros!$C$4,"") | W35: =IF(ISNUMBER($S35),$S35-$D35-IF(ISNUMBER($E35),$E35,0)-$O35-$T35-$U35-$V35,"") | X35: =IF(AND(ISNUMBER($S35),$S35>0),$W35/$S35,"") | Y35: 09/10
A36: =IF(Produtos!$A36="","",Produtos!$A36) -> L3050-A | B36: =IF(Produtos!$A36="","",Produtos!$B36) -> Lixeira Aço Inox c/Aro 30x50 35L | C36: =IF(Produtos!$A36="","",Produtos!$C36) -> Lixeiras em inox | D36: =IF(Produtos!$A36="","",IF(Produtos!$D36="","",Produtos!$D36)) -> 189.66 | E36: 49.35 | F36: =IF($A36="","",IF($C36="","⚠ categoria",IFERROR(INDEX(Parâmetros!$B$13:$B$22,MATCH($C36,Parâmetros!$A$13:$A$22,0)),"⚠ categoria"))) -> 0.13 | G36: 0.12 | H36: =IF($A36="","",IF(ISNUMBER($G36),$G36,IF(ISNUMBER($F36),$F36,""))) -> 0.12 | I36: =IF(OR($A36="",NOT(ISNUMBER($D36)),NOT(ISNUMBER($H36))),"",IF((1-$H36-Parâmetros!$B$4-Parâmetros!$C$4-Parâmetros!$D$4)<=0,"INVALIDO",($D36+IF(ISNUMBER($E36),$E36,0)+IF(ISNUMBER(Parâmetros!$E$4),Parâmetros!$E$4,0))/(1-$H36-Parâmetros!$B$4-Parâmetros!$C$4-Parâmetros!$D$4))) -> 434.56364 | J36: 436.77446 | K36: =IF(OR($A36="",NOT(ISNUMBER($D36)),NOT(ISNUMBER($H36))),"",IF(AND(ISNUMBER($J36),$J36>0),$J36,IF(ISNUMBER($I36),$I36,""))) -> 436.77446 | L36: =IF(ISNUMBER($K36),$K36*$H36,"") -> 52.412935 | M36: =IF(ISNUMBER($K36),$K36*Parâmetros!$B$4,"") -> 43.677446 | N36: =IF(ISNUMBER($K36),$K36*Parâmetros!$C$4,"") -> 13.103234 | O36: =IF(ISNUMBER($K36),IF(ISNUMBER(Parâmetros!$E$4),Parâmetros!$E$4,0),"") -> 0 | P36: =IF(ISNUMBER($K36),$K36-$D36-IF(ISNUMBER($E36),$E36,0)-$L36-$M36-$N36-$O36,"") -> 88.570842 | Q36: =IF(AND(ISNUMBER($K36),$K36>0),$P36/$K36,"") -> 0.20278393 | S36: =IF(OR(NOT(ISNUMBER($R36)),$R36=0,NOT(ISNUMBER($K36))),"",$K36*(1-$R36)) | T36: =IF(ISNUMBER($S36),$S36*$H36,"") | U36: =IF(ISNUMBER($S36),$S36*Parâmetros!$B$4,"") | V36: =IF(ISNUMBER($S36),$S36*Parâmetros!$C$4,"") | W36: =IF(ISNUMBER($S36),$S36-$D36-IF(ISNUMBER($E36),$E36,0)-$O36-$T36-$U36-$V36,"") | X36: =IF(AND(ISNUMBER($S36),$S36>0),$W36/$S36,"") | Y36: 09/10
A37: =IF(Produtos!$A37="","",Produtos!$A37) -> L3060-A | B37: =IF(Produtos!$A37="","",Produtos!$B37) -> Lixeira Aço Inox c/Aro 30x60 40L | C37: =IF(Produtos!$A37="","",Produtos!$C37) -> Lixeiras em inox | D37: =IF(Produtos!$A37="","",IF(Produtos!$D37="","",Produtos!$D37)) -> 205.57 | E37: 50.75 | F37: =IF($A37="","",IF($C37="","⚠ categoria",IFERROR(INDEX(Parâmetros!$B$13:$B$22,MATCH($C37,Parâmetros!$A$13:$A$22,0)),"⚠ categoria"))) -> 0.13 | G37: 0.12 | H37: =IF($A37="","",IF(ISNUMBER($G37),$G37,IF(ISNUMBER($F37),$F37,""))) -> 0.12 | I37: =IF(OR($A37="",NOT(ISNUMBER($D37)),NOT(ISNUMBER($H37))),"",IF((1-$H37-Parâmetros!$B$4-Parâmetros!$C$4-Parâmetros!$D$4)<=0,"INVALIDO",($D37+IF(ISNUMBER($E37),$E37,0)+IF(ISNUMBER(Parâmetros!$E$4),Parâmetros!$E$4,0))/(1-$H37-Parâmetros!$B$4-Parâmetros!$C$4-Parâmetros!$D$4))) -> 466.03636 | J37: 469.15372 | K37: =IF(OR($A37="",NOT(ISNUMBER($D37)),NOT(ISNUMBER($H37))),"",IF(AND(ISNUMBER($J37),$J37>0),$J37,IF(ISNUMBER($I37),$I37,""))) -> 469.15372 | L37: =IF(ISNUMBER($K37),$K37*$H37,"") -> 56.298446 | M37: =IF(ISNUMBER($K37),$K37*Parâmetros!$B$4,"") -> 46.915372 | N37: =IF(ISNUMBER($K37),$K37*Parâmetros!$C$4,"") -> 14.074612 | O37: =IF(ISNUMBER($K37),IF(ISNUMBER(Parâmetros!$E$4),Parâmetros!$E$4,0),"") -> 0 | P37: =IF(ISNUMBER($K37),$K37-$D37-IF(ISNUMBER($E37),$E37,0)-$L37-$M37-$N37-$O37,"") -> 95.545289 | Q37: =IF(AND(ISNUMBER($K37),$K37>0),$P37/$K37,"") -> 0.20365455 | S37: =IF(OR(NOT(ISNUMBER($R37)),$R37=0,NOT(ISNUMBER($K37))),"",$K37*(1-$R37)) | T37: =IF(ISNUMBER($S37),$S37*$H37,"") | U37: =IF(ISNUMBER($S37),$S37*Parâmetros!$B$4,"") | V37: =IF(ISNUMBER($S37),$S37*Parâmetros!$C$4,"") | W37: =IF(ISNUMBER($S37),$S37-$D37-IF(ISNUMBER($E37),$E37,0)-$O37-$T37-$U37-$V37,"") | X37: =IF(AND(ISNUMBER($S37),$S37>0),$W37/$S37,"") | Y37: 09/10
A38: =IF(Produtos!$A38="","",Produtos!$A38) -> L3070-A | B38: =IF(Produtos!$A38="","",Produtos!$B38) -> Lixeira Aço Inox c/Aro 30x70 50L | C38: =IF(Produtos!$A38="","",Produtos!$C38) -> Lixeiras em inox | D38: =IF(Produtos!$A38="","",IF(Produtos!$D38="","",Produtos!$D38)) -> 258.22 | E38: 69.35 | F38: =IF($A38="","",IF($C38="","⚠ categoria",IFERROR(INDEX(Parâmetros!$B$13:$B$22,MATCH($C38,Parâmetros!$A$13:$A$22,0)),"⚠ categoria"))) -> 0.13 | G38: 0.12 | H38: =IF($A38="","",IF(ISNUMBER($G38),$G38,IF(ISNUMBER($F38),$F38,""))) -> 0.12 | I38: =IF(OR($A38="",NOT(ISNUMBER($D38)),NOT(ISNUMBER($H38))),"",IF((1-$H38-Parâmetros!$B$4-Parâmetros!$C$4-Parâmetros!$D$4)<=0,"INVALIDO",($D38+IF(ISNUMBER($E38),$E38,0)+IF(ISNUMBER(Parâmetros!$E$4),Parâmetros!$E$4,0))/(1-$H38-Parâmetros!$B$4-Parâmetros!$C$4-Parâmetros!$D$4))) -> 595.58182 | J38: 595.9 | K38: =IF(OR($A38="",NOT(ISNUMBER($D38)),NOT(ISNUMBER($H38))),"",IF(AND(ISNUMBER($J38),$J38>0),$J38,IF(ISNUMBER($I38),$I38,""))) -> 595.9 | L38: =IF(ISNUMBER($K38),$K38*$H38,"") -> 71.508 | M38: =IF(ISNUMBER($K38),$K38*Parâmetros!$B$4,"") -> 59.59 | N38: =IF(ISNUMBER($K38),$K38*Parâmetros!$C$4,"") -> 17.877 | O38: =IF(ISNUMBER($K38),IF(ISNUMBER(Parâmetros!$E$4),Parâmetros!$E$4,0),"") -> 0 | P38: =IF(ISNUMBER($K38),$K38-$D38-IF(ISNUMBER($E38),$E38,0)-$L38-$M38-$N38-$O38,"") -> 119.355 | Q38: =IF(AND(ISNUMBER($K38),$K38>0),$P38/$K38,"") -> 0.20029367 | S38: =IF(OR(NOT(ISNUMBER($R38)),$R38=0,NOT(ISNUMBER($K38))),"",$K38*(1-$R38)) | T38: =IF(ISNUMBER($S38),$S38*$H38,"") | U38: =IF(ISNUMBER($S38),$S38*Parâmetros!$B$4,"") | V38: =IF(ISNUMBER($S38),$S38*Parâmetros!$C$4,"") | W38: =IF(ISNUMBER($S38),$S38-$D38-IF(ISNUMBER($E38),$E38,0)-$O38-$T38-$U38-$V38,"") | X38: =IF(AND(ISNUMBER($S38),$S38>0),$W38/$S38,"") | Y38: 09/10
A39: =IF(Produtos!$A39="","",Produtos!$A39) -> L3085-A | B39: =IF(Produtos!$A39="","",Produtos!$B39) -> Lixeira Aço Inox c/Aro 30x85 60L | C39: =IF(Produtos!$A39="","",Produtos!$C39) -> Lixeiras em inox | D39: =IF(Produtos!$A39="","",IF(Produtos!$D39="","",Produtos!$D39)) -> 321.8 | E39: 68.65 | F39: =IF($A39="","",IF($C39="","⚠ categoria",IFERROR(INDEX(Parâmetros!$B$13:$B$22,MATCH($C39,Parâmetros!$A$13:$A$22,0)),"⚠ categoria"))) -> 0.13 | G39: 0.12 | H39: =IF($A39="","",IF(ISNUMBER($G39),$G39,IF(ISNUMBER($F39),$F39,""))) -> 0.12 | I39: =IF(OR($A39="",NOT(ISNUMBER($D39)),NOT(ISNUMBER($H39))),"",IF((1-$H39-Parâmetros!$B$4-Parâmetros!$C$4-Parâmetros!$D$4)<=0,"INVALIDO",($D39+IF(ISNUMBER($E39),$E39,0)+IF(ISNUMBER(Parâmetros!$E$4),Parâmetros!$E$4,0))/(1-$H39-Parâmetros!$B$4-Parâmetros!$C$4-Parâmetros!$D$4))) -> 709.90909 | J39: 711.94814 | K39: =IF(OR($A39="",NOT(ISNUMBER($D39)),NOT(ISNUMBER($H39))),"",IF(AND(ISNUMBER($J39),$J39>0),$J39,IF(ISNUMBER($I39),$I39,""))) -> 711.94814 | L39: =IF(ISNUMBER($K39),$K39*$H39,"") -> 85.433777 | M39: =IF(ISNUMBER($K39),$K39*Parâmetros!$B$4,"") -> 71.194814 | N39: =IF(ISNUMBER($K39),$K39*Parâmetros!$C$4,"") -> 21.358444 | O39: =IF(ISNUMBER($K39),IF(ISNUMBER(Parâmetros!$E$4),Parâmetros!$E$4,0),"") -> 0 | P39: =IF(ISNUMBER($K39),$K39-$D39-IF(ISNUMBER($E39),$E39,0)-$L39-$M39-$N39-$O39,"") -> 143.51111 | Q39: =IF(AND(ISNUMBER($K39),$K39>0),$P39/$K39,"") -> 0.20157523 | S39: =IF(OR(NOT(ISNUMBER($R39)),$R39=0,NOT(ISNUMBER($K39))),"",$K39*(1-$R39)) | T39: =IF(ISNUMBER($S39),$S39*$H39,"") | U39: =IF(ISNUMBER($S39),$S39*Parâmetros!$B$4,"") | V39: =IF(ISNUMBER($S39),$S39*Parâmetros!$C$4,"") | W39: =IF(ISNUMBER($S39),$S39-$D39-IF(ISNUMBER($E39),$E39,0)-$O39-$T39-$U39-$V39,"") | X39: =IF(AND(ISNUMBER($S39),$S39>0),$W39/$S39,"") | Y39: 19/08
A40: =IF(Produtos!$A40="","",Produtos!$A40) -> L4050-A | B40: =IF(Produtos!$A40="","",Produtos!$B40) -> Lixeira Aço Inox c/Aro 40x50 62L | C40: =IF(Produtos!$A40="","",Produtos!$C40) -> Lixeiras em inox | D40: =IF(Produtos!$A40="","",IF(Produtos!$D40="","",Produtos!$D40)) -> 292.43 | E40: 75.65 | F40: =IF($A40="","",IF($C40="","⚠ categoria",IFERROR(INDEX(Parâmetros!$B$13:$B$22,MATCH($C40,Parâmetros!$A$13:$A$22,0)),"⚠ categoria"))) -> 0.13 | G40: 0.12 | H40: =IF($A40="","",IF(ISNUMBER($G40),$G40,IF(ISNUMBER($F40),$F40,""))) -> 0.12 | I40: =IF(OR($A40="",NOT(ISNUMBER($D40)),NOT(ISNUMBER($H40))),"",IF((1-$H40-Parâmetros!$B$4-Parâmetros!$C$4-Parâmetros!$D$4)<=0,"INVALIDO",($D40+IF(ISNUMBER($E40),$E40,0)+IF(ISNUMBER(Parâmetros!$E$4),Parâmetros!$E$4,0))/(1-$H40-Parâmetros!$B$4-Parâmetros!$C$4-Parâmetros!$D$4))) -> 669.23636 | J40: 671.05838 | K40: =IF(OR($A40="",NOT(ISNUMBER($D40)),NOT(ISNUMBER($H40))),"",IF(AND(ISNUMBER($J40),$J40>0),$J40,IF(ISNUMBER($I40),$I40,""))) -> 671.05838 | L40: =IF(ISNUMBER($K40),$K40*$H40,"") -> 80.527006 | M40: =IF(ISNUMBER($K40),$K40*Parâmetros!$B$4,"") -> 67.105838 | N40: =IF(ISNUMBER($K40),$K40*Parâmetros!$C$4,"") -> 20.131751 | O40: =IF(ISNUMBER($K40),IF(ISNUMBER(Parâmetros!$E$4),Parâmetros!$E$4,0),"") -> 0 | P40: =IF(ISNUMBER($K40),$K40-$D40-IF(ISNUMBER($E40),$E40,0)-$L40-$M40-$N40-$O40,"") -> 135.21379 | Q40: =IF(AND(ISNUMBER($K40),$K40>0),$P40/$K40,"") -> 0.20149333 | S40: =IF(OR(NOT(ISNUMBER($R40)),$R40=0,NOT(ISNUMBER($K40))),"",$K40*(1-$R40)) | T40: =IF(ISNUMBER($S40),$S40*$H40,"") | U40: =IF(ISNUMBER($S40),$S40*Parâmetros!$B$4,"") | V40: =IF(ISNUMBER($S40),$S40*Parâmetros!$C$4,"") | W40: =IF(ISNUMBER($S40),$S40-$D40-IF(ISNUMBER($E40),$E40,0)-$O40-$T40-$U40-$V40,"") | X40: =IF(AND(ISNUMBER($S40),$S40>0),$W40/$S40,"") | Y40: 09/10
A41: =IF(Produtos!$A41="","",Produtos!$A41) -> L4060-A | B41: =IF(Produtos!$A41="","",Produtos!$B41) -> Lixeira Aço Inox c/Aro 40x60 75L | C41: =IF(Produtos!$A41="","",Produtos!$C41) -> Lixeiras em inox | D41: =IF(Produtos!$A41="","",IF(Produtos!$D41="","",Produtos!$D41)) -> 329.38 | E41: 79.35 | F41: =IF($A41="","",IF($C41="","⚠ categoria",IFERROR(INDEX(Parâmetros!$B$13:$B$22,MATCH($C41,Parâmetros!$A$13:$A$22,0)),"⚠ categoria"))) -> 0.13 | H41: =IF($A41="","",IF(ISNUMBER($G41),$G41,IF(ISNUMBER($F41),$F41,""))) -> 0.13 | I41: =IF(OR($A41="",NOT(ISNUMBER($D41)),NOT(ISNUMBER($H41))),"",IF((1-$H41-Parâmetros!$B$4-Parâmetros!$C$4-Parâmetros!$D$4)<=0,"INVALIDO",($D41+IF(ISNUMBER($E41),$E41,0)+IF(ISNUMBER(Parâmetros!$E$4),Parâmetros!$E$4,0))/(1-$H41-Parâmetros!$B$4-Parâmetros!$C$4-Parâmetros!$D$4))) -> 756.90741 | J41: 756.46163 | K41: =IF(OR($A41="",NOT(ISNUMBER($D41)),NOT(ISNUMBER($H41))),"",IF(AND(ISNUMBER($J41),$J41>0),$J41,IF(ISNUMBER($I41),$I41,""))) -> 756.46163 | L41: =IF(ISNUMBER($K41),$K41*$H41,"") -> 98.340012 | M41: =IF(ISNUMBER($K41),$K41*Parâmetros!$B$4,"") -> 75.646163 | N41: =IF(ISNUMBER($K41),$K41*Parâmetros!$C$4,"") -> 22.693849 | O41: =IF(ISNUMBER($K41),IF(ISNUMBER(Parâmetros!$E$4),Parâmetros!$E$4,0),"") -> 0 | P41: =IF(ISNUMBER($K41),$K41-$D41-IF(ISNUMBER($E41),$E41,0)-$L41-$M41-$N41-$O41,"") -> 151.05161 | Q41: =IF(AND(ISNUMBER($K41),$K41>0),$P41/$K41,"") -> 0.19968178 | S41: =IF(OR(NOT(ISNUMBER($R41)),$R41=0,NOT(ISNUMBER($K41))),"",$K41*(1-$R41)) | T41: =IF(ISNUMBER($S41),$S41*$H41,"") | U41: =IF(ISNUMBER($S41),$S41*Parâmetros!$B$4,"") | V41: =IF(ISNUMBER($S41),$S41*Parâmetros!$C$4,"") | W41: =IF(ISNUMBER($S41),$S41-$D41-IF(ISNUMBER($E41),$E41,0)-$O41-$T41-$U41-$V41,"") | X41: =IF(AND(ISNUMBER($S41),$S41>0),$W41/$S41,"") | Y41: 02/10
A42: =IF(Produtos!$A42="","",Produtos!$A42) -> L4070-A | B42: =IF(Produtos!$A42="","",Produtos!$B42) -> Lixeira Aço Inox c/Aro 40x70 88L | C42: =IF(Produtos!$A42="","",Produtos!$C42) -> Lixeiras em inox | D42: =IF(Produtos!$A42="","",IF(Produtos!$D42="","",Produtos!$D42)) -> 331.22 | F42: =IF($A42="","",IF($C42="","⚠ categoria",IFERROR(INDEX(Parâmetros!$B$13:$B$22,MATCH($C42,Parâmetros!$A$13:$A$22,0)),"⚠ categoria"))) -> 0.13 | H42: =IF($A42="","",IF(ISNUMBER($G42),$G42,IF(ISNUMBER($F42),$F42,""))) -> 0.13 | I42: =IF(OR($A42="",NOT(ISNUMBER($D42)),NOT(ISNUMBER($H42))),"",IF((1-$H42-Parâmetros!$B$4-Parâmetros!$C$4-Parâmetros!$D$4)<=0,"INVALIDO",($D42+IF(ISNUMBER($E42),$E42,0)+IF(ISNUMBER(Parâmetros!$E$4),Parâmetros!$E$4,0))/(1-$H42-Parâmetros!$B$4-Parâmetros!$C$4-Parâmetros!$D$4))) -> 613.37037 | K42: =IF(OR($A42="",NOT(ISNUMBER($D42)),NOT(ISNUMBER($H42))),"",IF(AND(ISNUMBER($J42),$J42>0),$J42,IF(ISNUMBER($I42),$I42,""))) -> 613.37037 | L42: =IF(ISNUMBER($K42),$K42*$H42,"") -> 79.738148 | M42: =IF(ISNUMBER($K42),$K42*Parâmetros!$B$4,"") -> 61.337037 | N42: =IF(ISNUMBER($K42),$K42*Parâmetros!$C$4,"") -> 18.401111 | O42: =IF(ISNUMBER($K42),IF(ISNUMBER(Parâmetros!$E$4),Parâmetros!$E$4,0),"") -> 0 | P42: =IF(ISNUMBER($K42),$K42-$D42-IF(ISNUMBER($E42),$E42,0)-$L42-$M42-$N42-$O42,"") -> 122.67407 | Q42: =IF(AND(ISNUMBER($K42),$K42>0),$P42/$K42,"") -> 0.2 | S42: =IF(OR(NOT(ISNUMBER($R42)),$R42=0,NOT(ISNUMBER($K42))),"",$K42*(1-$R42)) | T42: =IF(ISNUMBER($S42),$S42*$H42,"") | U42: =IF(ISNUMBER($S42),$S42*Parâmetros!$B$4,"") | V42: =IF(ISNUMBER($S42),$S42*Parâmetros!$C$4,"") | W42: =IF(ISNUMBER($S42),$S42-$D42-IF(ISNUMBER($E42),$E42,0)-$O42-$T42-$U42-$V42,"") | X42: =IF(AND(ISNUMBER($S42),$S42>0),$W42/$S42,"")
A43: =IF(Produtos!$A43="","",Produtos!$A43) -> L4075-A | B43: =IF(Produtos!$A43="","",Produtos!$B43) -> Lixeira Aço Inox c/Aro 40x75 95L | C43: =IF(Produtos!$A43="","",Produtos!$C43) -> Lixeiras em inox | D43: =IF(Produtos!$A43="","",IF(Produtos!$D43="","",Produtos!$D43)) -> 392.8 | F43: =IF($A43="","",IF($C43="","⚠ categoria",IFERROR(INDEX(Parâmetros!$B$13:$B$22,MATCH($C43,Parâmetros!$A$13:$A$22,0)),"⚠ categoria"))) -> 0.13 | H43: =IF($A43="","",IF(ISNUMBER($G43),$G43,IF(ISNUMBER($F43),$F43,""))) -> 0.13 | I43: =IF(OR($A43="",NOT(ISNUMBER($D43)),NOT(ISNUMBER($H43))),"",IF((1-$H43-Parâmetros!$B$4-Parâmetros!$C$4-Parâmetros!$D$4)<=0,"INVALIDO",($D43+IF(ISNUMBER($E43),$E43,0)+IF(ISNUMBER(Parâmetros!$E$4),Parâmetros!$E$4,0))/(1-$H43-Parâmetros!$B$4-Parâmetros!$C$4-Parâmetros!$D$4))) -> 727.40741 | K43: =IF(OR($A43="",NOT(ISNUMBER($D43)),NOT(ISNUMBER($H43))),"",IF(AND(ISNUMBER($J43),$J43>0),$J43,IF(ISNUMBER($I43),$I43,""))) -> 727.40741 | L43: =IF(ISNUMBER($K43),$K43*$H43,"") -> 94.562963 | M43: =IF(ISNUMBER($K43),$K43*Parâmetros!$B$4,"") -> 72.740741 | N43: =IF(ISNUMBER($K43),$K43*Parâmetros!$C$4,"") -> 21.822222 | O43: =IF(ISNUMBER($K43),IF(ISNUMBER(Parâmetros!$E$4),Parâmetros!$E$4,0),"") -> 0 | P43: =IF(ISNUMBER($K43),$K43-$D43-IF(ISNUMBER($E43),$E43,0)-$L43-$M43-$N43-$O43,"") -> 145.48148 | Q43: =IF(AND(ISNUMBER($K43),$K43>0),$P43/$K43,"") -> 0.2 | S43: =IF(OR(NOT(ISNUMBER($R43)),$R43=0,NOT(ISNUMBER($K43))),"",$K43*(1-$R43)) | T43: =IF(ISNUMBER($S43),$S43*$H43,"") | U43: =IF(ISNUMBER($S43),$S43*Parâmetros!$B$4,"") | V43: =IF(ISNUMBER($S43),$S43*Parâmetros!$C$4,"") | W43: =IF(ISNUMBER($S43),$S43-$D43-IF(ISNUMBER($E43),$E43,0)-$O43-$T43-$U43-$V43,"") | X43: =IF(AND(ISNUMBER($S43),$S43>0),$W43/$S43,"")
A44: =IF(Produtos!$A44="","",Produtos!$A44) -> L4080-A | B44: =IF(Produtos!$A44="","",Produtos!$B44) -> Lixeira Aço Inox c/Aro 40x80 100L | C44: =IF(Produtos!$A44="","",Produtos!$C44) -> Lixeiras em inox | D44: =IF(Produtos!$A44="","",IF(Produtos!$D44="","",Produtos!$D44)) -> 400.17 | E44: 106.85 | F44: =IF($A44="","",IF($C44="","⚠ categoria",IFERROR(INDEX(Parâmetros!$B$13:$B$22,MATCH($C44,Parâmetros!$A$13:$A$22,0)),"⚠ categoria"))) -> 0.13 | H44: =IF($A44="","",IF(ISNUMBER($G44),$G44,IF(ISNUMBER($F44),$F44,""))) -> 0.13 | I44: =IF(OR($A44="",NOT(ISNUMBER($D44)),NOT(ISNUMBER($H44))),"",IF((1-$H44-Parâmetros!$B$4-Parâmetros!$C$4-Parâmetros!$D$4)<=0,"INVALIDO",($D44+IF(ISNUMBER($E44),$E44,0)+IF(ISNUMBER(Parâmetros!$E$4),Parâmetros!$E$4,0))/(1-$H44-Parâmetros!$B$4-Parâmetros!$C$4-Parâmetros!$D$4))) -> 938.92593 | J44: 938.93 | K44: =IF(OR($A44="",NOT(ISNUMBER($D44)),NOT(ISNUMBER($H44))),"",IF(AND(ISNUMBER($J44),$J44>0),$J44,IF(ISNUMBER($I44),$I44,""))) -> 938.93 | L44: =IF(ISNUMBER($K44),$K44*$H44,"") -> 122.0609 | M44: =IF(ISNUMBER($K44),$K44*Parâmetros!$B$4,"") -> 93.893 | N44: =IF(ISNUMBER($K44),$K44*Parâmetros!$C$4,"") -> 28.1679 | O44: =IF(ISNUMBER($K44),IF(ISNUMBER(Parâmetros!$E$4),Parâmetros!$E$4,0),"") -> 0 | P44: =IF(ISNUMBER($K44),$K44-$D44-IF(ISNUMBER($E44),$E44,0)-$L44-$M44-$N44-$O44,"") -> 187.7882 | Q44: =IF(AND(ISNUMBER($K44),$K44>0),$P44/$K44,"") -> 0.20000234 | S44: =IF(OR(NOT(ISNUMBER($R44)),$R44=0,NOT(ISNUMBER($K44))),"",$K44*(1-$R44)) | T44: =IF(ISNUMBER($S44),$S44*$H44,"") | U44: =IF(ISNUMBER($S44),$S44*Parâmetros!$B$4,"") | V44: =IF(ISNUMBER($S44),$S44*Parâmetros!$C$4,"") | W44: =IF(ISNUMBER($S44),$S44-$D44-IF(ISNUMBER($E44),$E44,0)-$O44-$T44-$U44-$V44,"") | X44: =IF(AND(ISNUMBER($S44),$S44>0),$W44/$S44,"") | Y44: 09/10
A45: =IF(Produtos!$A45="","",Produtos!$A45) -> L4090-A | B45: =IF(Produtos!$A45="","",Produtos!$B45) -> Lixeira Aço Inox c/Aro 40x90 120L | C45: =IF(Produtos!$A45="","",Produtos!$C45) -> Lixeiras em inox | D45: =IF(Produtos!$A45="","",IF(Produtos!$D45="","",Produtos!$D45)) -> 405.39 | E45: 106.85 | F45: =IF($A45="","",IF($C45="","⚠ categoria",IFERROR(INDEX(Parâmetros!$B$13:$B$22,MATCH($C45,Parâmetros!$A$13:$A$22,0)),"⚠ categoria"))) -> 0.13 | H45: =IF($A45="","",IF(ISNUMBER($G45),$G45,IF(ISNUMBER($F45),$F45,""))) -> 0.13 | I45: =IF(OR($A45="",NOT(ISNUMBER($D45)),NOT(ISNUMBER($H45))),"",IF((1-$H45-Parâmetros!$B$4-Parâmetros!$C$4-Parâmetros!$D$4)<=0,"INVALIDO",($D45+IF(ISNUMBER($E45),$E45,0)+IF(ISNUMBER(Parâmetros!$E$4),Parâmetros!$E$4,0))/(1-$H45-Parâmetros!$B$4-Parâmetros!$C$4-Parâmetros!$D$4))) -> 948.59259 | J45: 948.69 | K45: =IF(OR($A45="",NOT(ISNUMBER($D45)),NOT(ISNUMBER($H45))),"",IF(AND(ISNUMBER($J45),$J45>0),$J45,IF(ISNUMBER($I45),$I45,""))) -> 948.69 | L45: =IF(ISNUMBER($K45),$K45*$H45,"") -> 123.3297 | M45: =IF(ISNUMBER($K45),$K45*Parâmetros!$B$4,"") -> 94.869 | N45: =IF(ISNUMBER($K45),$K45*Parâmetros!$C$4,"") -> 28.4607 | O45: =IF(ISNUMBER($K45),IF(ISNUMBER(Parâmetros!$E$4),Parâmetros!$E$4,0),"") -> 0 | P45: =IF(ISNUMBER($K45),$K45-$D45-IF(ISNUMBER($E45),$E45,0)-$L45-$M45-$N45-$O45,"") -> 189.7906 | Q45: =IF(AND(ISNUMBER($K45),$K45>0),$P45/$K45,"") -> 0.20005544 | S45: =IF(OR(NOT(ISNUMBER($R45)),$R45=0,NOT(ISNUMBER($K45))),"",$K45*(1-$R45)) | T45: =IF(ISNUMBER($S45),$S45*$H45,"") | U45: =IF(ISNUMBER($S45),$S45*Parâmetros!$B$4,"") | V45: =IF(ISNUMBER($S45),$S45*Parâmetros!$C$4,"") | W45: =IF(ISNUMBER($S45),$S45-$D45-IF(ISNUMBER($E45),$E45,0)-$O45-$T45-$U45-$V45,"") | X45: =IF(AND(ISNUMBER($S45),$S45>0),$W45/$S45,"") | Y45: 09/10
A46: =IF(Produtos!$A46="","",Produtos!$A46) -> L40100-A | B46: =IF(Produtos!$A46="","",Produtos!$B46) -> Lixeira Aço Inox c/Aro 40x100L | C46: =IF(Produtos!$A46="","",Produtos!$C46) -> Lixeiras em inox | D46: =IF(Produtos!$A46="","",IF(Produtos!$D46="","",Produtos!$D46)) -> 566.56 | F46: =IF($A46="","",IF($C46="","⚠ categoria",IFERROR(INDEX(Parâmetros!$B$13:$B$22,MATCH($C46,Parâmetros!$A$13:$A$22,0)),"⚠ categoria"))) -> 0.13 | H46: =IF($A46="","",IF(ISNUMBER($G46),$G46,IF(ISNUMBER($F46),$F46,""))) -> 0.13 | I46: =IF(OR($A46="",NOT(ISNUMBER($D46)),NOT(ISNUMBER($H46))),"",IF((1-$H46-Parâmetros!$B$4-Parâmetros!$C$4-Parâmetros!$D$4)<=0,"INVALIDO",($D46+IF(ISNUMBER($E46),$E46,0)+IF(ISNUMBER(Parâmetros!$E$4),Parâmetros!$E$4,0))/(1-$H46-Parâmetros!$B$4-Parâmetros!$C$4-Parâmetros!$D$4))) -> 1049.1852 | K46: =IF(OR($A46="",NOT(ISNUMBER($D46)),NOT(ISNUMBER($H46))),"",IF(AND(ISNUMBER($J46),$J46>0),$J46,IF(ISNUMBER($I46),$I46,""))) -> 1049.1852 | L46: =IF(ISNUMBER($K46),$K46*$H46,"") -> 136.39407 | M46: =IF(ISNUMBER($K46),$K46*Parâmetros!$B$4,"") -> 104.91852 | N46: =IF(ISNUMBER($K46),$K46*Parâmetros!$C$4,"") -> 31.475556 | O46: =IF(ISNUMBER($K46),IF(ISNUMBER(Parâmetros!$E$4),Parâmetros!$E$4,0),"") -> 0 | P46: =IF(ISNUMBER($K46),$K46-$D46-IF(ISNUMBER($E46),$E46,0)-$L46-$M46-$N46-$O46,"") -> 209.83704 | Q46: =IF(AND(ISNUMBER($K46),$K46>0),$P46/$K46,"") -> 0.2 | S46: =IF(OR(NOT(ISNUMBER($R46)),$R46=0,NOT(ISNUMBER($K46))),"",$K46*(1-$R46)) | T46: =IF(ISNUMBER($S46),$S46*$H46,"") | U46: =IF(ISNUMBER($S46),$S46*Parâmetros!$B$4,"") | V46: =IF(ISNUMBER($S46),$S46*Parâmetros!$C$4,"") | W46: =IF(ISNUMBER($S46),$S46-$D46-IF(ISNUMBER($E46),$E46,0)-$O46-$T46-$U46-$V46,"") | X46: =IF(AND(ISNUMBER($S46),$S46>0),$W46/$S46,"")
A47: =IF(Produtos!$A47="","",Produtos!$A47) -> L40120-A | B47: =IF(Produtos!$A47="","",Produtos!$B47) -> Lixeira Aço Inox c/Aro 40x120L | C47: =IF(Produtos!$A47="","",Produtos!$C47) -> Lixeiras em inox | D47: =IF(Produtos!$A47="","",IF(Produtos!$D47="","",Produtos!$D47)) -> 762.87 | F47: =IF($A47="","",IF($C47="","⚠ categoria",IFERROR(INDEX(Parâmetros!$B$13:$B$22,MATCH($C47,Parâmetros!$A$13:$A$22,0)),"⚠ categoria"))) -> 0.13 | H47: =IF($A47="","",IF(ISNUMBER($G47),$G47,IF(ISNUMBER($F47),$F47,""))) -> 0.13 | I47: =IF(OR($A47="",NOT(ISNUMBER($D47)),NOT(ISNUMBER($H47))),"",IF((1-$H47-Parâmetros!$B$4-Parâmetros!$C$4-Parâmetros!$D$4)<=0,"INVALIDO",($D47+IF(ISNUMBER($E47),$E47,0)+IF(ISNUMBER(Parâmetros!$E$4),Parâmetros!$E$4,0))/(1-$H47-Parâmetros!$B$4-Parâmetros!$C$4-Parâmetros!$D$4))) -> 1412.7222 | K47: =IF(OR($A47="",NOT(ISNUMBER($D47)),NOT(ISNUMBER($H47))),"",IF(AND(ISNUMBER($J47),$J47>0),$J47,IF(ISNUMBER($I47),$I47,""))) -> 1412.7222 | L47: =IF(ISNUMBER($K47),$K47*$H47,"") -> 183.65389 | M47: =IF(ISNUMBER($K47),$K47*Parâmetros!$B$4,"") -> 141.27222 | N47: =IF(ISNUMBER($K47),$K47*Parâmetros!$C$4,"") -> 42.381667 | O47: =IF(ISNUMBER($K47),IF(ISNUMBER(Parâmetros!$E$4),Parâmetros!$E$4,0),"") -> 0 | P47: =IF(ISNUMBER($K47),$K47-$D47-IF(ISNUMBER($E47),$E47,0)-$L47-$M47-$N47-$O47,"") -> 282.54444 | Q47: =IF(AND(ISNUMBER($K47),$K47>0),$P47/$K47,"") -> 0.2 | S47: =IF(OR(NOT(ISNUMBER($R47)),$R47=0,NOT(ISNUMBER($K47))),"",$K47*(1-$R47)) | T47: =IF(ISNUMBER($S47),$S47*$H47,"") | U47: =IF(ISNUMBER($S47),$S47*Parâmetros!$B$4,"") | V47: =IF(ISNUMBER($S47),$S47*Parâmetros!$C$4,"") | W47: =IF(ISNUMBER($S47),$S47-$D47-IF(ISNUMBER($E47),$E47,0)-$O47-$T47-$U47-$V47,"") | X47: =IF(AND(ISNUMBER($S47),$S47>0),$W47/$S47,"")
A48: =IF(Produtos!$A48="","",Produtos!$A48) -> L2425-AML | B48: =IF(Produtos!$A48="","",Produtos!$B48) -> Lixeira c/Aro Meia Lua 24x25 13L | C48: =IF(Produtos!$A48="","",Produtos!$C48) -> Lixeiras em inox | D48: =IF(Produtos!$A48="","",IF(Produtos!$D48="","",Produtos!$D48)) -> 86.87 | E48: 27.05 | F48: =IF($A48="","",IF($C48="","⚠ categoria",IFERROR(INDEX(Parâmetros!$B$13:$B$22,MATCH($C48,Parâmetros!$A$13:$A$22,0)),"⚠ categoria"))) -> 0.13 | G48: 0.12 | H48: =IF($A48="","",IF(ISNUMBER($G48),$G48,IF(ISNUMBER($F48),$F48,""))) -> 0.12 | I48: =IF(OR($A48="",NOT(ISNUMBER($D48)),NOT(ISNUMBER($H48))),"",IF((1-$H48-Parâmetros!$B$4-Parâmetros!$C$4-Parâmetros!$D$4)<=0,"INVALIDO",($D48+IF(ISNUMBER($E48),$E48,0)+IF(ISNUMBER(Parâmetros!$E$4),Parâmetros!$E$4,0))/(1-$H48-Parâmetros!$B$4-Parâmetros!$C$4-Parâmetros!$D$4))) -> 207.12727 | J48: 208.415 | K48: =IF(OR($A48="",NOT(ISNUMBER($D48)),NOT(ISNUMBER($H48))),"",IF(AND(ISNUMBER($J48),$J48>0),$J48,IF(ISNUMBER($I48),$I48,""))) -> 208.415 | L48: =IF(ISNUMBER($K48),$K48*$H48,"") -> 25.0098 | M48: =IF(ISNUMBER($K48),$K48*Parâmetros!$B$4,"") -> 20.8415 | N48: =IF(ISNUMBER($K48),$K48*Parâmetros!$C$4,"") -> 6.25245 | O48: =IF(ISNUMBER($K48),IF(ISNUMBER(Parâmetros!$E$4),Parâmetros!$E$4,0),"") -> 0 | P48: =IF(ISNUMBER($K48),$K48-$D48-IF(ISNUMBER($E48),$E48,0)-$L48-$M48-$N48-$O48,"") -> 42.39125 | Q48: =IF(AND(ISNUMBER($K48),$K48>0),$P48/$K48,"") -> 0.20339827 | S48: =IF(OR(NOT(ISNUMBER($R48)),$R48=0,NOT(ISNUMBER($K48))),"",$K48*(1-$R48)) | T48: =IF(ISNUMBER($S48),$S48*$H48,"") | U48: =IF(ISNUMBER($S48),$S48*Parâmetros!$B$4,"") | V48: =IF(ISNUMBER($S48),$S48*Parâmetros!$C$4,"") | W48: =IF(ISNUMBER($S48),$S48-$D48-IF(ISNUMBER($E48),$E48,0)-$O48-$T48-$U48-$V48,"") | X48: =IF(AND(ISNUMBER($S48),$S48>0),$W48/$S48,"") | Y48: 09/10
A49: =IF(Produtos!$A49="","",Produtos!$A49) -> L2430-AML | B49: =IF(Produtos!$A49="","",Produtos!$B49) -> Lixeira c/Aro Meia Lua 24x30 15L | C49: =IF(Produtos!$A49="","",Produtos!$C49) -> Lixeiras em inox | D49: =IF(Produtos!$A49="","",IF(Produtos!$D49="","",Produtos!$D49)) -> 96.11 | E49: 27.05 | F49: =IF($A49="","",IF($C49="","⚠ categoria",IFERROR(INDEX(Parâmetros!$B$13:$B$22,MATCH($C49,Parâmetros!$A$13:$A$22,0)),"⚠ categoria"))) -> 0.13 | G49: 0.12 | H49: =IF($A49="","",IF(ISNUMBER($G49),$G49,IF(ISNUMBER($F49),$F49,""))) -> 0.12 | I49: =IF(OR($A49="",NOT(ISNUMBER($D49)),NOT(ISNUMBER($H49))),"",IF((1-$H49-Parâmetros!$B$4-Parâmetros!$C$4-Parâmetros!$D$4)<=0,"INVALIDO",($D49+IF(ISNUMBER($E49),$E49,0)+IF(ISNUMBER(Parâmetros!$E$4),Parâmetros!$E$4,0))/(1-$H49-Parâmetros!$B$4-Parâmetros!$C$4-Parâmetros!$D$4))) -> 223.92727 | J49: 227.73957 | K49: =IF(OR($A49="",NOT(ISNUMBER($D49)),NOT(ISNUMBER($H49))),"",IF(AND(ISNUMBER($J49),$J49>0),$J49,IF(ISNUMBER($I49),$I49,""))) -> 227.73957 | L49: =IF(ISNUMBER($K49),$K49*$H49,"") -> 27.328748 | M49: =IF(ISNUMBER($K49),$K49*Parâmetros!$B$4,"") -> 22.773957 | N49: =IF(ISNUMBER($K49),$K49*Parâmetros!$C$4,"") -> 6.832187 | O49: =IF(ISNUMBER($K49),IF(ISNUMBER(Parâmetros!$E$4),Parâmetros!$E$4,0),"") -> 0 | P49: =IF(ISNUMBER($K49),$K49-$D49-IF(ISNUMBER($E49),$E49,0)-$L49-$M49-$N49-$O49,"") -> 47.644675 | Q49: =IF(AND(ISNUMBER($K49),$K49>0),$P49/$K49,"") -> 0.20920684 | S49: =IF(OR(NOT(ISNUMBER($R49)),$R49=0,NOT(ISNUMBER($K49))),"",$K49*(1-$R49)) | T49: =IF(ISNUMBER($S49),$S49*$H49,"") | U49: =IF(ISNUMBER($S49),$S49*Parâmetros!$B$4,"") | V49: =IF(ISNUMBER($S49),$S49*Parâmetros!$C$4,"") | W49: =IF(ISNUMBER($S49),$S49-$D49-IF(ISNUMBER($E49),$E49,0)-$O49-$T49-$U49-$V49,"") | X49: =IF(AND(ISNUMBER($S49),$S49>0),$W49/$S49,"") | Y49: 02/10
A50: =IF(Produtos!$A50="","",Produtos!$A50) -> L2440-AML | B50: =IF(Produtos!$A50="","",Produtos!$B50) -> Lixeira c/Aro Meia Lua 24x40 20L | C50: =IF(Produtos!$A50="","",Produtos!$C50) -> Lixeiras em inox | D50: =IF(Produtos!$A50="","",IF(Produtos!$D50="","",Produtos!$D50)) -> 113.2 | E50: 29.25 | F50: =IF($A50="","",IF($C50="","⚠ categoria",IFERROR(INDEX(Parâmetros!$B$13:$B$22,MATCH($C50,Parâmetros!$A$13:$A$22,0)),"⚠ categoria"))) -> 0.13 | G50: 0.12 | H50: =IF($A50="","",IF(ISNUMBER($G50),$G50,IF(ISNUMBER($F50),$F50,""))) -> 0.12 | I50: =IF(OR($A50="",NOT(ISNUMBER($D50)),NOT(ISNUMBER($H50))),"",IF((1-$H50-Parâmetros!$B$4-Parâmetros!$C$4-Parâmetros!$D$4)<=0,"INVALIDO",($D50+IF(ISNUMBER($E50),$E50,0)+IF(ISNUMBER(Parâmetros!$E$4),Parâmetros!$E$4,0))/(1-$H50-Parâmetros!$B$4-Parâmetros!$C$4-Parâmetros!$D$4))) -> 259 | J50: 259.5 | K50: =IF(OR($A50="",NOT(ISNUMBER($D50)),NOT(ISNUMBER($H50))),"",IF(AND(ISNUMBER($J50),$J50>0),$J50,IF(ISNUMBER($I50),$I50,""))) -> 259.5 | L50: =IF(ISNUMBER($K50),$K50*$H50,"") -> 31.14 | M50: =IF(ISNUMBER($K50),$K50*Parâmetros!$B$4,"") -> 25.95 | N50: =IF(ISNUMBER($K50),$K50*Parâmetros!$C$4,"") -> 7.785 | O50: =IF(ISNUMBER($K50),IF(ISNUMBER(Parâmetros!$E$4),Parâmetros!$E$4,0),"") -> 0 | P50: =IF(ISNUMBER($K50),$K50-$D50-IF(ISNUMBER($E50),$E50,0)-$L50-$M50-$N50-$O50,"") -> 52.175 | Q50: =IF(AND(ISNUMBER($K50),$K50>0),$P50/$K50,"") -> 0.20105973 | S50: =IF(OR(NOT(ISNUMBER($R50)),$R50=0,NOT(ISNUMBER($K50))),"",$K50*(1-$R50)) | T50: =IF(ISNUMBER($S50),$S50*$H50,"") | U50: =IF(ISNUMBER($S50),$S50*Parâmetros!$B$4,"") | V50: =IF(ISNUMBER($S50),$S50*Parâmetros!$C$4,"") | W50: =IF(ISNUMBER($S50),$S50-$D50-IF(ISNUMBER($E50),$E50,0)-$O50-$T50-$U50-$V50,"") | X50: =IF(AND(ISNUMBER($S50),$S50>0),$W50/$S50,"") | Y50: 09/10
A51: =IF(Produtos!$A51="","",Produtos!$A51) -> L2450-AML | B51: =IF(Produtos!$A51="","",Produtos!$B51) -> Lixeira c/Aro Meia Lua 24x50 25L | C51: =IF(Produtos!$A51="","",Produtos!$C51) -> Lixeiras em inox | D51: =IF(Produtos!$A51="","",IF(Produtos!$D51="","",Produtos!$D51)) -> 139.49 | E51: 40.85 | F51: =IF($A51="","",IF($C51="","⚠ categoria",IFERROR(INDEX(Parâmetros!$B$13:$B$22,MATCH($C51,Parâmetros!$A$13:$A$22,0)),"⚠ categoria"))) -> 0.13 | G51: 0.12 | H51: =IF($A51="","",IF(ISNUMBER($G51),$G51,IF(ISNUMBER($F51),$F51,""))) -> 0.12 | I51: =IF(OR($A51="",NOT(ISNUMBER($D51)),NOT(ISNUMBER($H51))),"",IF((1-$H51-Parâmetros!$B$4-Parâmetros!$C$4-Parâmetros!$D$4)<=0,"INVALIDO",($D51+IF(ISNUMBER($E51),$E51,0)+IF(ISNUMBER(Parâmetros!$E$4),Parâmetros!$E$4,0))/(1-$H51-Parâmetros!$B$4-Parâmetros!$C$4-Parâmetros!$D$4))) -> 327.89091 | J51: 322.97737 | K51: =IF(OR($A51="",NOT(ISNUMBER($D51)),NOT(ISNUMBER($H51))),"",IF(AND(ISNUMBER($J51),$J51>0),$J51,IF(ISNUMBER($I51),$I51,""))) -> 322.97737 | L51: =IF(ISNUMBER($K51),$K51*$H51,"") -> 38.757285 | M51: =IF(ISNUMBER($K51),$K51*Parâmetros!$B$4,"") -> 32.297737 | N51: =IF(ISNUMBER($K51),$K51*Parâmetros!$C$4,"") -> 9.6893213 | O51: =IF(ISNUMBER($K51),IF(ISNUMBER(Parâmetros!$E$4),Parâmetros!$E$4,0),"") -> 0 | P51: =IF(ISNUMBER($K51),$K51-$D51-IF(ISNUMBER($E51),$E51,0)-$L51-$M51-$N51-$O51,"") -> 61.893031 | Q51: =IF(AND(ISNUMBER($K51),$K51>0),$P51/$K51,"") -> 0.19163271 | S51: =IF(OR(NOT(ISNUMBER($R51)),$R51=0,NOT(ISNUMBER($K51))),"",$K51*(1-$R51)) | T51: =IF(ISNUMBER($S51),$S51*$H51,"") | U51: =IF(ISNUMBER($S51),$S51*Parâmetros!$B$4,"") | V51: =IF(ISNUMBER($S51),$S51*Parâmetros!$C$4,"") | W51: =IF(ISNUMBER($S51),$S51-$D51-IF(ISNUMBER($E51),$E51,0)-$O51-$T51-$U51-$V51,"") | X51: =IF(AND(ISNUMBER($S51),$S51>0),$W51/$S51,"") | Y51: 05/10
A52: =IF(Produtos!$A52="","",Produtos!$A52) -> L2460-AML | B52: =IF(Produtos!$A52="","",Produtos!$B52) -> Lixeira c/Aro Meia Lua 24x60 27L | C52: =IF(Produtos!$A52="","",Produtos!$C52) -> Lixeiras em inox | D52: =IF(Produtos!$A52="","",IF(Produtos!$D52="","",Produtos!$D52)) -> 140.97 | E52: 40.85 | F52: =IF($A52="","",IF($C52="","⚠ categoria",IFERROR(INDEX(Parâmetros!$B$13:$B$22,MATCH($C52,Parâmetros!$A$13:$A$22,0)),"⚠ categoria"))) -> 0.13 | G52: 0.12 | H52: =IF($A52="","",IF(ISNUMBER($G52),$G52,IF(ISNUMBER($F52),$F52,""))) -> 0.12 | I52: =IF(OR($A52="",NOT(ISNUMBER($D52)),NOT(ISNUMBER($H52))),"",IF((1-$H52-Parâmetros!$B$4-Parâmetros!$C$4-Parâmetros!$D$4)<=0,"INVALIDO",($D52+IF(ISNUMBER($E52),$E52,0)+IF(ISNUMBER(Parâmetros!$E$4),Parâmetros!$E$4,0))/(1-$H52-Parâmetros!$B$4-Parâmetros!$C$4-Parâmetros!$D$4))) -> 330.58182 | J52: 336.08169 | K52: =IF(OR($A52="",NOT(ISNUMBER($D52)),NOT(ISNUMBER($H52))),"",IF(AND(ISNUMBER($J52),$J52>0),$J52,IF(ISNUMBER($I52),$I52,""))) -> 336.08169 | L52: =IF(ISNUMBER($K52),$K52*$H52,"") -> 40.329803 | M52: =IF(ISNUMBER($K52),$K52*Parâmetros!$B$4,"") -> 33.608169 | N52: =IF(ISNUMBER($K52),$K52*Parâmetros!$C$4,"") -> 10.082451 | O52: =IF(ISNUMBER($K52),IF(ISNUMBER(Parâmetros!$E$4),Parâmetros!$E$4,0),"") -> 0 | P52: =IF(ISNUMBER($K52),$K52-$D52-IF(ISNUMBER($E52),$E52,0)-$L52-$M52-$N52-$O52,"") -> 70.241268 | Q52: =IF(AND(ISNUMBER($K52),$K52>0),$P52/$K52,"") -> 0.20900058 | S52: =IF(OR(NOT(ISNUMBER($R52)),$R52=0,NOT(ISNUMBER($K52))),"",$K52*(1-$R52)) | T52: =IF(ISNUMBER($S52),$S52*$H52,"") | U52: =IF(ISNUMBER($S52),$S52*Parâmetros!$B$4,"") | V52: =IF(ISNUMBER($S52),$S52*Parâmetros!$C$4,"") | W52: =IF(ISNUMBER($S52),$S52-$D52-IF(ISNUMBER($E52),$E52,0)-$O52-$T52-$U52-$V52,"") | X52: =IF(AND(ISNUMBER($S52),$S52>0),$W52/$S52,"") | Y52: 05/10
A53: =IF(Produtos!$A53="","",Produtos!$A53) -> L2470-AML | B53: =IF(Produtos!$A53="","",Produtos!$B53) -> Lixeira c/Aro Meia Lua 24x70 30L | C53: =IF(Produtos!$A53="","",Produtos!$C53) -> Lixeiras em inox | D53: =IF(Produtos!$A53="","",IF(Produtos!$D53="","",Produtos!$D53)) -> 208.28 | E53: 45.25 | F53: =IF($A53="","",IF($C53="","⚠ categoria",IFERROR(INDEX(Parâmetros!$B$13:$B$22,MATCH($C53,Parâmetros!$A$13:$A$22,0)),"⚠ categoria"))) -> 0.13 | G53: 0.12 | H53: =IF($A53="","",IF(ISNUMBER($G53),$G53,IF(ISNUMBER($F53),$F53,""))) -> 0.12 | I53: =IF(OR($A53="",NOT(ISNUMBER($D53)),NOT(ISNUMBER($H53))),"",IF((1-$H53-Parâmetros!$B$4-Parâmetros!$C$4-Parâmetros!$D$4)<=0,"INVALIDO",($D53+IF(ISNUMBER($E53),$E53,0)+IF(ISNUMBER(Parâmetros!$E$4),Parâmetros!$E$4,0))/(1-$H53-Parâmetros!$B$4-Parâmetros!$C$4-Parâmetros!$D$4))) -> 460.96364 | J53: 464.09186 | K53: =IF(OR($A53="",NOT(ISNUMBER($D53)),NOT(ISNUMBER($H53))),"",IF(AND(ISNUMBER($J53),$J53>0),$J53,IF(ISNUMBER($I53),$I53,""))) -> 464.09186 | L53: =IF(ISNUMBER($K53),$K53*$H53,"") -> 55.691024 | M53: =IF(ISNUMBER($K53),$K53*Parâmetros!$B$4,"") -> 46.409186 | N53: =IF(ISNUMBER($K53),$K53*Parâmetros!$C$4,"") -> 13.922756 | O53: =IF(ISNUMBER($K53),IF(ISNUMBER(Parâmetros!$E$4),Parâmetros!$E$4,0),"") -> 0 | P53: =IF(ISNUMBER($K53),$K53-$D53-IF(ISNUMBER($E53),$E53,0)-$L53-$M53-$N53-$O53,"") -> 94.538897 | Q53: =IF(AND(ISNUMBER($K53),$K53>0),$P53/$K53,"") -> 0.20370729 | S53: =IF(OR(NOT(ISNUMBER($R53)),$R53=0,NOT(ISNUMBER($K53))),"",$K53*(1-$R53)) | T53: =IF(ISNUMBER($S53),$S53*$H53,"") | U53: =IF(ISNUMBER($S53),$S53*Parâmetros!$B$4,"") | V53: =IF(ISNUMBER($S53),$S53*Parâmetros!$C$4,"") | W53: =IF(ISNUMBER($S53),$S53-$D53-IF(ISNUMBER($E53),$E53,0)-$O53-$T53-$U53-$V53,"") | X53: =IF(AND(ISNUMBER($S53),$S53>0),$W53/$S53,"") | Y53: 05/10
A54: =IF(Produtos!$A54="","",Produtos!$A54) -> L3040-AML | B54: =IF(Produtos!$A54="","",Produtos!$B54) -> Lixeira c/Aro Meia Lua 30x40 30L | C54: =IF(Produtos!$A54="","",Produtos!$C54) -> Lixeiras em inox | D54: =IF(Produtos!$A54="","",IF(Produtos!$D54="","",Produtos!$D54)) -> 161.26 | F54: =IF($A54="","",IF($C54="","⚠ categoria",IFERROR(INDEX(Parâmetros!$B$13:$B$22,MATCH($C54,Parâmetros!$A$13:$A$22,0)),"⚠ categoria"))) -> 0.13 | H54: =IF($A54="","",IF(ISNUMBER($G54),$G54,IF(ISNUMBER($F54),$F54,""))) -> 0.13 | I54: =IF(OR($A54="",NOT(ISNUMBER($D54)),NOT(ISNUMBER($H54))),"",IF((1-$H54-Parâmetros!$B$4-Parâmetros!$C$4-Parâmetros!$D$4)<=0,"INVALIDO",($D54+IF(ISNUMBER($E54),$E54,0)+IF(ISNUMBER(Parâmetros!$E$4),Parâmetros!$E$4,0))/(1-$H54-Parâmetros!$B$4-Parâmetros!$C$4-Parâmetros!$D$4))) -> 298.62963 | K54: =IF(OR($A54="",NOT(ISNUMBER($D54)),NOT(ISNUMBER($H54))),"",IF(AND(ISNUMBER($J54),$J54>0),$J54,IF(ISNUMBER($I54),$I54,""))) -> 298.62963 | L54: =IF(ISNUMBER($K54),$K54*$H54,"") -> 38.821852 | M54: =IF(ISNUMBER($K54),$K54*Parâmetros!$B$4,"") -> 29.862963 | N54: =IF(ISNUMBER($K54),$K54*Parâmetros!$C$4,"") -> 8.9588889 | O54: =IF(ISNUMBER($K54),IF(ISNUMBER(Parâmetros!$E$4),Parâmetros!$E$4,0),"") -> 0 | P54: =IF(ISNUMBER($K54),$K54-$D54-IF(ISNUMBER($E54),$E54,0)-$L54-$M54-$N54-$O54,"") -> 59.725926 | Q54: =IF(AND(ISNUMBER($K54),$K54>0),$P54/$K54,"") -> 0.2 | S54: =IF(OR(NOT(ISNUMBER($R54)),$R54=0,NOT(ISNUMBER($K54))),"",$K54*(1-$R54)) | T54: =IF(ISNUMBER($S54),$S54*$H54,"") | U54: =IF(ISNUMBER($S54),$S54*Parâmetros!$B$4,"") | V54: =IF(ISNUMBER($S54),$S54*Parâmetros!$C$4,"") | W54: =IF(ISNUMBER($S54),$S54-$D54-IF(ISNUMBER($E54),$E54,0)-$O54-$T54-$U54-$V54,"") | X54: =IF(AND(ISNUMBER($S54),$S54>0),$W54/$S54,"")
A55: =IF(Produtos!$A55="","",Produtos!$A55) -> L3050-AML | B55: =IF(Produtos!$A55="","",Produtos!$B55) -> Lixeira c/Aro Meia Lua 30x50 35L | C55: =IF(Produtos!$A55="","",Produtos!$C55) -> Lixeiras em inox | D55: =IF(Produtos!$A55="","",IF(Produtos!$D55="","",Produtos!$D55)) -> 205.71 | F55: =IF($A55="","",IF($C55="","⚠ categoria",IFERROR(INDEX(Parâmetros!$B$13:$B$22,MATCH($C55,Parâmetros!$A$13:$A$22,0)),"⚠ categoria"))) -> 0.13 | H55: =IF($A55="","",IF(ISNUMBER($G55),$G55,IF(ISNUMBER($F55),$F55,""))) -> 0.13 | I55: =IF(OR($A55="",NOT(ISNUMBER($D55)),NOT(ISNUMBER($H55))),"",IF((1-$H55-Parâmetros!$B$4-Parâmetros!$C$4-Parâmetros!$D$4)<=0,"INVALIDO",($D55+IF(ISNUMBER($E55),$E55,0)+IF(ISNUMBER(Parâmetros!$E$4),Parâmetros!$E$4,0))/(1-$H55-Parâmetros!$B$4-Parâmetros!$C$4-Parâmetros!$D$4))) -> 380.94444 | K55: =IF(OR($A55="",NOT(ISNUMBER($D55)),NOT(ISNUMBER($H55))),"",IF(AND(ISNUMBER($J55),$J55>0),$J55,IF(ISNUMBER($I55),$I55,""))) -> 380.94444 | L55: =IF(ISNUMBER($K55),$K55*$H55,"") -> 49.522778 | M55: =IF(ISNUMBER($K55),$K55*Parâmetros!$B$4,"") -> 38.094444 | N55: =IF(ISNUMBER($K55),$K55*Parâmetros!$C$4,"") -> 11.428333 | O55: =IF(ISNUMBER($K55),IF(ISNUMBER(Parâmetros!$E$4),Parâmetros!$E$4,0),"") -> 0 | P55: =IF(ISNUMBER($K55),$K55-$D55-IF(ISNUMBER($E55),$E55,0)-$L55-$M55-$N55-$O55,"") -> 76.188889 | Q55: =IF(AND(ISNUMBER($K55),$K55>0),$P55/$K55,"") -> 0.2 | S55: =IF(OR(NOT(ISNUMBER($R55)),$R55=0,NOT(ISNUMBER($K55))),"",$K55*(1-$R55)) | T55: =IF(ISNUMBER($S55),$S55*$H55,"") | U55: =IF(ISNUMBER($S55),$S55*Parâmetros!$B$4,"") | V55: =IF(ISNUMBER($S55),$S55*Parâmetros!$C$4,"") | W55: =IF(ISNUMBER($S55),$S55-$D55-IF(ISNUMBER($E55),$E55,0)-$O55-$T55-$U55-$V55,"") | X55: =IF(AND(ISNUMBER($S55),$S55>0),$W55/$S55,"")
A56: =IF(Produtos!$A56="","",Produtos!$A56) -> L3060-AML | B56: =IF(Produtos!$A56="","",Produtos!$B56) -> Lixeira c/Aro Meia Lua 30x60 40L | C56: =IF(Produtos!$A56="","",Produtos!$C56) -> Lixeiras em inox | D56: =IF(Produtos!$A56="","",IF(Produtos!$D56="","",Produtos!$D56)) -> 235.28 | E56: 50.75 | F56: =IF($A56="","",IF($C56="","⚠ categoria",IFERROR(INDEX(Parâmetros!$B$13:$B$22,MATCH($C56,Parâmetros!$A$13:$A$22,0)),"⚠ categoria"))) -> 0.13 | G56: 0.12 | H56: =IF($A56="","",IF(ISNUMBER($G56),$G56,IF(ISNUMBER($F56),$F56,""))) -> 0.12 | I56: =IF(OR($A56="",NOT(ISNUMBER($D56)),NOT(ISNUMBER($H56))),"",IF((1-$H56-Parâmetros!$B$4-Parâmetros!$C$4-Parâmetros!$D$4)<=0,"INVALIDO",($D56+IF(ISNUMBER($E56),$E56,0)+IF(ISNUMBER(Parâmetros!$E$4),Parâmetros!$E$4,0))/(1-$H56-Parâmetros!$B$4-Parâmetros!$C$4-Parâmetros!$D$4))) -> 520.05455 | J56: 507.71117 | K56: =IF(OR($A56="",NOT(ISNUMBER($D56)),NOT(ISNUMBER($H56))),"",IF(AND(ISNUMBER($J56),$J56>0),$J56,IF(ISNUMBER($I56),$I56,""))) -> 507.71117 | L56: =IF(ISNUMBER($K56),$K56*$H56,"") -> 60.925341 | M56: =IF(ISNUMBER($K56),$K56*Parâmetros!$B$4,"") -> 50.771117 | N56: =IF(ISNUMBER($K56),$K56*Parâmetros!$C$4,"") -> 15.231335 | O56: =IF(ISNUMBER($K56),IF(ISNUMBER(Parâmetros!$E$4),Parâmetros!$E$4,0),"") -> 0 | P56: =IF(ISNUMBER($K56),$K56-$D56-IF(ISNUMBER($E56),$E56,0)-$L56-$M56-$N56-$O56,"") -> 94.753379 | Q56: =IF(AND(ISNUMBER($K56),$K56>0),$P56/$K56,"") -> 0.18662851 | S56: =IF(OR(NOT(ISNUMBER($R56)),$R56=0,NOT(ISNUMBER($K56))),"",$K56*(1-$R56)) | T56: =IF(ISNUMBER($S56),$S56*$H56,"") | U56: =IF(ISNUMBER($S56),$S56*Parâmetros!$B$4,"") | V56: =IF(ISNUMBER($S56),$S56*Parâmetros!$C$4,"") | W56: =IF(ISNUMBER($S56),$S56-$D56-IF(ISNUMBER($E56),$E56,0)-$O56-$T56-$U56-$V56,"") | X56: =IF(AND(ISNUMBER($S56),$S56>0),$W56/$S56,"") | Y56: 05/10
A57: =IF(Produtos!$A57="","",Produtos!$A57) -> L3070-AML | B57: =IF(Produtos!$A57="","",Produtos!$B57) -> Lixeira c/Aro Meia Lua 30x70 50L | C57: =IF(Produtos!$A57="","",Produtos!$C57) -> Lixeiras em inox | D57: =IF(Produtos!$A57="","",IF(Produtos!$D57="","",Produtos!$D57)) -> 269.82 | E57: 69.35 | F57: =IF($A57="","",IF($C57="","⚠ categoria",IFERROR(INDEX(Parâmetros!$B$13:$B$22,MATCH($C57,Parâmetros!$A$13:$A$22,0)),"⚠ categoria"))) -> 0.13 | G57: 0.12 | H57: =IF($A57="","",IF(ISNUMBER($G57),$G57,IF(ISNUMBER($F57),$F57,""))) -> 0.12 | I57: =IF(OR($A57="",NOT(ISNUMBER($D57)),NOT(ISNUMBER($H57))),"",IF((1-$H57-Parâmetros!$B$4-Parâmetros!$C$4-Parâmetros!$D$4)<=0,"INVALIDO",($D57+IF(ISNUMBER($E57),$E57,0)+IF(ISNUMBER(Parâmetros!$E$4),Parâmetros!$E$4,0))/(1-$H57-Parâmetros!$B$4-Parâmetros!$C$4-Parâmetros!$D$4))) -> 616.67273 | J57: 598.19114 | K57: =IF(OR($A57="",NOT(ISNUMBER($D57)),NOT(ISNUMBER($H57))),"",IF(AND(ISNUMBER($J57),$J57>0),$J57,IF(ISNUMBER($I57),$I57,""))) -> 598.19114 | L57: =IF(ISNUMBER($K57),$K57*$H57,"") -> 71.782937 | M57: =IF(ISNUMBER($K57),$K57*Parâmetros!$B$4,"") -> 59.819114 | N57: =IF(ISNUMBER($K57),$K57*Parâmetros!$C$4,"") -> 17.945734 | O57: =IF(ISNUMBER($K57),IF(ISNUMBER(Parâmetros!$E$4),Parâmetros!$E$4,0),"") -> 0 | P57: =IF(ISNUMBER($K57),$K57-$D57-IF(ISNUMBER($E57),$E57,0)-$L57-$M57-$N57-$O57,"") -> 109.47336 | Q57: =IF(AND(ISNUMBER($K57),$K57>0),$P57/$K57,"") -> 0.18300732 | S57: =IF(OR(NOT(ISNUMBER($R57)),$R57=0,NOT(ISNUMBER($K57))),"",$K57*(1-$R57)) | T57: =IF(ISNUMBER($S57),$S57*$H57,"") | U57: =IF(ISNUMBER($S57),$S57*Parâmetros!$B$4,"") | V57: =IF(ISNUMBER($S57),$S57*Parâmetros!$C$4,"") | W57: =IF(ISNUMBER($S57),$S57-$D57-IF(ISNUMBER($E57),$E57,0)-$O57-$T57-$U57-$V57,"") | X57: =IF(AND(ISNUMBER($S57),$S57>0),$W57/$S57,"") | Y57: 05/10
A58: =IF(Produtos!$A58="","",Produtos!$A58) -> L3085-AML | B58: =IF(Produtos!$A58="","",Produtos!$B58) -> Lixeira c/Aro Meia Lua 30x85 60L | C58: =IF(Produtos!$A58="","",Produtos!$C58) -> Lixeiras em inox | D58: =IF(Produtos!$A58="","",IF(Produtos!$D58="","",Produtos!$D58)) -> 360.65 | F58: =IF($A58="","",IF($C58="","⚠ categoria",IFERROR(INDEX(Parâmetros!$B$13:$B$22,MATCH($C58,Parâmetros!$A$13:$A$22,0)),"⚠ categoria"))) -> 0.13 | H58: =IF($A58="","",IF(ISNUMBER($G58),$G58,IF(ISNUMBER($F58),$F58,""))) -> 0.13 | I58: =IF(OR($A58="",NOT(ISNUMBER($D58)),NOT(ISNUMBER($H58))),"",IF((1-$H58-Parâmetros!$B$4-Parâmetros!$C$4-Parâmetros!$D$4)<=0,"INVALIDO",($D58+IF(ISNUMBER($E58),$E58,0)+IF(ISNUMBER(Parâmetros!$E$4),Parâmetros!$E$4,0))/(1-$H58-Parâmetros!$B$4-Parâmetros!$C$4-Parâmetros!$D$4))) -> 667.87037 | K58: =IF(OR($A58="",NOT(ISNUMBER($D58)),NOT(ISNUMBER($H58))),"",IF(AND(ISNUMBER($J58),$J58>0),$J58,IF(ISNUMBER($I58),$I58,""))) -> 667.87037 | L58: =IF(ISNUMBER($K58),$K58*$H58,"") -> 86.823148 | M58: =IF(ISNUMBER($K58),$K58*Parâmetros!$B$4,"") -> 66.787037 | N58: =IF(ISNUMBER($K58),$K58*Parâmetros!$C$4,"") -> 20.036111 | O58: =IF(ISNUMBER($K58),IF(ISNUMBER(Parâmetros!$E$4),Parâmetros!$E$4,0),"") -> 0 | P58: =IF(ISNUMBER($K58),$K58-$D58-IF(ISNUMBER($E58),$E58,0)-$L58-$M58-$N58-$O58,"") -> 133.57407 | Q58: =IF(AND(ISNUMBER($K58),$K58>0),$P58/$K58,"") -> 0.2 | S58: =IF(OR(NOT(ISNUMBER($R58)),$R58=0,NOT(ISNUMBER($K58))),"",$K58*(1-$R58)) | T58: =IF(ISNUMBER($S58),$S58*$H58,"") | U58: =IF(ISNUMBER($S58),$S58*Parâmetros!$B$4,"") | V58: =IF(ISNUMBER($S58),$S58*Parâmetros!$C$4,"") | W58: =IF(ISNUMBER($S58),$S58-$D58-IF(ISNUMBER($E58),$E58,0)-$O58-$T58-$U58-$V58,"") | X58: =IF(AND(ISNUMBER($S58),$S58>0),$W58/$S58,"")
A59: =IF(Produtos!$A59="","",Produtos!$A59) -> L4050-AML | B59: =IF(Produtos!$A59="","",Produtos!$B59) -> Lixeira c/Aro Meia Lua 40x50 62L | C59: =IF(Produtos!$A59="","",Produtos!$C59) -> Lixeiras em inox | D59: =IF(Produtos!$A59="","",IF(Produtos!$D59="","",Produtos!$D59)) -> 305.35 | F59: =IF($A59="","",IF($C59="","⚠ categoria",IFERROR(INDEX(Parâmetros!$B$13:$B$22,MATCH($C59,Parâmetros!$A$13:$A$22,0)),"⚠ categoria"))) -> 0.13 | H59: =IF($A59="","",IF(ISNUMBER($G59),$G59,IF(ISNUMBER($F59),$F59,""))) -> 0.13 | I59: =IF(OR($A59="",NOT(ISNUMBER($D59)),NOT(ISNUMBER($H59))),"",IF((1-$H59-Parâmetros!$B$4-Parâmetros!$C$4-Parâmetros!$D$4)<=0,"INVALIDO",($D59+IF(ISNUMBER($E59),$E59,0)+IF(ISNUMBER(Parâmetros!$E$4),Parâmetros!$E$4,0))/(1-$H59-Parâmetros!$B$4-Parâmetros!$C$4-Parâmetros!$D$4))) -> 565.46296 | K59: =IF(OR($A59="",NOT(ISNUMBER($D59)),NOT(ISNUMBER($H59))),"",IF(AND(ISNUMBER($J59),$J59>0),$J59,IF(ISNUMBER($I59),$I59,""))) -> 565.46296 | L59: =IF(ISNUMBER($K59),$K59*$H59,"") -> 73.510185 | M59: =IF(ISNUMBER($K59),$K59*Parâmetros!$B$4,"") -> 56.546296 | N59: =IF(ISNUMBER($K59),$K59*Parâmetros!$C$4,"") -> 16.963889 | O59: =IF(ISNUMBER($K59),IF(ISNUMBER(Parâmetros!$E$4),Parâmetros!$E$4,0),"") -> 0 | P59: =IF(ISNUMBER($K59),$K59-$D59-IF(ISNUMBER($E59),$E59,0)-$L59-$M59-$N59-$O59,"") -> 113.09259 | Q59: =IF(AND(ISNUMBER($K59),$K59>0),$P59/$K59,"") -> 0.2 | S59: =IF(OR(NOT(ISNUMBER($R59)),$R59=0,NOT(ISNUMBER($K59))),"",$K59*(1-$R59)) | T59: =IF(ISNUMBER($S59),$S59*$H59,"") | U59: =IF(ISNUMBER($S59),$S59*Parâmetros!$B$4,"") | V59: =IF(ISNUMBER($S59),$S59*Parâmetros!$C$4,"") | W59: =IF(ISNUMBER($S59),$S59-$D59-IF(ISNUMBER($E59),$E59,0)-$O59-$T59-$U59-$V59,"") | X59: =IF(AND(ISNUMBER($S59),$S59>0),$W59/$S59,"")
A60: =IF(Produtos!$A60="","",Produtos!$A60) -> L4060-AML | B60: =IF(Produtos!$A60="","",Produtos!$B60) -> Lixeira c/Aro Meia Lua 40x60 75L | C60: =IF(Produtos!$A60="","",Produtos!$C60) -> Lixeiras em inox | D60: =IF(Produtos!$A60="","",IF(Produtos!$D60="","",Produtos!$D60)) -> 342.54 | F60: =IF($A60="","",IF($C60="","⚠ categoria",IFERROR(INDEX(Parâmetros!$B$13:$B$22,MATCH($C60,Parâmetros!$A$13:$A$22,0)),"⚠ categoria"))) -> 0.13 | H60: =IF($A60="","",IF(ISNUMBER($G60),$G60,IF(ISNUMBER($F60),$F60,""))) -> 0.13 | I60: =IF(OR($A60="",NOT(ISNUMBER($D60)),NOT(ISNUMBER($H60))),"",IF((1-$H60-Parâmetros!$B$4-Parâmetros!$C$4-Parâmetros!$D$4)<=0,"INVALIDO",($D60+IF(ISNUMBER($E60),$E60,0)+IF(ISNUMBER(Parâmetros!$E$4),Parâmetros!$E$4,0))/(1-$H60-Parâmetros!$B$4-Parâmetros!$C$4-Parâmetros!$D$4))) -> 634.33333 | K60: =IF(OR($A60="",NOT(ISNUMBER($D60)),NOT(ISNUMBER($H60))),"",IF(AND(ISNUMBER($J60),$J60>0),$J60,IF(ISNUMBER($I60),$I60,""))) -> 634.33333 | L60: =IF(ISNUMBER($K60),$K60*$H60,"") -> 82.463333 | M60: =IF(ISNUMBER($K60),$K60*Parâmetros!$B$4,"") -> 63.433333 | N60: =IF(ISNUMBER($K60),$K60*Parâmetros!$C$4,"") -> 19.03 | O60: =IF(ISNUMBER($K60),IF(ISNUMBER(Parâmetros!$E$4),Parâmetros!$E$4,0),"") -> 0 | P60: =IF(ISNUMBER($K60),$K60-$D60-IF(ISNUMBER($E60),$E60,0)-$L60-$M60-$N60-$O60,"") -> 126.86667 | Q60: =IF(AND(ISNUMBER($K60),$K60>0),$P60/$K60,"") -> 0.2 | S60: =IF(OR(NOT(ISNUMBER($R60)),$R60=0,NOT(ISNUMBER($K60))),"",$K60*(1-$R60)) | T60: =IF(ISNUMBER($S60),$S60*$H60,"") | U60: =IF(ISNUMBER($S60),$S60*Parâmetros!$B$4,"") | V60: =IF(ISNUMBER($S60),$S60*Parâmetros!$C$4,"") | W60: =IF(ISNUMBER($S60),$S60-$D60-IF(ISNUMBER($E60),$E60,0)-$O60-$T60-$U60-$V60,"") | X60: =IF(AND(ISNUMBER($S60),$S60>0),$W60/$S60,"")
A61: =IF(Produtos!$A61="","",Produtos!$A61) -> L4070-AML | B61: =IF(Produtos!$A61="","",Produtos!$B61) -> Lixeira c/Aro Meia Lua 40x70 88L | C61: =IF(Produtos!$A61="","",Produtos!$C61) -> Lixeiras em inox | D61: =IF(Produtos!$A61="","",IF(Produtos!$D61="","",Produtos!$D61)) -> 348.66 | F61: =IF($A61="","",IF($C61="","⚠ categoria",IFERROR(INDEX(Parâmetros!$B$13:$B$22,MATCH($C61,Parâmetros!$A$13:$A$22,0)),"⚠ categoria"))) -> 0.13 | H61: =IF($A61="","",IF(ISNUMBER($G61),$G61,IF(ISNUMBER($F61),$F61,""))) -> 0.13 | I61: =IF(OR($A61="",NOT(ISNUMBER($D61)),NOT(ISNUMBER($H61))),"",IF((1-$H61-Parâmetros!$B$4-Parâmetros!$C$4-Parâmetros!$D$4)<=0,"INVALIDO",($D61+IF(ISNUMBER($E61),$E61,0)+IF(ISNUMBER(Parâmetros!$E$4),Parâmetros!$E$4,0))/(1-$H61-Parâmetros!$B$4-Parâmetros!$C$4-Parâmetros!$D$4))) -> 645.66667 | K61: =IF(OR($A61="",NOT(ISNUMBER($D61)),NOT(ISNUMBER($H61))),"",IF(AND(ISNUMBER($J61),$J61>0),$J61,IF(ISNUMBER($I61),$I61,""))) -> 645.66667 | L61: =IF(ISNUMBER($K61),$K61*$H61,"") -> 83.936667 | M61: =IF(ISNUMBER($K61),$K61*Parâmetros!$B$4,"") -> 64.566667 | N61: =IF(ISNUMBER($K61),$K61*Parâmetros!$C$4,"") -> 19.37 | O61: =IF(ISNUMBER($K61),IF(ISNUMBER(Parâmetros!$E$4),Parâmetros!$E$4,0),"") -> 0 | P61: =IF(ISNUMBER($K61),$K61-$D61-IF(ISNUMBER($E61),$E61,0)-$L61-$M61-$N61-$O61,"") -> 129.13333 | Q61: =IF(AND(ISNUMBER($K61),$K61>0),$P61/$K61,"") -> 0.2 | S61: =IF(OR(NOT(ISNUMBER($R61)),$R61=0,NOT(ISNUMBER($K61))),"",$K61*(1-$R61)) | T61: =IF(ISNUMBER($S61),$S61*$H61,"") | U61: =IF(ISNUMBER($S61),$S61*Parâmetros!$B$4,"") | V61: =IF(ISNUMBER($S61),$S61*Parâmetros!$C$4,"") | W61: =IF(ISNUMBER($S61),$S61-$D61-IF(ISNUMBER($E61),$E61,0)-$O61-$T61-$U61-$V61,"") | X61: =IF(AND(ISNUMBER($S61),$S61>0),$W61/$S61,"")
A62: =IF(Produtos!$A62="","",Produtos!$A62) -> L4075-AML | B62: =IF(Produtos!$A62="","",Produtos!$B62) -> Lixeira c/Aro Meia Lua 40x75 95L | C62: =IF(Produtos!$A62="","",Produtos!$C62) -> Lixeiras em inox | D62: =IF(Produtos!$A62="","",IF(Produtos!$D62="","",Produtos!$D62)) -> 408.87 | F62: =IF($A62="","",IF($C62="","⚠ categoria",IFERROR(INDEX(Parâmetros!$B$13:$B$22,MATCH($C62,Parâmetros!$A$13:$A$22,0)),"⚠ categoria"))) -> 0.13 | H62: =IF($A62="","",IF(ISNUMBER($G62),$G62,IF(ISNUMBER($F62),$F62,""))) -> 0.13 | I62: =IF(OR($A62="",NOT(ISNUMBER($D62)),NOT(ISNUMBER($H62))),"",IF((1-$H62-Parâmetros!$B$4-Parâmetros!$C$4-Parâmetros!$D$4)<=0,"INVALIDO",($D62+IF(ISNUMBER($E62),$E62,0)+IF(ISNUMBER(Parâmetros!$E$4),Parâmetros!$E$4,0))/(1-$H62-Parâmetros!$B$4-Parâmetros!$C$4-Parâmetros!$D$4))) -> 757.16667 | K62: =IF(OR($A62="",NOT(ISNUMBER($D62)),NOT(ISNUMBER($H62))),"",IF(AND(ISNUMBER($J62),$J62>0),$J62,IF(ISNUMBER($I62),$I62,""))) -> 757.16667 | L62: =IF(ISNUMBER($K62),$K62*$H62,"") -> 98.431667 | M62: =IF(ISNUMBER($K62),$K62*Parâmetros!$B$4,"") -> 75.716667 | N62: =IF(ISNUMBER($K62),$K62*Parâmetros!$C$4,"") -> 22.715 | O62: =IF(ISNUMBER($K62),IF(ISNUMBER(Parâmetros!$E$4),Parâmetros!$E$4,0),"") -> 0 | P62: =IF(ISNUMBER($K62),$K62-$D62-IF(ISNUMBER($E62),$E62,0)-$L62-$M62-$N62-$O62,"") -> 151.43333 | Q62: =IF(AND(ISNUMBER($K62),$K62>0),$P62/$K62,"") -> 0.2 | S62: =IF(OR(NOT(ISNUMBER($R62)),$R62=0,NOT(ISNUMBER($K62))),"",$K62*(1-$R62)) | T62: =IF(ISNUMBER($S62),$S62*$H62,"") | U62: =IF(ISNUMBER($S62),$S62*Parâmetros!$B$4,"") | V62: =IF(ISNUMBER($S62),$S62*Parâmetros!$C$4,"") | W62: =IF(ISNUMBER($S62),$S62-$D62-IF(ISNUMBER($E62),$E62,0)-$O62-$T62-$U62-$V62,"") | X62: =IF(AND(ISNUMBER($S62),$S62>0),$W62/$S62,"")
A63: =IF(Produtos!$A63="","",Produtos!$A63) -> L4080-AML | B63: =IF(Produtos!$A63="","",Produtos!$B63) -> Lixeira c/Aro Meia Lua 40x80 100L | C63: =IF(Produtos!$A63="","",Produtos!$C63) -> Lixeiras em inox | D63: =IF(Produtos!$A63="","",IF(Produtos!$D63="","",Produtos!$D63)) -> 411.4 | E63: 106.85 | F63: =IF($A63="","",IF($C63="","⚠ categoria",IFERROR(INDEX(Parâmetros!$B$13:$B$22,MATCH($C63,Parâmetros!$A$13:$A$22,0)),"⚠ categoria"))) -> 0.13 | H63: =IF($A63="","",IF(ISNUMBER($G63),$G63,IF(ISNUMBER($F63),$F63,""))) -> 0.13 | I63: =IF(OR($A63="",NOT(ISNUMBER($D63)),NOT(ISNUMBER($H63))),"",IF((1-$H63-Parâmetros!$B$4-Parâmetros!$C$4-Parâmetros!$D$4)<=0,"INVALIDO",($D63+IF(ISNUMBER($E63),$E63,0)+IF(ISNUMBER(Parâmetros!$E$4),Parâmetros!$E$4,0))/(1-$H63-Parâmetros!$B$4-Parâmetros!$C$4-Parâmetros!$D$4))) -> 959.72222 | J63: 953.07 | K63: =IF(OR($A63="",NOT(ISNUMBER($D63)),NOT(ISNUMBER($H63))),"",IF(AND(ISNUMBER($J63),$J63>0),$J63,IF(ISNUMBER($I63),$I63,""))) -> 953.07 | L63: =IF(ISNUMBER($K63),$K63*$H63,"") -> 123.8991 | M63: =IF(ISNUMBER($K63),$K63*Parâmetros!$B$4,"") -> 95.307 | N63: =IF(ISNUMBER($K63),$K63*Parâmetros!$C$4,"") -> 28.5921 | O63: =IF(ISNUMBER($K63),IF(ISNUMBER(Parâmetros!$E$4),Parâmetros!$E$4,0),"") -> 0 | P63: =IF(ISNUMBER($K63),$K63-$D63-IF(ISNUMBER($E63),$E63,0)-$L63-$M63-$N63-$O63,"") -> 187.0218 | Q63: =IF(AND(ISNUMBER($K63),$K63>0),$P63/$K63,"") -> 0.19623092 | S63: =IF(OR(NOT(ISNUMBER($R63)),$R63=0,NOT(ISNUMBER($K63))),"",$K63*(1-$R63)) | T63: =IF(ISNUMBER($S63),$S63*$H63,"") | U63: =IF(ISNUMBER($S63),$S63*Parâmetros!$B$4,"") | V63: =IF(ISNUMBER($S63),$S63*Parâmetros!$C$4,"") | W63: =IF(ISNUMBER($S63),$S63-$D63-IF(ISNUMBER($E63),$E63,0)-$O63-$T63-$U63-$V63,"") | X63: =IF(AND(ISNUMBER($S63),$S63>0),$W63/$S63,"") | Y63: 05/10
A64: =IF(Produtos!$A64="","",Produtos!$A64) -> L4090-AML | B64: =IF(Produtos!$A64="","",Produtos!$B64) -> Lixeira c/Aro Meia Lua 40x90 120L | C64: =IF(Produtos!$A64="","",Produtos!$C64) -> Lixeiras em inox | D64: =IF(Produtos!$A64="","",IF(Produtos!$D64="","",Produtos!$D64)) -> 442.44 | F64: =IF($A64="","",IF($C64="","⚠ categoria",IFERROR(INDEX(Parâmetros!$B$13:$B$22,MATCH($C64,Parâmetros!$A$13:$A$22,0)),"⚠ categoria"))) -> 0.13 | H64: =IF($A64="","",IF(ISNUMBER($G64),$G64,IF(ISNUMBER($F64),$F64,""))) -> 0.13 | I64: =IF(OR($A64="",NOT(ISNUMBER($D64)),NOT(ISNUMBER($H64))),"",IF((1-$H64-Parâmetros!$B$4-Parâmetros!$C$4-Parâmetros!$D$4)<=0,"INVALIDO",($D64+IF(ISNUMBER($E64),$E64,0)+IF(ISNUMBER(Parâmetros!$E$4),Parâmetros!$E$4,0))/(1-$H64-Parâmetros!$B$4-Parâmetros!$C$4-Parâmetros!$D$4))) -> 819.33333 | K64: =IF(OR($A64="",NOT(ISNUMBER($D64)),NOT(ISNUMBER($H64))),"",IF(AND(ISNUMBER($J64),$J64>0),$J64,IF(ISNUMBER($I64),$I64,""))) -> 819.33333 | L64: =IF(ISNUMBER($K64),$K64*$H64,"") -> 106.51333 | M64: =IF(ISNUMBER($K64),$K64*Parâmetros!$B$4,"") -> 81.933333 | N64: =IF(ISNUMBER($K64),$K64*Parâmetros!$C$4,"") -> 24.58 | O64: =IF(ISNUMBER($K64),IF(ISNUMBER(Parâmetros!$E$4),Parâmetros!$E$4,0),"") -> 0 | P64: =IF(ISNUMBER($K64),$K64-$D64-IF(ISNUMBER($E64),$E64,0)-$L64-$M64-$N64-$O64,"") -> 163.86667 | Q64: =IF(AND(ISNUMBER($K64),$K64>0),$P64/$K64,"") -> 0.2 | S64: =IF(OR(NOT(ISNUMBER($R64)),$R64=0,NOT(ISNUMBER($K64))),"",$K64*(1-$R64)) | T64: =IF(ISNUMBER($S64),$S64*$H64,"") | U64: =IF(ISNUMBER($S64),$S64*Parâmetros!$B$4,"") | V64: =IF(ISNUMBER($S64),$S64*Parâmetros!$C$4,"") | W64: =IF(ISNUMBER($S64),$S64-$D64-IF(ISNUMBER($E64),$E64,0)-$O64-$T64-$U64-$V64,"") | X64: =IF(AND(ISNUMBER($S64),$S64>0),$W64/$S64,"")
A65: =IF(Produtos!$A65="","",Produtos!$A65) -> L1618-B | B65: =IF(Produtos!$A65="","",Produtos!$B65) -> Lixeira c/Aro Basculante 16x18 03L | C65: =IF(Produtos!$A65="","",Produtos!$C65) -> Lixeiras em inox | D65: =IF(Produtos!$A65="","",IF(Produtos!$D65="","",Produtos!$D65)) -> 60.62 | E65: 21.75 | F65: =IF($A65="","",IF($C65="","⚠ categoria",IFERROR(INDEX(Parâmetros!$B$13:$B$22,MATCH($C65,Parâmetros!$A$13:$A$22,0)),"⚠ categoria"))) -> 0.13 | G65: 0.12 | H65: =IF($A65="","",IF(ISNUMBER($G65),$G65,IF(ISNUMBER($F65),$F65,""))) -> 0.12 | I65: =IF(OR($A65="",NOT(ISNUMBER($D65)),NOT(ISNUMBER($H65))),"",IF((1-$H65-Parâmetros!$B$4-Parâmetros!$C$4-Parâmetros!$D$4)<=0,"INVALIDO",($D65+IF(ISNUMBER($E65),$E65,0)+IF(ISNUMBER(Parâmetros!$E$4),Parâmetros!$E$4,0))/(1-$H65-Parâmetros!$B$4-Parâmetros!$C$4-Parâmetros!$D$4))) -> 149.76364 | J65: 152.775 | K65: =IF(OR($A65="",NOT(ISNUMBER($D65)),NOT(ISNUMBER($H65))),"",IF(AND(ISNUMBER($J65),$J65>0),$J65,IF(ISNUMBER($I65),$I65,""))) -> 152.775 | L65: =IF(ISNUMBER($K65),$K65*$H65,"") -> 18.333 | M65: =IF(ISNUMBER($K65),$K65*Parâmetros!$B$4,"") -> 15.2775 | N65: =IF(ISNUMBER($K65),$K65*Parâmetros!$C$4,"") -> 4.58325 | O65: =IF(ISNUMBER($K65),IF(ISNUMBER(Parâmetros!$E$4),Parâmetros!$E$4,0),"") -> 0 | P65: =IF(ISNUMBER($K65),$K65-$D65-IF(ISNUMBER($E65),$E65,0)-$L65-$M65-$N65-$O65,"") -> 32.21125 | Q65: =IF(AND(ISNUMBER($K65),$K65>0),$P65/$K65,"") -> 0.21084111 | S65: =IF(OR(NOT(ISNUMBER($R65)),$R65=0,NOT(ISNUMBER($K65))),"",$K65*(1-$R65)) | T65: =IF(ISNUMBER($S65),$S65*$H65,"") | U65: =IF(ISNUMBER($S65),$S65*Parâmetros!$B$4,"") | V65: =IF(ISNUMBER($S65),$S65*Parâmetros!$C$4,"") | W65: =IF(ISNUMBER($S65),$S65-$D65-IF(ISNUMBER($E65),$E65,0)-$O65-$T65-$U65-$V65,"") | X65: =IF(AND(ISNUMBER($S65),$S65>0),$W65/$S65,"") | Y65: 05/10
A66: =IF(Produtos!$A66="","",Produtos!$A66) -> L1623-B | B66: =IF(Produtos!$A66="","",Produtos!$B66) -> Lixeira c/Aro Basculante 16x23 05L | C66: =IF(Produtos!$A66="","",Produtos!$C66) -> Lixeiras em inox | D66: =IF(Produtos!$A66="","",IF(Produtos!$D66="","",Produtos!$D66)) -> 65.95 | E66: 21.75 | F66: =IF($A66="","",IF($C66="","⚠ categoria",IFERROR(INDEX(Parâmetros!$B$13:$B$22,MATCH($C66,Parâmetros!$A$13:$A$22,0)),"⚠ categoria"))) -> 0.13 | G66: 0.12 | H66: =IF($A66="","",IF(ISNUMBER($G66),$G66,IF(ISNUMBER($F66),$F66,""))) -> 0.12 | I66: =IF(OR($A66="",NOT(ISNUMBER($D66)),NOT(ISNUMBER($H66))),"",IF((1-$H66-Parâmetros!$B$4-Parâmetros!$C$4-Parâmetros!$D$4)<=0,"INVALIDO",($D66+IF(ISNUMBER($E66),$E66,0)+IF(ISNUMBER(Parâmetros!$E$4),Parâmetros!$E$4,0))/(1-$H66-Parâmetros!$B$4-Parâmetros!$C$4-Parâmetros!$D$4))) -> 159.45455 | J66: 163.17 | K66: =IF(OR($A66="",NOT(ISNUMBER($D66)),NOT(ISNUMBER($H66))),"",IF(AND(ISNUMBER($J66),$J66>0),$J66,IF(ISNUMBER($I66),$I66,""))) -> 163.17 | L66: =IF(ISNUMBER($K66),$K66*$H66,"") -> 19.5804 | M66: =IF(ISNUMBER($K66),$K66*Parâmetros!$B$4,"") -> 16.317 | N66: =IF(ISNUMBER($K66),$K66*Parâmetros!$C$4,"") -> 4.8951 | O66: =IF(ISNUMBER($K66),IF(ISNUMBER(Parâmetros!$E$4),Parâmetros!$E$4,0),"") -> 0 | P66: =IF(ISNUMBER($K66),$K66-$D66-IF(ISNUMBER($E66),$E66,0)-$L66-$M66-$N66-$O66,"") -> 34.6775 | Q66: =IF(AND(ISNUMBER($K66),$K66>0),$P66/$K66,"") -> 0.21252375 | S66: =IF(OR(NOT(ISNUMBER($R66)),$R66=0,NOT(ISNUMBER($K66))),"",$K66*(1-$R66)) | T66: =IF(ISNUMBER($S66),$S66*$H66,"") | U66: =IF(ISNUMBER($S66),$S66*Parâmetros!$B$4,"") | V66: =IF(ISNUMBER($S66),$S66*Parâmetros!$C$4,"") | W66: =IF(ISNUMBER($S66),$S66-$D66-IF(ISNUMBER($E66),$E66,0)-$O66-$T66-$U66-$V66,"") | X66: =IF(AND(ISNUMBER($S66),$S66>0),$W66/$S66,"") | Y66: 05/10
A67: =IF(Produtos!$A67="","",Produtos!$A67) -> L2025-B | B67: =IF(Produtos!$A67="","",Produtos!$B67) -> Lixeira c/Aro Basculante 20x25 07L | C67: =IF(Produtos!$A67="","",Produtos!$C67) -> Lixeiras em inox | D67: =IF(Produtos!$A67="","",IF(Produtos!$D67="","",Produtos!$D67)) -> 69.52 | E67: 24.35 | F67: =IF($A67="","",IF($C67="","⚠ categoria",IFERROR(INDEX(Parâmetros!$B$13:$B$22,MATCH($C67,Parâmetros!$A$13:$A$22,0)),"⚠ categoria"))) -> 0.13 | G67: 0.12 | H67: =IF($A67="","",IF(ISNUMBER($G67),$G67,IF(ISNUMBER($F67),$F67,""))) -> 0.12 | I67: =IF(OR($A67="",NOT(ISNUMBER($D67)),NOT(ISNUMBER($H67))),"",IF((1-$H67-Parâmetros!$B$4-Parâmetros!$C$4-Parâmetros!$D$4)<=0,"INVALIDO",($D67+IF(ISNUMBER($E67),$E67,0)+IF(ISNUMBER(Parâmetros!$E$4),Parâmetros!$E$4,0))/(1-$H67-Parâmetros!$B$4-Parâmetros!$C$4-Parâmetros!$D$4))) -> 170.67273 | J67: 170.93491 | K67: =IF(OR($A67="",NOT(ISNUMBER($D67)),NOT(ISNUMBER($H67))),"",IF(AND(ISNUMBER($J67),$J67>0),$J67,IF(ISNUMBER($I67),$I67,""))) -> 170.93491 | L67: =IF(ISNUMBER($K67),$K67*$H67,"") -> 20.512189 | M67: =IF(ISNUMBER($K67),$K67*Parâmetros!$B$4,"") -> 17.093491 | N67: =IF(ISNUMBER($K67),$K67*Parâmetros!$C$4,"") -> 5.1280472 | O67: =IF(ISNUMBER($K67),IF(ISNUMBER(Parâmetros!$E$4),Parâmetros!$E$4,0),"") -> 0 | P67: =IF(ISNUMBER($K67),$K67-$D67-IF(ISNUMBER($E67),$E67,0)-$L67-$M67-$N67-$O67,"") -> 34.331181 | Q67: =IF(AND(ISNUMBER($K67),$K67>0),$P67/$K67,"") -> 0.20084359 | S67: =IF(OR(NOT(ISNUMBER($R67)),$R67=0,NOT(ISNUMBER($K67))),"",$K67*(1-$R67)) | T67: =IF(ISNUMBER($S67),$S67*$H67,"") | U67: =IF(ISNUMBER($S67),$S67*Parâmetros!$B$4,"") | V67: =IF(ISNUMBER($S67),$S67*Parâmetros!$C$4,"") | W67: =IF(ISNUMBER($S67),$S67-$D67-IF(ISNUMBER($E67),$E67,0)-$O67-$T67-$U67-$V67,"") | X67: =IF(AND(ISNUMBER($S67),$S67>0),$W67/$S67,"") | Y67: 05/10
A68: =IF(Produtos!$A68="","",Produtos!$A68) -> L2030-B | B68: =IF(Produtos!$A68="","",Produtos!$B68) -> Lixeira c/Aro Basculante 20x30 10L | C68: =IF(Produtos!$A68="","",Produtos!$C68) -> Lixeiras em inox | D68: =IF(Produtos!$A68="","",IF(Produtos!$D68="","",Produtos!$D68)) -> 75.68 | E68: 24.35 | F68: =IF($A68="","",IF($C68="","⚠ categoria",IFERROR(INDEX(Parâmetros!$B$13:$B$22,MATCH($C68,Parâmetros!$A$13:$A$22,0)),"⚠ categoria"))) -> 0.13 | G68: 0.12 | H68: =IF($A68="","",IF(ISNUMBER($G68),$G68,IF(ISNUMBER($F68),$F68,""))) -> 0.12 | I68: =IF(OR($A68="",NOT(ISNUMBER($D68)),NOT(ISNUMBER($H68))),"",IF((1-$H68-Parâmetros!$B$4-Parâmetros!$C$4-Parâmetros!$D$4)<=0,"INVALIDO",($D68+IF(ISNUMBER($E68),$E68,0)+IF(ISNUMBER(Parâmetros!$E$4),Parâmetros!$E$4,0))/(1-$H68-Parâmetros!$B$4-Parâmetros!$C$4-Parâmetros!$D$4))) -> 181.87273 | J68: 182.9 | K68: =IF(OR($A68="",NOT(ISNUMBER($D68)),NOT(ISNUMBER($H68))),"",IF(AND(ISNUMBER($J68),$J68>0),$J68,IF(ISNUMBER($I68),$I68,""))) -> 182.9 | L68: =IF(ISNUMBER($K68),$K68*$H68,"") -> 21.948 | M68: =IF(ISNUMBER($K68),$K68*Parâmetros!$B$4,"") -> 18.29 | N68: =IF(ISNUMBER($K68),$K68*Parâmetros!$C$4,"") -> 5.487 | O68: =IF(ISNUMBER($K68),IF(ISNUMBER(Parâmetros!$E$4),Parâmetros!$E$4,0),"") -> 0 | P68: =IF(ISNUMBER($K68),$K68-$D68-IF(ISNUMBER($E68),$E68,0)-$L68-$M68-$N68-$O68,"") -> 37.145 | Q68: =IF(AND(ISNUMBER($K68),$K68>0),$P68/$K68,"") -> 0.20308912 | S68: =IF(OR(NOT(ISNUMBER($R68)),$R68=0,NOT(ISNUMBER($K68))),"",$K68*(1-$R68)) | T68: =IF(ISNUMBER($S68),$S68*$H68,"") | U68: =IF(ISNUMBER($S68),$S68*Parâmetros!$B$4,"") | V68: =IF(ISNUMBER($S68),$S68*Parâmetros!$C$4,"") | W68: =IF(ISNUMBER($S68),$S68-$D68-IF(ISNUMBER($E68),$E68,0)-$O68-$T68-$U68-$V68,"") | X68: =IF(AND(ISNUMBER($S68),$S68>0),$W68/$S68,"") | Y68: 06/10
A69: =IF(Produtos!$A69="","",Produtos!$A69) -> L2425-B | B69: =IF(Produtos!$A69="","",Produtos!$B69) -> Lixeira c/Aro Basculante 24x25 13L | C69: =IF(Produtos!$A69="","",Produtos!$C69) -> Lixeiras em inox | D69: =IF(Produtos!$A69="","",IF(Produtos!$D69="","",Produtos!$D69)) -> 94.18 | E69: 27.05 | F69: =IF($A69="","",IF($C69="","⚠ categoria",IFERROR(INDEX(Parâmetros!$B$13:$B$22,MATCH($C69,Parâmetros!$A$13:$A$22,0)),"⚠ categoria"))) -> 0.13 | G69: 0.12 | H69: =IF($A69="","",IF(ISNUMBER($G69),$G69,IF(ISNUMBER($F69),$F69,""))) -> 0.12 | I69: =IF(OR($A69="",NOT(ISNUMBER($D69)),NOT(ISNUMBER($H69))),"",IF((1-$H69-Parâmetros!$B$4-Parâmetros!$C$4-Parâmetros!$D$4)<=0,"INVALIDO",($D69+IF(ISNUMBER($E69),$E69,0)+IF(ISNUMBER(Parâmetros!$E$4),Parâmetros!$E$4,0))/(1-$H69-Parâmetros!$B$4-Parâmetros!$C$4-Parâmetros!$D$4))) -> 220.41818 | J69: 222.485 | K69: =IF(OR($A69="",NOT(ISNUMBER($D69)),NOT(ISNUMBER($H69))),"",IF(AND(ISNUMBER($J69),$J69>0),$J69,IF(ISNUMBER($I69),$I69,""))) -> 222.485 | L69: =IF(ISNUMBER($K69),$K69*$H69,"") -> 26.6982 | M69: =IF(ISNUMBER($K69),$K69*Parâmetros!$B$4,"") -> 22.2485 | N69: =IF(ISNUMBER($K69),$K69*Parâmetros!$C$4,"") -> 6.67455 | O69: =IF(ISNUMBER($K69),IF(ISNUMBER(Parâmetros!$E$4),Parâmetros!$E$4,0),"") -> 0 | P69: =IF(ISNUMBER($K69),$K69-$D69-IF(ISNUMBER($E69),$E69,0)-$L69-$M69-$N69-$O69,"") -> 45.63375 | Q69: =IF(AND(ISNUMBER($K69),$K69>0),$P69/$K69,"") -> 0.20510933 | S69: =IF(OR(NOT(ISNUMBER($R69)),$R69=0,NOT(ISNUMBER($K69))),"",$K69*(1-$R69)) | T69: =IF(ISNUMBER($S69),$S69*$H69,"") | U69: =IF(ISNUMBER($S69),$S69*Parâmetros!$B$4,"") | V69: =IF(ISNUMBER($S69),$S69*Parâmetros!$C$4,"") | W69: =IF(ISNUMBER($S69),$S69-$D69-IF(ISNUMBER($E69),$E69,0)-$O69-$T69-$U69-$V69,"") | X69: =IF(AND(ISNUMBER($S69),$S69>0),$W69/$S69,"") | Y69: 06/10
A70: =IF(Produtos!$A70="","",Produtos!$A70) -> L2430-B | B70: =IF(Produtos!$A70="","",Produtos!$B70) -> Lixeira c/Aro Basculante 24x30 15L | C70: =IF(Produtos!$A70="","",Produtos!$C70) -> Lixeiras em inox | D70: =IF(Produtos!$A70="","",IF(Produtos!$D70="","",Produtos!$D70)) -> 103.42 | E70: 27.05 | F70: =IF($A70="","",IF($C70="","⚠ categoria",IFERROR(INDEX(Parâmetros!$B$13:$B$22,MATCH($C70,Parâmetros!$A$13:$A$22,0)),"⚠ categoria"))) -> 0.13 | G70: 0.12 | H70: =IF($A70="","",IF(ISNUMBER($G70),$G70,IF(ISNUMBER($F70),$F70,""))) -> 0.12 | I70: =IF(OR($A70="",NOT(ISNUMBER($D70)),NOT(ISNUMBER($H70))),"",IF((1-$H70-Parâmetros!$B$4-Parâmetros!$C$4-Parâmetros!$D$4)<=0,"INVALIDO",($D70+IF(ISNUMBER($E70),$E70,0)+IF(ISNUMBER(Parâmetros!$E$4),Parâmetros!$E$4,0))/(1-$H70-Parâmetros!$B$4-Parâmetros!$C$4-Parâmetros!$D$4))) -> 237.21818 | J70: 239.1125 | K70: =IF(OR($A70="",NOT(ISNUMBER($D70)),NOT(ISNUMBER($H70))),"",IF(AND(ISNUMBER($J70),$J70>0),$J70,IF(ISNUMBER($I70),$I70,""))) -> 239.1125 | L70: =IF(ISNUMBER($K70),$K70*$H70,"") -> 28.6935 | M70: =IF(ISNUMBER($K70),$K70*Parâmetros!$B$4,"") -> 23.91125 | N70: =IF(ISNUMBER($K70),$K70*Parâmetros!$C$4,"") -> 7.173375 | O70: =IF(ISNUMBER($K70),IF(ISNUMBER(Parâmetros!$E$4),Parâmetros!$E$4,0),"") -> 0 | P70: =IF(ISNUMBER($K70),$K70-$D70-IF(ISNUMBER($E70),$E70,0)-$L70-$M70-$N70-$O70,"") -> 48.864375 | Q70: =IF(AND(ISNUMBER($K70),$K70>0),$P70/$K70,"") -> 0.20435726 | S70: =IF(OR(NOT(ISNUMBER($R70)),$R70=0,NOT(ISNUMBER($K70))),"",$K70*(1-$R70)) | T70: =IF(ISNUMBER($S70),$S70*$H70,"") | U70: =IF(ISNUMBER($S70),$S70*Parâmetros!$B$4,"") | V70: =IF(ISNUMBER($S70),$S70*Parâmetros!$C$4,"") | W70: =IF(ISNUMBER($S70),$S70-$D70-IF(ISNUMBER($E70),$E70,0)-$O70-$T70-$U70-$V70,"") | X70: =IF(AND(ISNUMBER($S70),$S70>0),$W70/$S70,"") | Y70: 06/10
A71: =IF(Produtos!$A71="","",Produtos!$A71) -> L2440-B | B71: =IF(Produtos!$A71="","",Produtos!$B71) -> Lixeira c/Aro Basculante 24x40 20L | C71: =IF(Produtos!$A71="","",Produtos!$C71) -> Lixeiras em inox | D71: =IF(Produtos!$A71="","",IF(Produtos!$D71="","",Produtos!$D71)) -> 120.51 | E71: 29.25 | F71: =IF($A71="","",IF($C71="","⚠ categoria",IFERROR(INDEX(Parâmetros!$B$13:$B$22,MATCH($C71,Parâmetros!$A$13:$A$22,0)),"⚠ categoria"))) -> 0.13 | G71: 0.12 | H71: =IF($A71="","",IF(ISNUMBER($G71),$G71,IF(ISNUMBER($F71),$F71,""))) -> 0.12 | I71: =IF(OR($A71="",NOT(ISNUMBER($D71)),NOT(ISNUMBER($H71))),"",IF((1-$H71-Parâmetros!$B$4-Parâmetros!$C$4-Parâmetros!$D$4)<=0,"INVALIDO",($D71+IF(ISNUMBER($E71),$E71,0)+IF(ISNUMBER(Parâmetros!$E$4),Parâmetros!$E$4,0))/(1-$H71-Parâmetros!$B$4-Parâmetros!$C$4-Parâmetros!$D$4))) -> 272.29091 | J71: 272.78 | K71: =IF(OR($A71="",NOT(ISNUMBER($D71)),NOT(ISNUMBER($H71))),"",IF(AND(ISNUMBER($J71),$J71>0),$J71,IF(ISNUMBER($I71),$I71,""))) -> 272.78 | L71: =IF(ISNUMBER($K71),$K71*$H71,"") -> 32.7336 | M71: =IF(ISNUMBER($K71),$K71*Parâmetros!$B$4,"") -> 27.278 | N71: =IF(ISNUMBER($K71),$K71*Parâmetros!$C$4,"") -> 8.1834 | O71: =IF(ISNUMBER($K71),IF(ISNUMBER(Parâmetros!$E$4),Parâmetros!$E$4,0),"") -> 0 | P71: =IF(ISNUMBER($K71),$K71-$D71-IF(ISNUMBER($E71),$E71,0)-$L71-$M71-$N71-$O71,"") -> 54.825 | Q71: =IF(AND(ISNUMBER($K71),$K71>0),$P71/$K71,"") -> 0.20098614 | S71: =IF(OR(NOT(ISNUMBER($R71)),$R71=0,NOT(ISNUMBER($K71))),"",$K71*(1-$R71)) | T71: =IF(ISNUMBER($S71),$S71*$H71,"") | U71: =IF(ISNUMBER($S71),$S71*Parâmetros!$B$4,"") | V71: =IF(ISNUMBER($S71),$S71*Parâmetros!$C$4,"") | W71: =IF(ISNUMBER($S71),$S71-$D71-IF(ISNUMBER($E71),$E71,0)-$O71-$T71-$U71-$V71,"") | X71: =IF(AND(ISNUMBER($S71),$S71>0),$W71/$S71,"") | Y71: 06/10
A72: =IF(Produtos!$A72="","",Produtos!$A72) -> L2450-B | B72: =IF(Produtos!$A72="","",Produtos!$B72) -> Lixeira c/Aro Basculante 24x50 25L | C72: =IF(Produtos!$A72="","",Produtos!$C72) -> Lixeiras em inox | D72: =IF(Produtos!$A72="","",IF(Produtos!$D72="","",Produtos!$D72)) -> 151.31 | E72: 32.45 | F72: =IF($A72="","",IF($C72="","⚠ categoria",IFERROR(INDEX(Parâmetros!$B$13:$B$22,MATCH($C72,Parâmetros!$A$13:$A$22,0)),"⚠ categoria"))) -> 0.13 | G72: 0.12 | H72: =IF($A72="","",IF(ISNUMBER($G72),$G72,IF(ISNUMBER($F72),$F72,""))) -> 0.12 | I72: =IF(OR($A72="",NOT(ISNUMBER($D72)),NOT(ISNUMBER($H72))),"",IF((1-$H72-Parâmetros!$B$4-Parâmetros!$C$4-Parâmetros!$D$4)<=0,"INVALIDO",($D72+IF(ISNUMBER($E72),$E72,0)+IF(ISNUMBER(Parâmetros!$E$4),Parâmetros!$E$4,0))/(1-$H72-Parâmetros!$B$4-Parâmetros!$C$4-Parâmetros!$D$4))) -> 334.10909 | J72: 335.87183 | K72: =IF(OR($A72="",NOT(ISNUMBER($D72)),NOT(ISNUMBER($H72))),"",IF(AND(ISNUMBER($J72),$J72>0),$J72,IF(ISNUMBER($I72),$I72,""))) -> 335.87183 | L72: =IF(ISNUMBER($K72),$K72*$H72,"") -> 40.304619 | M72: =IF(ISNUMBER($K72),$K72*Parâmetros!$B$4,"") -> 33.587182 | N72: =IF(ISNUMBER($K72),$K72*Parâmetros!$C$4,"") -> 10.076155 | O72: =IF(ISNUMBER($K72),IF(ISNUMBER(Parâmetros!$E$4),Parâmetros!$E$4,0),"") -> 0 | P72: =IF(ISNUMBER($K72),$K72-$D72-IF(ISNUMBER($E72),$E72,0)-$L72-$M72-$N72-$O72,"") -> 68.143869 | Q72: =IF(AND(ISNUMBER($K72),$K72>0),$P72/$K72,"") -> 0.20288653 | S72: =IF(OR(NOT(ISNUMBER($R72)),$R72=0,NOT(ISNUMBER($K72))),"",$K72*(1-$R72)) | T72: =IF(ISNUMBER($S72),$S72*$H72,"") | U72: =IF(ISNUMBER($S72),$S72*Parâmetros!$B$4,"") | V72: =IF(ISNUMBER($S72),$S72*Parâmetros!$C$4,"") | W72: =IF(ISNUMBER($S72),$S72-$D72-IF(ISNUMBER($E72),$E72,0)-$O72-$T72-$U72-$V72,"") | X72: =IF(AND(ISNUMBER($S72),$S72>0),$W72/$S72,"") | Y72: 06/10
A73: =IF(Produtos!$A73="","",Produtos!$A73) -> L2460-B | B73: =IF(Produtos!$A73="","",Produtos!$B73) -> Lixeira c/Aro Basculante 24x60 27L | C73: =IF(Produtos!$A73="","",Produtos!$C73) -> Lixeiras em inox | D73: =IF(Produtos!$A73="","",IF(Produtos!$D73="","",Produtos!$D73)) -> 152.83 | E73: 49.35 | F73: =IF($A73="","",IF($C73="","⚠ categoria",IFERROR(INDEX(Parâmetros!$B$13:$B$22,MATCH($C73,Parâmetros!$A$13:$A$22,0)),"⚠ categoria"))) -> 0.13 | G73: 0.12 | H73: =IF($A73="","",IF(ISNUMBER($G73),$G73,IF(ISNUMBER($F73),$F73,""))) -> 0.12 | I73: =IF(OR($A73="",NOT(ISNUMBER($D73)),NOT(ISNUMBER($H73))),"",IF((1-$H73-Parâmetros!$B$4-Parâmetros!$C$4-Parâmetros!$D$4)<=0,"INVALIDO",($D73+IF(ISNUMBER($E73),$E73,0)+IF(ISNUMBER(Parâmetros!$E$4),Parâmetros!$E$4,0))/(1-$H73-Parâmetros!$B$4-Parâmetros!$C$4-Parâmetros!$D$4))) -> 367.6 | J73: 357.13701 | K73: =IF(OR($A73="",NOT(ISNUMBER($D73)),NOT(ISNUMBER($H73))),"",IF(AND(ISNUMBER($J73),$J73>0),$J73,IF(ISNUMBER($I73),$I73,""))) -> 357.13701 | L73: =IF(ISNUMBER($K73),$K73*$H73,"") -> 42.856441 | M73: =IF(ISNUMBER($K73),$K73*Parâmetros!$B$4,"") -> 35.713701 | N73: =IF(ISNUMBER($K73),$K73*Parâmetros!$C$4,"") -> 10.71411 | O73: =IF(ISNUMBER($K73),IF(ISNUMBER(Parâmetros!$E$4),Parâmetros!$E$4,0),"") -> 0 | P73: =IF(ISNUMBER($K73),$K73-$D73-IF(ISNUMBER($E73),$E73,0)-$L73-$M73-$N73-$O73,"") -> 65.672757 | Q73: =IF(AND(ISNUMBER($K73),$K73>0),$P73/$K73,"") -> 0.18388673 | S73: =IF(OR(NOT(ISNUMBER($R73)),$R73=0,NOT(ISNUMBER($K73))),"",$K73*(1-$R73)) | T73: =IF(ISNUMBER($S73),$S73*$H73,"") | U73: =IF(ISNUMBER($S73),$S73*Parâmetros!$B$4,"") | V73: =IF(ISNUMBER($S73),$S73*Parâmetros!$C$4,"") | W73: =IF(ISNUMBER($S73),$S73-$D73-IF(ISNUMBER($E73),$E73,0)-$O73-$T73-$U73-$V73,"") | X73: =IF(AND(ISNUMBER($S73),$S73>0),$W73/$S73,"") | Y73: 06/10
A74: =IF(Produtos!$A74="","",Produtos!$A74) -> L2470-B | B74: =IF(Produtos!$A74="","",Produtos!$B74) -> Lixeira c/Aro Basculante 24x70 30L | C74: =IF(Produtos!$A74="","",Produtos!$C74) -> Lixeiras em inox | D74: =IF(Produtos!$A74="","",IF(Produtos!$D74="","",Produtos!$D74)) -> 211.1 | E74: 45.25 | F74: =IF($A74="","",IF($C74="","⚠ categoria",IFERROR(INDEX(Parâmetros!$B$13:$B$22,MATCH($C74,Parâmetros!$A$13:$A$22,0)),"⚠ categoria"))) -> 0.13 | G74: 0.12 | H74: =IF($A74="","",IF(ISNUMBER($G74),$G74,IF(ISNUMBER($F74),$F74,""))) -> 0.12 | I74: =IF(OR($A74="",NOT(ISNUMBER($D74)),NOT(ISNUMBER($H74))),"",IF((1-$H74-Parâmetros!$B$4-Parâmetros!$C$4-Parâmetros!$D$4)<=0,"INVALIDO",($D74+IF(ISNUMBER($E74),$E74,0)+IF(ISNUMBER(Parâmetros!$E$4),Parâmetros!$E$4,0))/(1-$H74-Parâmetros!$B$4-Parâmetros!$C$4-Parâmetros!$D$4))) -> 466.09091 | J74: 452.74714 | K74: =IF(OR($A74="",NOT(ISNUMBER($D74)),NOT(ISNUMBER($H74))),"",IF(AND(ISNUMBER($J74),$J74>0),$J74,IF(ISNUMBER($I74),$I74,""))) -> 452.74714 | L74: =IF(ISNUMBER($K74),$K74*$H74,"") -> 54.329656 | M74: =IF(ISNUMBER($K74),$K74*Parâmetros!$B$4,"") -> 45.274714 | N74: =IF(ISNUMBER($K74),$K74*Parâmetros!$C$4,"") -> 13.582414 | O74: =IF(ISNUMBER($K74),IF(ISNUMBER(Parâmetros!$E$4),Parâmetros!$E$4,0),"") -> 0 | P74: =IF(ISNUMBER($K74),$K74-$D74-IF(ISNUMBER($E74),$E74,0)-$L74-$M74-$N74-$O74,"") -> 83.210353 | Q74: =IF(AND(ISNUMBER($K74),$K74>0),$P74/$K74,"") -> 0.1837899 | S74: =IF(OR(NOT(ISNUMBER($R74)),$R74=0,NOT(ISNUMBER($K74))),"",$K74*(1-$R74)) | T74: =IF(ISNUMBER($S74),$S74*$H74,"") | U74: =IF(ISNUMBER($S74),$S74*Parâmetros!$B$4,"") | V74: =IF(ISNUMBER($S74),$S74*Parâmetros!$C$4,"") | W74: =IF(ISNUMBER($S74),$S74-$D74-IF(ISNUMBER($E74),$E74,0)-$O74-$T74-$U74-$V74,"") | X74: =IF(AND(ISNUMBER($S74),$S74>0),$W74/$S74,"") | Y74: 06/10
A75: =IF(Produtos!$A75="","",Produtos!$A75) -> L3040-B | B75: =IF(Produtos!$A75="","",Produtos!$B75) -> Lixeira c/Aro Basculante 30x40 30L | C75: =IF(Produtos!$A75="","",Produtos!$C75) -> Lixeiras em inox | D75: =IF(Produtos!$A75="","",IF(Produtos!$D75="","",Produtos!$D75)) -> 172.54 | E75: 40.85 | F75: =IF($A75="","",IF($C75="","⚠ categoria",IFERROR(INDEX(Parâmetros!$B$13:$B$22,MATCH($C75,Parâmetros!$A$13:$A$22,0)),"⚠ categoria"))) -> 0.13 | G75: 0.12 | H75: =IF($A75="","",IF(ISNUMBER($G75),$G75,IF(ISNUMBER($F75),$F75,""))) -> 0.12 | I75: =IF(OR($A75="",NOT(ISNUMBER($D75)),NOT(ISNUMBER($H75))),"",IF((1-$H75-Parâmetros!$B$4-Parâmetros!$C$4-Parâmetros!$D$4)<=0,"INVALIDO",($D75+IF(ISNUMBER($E75),$E75,0)+IF(ISNUMBER(Parâmetros!$E$4),Parâmetros!$E$4,0))/(1-$H75-Parâmetros!$B$4-Parâmetros!$C$4-Parâmetros!$D$4))) -> 387.98182 | J75: 391.21749 | K75: =IF(OR($A75="",NOT(ISNUMBER($D75)),NOT(ISNUMBER($H75))),"",IF(AND(ISNUMBER($J75),$J75>0),$J75,IF(ISNUMBER($I75),$I75,""))) -> 391.21749 | L75: =IF(ISNUMBER($K75),$K75*$H75,"") -> 46.946099 | M75: =IF(ISNUMBER($K75),$K75*Parâmetros!$B$4,"") -> 39.121749 | N75: =IF(ISNUMBER($K75),$K75*Parâmetros!$C$4,"") -> 11.736525 | O75: =IF(ISNUMBER($K75),IF(ISNUMBER(Parâmetros!$E$4),Parâmetros!$E$4,0),"") -> 0 | P75: =IF(ISNUMBER($K75),$K75-$D75-IF(ISNUMBER($E75),$E75,0)-$L75-$M75-$N75-$O75,"") -> 80.023117 | Q75: =IF(AND(ISNUMBER($K75),$K75>0),$P75/$K75,"") -> 0.20454892 | S75: =IF(OR(NOT(ISNUMBER($R75)),$R75=0,NOT(ISNUMBER($K75))),"",$K75*(1-$R75)) | T75: =IF(ISNUMBER($S75),$S75*$H75,"") | U75: =IF(ISNUMBER($S75),$S75*Parâmetros!$B$4,"") | V75: =IF(ISNUMBER($S75),$S75*Parâmetros!$C$4,"") | W75: =IF(ISNUMBER($S75),$S75-$D75-IF(ISNUMBER($E75),$E75,0)-$O75-$T75-$U75-$V75,"") | X75: =IF(AND(ISNUMBER($S75),$S75>0),$W75/$S75,"") | Y75: 06/10
A76: =IF(Produtos!$A76="","",Produtos!$A76) -> L3050-B | B76: =IF(Produtos!$A76="","",Produtos!$B76) -> Lixeira c/Aro Basculante 30x50 35L | C76: =IF(Produtos!$A76="","",Produtos!$C76) -> Lixeiras em inox | D76: =IF(Produtos!$A76="","",IF(Produtos!$D76="","",Produtos!$D76)) -> 216.99 | E76: 49.35 | F76: =IF($A76="","",IF($C76="","⚠ categoria",IFERROR(INDEX(Parâmetros!$B$13:$B$22,MATCH($C76,Parâmetros!$A$13:$A$22,0)),"⚠ categoria"))) -> 0.13 | G76: 0.12 | H76: =IF($A76="","",IF(ISNUMBER($G76),$G76,IF(ISNUMBER($F76),$F76,""))) -> 0.12 | I76: =IF(OR($A76="",NOT(ISNUMBER($D76)),NOT(ISNUMBER($H76))),"",IF((1-$H76-Parâmetros!$B$4-Parâmetros!$C$4-Parâmetros!$D$4)<=0,"INVALIDO",($D76+IF(ISNUMBER($E76),$E76,0)+IF(ISNUMBER(Parâmetros!$E$4),Parâmetros!$E$4,0))/(1-$H76-Parâmetros!$B$4-Parâmetros!$C$4-Parâmetros!$D$4))) -> 484.25455 | J76: 486.9 | K76: =IF(OR($A76="",NOT(ISNUMBER($D76)),NOT(ISNUMBER($H76))),"",IF(AND(ISNUMBER($J76),$J76>0),$J76,IF(ISNUMBER($I76),$I76,""))) -> 486.9 | L76: =IF(ISNUMBER($K76),$K76*$H76,"") -> 58.428 | M76: =IF(ISNUMBER($K76),$K76*Parâmetros!$B$4,"") -> 48.69 | N76: =IF(ISNUMBER($K76),$K76*Parâmetros!$C$4,"") -> 14.607 | O76: =IF(ISNUMBER($K76),IF(ISNUMBER(Parâmetros!$E$4),Parâmetros!$E$4,0),"") -> 0 | P76: =IF(ISNUMBER($K76),$K76-$D76-IF(ISNUMBER($E76),$E76,0)-$L76-$M76-$N76-$O76,"") -> 98.835 | Q76: =IF(AND(ISNUMBER($K76),$K76>0),$P76/$K76,"") -> 0.20298829 | S76: =IF(OR(NOT(ISNUMBER($R76)),$R76=0,NOT(ISNUMBER($K76))),"",$K76*(1-$R76)) | T76: =IF(ISNUMBER($S76),$S76*$H76,"") | U76: =IF(ISNUMBER($S76),$S76*Parâmetros!$B$4,"") | V76: =IF(ISNUMBER($S76),$S76*Parâmetros!$C$4,"") | W76: =IF(ISNUMBER($S76),$S76-$D76-IF(ISNUMBER($E76),$E76,0)-$O76-$T76-$U76-$V76,"") | X76: =IF(AND(ISNUMBER($S76),$S76>0),$W76/$S76,"") | Y76: 06/10
... A78: =IF(Produtos!$A78="","",Produtos!$A78) -> L3070-B | B78: =IF(Produtos!$A78="","",Produtos!$B78) -> Lixeira c/Aro Basculante 30x70 50L | C78: =IF(Produtos!$A78="","",Produtos!$C78) -> Lixeiras em inox | D78: =IF(Produtos!$A78="","",IF(Produtos!$D78="","",Produtos!$D78)) -> 279.42 | E78: 69.35 | F78: =IF($A78="","",IF($C78="","⚠ categoria",IFERROR(INDEX(Parâmetros!$B$13:$B$22,MATCH($C78,Parâmetros!$A$13:$A$22,0)),"⚠ categoria"))) -> 0.13 | G78: 0.12 | H78: =IF($A78="","",IF(ISNUMBER($G78),$G78,IF(ISNUMBER($F78),$F78,""))) -> 0.12 | I78: =IF(OR($A78="",NOT(ISNUMBER($D78)),NOT(ISNUMBER($H78))),"",IF((1-$H78-Parâmetros!$B$4-Parâmetros!$C$4-Parâmetros!$D$4)<=0,"INVALIDO",($D78+IF(ISNUMBER($E78),$E78,0)+IF(ISNUMBER(Parâmetros!$E$4),Parâmetros!$E$4,0))/(1-$H78-Parâmetros!$B$4-Parâmetros!$C$4-Parâmetros!$D$4))) -> 634.12727 | J78: 615.59025 | K78: =IF(OR($A78="",NOT(ISNUMBER($D78)),NOT(ISNUMBER($H78))),"",IF(AND(ISNUMBER($J78),$J78>0),$J78,IF(ISNUMBER($I78),$I78,""))) -> 615.59025 | L78: =IF(ISNUMBER($K78),$K78*$H78,"") -> 73.87083 | M78: =IF(ISNUMBER($K78),$K78*Parâmetros!$B$4,"") -> 61.559025 | N78: =IF(ISNUMBER($K78),$K78*Parâmetros!$C$4,"") -> 18.467707 | O78: =IF(ISNUMBER($K78),IF(ISNUMBER(Parâmetros!$E$4),Parâmetros!$E$4,0),"") -> 0 | P78: =IF(ISNUMBER($K78),$K78-$D78-IF(ISNUMBER($E78),$E78,0)-$L78-$M78-$N78-$O78,"") -> 112.92268 | Q78: =IF(AND(ISNUMBER($K78),$K78>0),$P78/$K78,"") -> 0.18343807 | S78: =IF(OR(NOT(ISNUMBER($R78)),$R78=0,NOT(ISNUMBER($K78))),"",$K78*(1-$R78)) | T78: =IF(ISNUMBER($S78),$S78*$H78,"") | U78: =IF(ISNUMBER($S78),$S78*Parâmetros!$B$4,"") | V78: =IF(ISNUMBER($S78),$S78*Parâmetros!$C$4,"") | W78: =IF(ISNUMBER($S78),$S78-$D78-IF(ISNUMBER($E78),$E78,0)-$O78-$T78-$U78-$V78,"") | X78: =IF(AND(ISNUMBER($S78),$S78>0),$W78/$S78,"") | Y78: 06/10
A79: =IF(Produtos!$A79="","",Produtos!$A79) -> L3085-B | B79: =IF(Produtos!$A79="","",Produtos!$B79) -> Lixeira c/Aro Basculante 30x85 60L | C79: =IF(Produtos!$A79="","",Produtos!$C79) -> Lixeiras em inox | D79: =IF(Produtos!$A79="","",IF(Produtos!$D79="","",Produtos!$D79)) -> 341.01 | E79: 70.95 | F79: =IF($A79="","",IF($C79="","⚠ categoria",IFERROR(INDEX(Parâmetros!$B$13:$B$22,MATCH($C79,Parâmetros!$A$13:$A$22,0)),"⚠ categoria"))) -> 0.13 | H79: =IF($A79="","",IF(ISNUMBER($G79),$G79,IF(ISNUMBER($F79),$F79,""))) -> 0.13 | I79: =IF(OR($A79="",NOT(ISNUMBER($D79)),NOT(ISNUMBER($H79))),"",IF((1-$H79-Parâmetros!$B$4-Parâmetros!$C$4-Parâmetros!$D$4)<=0,"INVALIDO",($D79+IF(ISNUMBER($E79),$E79,0)+IF(ISNUMBER(Parâmetros!$E$4),Parâmetros!$E$4,0))/(1-$H79-Parâmetros!$B$4-Parâmetros!$C$4-Parâmetros!$D$4))) -> 762.88889 | J79: 729.94044 | K79: =IF(OR($A79="",NOT(ISNUMBER($D79)),NOT(ISNUMBER($H79))),"",IF(AND(ISNUMBER($J79),$J79>0),$J79,IF(ISNUMBER($I79),$I79,""))) -> 729.94044 | L79: =IF(ISNUMBER($K79),$K79*$H79,"") -> 94.892258 | M79: =IF(ISNUMBER($K79),$K79*Parâmetros!$B$4,"") -> 72.994044 | N79: =IF(ISNUMBER($K79),$K79*Parâmetros!$C$4,"") -> 21.898213 | O79: =IF(ISNUMBER($K79),IF(ISNUMBER(Parâmetros!$E$4),Parâmetros!$E$4,0),"") -> 0 | P79: =IF(ISNUMBER($K79),$K79-$D79-IF(ISNUMBER($E79),$E79,0)-$L79-$M79-$N79-$O79,"") -> 128.19593 | Q79: =IF(AND(ISNUMBER($K79),$K79>0),$P79/$K79,"") -> 0.17562519 | S79: =IF(OR(NOT(ISNUMBER($R79)),$R79=0,NOT(ISNUMBER($K79))),"",$K79*(1-$R79)) | T79: =IF(ISNUMBER($S79),$S79*$H79,"") | U79: =IF(ISNUMBER($S79),$S79*Parâmetros!$B$4,"") | V79: =IF(ISNUMBER($S79),$S79*Parâmetros!$C$4,"") | W79: =IF(ISNUMBER($S79),$S79-$D79-IF(ISNUMBER($E79),$E79,0)-$O79-$T79-$U79-$V79,"") | X79: =IF(AND(ISNUMBER($S79),$S79>0),$W79/$S79,"") | Y79: 06/10
A80: =IF(Produtos!$A80="","",Produtos!$A80) -> L4050-B | B80: =IF(Produtos!$A80="","",Produtos!$B80) -> Lixeira c/Aro Basculante 40x50 62L | C80: =IF(Produtos!$A80="","",Produtos!$C80) -> Lixeiras em inox | D80: =IF(Produtos!$A80="","",IF(Produtos!$D80="","",Produtos!$D80)) -> 342.16 | E80: 75.65 | F80: =IF($A80="","",IF($C80="","⚠ categoria",IFERROR(INDEX(Parâmetros!$B$13:$B$22,MATCH($C80,Parâmetros!$A$13:$A$22,0)),"⚠ categoria"))) -> 0.13 | H80: =IF($A80="","",IF(ISNUMBER($G80),$G80,IF(ISNUMBER($F80),$F80,""))) -> 0.13 | I80: =IF(OR($A80="",NOT(ISNUMBER($D80)),NOT(ISNUMBER($H80))),"",IF((1-$H80-Parâmetros!$B$4-Parâmetros!$C$4-Parâmetros!$D$4)<=0,"INVALIDO",($D80+IF(ISNUMBER($E80),$E80,0)+IF(ISNUMBER(Parâmetros!$E$4),Parâmetros!$E$4,0))/(1-$H80-Parâmetros!$B$4-Parâmetros!$C$4-Parâmetros!$D$4))) -> 773.72222 | J80: 739.49085 | K80: =IF(OR($A80="",NOT(ISNUMBER($D80)),NOT(ISNUMBER($H80))),"",IF(AND(ISNUMBER($J80),$J80>0),$J80,IF(ISNUMBER($I80),$I80,""))) -> 739.49085 | L80: =IF(ISNUMBER($K80),$K80*$H80,"") -> 96.13381 | M80: =IF(ISNUMBER($K80),$K80*Parâmetros!$B$4,"") -> 73.949085 | N80: =IF(ISNUMBER($K80),$K80*Parâmetros!$C$4,"") -> 22.184725 | O80: =IF(ISNUMBER($K80),IF(ISNUMBER(Parâmetros!$E$4),Parâmetros!$E$4,0),"") -> 0 | P80: =IF(ISNUMBER($K80),$K80-$D80-IF(ISNUMBER($E80),$E80,0)-$L80-$M80-$N80-$O80,"") -> 129.41323 | Q80: =IF(AND(ISNUMBER($K80),$K80>0),$P80/$K80,"") -> 0.17500315 | S80: =IF(OR(NOT(ISNUMBER($R80)),$R80=0,NOT(ISNUMBER($K80))),"",$K80*(1-$R80)) | T80: =IF(ISNUMBER($S80),$S80*$H80,"") | U80: =IF(ISNUMBER($S80),$S80*Parâmetros!$B$4,"") | V80: =IF(ISNUMBER($S80),$S80*Parâmetros!$C$4,"") | W80: =IF(ISNUMBER($S80),$S80-$D80-IF(ISNUMBER($E80),$E80,0)-$O80-$T80-$U80-$V80,"") | X80: =IF(AND(ISNUMBER($S80),$S80>0),$W80/$S80,"") | Y80: 06/10
A81: =IF(Produtos!$A81="","",Produtos!$A81) -> L4060-B | B81: =IF(Produtos!$A81="","",Produtos!$B81) -> Lixeira c/Aro Basculante 40x60 75L | C81: =IF(Produtos!$A81="","",Produtos!$C81) -> Lixeiras em inox | D81: =IF(Produtos!$A81="","",IF(Produtos!$D81="","",Produtos!$D81)) -> 364.77 | E81: 79.35 | F81: =IF($A81="","",IF($C81="","⚠ categoria",IFERROR(INDEX(Parâmetros!$B$13:$B$22,MATCH($C81,Parâmetros!$A$13:$A$22,0)),"⚠ categoria"))) -> 0.13 | H81: =IF($A81="","",IF(ISNUMBER($G81),$G81,IF(ISNUMBER($F81),$F81,""))) -> 0.13 | I81: =IF(OR($A81="",NOT(ISNUMBER($D81)),NOT(ISNUMBER($H81))),"",IF((1-$H81-Parâmetros!$B$4-Parâmetros!$C$4-Parâmetros!$D$4)<=0,"INVALIDO",($D81+IF(ISNUMBER($E81),$E81,0)+IF(ISNUMBER(Parâmetros!$E$4),Parâmetros!$E$4,0))/(1-$H81-Parâmetros!$B$4-Parâmetros!$C$4-Parâmetros!$D$4))) -> 822.44444 | J81: 786.35151 | K81: =IF(OR($A81="",NOT(ISNUMBER($D81)),NOT(ISNUMBER($H81))),"",IF(AND(ISNUMBER($J81),$J81>0),$J81,IF(ISNUMBER($I81),$I81,""))) -> 786.35151 | L81: =IF(ISNUMBER($K81),$K81*$H81,"") -> 102.2257 | M81: =IF(ISNUMBER($K81),$K81*Parâmetros!$B$4,"") -> 78.635151 | N81: =IF(ISNUMBER($K81),$K81*Parâmetros!$C$4,"") -> 23.590545 | O81: =IF(ISNUMBER($K81),IF(ISNUMBER(Parâmetros!$E$4),Parâmetros!$E$4,0),"") -> 0 | P81: =IF(ISNUMBER($K81),$K81-$D81-IF(ISNUMBER($E81),$E81,0)-$L81-$M81-$N81-$O81,"") -> 137.78012 | Q81: =IF(AND(ISNUMBER($K81),$K81>0),$P81/$K81,"") -> 0.17521441 | S81: =IF(OR(NOT(ISNUMBER($R81)),$R81=0,NOT(ISNUMBER($K81))),"",$K81*(1-$R81)) | T81: =IF(ISNUMBER($S81),$S81*$H81,"") | U81: =IF(ISNUMBER($S81),$S81*Parâmetros!$B$4,"") | V81: =IF(ISNUMBER($S81),$S81*Parâmetros!$C$4,"") | W81: =IF(ISNUMBER($S81),$S81-$D81-IF(ISNUMBER($E81),$E81,0)-$O81-$T81-$U81-$V81,"") | X81: =IF(AND(ISNUMBER($S81),$S81>0),$W81/$S81,"") | Y81: 06/10
A82: =IF(Produtos!$A82="","",Produtos!$A82) -> L4070-B | B82: =IF(Produtos!$A82="","",Produtos!$B82) -> Lixeira c/Aro Basculante 40x70 88L | C82: =IF(Produtos!$A82="","",Produtos!$C82) -> Lixeiras em inox | D82: =IF(Produtos!$A82="","",IF(Produtos!$D82="","",Produtos!$D82)) -> 366.6 | E82: 91.95 | F82: =IF($A82="","",IF($C82="","⚠ categoria",IFERROR(INDEX(Parâmetros!$B$13:$B$22,MATCH($C82,Parâmetros!$A$13:$A$22,0)),"⚠ categoria"))) -> 0.13 | H82: =IF($A82="","",IF(ISNUMBER($G82),$G82,IF(ISNUMBER($F82),$F82,""))) -> 0.13 | I82: =IF(OR($A82="",NOT(ISNUMBER($D82)),NOT(ISNUMBER($H82))),"",IF((1-$H82-Parâmetros!$B$4-Parâmetros!$C$4-Parâmetros!$D$4)<=0,"INVALIDO",($D82+IF(ISNUMBER($E82),$E82,0)+IF(ISNUMBER(Parâmetros!$E$4),Parâmetros!$E$4,0))/(1-$H82-Parâmetros!$B$4-Parâmetros!$C$4-Parâmetros!$D$4))) -> 849.16667 | J82: 809.4114 | K82: =IF(OR($A82="",NOT(ISNUMBER($D82)),NOT(ISNUMBER($H82))),"",IF(AND(ISNUMBER($J82),$J82>0),$J82,IF(ISNUMBER($I82),$I82,""))) -> 809.4114 | L82: =IF(ISNUMBER($K82),$K82*$H82,"") -> 105.22348 | M82: =IF(ISNUMBER($K82),$K82*Parâmetros!$B$4,"") -> 80.94114 | N82: =IF(ISNUMBER($K82),$K82*Parâmetros!$C$4,"") -> 24.282342 | O82: =IF(ISNUMBER($K82),IF(ISNUMBER(Parâmetros!$E$4),Parâmetros!$E$4,0),"") -> 0 | P82: =IF(ISNUMBER($K82),$K82-$D82-IF(ISNUMBER($E82),$E82,0)-$L82-$M82-$N82-$O82,"") -> 140.41444 | Q82: =IF(AND(ISNUMBER($K82),$K82>0),$P82/$K82,"") -> 0.17347722 | S82: =IF(OR(NOT(ISNUMBER($R82)),$R82=0,NOT(ISNUMBER($K82))),"",$K82*(1-$R82)) | T82: =IF(ISNUMBER($S82),$S82*$H82,"") | U82: =IF(ISNUMBER($S82),$S82*Parâmetros!$B$4,"") | V82: =IF(ISNUMBER($S82),$S82*Parâmetros!$C$4,"") | W82: =IF(ISNUMBER($S82),$S82-$D82-IF(ISNUMBER($E82),$E82,0)-$O82-$T82-$U82-$V82,"") | X82: =IF(AND(ISNUMBER($S82),$S82>0),$W82/$S82,"") | Y82: 06/10
A83: =IF(Produtos!$A83="","",Produtos!$A83) -> L4075-B | B83: =IF(Produtos!$A83="","",Produtos!$B83) -> Lixeira c/Aro Basculante 40x75 95L | C83: =IF(Produtos!$A83="","",Produtos!$C83) -> Lixeiras em inox | D83: =IF(Produtos!$A83="","",IF(Produtos!$D83="","",Produtos!$D83)) -> 428.19 | E83: 91.95 | F83: =IF($A83="","",IF($C83="","⚠ categoria",IFERROR(INDEX(Parâmetros!$B$13:$B$22,MATCH($C83,Parâmetros!$A$13:$A$22,0)),"⚠ categoria"))) -> 0.13 | H83: =IF($A83="","",IF(ISNUMBER($G83),$G83,IF(ISNUMBER($F83),$F83,""))) -> 0.13 | I83: =IF(OR($A83="",NOT(ISNUMBER($D83)),NOT(ISNUMBER($H83))),"",IF((1-$H83-Parâmetros!$B$4-Parâmetros!$C$4-Parâmetros!$D$4)<=0,"INVALIDO",($D83+IF(ISNUMBER($E83),$E83,0)+IF(ISNUMBER(Parâmetros!$E$4),Parâmetros!$E$4,0))/(1-$H83-Parâmetros!$B$4-Parâmetros!$C$4-Parâmetros!$D$4))) -> 963.22222 | J83: 921.19167 | K83: =IF(OR($A83="",NOT(ISNUMBER($D83)),NOT(ISNUMBER($H83))),"",IF(AND(ISNUMBER($J83),$J83>0),$J83,IF(ISNUMBER($I83),$I83,""))) -> 921.19167 | L83: =IF(ISNUMBER($K83),$K83*$H83,"") -> 119.75492 | M83: =IF(ISNUMBER($K83),$K83*Parâmetros!$B$4,"") -> 92.119167 | N83: =IF(ISNUMBER($K83),$K83*Parâmetros!$C$4,"") -> 27.63575 | O83: =IF(ISNUMBER($K83),IF(ISNUMBER(Parâmetros!$E$4),Parâmetros!$E$4,0),"") -> 0 | P83: =IF(ISNUMBER($K83),$K83-$D83-IF(ISNUMBER($E83),$E83,0)-$L83-$M83-$N83-$O83,"") -> 161.54184 | Q83: =IF(AND(ISNUMBER($K83),$K83>0),$P83/$K83,"") -> 0.17536181 | S83: =IF(OR(NOT(ISNUMBER($R83)),$R83=0,NOT(ISNUMBER($K83))),"",$K83*(1-$R83)) | T83: =IF(ISNUMBER($S83),$S83*$H83,"") | U83: =IF(ISNUMBER($S83),$S83*Parâmetros!$B$4,"") | V83: =IF(ISNUMBER($S83),$S83*Parâmetros!$C$4,"") | W83: =IF(ISNUMBER($S83),$S83-$D83-IF(ISNUMBER($E83),$E83,0)-$O83-$T83-$U83-$V83,"") | X83: =IF(AND(ISNUMBER($S83),$S83>0),$W83/$S83,"") | Y83: 06/10
A84: =IF(Produtos!$A84="","",Produtos!$A84) -> L4080-B | B84: =IF(Produtos!$A84="","",Produtos!$B84) -> Lixeira c/Aro Basculante 40x80 100L | C84: =IF(Produtos!$A84="","",Produtos!$C84) -> Lixeiras em inox | D84: =IF(Produtos!$A84="","",IF(Produtos!$D84="","",Produtos!$D84)) -> 428.19 | E84: 106.85 | F84: =IF($A84="","",IF($C84="","⚠ categoria",IFERROR(INDEX(Parâmetros!$B$13:$B$22,MATCH($C84,Parâmetros!$A$13:$A$22,0)),"⚠ categoria"))) -> 0.13 | H84: =IF($A84="","",IF(ISNUMBER($G84),$G84,IF(ISNUMBER($F84),$F84,""))) -> 0.13 | I84: =IF(OR($A84="",NOT(ISNUMBER($D84)),NOT(ISNUMBER($H84))),"",IF((1-$H84-Parâmetros!$B$4-Parâmetros!$C$4-Parâmetros!$D$4)<=0,"INVALIDO",($D84+IF(ISNUMBER($E84),$E84,0)+IF(ISNUMBER(Parâmetros!$E$4),Parâmetros!$E$4,0))/(1-$H84-Parâmetros!$B$4-Parâmetros!$C$4-Parâmetros!$D$4))) -> 990.81481 | J84: 944.50624 | K84: =IF(OR($A84="",NOT(ISNUMBER($D84)),NOT(ISNUMBER($H84))),"",IF(AND(ISNUMBER($J84),$J84>0),$J84,IF(ISNUMBER($I84),$I84,""))) -> 944.50624 | L84: =IF(ISNUMBER($K84),$K84*$H84,"") -> 122.78581 | M84: =IF(ISNUMBER($K84),$K84*Parâmetros!$B$4,"") -> 94.450624 | N84: =IF(ISNUMBER($K84),$K84*Parâmetros!$C$4,"") -> 28.335187 | O84: =IF(ISNUMBER($K84),IF(ISNUMBER(Parâmetros!$E$4),Parâmetros!$E$4,0),"") -> 0 | P84: =IF(ISNUMBER($K84),$K84-$D84-IF(ISNUMBER($E84),$E84,0)-$L84-$M84-$N84-$O84,"") -> 163.89462 | Q84: =IF(AND(ISNUMBER($K84),$K84>0),$P84/$K84,"") -> 0.17352412 | S84: =IF(OR(NOT(ISNUMBER($R84)),$R84=0,NOT(ISNUMBER($K84))),"",$K84*(1-$R84)) | T84: =IF(ISNUMBER($S84),$S84*$H84,"") | U84: =IF(ISNUMBER($S84),$S84*Parâmetros!$B$4,"") | V84: =IF(ISNUMBER($S84),$S84*Parâmetros!$C$4,"") | W84: =IF(ISNUMBER($S84),$S84-$D84-IF(ISNUMBER($E84),$E84,0)-$O84-$T84-$U84-$V84,"") | X84: =IF(AND(ISNUMBER($S84),$S84>0),$W84/$S84,"") | Y84: 06/10
A85: =IF(Produtos!$A85="","",Produtos!$A85) -> L4090-B | B85: =IF(Produtos!$A85="","",Produtos!$B85) -> Lixeira c/Aro Basculante 40x90 120L | C85: =IF(Produtos!$A85="","",Produtos!$C85) -> Lixeiras em inox | D85: =IF(Produtos!$A85="","",IF(Produtos!$D85="","",Produtos!$D85)) -> 468.32 | E85: 106.85 | F85: =IF($A85="","",IF($C85="","⚠ categoria",IFERROR(INDEX(Parâmetros!$B$13:$B$22,MATCH($C85,Parâmetros!$A$13:$A$22,0)),"⚠ categoria"))) -> 0.13 | H85: =IF($A85="","",IF(ISNUMBER($G85),$G85,IF(ISNUMBER($F85),$F85,""))) -> 0.13 | I85: =IF(OR($A85="",NOT(ISNUMBER($D85)),NOT(ISNUMBER($H85))),"",IF((1-$H85-Parâmetros!$B$4-Parâmetros!$C$4-Parâmetros!$D$4)<=0,"INVALIDO",($D85+IF(ISNUMBER($E85),$E85,0)+IF(ISNUMBER(Parâmetros!$E$4),Parâmetros!$E$4,0))/(1-$H85-Parâmetros!$B$4-Parâmetros!$C$4-Parâmetros!$D$4))) -> 1065.1296 | J85: 1017.425 | K85: =IF(OR($A85="",NOT(ISNUMBER($D85)),NOT(ISNUMBER($H85))),"",IF(AND(ISNUMBER($J85),$J85>0),$J85,IF(ISNUMBER($I85),$I85,""))) -> 1017.425 | L85: =IF(ISNUMBER($K85),$K85*$H85,"") -> 132.26525 | M85: =IF(ISNUMBER($K85),$K85*Parâmetros!$B$4,"") -> 101.7425 | N85: =IF(ISNUMBER($K85),$K85*Parâmetros!$C$4,"") -> 30.522751 | O85: =IF(ISNUMBER($K85),IF(ISNUMBER(Parâmetros!$E$4),Parâmetros!$E$4,0),"") -> 0 | P85: =IF(ISNUMBER($K85),$K85-$D85-IF(ISNUMBER($E85),$E85,0)-$L85-$M85-$N85-$O85,"") -> 177.72453 | Q85: =IF(AND(ISNUMBER($K85),$K85>0),$P85/$K85,"") -> 0.17468071 | S85: =IF(OR(NOT(ISNUMBER($R85)),$R85=0,NOT(ISNUMBER($K85))),"",$K85*(1-$R85)) | T85: =IF(ISNUMBER($S85),$S85*$H85,"") | U85: =IF(ISNUMBER($S85),$S85*Parâmetros!$B$4,"") | V85: =IF(ISNUMBER($S85),$S85*Parâmetros!$C$4,"") | W85: =IF(ISNUMBER($S85),$S85-$D85-IF(ISNUMBER($E85),$E85,0)-$O85-$T85-$U85-$V85,"") | X85: =IF(AND(ISNUMBER($S85),$S85>0),$W85/$S85,"") | Y85: 06/10
A86: =IF(Produtos!$A86="","",Produtos!$A86) -> P1618 | B86: =IF(Produtos!$A86="","",Produtos!$B86) -> Lixeira c/Tampa Pedal 16x18 03L | C86: =IF(Produtos!$A86="","",Produtos!$C86) -> Lixeiras com pedal | D86: =IF(Produtos!$A86="","",IF(Produtos!$D86="","",Produtos!$D86)) -> 78.15 | F86: =IF($A86="","",IF($C86="","⚠ categoria",IFERROR(INDEX(Parâmetros!$B$13:$B$22,MATCH($C86,Parâmetros!$A$13:$A$22,0)),"⚠ categoria"))) -> 0.13 | H86: =IF($A86="","",IF(ISNUMBER($G86),$G86,IF(ISNUMBER($F86),$F86,""))) -> 0.13 | I86: =IF(OR($A86="",NOT(ISNUMBER($D86)),NOT(ISNUMBER($H86))),"",IF((1-$H86-Parâmetros!$B$4-Parâmetros!$C$4-Parâmetros!$D$4)<=0,"INVALIDO",($D86+IF(ISNUMBER($E86),$E86,0)+IF(ISNUMBER(Parâmetros!$E$4),Parâmetros!$E$4,0))/(1-$H86-Parâmetros!$B$4-Parâmetros!$C$4-Parâmetros!$D$4))) -> 144.72222 | K86: =IF(OR($A86="",NOT(ISNUMBER($D86)),NOT(ISNUMBER($H86))),"",IF(AND(ISNUMBER($J86),$J86>0),$J86,IF(ISNUMBER($I86),$I86,""))) -> 144.72222 | L86: =IF(ISNUMBER($K86),$K86*$H86,"") -> 18.813889 | M86: =IF(ISNUMBER($K86),$K86*Parâmetros!$B$4,"") -> 14.472222 | N86: =IF(ISNUMBER($K86),$K86*Parâmetros!$C$4,"") -> 4.3416667 | O86: =IF(ISNUMBER($K86),IF(ISNUMBER(Parâmetros!$E$4),Parâmetros!$E$4,0),"") -> 0 | P86: =IF(ISNUMBER($K86),$K86-$D86-IF(ISNUMBER($E86),$E86,0)-$L86-$M86-$N86-$O86,"") -> 28.944444 | Q86: =IF(AND(ISNUMBER($K86),$K86>0),$P86/$K86,"") -> 0.2 | S86: =IF(OR(NOT(ISNUMBER($R86)),$R86=0,NOT(ISNUMBER($K86))),"",$K86*(1-$R86)) | T86: =IF(ISNUMBER($S86),$S86*$H86,"") | U86: =IF(ISNUMBER($S86),$S86*Parâmetros!$B$4,"") | V86: =IF(ISNUMBER($S86),$S86*Parâmetros!$C$4,"") | W86: =IF(ISNUMBER($S86),$S86-$D86-IF(ISNUMBER($E86),$E86,0)-$O86-$T86-$U86-$V86,"") | X86: =IF(AND(ISNUMBER($S86),$S86>0),$W86/$S86,"")
A87: =IF(Produtos!$A87="","",Produtos!$A87) -> P1623 | B87: =IF(Produtos!$A87="","",Produtos!$B87) -> Lixeira c/Tampa Pedal 16x23 05L | C87: =IF(Produtos!$A87="","",Produtos!$C87) -> Lixeiras com pedal | D87: =IF(Produtos!$A87="","",IF(Produtos!$D87="","",Produtos!$D87)) -> 81.62 | E87: 21.75 | F87: =IF($A87="","",IF($C87="","⚠ categoria",IFERROR(INDEX(Parâmetros!$B$13:$B$22,MATCH($C87,Parâmetros!$A$13:$A$22,0)),"⚠ categoria"))) -> 0.13 | G87: 0.12 | H87: =IF($A87="","",IF(ISNUMBER($G87),$G87,IF(ISNUMBER($F87),$F87,""))) -> 0.12 | I87: =IF(OR($A87="",NOT(ISNUMBER($D87)),NOT(ISNUMBER($H87))),"",IF((1-$H87-Parâmetros!$B$4-Parâmetros!$C$4-Parâmetros!$D$4)<=0,"INVALIDO",($D87+IF(ISNUMBER($E87),$E87,0)+IF(ISNUMBER(Parâmetros!$E$4),Parâmetros!$E$4,0))/(1-$H87-Parâmetros!$B$4-Parâmetros!$C$4-Parâmetros!$D$4))) -> 187.94545 | J87: 188.61453 | K87: =IF(OR($A87="",NOT(ISNUMBER($D87)),NOT(ISNUMBER($H87))),"",IF(AND(ISNUMBER($J87),$J87>0),$J87,IF(ISNUMBER($I87),$I87,""))) -> 188.61453 | L87: =IF(ISNUMBER($K87),$K87*$H87,"") -> 22.633744 | M87: =IF(ISNUMBER($K87),$K87*Parâmetros!$B$4,"") -> 18.861453 | N87: =IF(ISNUMBER($K87),$K87*Parâmetros!$C$4,"") -> 5.658436 | O87: =IF(ISNUMBER($K87),IF(ISNUMBER(Parâmetros!$E$4),Parâmetros!$E$4,0),"") -> 0 | P87: =IF(ISNUMBER($K87),$K87-$D87-IF(ISNUMBER($E87),$E87,0)-$L87-$M87-$N87-$O87,"") -> 38.090899 | Q87: =IF(AND(ISNUMBER($K87),$K87>0),$P87/$K87,"") -> 0.20195103 | S87: =IF(OR(NOT(ISNUMBER($R87)),$R87=0,NOT(ISNUMBER($K87))),"",$K87*(1-$R87)) | T87: =IF(ISNUMBER($S87),$S87*$H87,"") | U87: =IF(ISNUMBER($S87),$S87*Parâmetros!$B$4,"") | V87: =IF(ISNUMBER($S87),$S87*Parâmetros!$C$4,"") | W87: =IF(ISNUMBER($S87),$S87-$D87-IF(ISNUMBER($E87),$E87,0)-$O87-$T87-$U87-$V87,"") | X87: =IF(AND(ISNUMBER($S87),$S87>0),$W87/$S87,"") | Y87: 06/10
A88: =IF(Produtos!$A88="","",Produtos!$A88) -> P2025 | B88: =IF(Produtos!$A88="","",Produtos!$B88) -> Lixeira c/Tampa Pedal 20x25 07L | C88: =IF(Produtos!$A88="","",Produtos!$C88) -> Lixeiras com pedal | D88: =IF(Produtos!$A88="","",IF(Produtos!$D88="","",Produtos!$D88)) -> 99.57 | E88: 25.55 | F88: =IF($A88="","",IF($C88="","⚠ categoria",IFERROR(INDEX(Parâmetros!$B$13:$B$22,MATCH($C88,Parâmetros!$A$13:$A$22,0)),"⚠ categoria"))) -> 0.13 | G88: 0.12 | H88: =IF($A88="","",IF(ISNUMBER($G88),$G88,IF(ISNUMBER($F88),$F88,""))) -> 0.12 | I88: =IF(OR($A88="",NOT(ISNUMBER($D88)),NOT(ISNUMBER($H88))),"",IF((1-$H88-Parâmetros!$B$4-Parâmetros!$C$4-Parâmetros!$D$4)<=0,"INVALIDO",($D88+IF(ISNUMBER($E88),$E88,0)+IF(ISNUMBER(Parâmetros!$E$4),Parâmetros!$E$4,0))/(1-$H88-Parâmetros!$B$4-Parâmetros!$C$4-Parâmetros!$D$4))) -> 227.49091 | J88: 230.97874 | K88: =IF(OR($A88="",NOT(ISNUMBER($D88)),NOT(ISNUMBER($H88))),"",IF(AND(ISNUMBER($J88),$J88>0),$J88,IF(ISNUMBER($I88),$I88,""))) -> 230.97874 | L88: =IF(ISNUMBER($K88),$K88*$H88,"") -> 27.717448 | M88: =IF(ISNUMBER($K88),$K88*Parâmetros!$B$4,"") -> 23.097874 | N88: =IF(ISNUMBER($K88),$K88*Parâmetros!$C$4,"") -> 6.9293621 | O88: =IF(ISNUMBER($K88),IF(ISNUMBER(Parâmetros!$E$4),Parâmetros!$E$4,0),"") -> 0 | P88: =IF(ISNUMBER($K88),$K88-$D88-IF(ISNUMBER($E88),$E88,0)-$L88-$M88-$N88-$O88,"") -> 48.114053 | Q88: =IF(AND(ISNUMBER($K88),$K88>0),$P88/$K88,"") -> 0.20830512 | S88: =IF(OR(NOT(ISNUMBER($R88)),$R88=0,NOT(ISNUMBER($K88))),"",$K88*(1-$R88)) | T88: =IF(ISNUMBER($S88),$S88*$H88,"") | U88: =IF(ISNUMBER($S88),$S88*Parâmetros!$B$4,"") | V88: =IF(ISNUMBER($S88),$S88*Parâmetros!$C$4,"") | W88: =IF(ISNUMBER($S88),$S88-$D88-IF(ISNUMBER($E88),$E88,0)-$O88-$T88-$U88-$V88,"") | X88: =IF(AND(ISNUMBER($S88),$S88>0),$W88/$S88,"") | Y88: 06/10
A89: =IF(Produtos!$A89="","",Produtos!$A89) -> P2030 | B89: =IF(Produtos!$A89="","",Produtos!$B89) -> Lixeira c/Tampa Pedal 20x30 10L | C89: =IF(Produtos!$A89="","",Produtos!$C89) -> Lixeiras com pedal | D89: =IF(Produtos!$A89="","",IF(Produtos!$D89="","",Produtos!$D89)) -> 111.27 | E89: 27.05 | F89: =IF($A89="","",IF($C89="","⚠ categoria",IFERROR(INDEX(Parâmetros!$B$13:$B$22,MATCH($C89,Parâmetros!$A$13:$A$22,0)),"⚠ categoria"))) -> 0.13 | G89: 0.12 | H89: =IF($A89="","",IF(ISNUMBER($G89),$G89,IF(ISNUMBER($F89),$F89,""))) -> 0.12 | I89: =IF(OR($A89="",NOT(ISNUMBER($D89)),NOT(ISNUMBER($H89))),"",IF((1-$H89-Parâmetros!$B$4-Parâmetros!$C$4-Parâmetros!$D$4)<=0,"INVALIDO",($D89+IF(ISNUMBER($E89),$E89,0)+IF(ISNUMBER(Parâmetros!$E$4),Parâmetros!$E$4,0))/(1-$H89-Parâmetros!$B$4-Parâmetros!$C$4-Parâmetros!$D$4))) -> 251.49091 | J89: 251.56 | K89: =IF(OR($A89="",NOT(ISNUMBER($D89)),NOT(ISNUMBER($H89))),"",IF(AND(ISNUMBER($J89),$J89>0),$J89,IF(ISNUMBER($I89),$I89,""))) -> 251.56 | L89: =IF(ISNUMBER($K89),$K89*$H89,"") -> 30.1872 | M89: =IF(ISNUMBER($K89),$K89*Parâmetros!$B$4,"") -> 25.156 | N89: =IF(ISNUMBER($K89),$K89*Parâmetros!$C$4,"") -> 7.5468 | O89: =IF(ISNUMBER($K89),IF(ISNUMBER(Parâmetros!$E$4),Parâmetros!$E$4,0),"") -> 0 | P89: =IF(ISNUMBER($K89),$K89-$D89-IF(ISNUMBER($E89),$E89,0)-$L89-$M89-$N89-$O89,"") -> 50.35 | Q89: =IF(AND(ISNUMBER($K89),$K89>0),$P89/$K89,"") -> 0.20015106 | S89: =IF(OR(NOT(ISNUMBER($R89)),$R89=0,NOT(ISNUMBER($K89))),"",$K89*(1-$R89)) | T89: =IF(ISNUMBER($S89),$S89*$H89,"") | U89: =IF(ISNUMBER($S89),$S89*Parâmetros!$B$4,"") | V89: =IF(ISNUMBER($S89),$S89*Parâmetros!$C$4,"") | W89: =IF(ISNUMBER($S89),$S89-$D89-IF(ISNUMBER($E89),$E89,0)-$O89-$T89-$U89-$V89,"") | X89: =IF(AND(ISNUMBER($S89),$S89>0),$W89/$S89,"") | Y89: 24/09
A90: =IF(Produtos!$A90="","",Produtos!$A90) -> P2425 | B90: =IF(Produtos!$A90="","",Produtos!$B90) -> Lixeira c/Tampa Pedal 24x25 12L | C90: =IF(Produtos!$A90="","",Produtos!$C90) -> Lixeiras com pedal | D90: =IF(Produtos!$A90="","",IF(Produtos!$D90="","",Produtos!$D90)) -> 121.08 | E90: 29.25 | F90: =IF($A90="","",IF($C90="","⚠ categoria",IFERROR(INDEX(Parâmetros!$B$13:$B$22,MATCH($C90,Parâmetros!$A$13:$A$22,0)),"⚠ categoria"))) -> 0.13 | G90: 0.12 | H90: =IF($A90="","",IF(ISNUMBER($G90),$G90,IF(ISNUMBER($F90),$F90,""))) -> 0.12 | I90: =IF(OR($A90="",NOT(ISNUMBER($D90)),NOT(ISNUMBER($H90))),"",IF((1-$H90-Parâmetros!$B$4-Parâmetros!$C$4-Parâmetros!$D$4)<=0,"INVALIDO",($D90+IF(ISNUMBER($E90),$E90,0)+IF(ISNUMBER(Parâmetros!$E$4),Parâmetros!$E$4,0))/(1-$H90-Parâmetros!$B$4-Parâmetros!$C$4-Parâmetros!$D$4))) -> 273.32727 | J90: 274.10245 | K90: =IF(OR($A90="",NOT(ISNUMBER($D90)),NOT(ISNUMBER($H90))),"",IF(AND(ISNUMBER($J90),$J90>0),$J90,IF(ISNUMBER($I90),$I90,""))) -> 274.10245 | L90: =IF(ISNUMBER($K90),$K90*$H90,"") -> 32.892294 | M90: =IF(ISNUMBER($K90),$K90*Parâmetros!$B$4,"") -> 27.410245 | N90: =IF(ISNUMBER($K90),$K90*Parâmetros!$C$4,"") -> 8.2230734 | O90: =IF(ISNUMBER($K90),IF(ISNUMBER(Parâmetros!$E$4),Parâmetros!$E$4,0),"") -> 0 | P90: =IF(ISNUMBER($K90),$K90-$D90-IF(ISNUMBER($E90),$E90,0)-$L90-$M90-$N90-$O90,"") -> 55.246836 | Q90: =IF(AND(ISNUMBER($K90),$K90>0),$P90/$K90,"") -> 0.20155543 | S90: =IF(OR(NOT(ISNUMBER($R90)),$R90=0,NOT(ISNUMBER($K90))),"",$K90*(1-$R90)) | T90: =IF(ISNUMBER($S90),$S90*$H90,"") | U90: =IF(ISNUMBER($S90),$S90*Parâmetros!$B$4,"") | V90: =IF(ISNUMBER($S90),$S90*Parâmetros!$C$4,"") | W90: =IF(ISNUMBER($S90),$S90-$D90-IF(ISNUMBER($E90),$E90,0)-$O90-$T90-$U90-$V90,"") | X90: =IF(AND(ISNUMBER($S90),$S90>0),$W90/$S90,"") | Y90: 06/10
A91: =IF(Produtos!$A91="","",Produtos!$A91) -> P2430 | B91: =IF(Produtos!$A91="","",Produtos!$B91) -> Lixeira c/Tampa Pedal 24x30 15L | C91: =IF(Produtos!$A91="","",Produtos!$C91) -> Lixeiras com pedal | D91: =IF(Produtos!$A91="","",IF(Produtos!$D91="","",Produtos!$D91)) -> 124.7 | E91: 27.05 | F91: =IF($A91="","",IF($C91="","⚠ categoria",IFERROR(INDEX(Parâmetros!$B$13:$B$22,MATCH($C91,Parâmetros!$A$13:$A$22,0)),"⚠ categoria"))) -> 0.13 | G91: 0.12 | H91: =IF($A91="","",IF(ISNUMBER($G91),$G91,IF(ISNUMBER($F91),$F91,""))) -> 0.12 | I91: =IF(OR($A91="",NOT(ISNUMBER($D91)),NOT(ISNUMBER($H91))),"",IF((1-$H91-Parâmetros!$B$4-Parâmetros!$C$4-Parâmetros!$D$4)<=0,"INVALIDO",($D91+IF(ISNUMBER($E91),$E91,0)+IF(ISNUMBER(Parâmetros!$E$4),Parâmetros!$E$4,0))/(1-$H91-Parâmetros!$B$4-Parâmetros!$C$4-Parâmetros!$D$4))) -> 275.90909 | J91: 277.69108 | K91: =IF(OR($A91="",NOT(ISNUMBER($D91)),NOT(ISNUMBER($H91))),"",IF(AND(ISNUMBER($J91),$J91>0),$J91,IF(ISNUMBER($I91),$I91,""))) -> 277.69108 | L91: =IF(ISNUMBER($K91),$K91*$H91,"") -> 33.32293 | M91: =IF(ISNUMBER($K91),$K91*Parâmetros!$B$4,"") -> 27.769109 | N91: =IF(ISNUMBER($K91),$K91*Parâmetros!$C$4,"") -> 8.3307326 | O91: =IF(ISNUMBER($K91),IF(ISNUMBER(Parâmetros!$E$4),Parâmetros!$E$4,0),"") -> 0 | P91: =IF(ISNUMBER($K91),$K91-$D91-IF(ISNUMBER($E91),$E91,0)-$L91-$M91-$N91-$O91,"") -> 56.518314 | Q91: =IF(AND(ISNUMBER($K91),$K91>0),$P91/$K91,"") -> 0.20352945 | S91: =IF(OR(NOT(ISNUMBER($R91)),$R91=0,NOT(ISNUMBER($K91))),"",$K91*(1-$R91)) | T91: =IF(ISNUMBER($S91),$S91*$H91,"") | U91: =IF(ISNUMBER($S91),$S91*Parâmetros!$B$4,"") | V91: =IF(ISNUMBER($S91),$S91*Parâmetros!$C$4,"") | W91: =IF(ISNUMBER($S91),$S91-$D91-IF(ISNUMBER($E91),$E91,0)-$O91-$T91-$U91-$V91,"") | X91: =IF(AND(ISNUMBER($S91),$S91>0),$W91/$S91,"") | Y91: 06/10
A92: =IF(Produtos!$A92="","",Produtos!$A92) -> P2440 | B92: =IF(Produtos!$A92="","",Produtos!$B92) -> Lixeira c/Tampa Pedal 24x40 20L | C92: =IF(Produtos!$A92="","",Produtos!$C92) -> Lixeiras com pedal | D92: =IF(Produtos!$A92="","",IF(Produtos!$D92="","",Produtos!$D92)) -> 140.24 | E92: 29.25 | F92: =IF($A92="","",IF($C92="","⚠ categoria",IFERROR(INDEX(Parâmetros!$B$13:$B$22,MATCH($C92,Parâmetros!$A$13:$A$22,0)),"⚠ categoria"))) -> 0.13 | G92: 0.12 | H92: =IF($A92="","",IF(ISNUMBER($G92),$G92,IF(ISNUMBER($F92),$F92,""))) -> 0.12 | I92: =IF(OR($A92="",NOT(ISNUMBER($D92)),NOT(ISNUMBER($H92))),"",IF((1-$H92-Parâmetros!$B$4-Parâmetros!$C$4-Parâmetros!$D$4)<=0,"INVALIDO",($D92+IF(ISNUMBER($E92),$E92,0)+IF(ISNUMBER(Parâmetros!$E$4),Parâmetros!$E$4,0))/(1-$H92-Parâmetros!$B$4-Parâmetros!$C$4-Parâmetros!$D$4))) -> 308.16364 | J92: 310.41599 | K92: =IF(OR($A92="",NOT(ISNUMBER($D92)),NOT(ISNUMBER($H92))),"",IF(AND(ISNUMBER($J92),$J92>0),$J92,IF(ISNUMBER($I92),$I92,""))) -> 310.41599 | L92: =IF(ISNUMBER($K92),$K92*$H92,"") -> 37.249918 | M92: =IF(ISNUMBER($K92),$K92*Parâmetros!$B$4,"") -> 31.041599 | N92: =IF(ISNUMBER($K92),$K92*Parâmetros!$C$4,"") -> 9.3124796 | O92: =IF(ISNUMBER($K92),IF(ISNUMBER(Parâmetros!$E$4),Parâmetros!$E$4,0),"") -> 0 | P92: =IF(ISNUMBER($K92),$K92-$D92-IF(ISNUMBER($E92),$E92,0)-$L92-$M92-$N92-$O92,"") -> 63.32199 | Q92: =IF(AND(ISNUMBER($K92),$K92>0),$P92/$K92,"") -> 0.20399075 | S92: =IF(OR(NOT(ISNUMBER($R92)),$R92=0,NOT(ISNUMBER($K92))),"",$K92*(1-$R92)) | T92: =IF(ISNUMBER($S92),$S92*$H92,"") | U92: =IF(ISNUMBER($S92),$S92*Parâmetros!$B$4,"") | V92: =IF(ISNUMBER($S92),$S92*Parâmetros!$C$4,"") | W92: =IF(ISNUMBER($S92),$S92-$D92-IF(ISNUMBER($E92),$E92,0)-$O92-$T92-$U92-$V92,"") | X92: =IF(AND(ISNUMBER($S92),$S92>0),$W92/$S92,"") | Y92: 06/10
A93: =IF(Produtos!$A93="","",Produtos!$A93) -> P3040 | B93: =IF(Produtos!$A93="","",Produtos!$B93) -> Lixeira c/Tampa Pedal 30x40 30L | C93: =IF(Produtos!$A93="","",Produtos!$C93) -> Lixeiras com pedal | D93: =IF(Produtos!$A93="","",IF(Produtos!$D93="","",Produtos!$D93)) -> 194.88 | E93: 49.35 | F93: =IF($A93="","",IF($C93="","⚠ categoria",IFERROR(INDEX(Parâmetros!$B$13:$B$22,MATCH($C93,Parâmetros!$A$13:$A$22,0)),"⚠ categoria"))) -> 0.13 | G93: 0.12 | H93: =IF($A93="","",IF(ISNUMBER($G93),$G93,IF(ISNUMBER($F93),$F93,""))) -> 0.12 | I93: =IF(OR($A93="",NOT(ISNUMBER($D93)),NOT(ISNUMBER($H93))),"",IF((1-$H93-Parâmetros!$B$4-Parâmetros!$C$4-Parâmetros!$D$4)<=0,"INVALIDO",($D93+IF(ISNUMBER($E93),$E93,0)+IF(ISNUMBER(Parâmetros!$E$4),Parâmetros!$E$4,0))/(1-$H93-Parâmetros!$B$4-Parâmetros!$C$4-Parâmetros!$D$4))) -> 444.05455 | J93: 445.0142 | K93: =IF(OR($A93="",NOT(ISNUMBER($D93)),NOT(ISNUMBER($H93))),"",IF(AND(ISNUMBER($J93),$J93>0),$J93,IF(ISNUMBER($I93),$I93,""))) -> 445.0142 | L93: =IF(ISNUMBER($K93),$K93*$H93,"") -> 53.401704 | M93: =IF(ISNUMBER($K93),$K93*Parâmetros!$B$4,"") -> 44.50142 | N93: =IF(ISNUMBER($K93),$K93*Parâmetros!$C$4,"") -> 13.350426 | O93: =IF(ISNUMBER($K93),IF(ISNUMBER(Parâmetros!$E$4),Parâmetros!$E$4,0),"") -> 0 | P93: =IF(ISNUMBER($K93),$K93-$D93-IF(ISNUMBER($E93),$E93,0)-$L93-$M93-$N93-$O93,"") -> 89.530652 | Q93: =IF(AND(ISNUMBER($K93),$K93>0),$P93/$K93,"") -> 0.20118606 | S93: =IF(OR(NOT(ISNUMBER($R93)),$R93=0,NOT(ISNUMBER($K93))),"",$K93*(1-$R93)) | T93: =IF(ISNUMBER($S93),$S93*$H93,"") | U93: =IF(ISNUMBER($S93),$S93*Parâmetros!$B$4,"") | V93: =IF(ISNUMBER($S93),$S93*Parâmetros!$C$4,"") | W93: =IF(ISNUMBER($S93),$S93-$D93-IF(ISNUMBER($E93),$E93,0)-$O93-$T93-$U93-$V93,"") | X93: =IF(AND(ISNUMBER($S93),$S93>0),$W93/$S93,"") | Y93: 06/10
A94: =IF(Produtos!$A94="","",Produtos!$A94) -> P3050 | B94: =IF(Produtos!$A94="","",Produtos!$B94) -> Lixeira c/Tampa Pedal 30x50 40L | C94: =IF(Produtos!$A94="","",Produtos!$C94) -> Lixeiras com pedal | D94: =IF(Produtos!$A94="","",IF(Produtos!$D94="","",Produtos!$D94)) -> 240.55 | E94: 69.35 | F94: =IF($A94="","",IF($C94="","⚠ categoria",IFERROR(INDEX(Parâmetros!$B$13:$B$22,MATCH($C94,Parâmetros!$A$13:$A$22,0)),"⚠ categoria"))) -> 0.13 | G94: 0.12 | H94: =IF($A94="","",IF(ISNUMBER($G94),$G94,IF(ISNUMBER($F94),$F94,""))) -> 0.12 | I94: =IF(OR($A94="",NOT(ISNUMBER($D94)),NOT(ISNUMBER($H94))),"",IF((1-$H94-Parâmetros!$B$4-Parâmetros!$C$4-Parâmetros!$D$4)<=0,"INVALIDO",($D94+IF(ISNUMBER($E94),$E94,0)+IF(ISNUMBER(Parâmetros!$E$4),Parâmetros!$E$4,0))/(1-$H94-Parâmetros!$B$4-Parâmetros!$C$4-Parâmetros!$D$4))) -> 563.45455 | J94: 564.05278 | K94: =IF(OR($A94="",NOT(ISNUMBER($D94)),NOT(ISNUMBER($H94))),"",IF(AND(ISNUMBER($J94),$J94>0),$J94,IF(ISNUMBER($I94),$I94,""))) -> 564.05278 | L94: =IF(ISNUMBER($K94),$K94*$H94,"") -> 67.686334 | M94: =IF(ISNUMBER($K94),$K94*Parâmetros!$B$4,"") -> 56.405278 | N94: =IF(ISNUMBER($K94),$K94*Parâmetros!$C$4,"") -> 16.921583 | O94: =IF(ISNUMBER($K94),IF(ISNUMBER(Parâmetros!$E$4),Parâmetros!$E$4,0),"") -> 0 | P94: =IF(ISNUMBER($K94),$K94-$D94-IF(ISNUMBER($E94),$E94,0)-$L94-$M94-$N94-$O94,"") -> 113.13959 | Q94: =IF(AND(ISNUMBER($K94),$K94>0),$P94/$K94,"") -> 0.20058333 | S94: =IF(OR(NOT(ISNUMBER($R94)),$R94=0,NOT(ISNUMBER($K94))),"",$K94*(1-$R94)) | T94: =IF(ISNUMBER($S94),$S94*$H94,"") | U94: =IF(ISNUMBER($S94),$S94*Parâmetros!$B$4,"") | V94: =IF(ISNUMBER($S94),$S94*Parâmetros!$C$4,"") | W94: =IF(ISNUMBER($S94),$S94-$D94-IF(ISNUMBER($E94),$E94,0)-$O94-$T94-$U94-$V94,"") | X94: =IF(AND(ISNUMBER($S94),$S94>0),$W94/$S94,"") | Y94: 06/10
A95: =IF(Produtos!$A95="","",Produtos!$A95) -> P3060 | B95: =IF(Produtos!$A95="","",Produtos!$B95) -> Lixeira c/Tampa Pedal 30x60 50L | C95: =IF(Produtos!$A95="","",Produtos!$C95) -> Lixeiras com pedal | D95: =IF(Produtos!$A95="","",IF(Produtos!$D95="","",Produtos!$D95)) -> 242.26 | E95: 70.95 | F95: =IF($A95="","",IF($C95="","⚠ categoria",IFERROR(INDEX(Parâmetros!$B$13:$B$22,MATCH($C95,Parâmetros!$A$13:$A$22,0)),"⚠ categoria"))) -> 0.13 | G95: 0.12 | H95: =IF($A95="","",IF(ISNUMBER($G95),$G95,IF(ISNUMBER($F95),$F95,""))) -> 0.12 | I95: =IF(OR($A95="",NOT(ISNUMBER($D95)),NOT(ISNUMBER($H95))),"",IF((1-$H95-Parâmetros!$B$4-Parâmetros!$C$4-Parâmetros!$D$4)<=0,"INVALIDO",($D95+IF(ISNUMBER($E95),$E95,0)+IF(ISNUMBER(Parâmetros!$E$4),Parâmetros!$E$4,0))/(1-$H95-Parâmetros!$B$4-Parâmetros!$C$4-Parâmetros!$D$4))) -> 569.47273 | J95: 574.50802 | K95: =IF(OR($A95="",NOT(ISNUMBER($D95)),NOT(ISNUMBER($H95))),"",IF(AND(ISNUMBER($J95),$J95>0),$J95,IF(ISNUMBER($I95),$I95,""))) -> 574.50802 | L95: =IF(ISNUMBER($K95),$K95*$H95,"") -> 68.940962 | M95: =IF(ISNUMBER($K95),$K95*Parâmetros!$B$4,"") -> 57.450801 | N95: =IF(ISNUMBER($K95),$K95*Parâmetros!$C$4,"") -> 17.23524 | O95: =IF(ISNUMBER($K95),IF(ISNUMBER(Parâmetros!$E$4),Parâmetros!$E$4,0),"") -> 0 | P95: =IF(ISNUMBER($K95),$K95-$D95-IF(ISNUMBER($E95),$E95,0)-$L95-$M95-$N95-$O95,"") -> 117.67101 | Q95: =IF(AND(ISNUMBER($K95),$K95>0),$P95/$K95,"") -> 0.20482049 | S95: =IF(OR(NOT(ISNUMBER($R95)),$R95=0,NOT(ISNUMBER($K95))),"",$K95*(1-$R95)) | T95: =IF(ISNUMBER($S95),$S95*$H95,"") | U95: =IF(ISNUMBER($S95),$S95*Parâmetros!$B$4,"") | V95: =IF(ISNUMBER($S95),$S95*Parâmetros!$C$4,"") | W95: =IF(ISNUMBER($S95),$S95-$D95-IF(ISNUMBER($E95),$E95,0)-$O95-$T95-$U95-$V95,"") | X95: =IF(AND(ISNUMBER($S95),$S95>0),$W95/$S95,"") | Y95: 06/10
A96: =IF(Produtos!$A96="","",Produtos!$A96) -> P3070 | B96: =IF(Produtos!$A96="","",Produtos!$B96) -> Lixeira c/Tampa Pedal 30x70 60L | C96: =IF(Produtos!$A96="","",Produtos!$C96) -> Lixeiras com pedal | D96: =IF(Produtos!$A96="","",IF(Produtos!$D96="","",Produtos!$D96)) -> 307.26 | E96: 70.95 | F96: =IF($A96="","",IF($C96="","⚠ categoria",IFERROR(INDEX(Parâmetros!$B$13:$B$22,MATCH($C96,Parâmetros!$A$13:$A$22,0)),"⚠ categoria"))) -> 0.13 | G96: 0.12 | H96: =IF($A96="","",IF(ISNUMBER($G96),$G96,IF(ISNUMBER($F96),$F96,""))) -> 0.12 | I96: =IF(OR($A96="",NOT(ISNUMBER($D96)),NOT(ISNUMBER($H96))),"",IF((1-$H96-Parâmetros!$B$4-Parâmetros!$C$4-Parâmetros!$D$4)<=0,"INVALIDO",($D96+IF(ISNUMBER($E96),$E96,0)+IF(ISNUMBER(Parâmetros!$E$4),Parâmetros!$E$4,0))/(1-$H96-Parâmetros!$B$4-Parâmetros!$C$4-Parâmetros!$D$4))) -> 687.65455 | J96: 690.9 | K96: =IF(OR($A96="",NOT(ISNUMBER($D96)),NOT(ISNUMBER($H96))),"",IF(AND(ISNUMBER($J96),$J96>0),$J96,IF(ISNUMBER($I96),$I96,""))) -> 690.9 | L96: =IF(ISNUMBER($K96),$K96*$H96,"") -> 82.908 | M96: =IF(ISNUMBER($K96),$K96*Parâmetros!$B$4,"") -> 69.09 | N96: =IF(ISNUMBER($K96),$K96*Parâmetros!$C$4,"") -> 20.727 | O96: =IF(ISNUMBER($K96),IF(ISNUMBER(Parâmetros!$E$4),Parâmetros!$E$4,0),"") -> 0 | P96: =IF(ISNUMBER($K96),$K96-$D96-IF(ISNUMBER($E96),$E96,0)-$L96-$M96-$N96-$O96,"") -> 139.965 | Q96: =IF(AND(ISNUMBER($K96),$K96>0),$P96/$K96,"") -> 0.20258359 | S96: =IF(OR(NOT(ISNUMBER($R96)),$R96=0,NOT(ISNUMBER($K96))),"",$K96*(1-$R96)) | T96: =IF(ISNUMBER($S96),$S96*$H96,"") | U96: =IF(ISNUMBER($S96),$S96*Parâmetros!$B$4,"") | V96: =IF(ISNUMBER($S96),$S96*Parâmetros!$C$4,"") | W96: =IF(ISNUMBER($S96),$S96-$D96-IF(ISNUMBER($E96),$E96,0)-$O96-$T96-$U96-$V96,"") | X96: =IF(AND(ISNUMBER($S96),$S96>0),$W96/$S96,"") | Y96: 06/10
A97: =IF(Produtos!$A97="","",Produtos!$A97) -> P4050 | B97: =IF(Produtos!$A97="","",Produtos!$B97) -> Lixeira c/Tampa Pedal 40x50 65L | C97: =IF(Produtos!$A97="","",Produtos!$C97) -> Lixeiras com pedal | D97: =IF(Produtos!$A97="","",IF(Produtos!$D97="","",Produtos!$D97)) -> 374.18 | F97: =IF($A97="","",IF($C97="","⚠ categoria",IFERROR(INDEX(Parâmetros!$B$13:$B$22,MATCH($C97,Parâmetros!$A$13:$A$22,0)),"⚠ categoria"))) -> 0.13 | H97: =IF($A97="","",IF(ISNUMBER($G97),$G97,IF(ISNUMBER($F97),$F97,""))) -> 0.13 | I97: =IF(OR($A97="",NOT(ISNUMBER($D97)),NOT(ISNUMBER($H97))),"",IF((1-$H97-Parâmetros!$B$4-Parâmetros!$C$4-Parâmetros!$D$4)<=0,"INVALIDO",($D97+IF(ISNUMBER($E97),$E97,0)+IF(ISNUMBER(Parâmetros!$E$4),Parâmetros!$E$4,0))/(1-$H97-Parâmetros!$B$4-Parâmetros!$C$4-Parâmetros!$D$4))) -> 692.92593 | K97: =IF(OR($A97="",NOT(ISNUMBER($D97)),NOT(ISNUMBER($H97))),"",IF(AND(ISNUMBER($J97),$J97>0),$J97,IF(ISNUMBER($I97),$I97,""))) -> 692.92593 | L97: =IF(ISNUMBER($K97),$K97*$H97,"") -> 90.08037 | M97: =IF(ISNUMBER($K97),$K97*Parâmetros!$B$4,"") -> 69.292593 | N97: =IF(ISNUMBER($K97),$K97*Parâmetros!$C$4,"") -> 20.787778 | O97: =IF(ISNUMBER($K97),IF(ISNUMBER(Parâmetros!$E$4),Parâmetros!$E$4,0),"") -> 0 | P97: =IF(ISNUMBER($K97),$K97-$D97-IF(ISNUMBER($E97),$E97,0)-$L97-$M97-$N97-$O97,"") -> 138.58519 | Q97: =IF(AND(ISNUMBER($K97),$K97>0),$P97/$K97,"") -> 0.2 | S97: =IF(OR(NOT(ISNUMBER($R97)),$R97=0,NOT(ISNUMBER($K97))),"",$K97*(1-$R97)) | T97: =IF(ISNUMBER($S97),$S97*$H97,"") | U97: =IF(ISNUMBER($S97),$S97*Parâmetros!$B$4,"") | V97: =IF(ISNUMBER($S97),$S97*Parâmetros!$C$4,"") | W97: =IF(ISNUMBER($S97),$S97-$D97-IF(ISNUMBER($E97),$E97,0)-$O97-$T97-$U97-$V97,"") | X97: =IF(AND(ISNUMBER($S97),$S97>0),$W97/$S97,"")
A98: =IF(Produtos!$A98="","",Produtos!$A98) -> P4060 | B98: =IF(Produtos!$A98="","",Produtos!$B98) -> Lixeira c/Tampa Pedal 40x60 75L | C98: =IF(Produtos!$A98="","",Produtos!$C98) -> Lixeiras com pedal | D98: =IF(Produtos!$A98="","",IF(Produtos!$D98="","",Produtos!$D98)) -> 411.2 | E98: 79.35 | F98: =IF($A98="","",IF($C98="","⚠ categoria",IFERROR(INDEX(Parâmetros!$B$13:$B$22,MATCH($C98,Parâmetros!$A$13:$A$22,0)),"⚠ categoria"))) -> 0.13 | H98: =IF($A98="","",IF(ISNUMBER($G98),$G98,IF(ISNUMBER($F98),$F98,""))) -> 0.13 | I98: =IF(OR($A98="",NOT(ISNUMBER($D98)),NOT(ISNUMBER($H98))),"",IF((1-$H98-Parâmetros!$B$4-Parâmetros!$C$4-Parâmetros!$D$4)<=0,"INVALIDO",($D98+IF(ISNUMBER($E98),$E98,0)+IF(ISNUMBER(Parâmetros!$E$4),Parâmetros!$E$4,0))/(1-$H98-Parâmetros!$B$4-Parâmetros!$C$4-Parâmetros!$D$4))) -> 908.42593 | J98: 908.8 | K98: =IF(OR($A98="",NOT(ISNUMBER($D98)),NOT(ISNUMBER($H98))),"",IF(AND(ISNUMBER($J98),$J98>0),$J98,IF(ISNUMBER($I98),$I98,""))) -> 908.8 | L98: =IF(ISNUMBER($K98),$K98*$H98,"") -> 118.144 | M98: =IF(ISNUMBER($K98),$K98*Parâmetros!$B$4,"") -> 90.88 | N98: =IF(ISNUMBER($K98),$K98*Parâmetros!$C$4,"") -> 27.264 | O98: =IF(ISNUMBER($K98),IF(ISNUMBER(Parâmetros!$E$4),Parâmetros!$E$4,0),"") -> 0 | P98: =IF(ISNUMBER($K98),$K98-$D98-IF(ISNUMBER($E98),$E98,0)-$L98-$M98-$N98-$O98,"") -> 181.962 | Q98: =IF(AND(ISNUMBER($K98),$K98>0),$P98/$K98,"") -> 0.20022227 | S98: =IF(OR(NOT(ISNUMBER($R98)),$R98=0,NOT(ISNUMBER($K98))),"",$K98*(1-$R98)) | T98: =IF(ISNUMBER($S98),$S98*$H98,"") | U98: =IF(ISNUMBER($S98),$S98*Parâmetros!$B$4,"") | V98: =IF(ISNUMBER($S98),$S98*Parâmetros!$C$4,"") | W98: =IF(ISNUMBER($S98),$S98-$D98-IF(ISNUMBER($E98),$E98,0)-$O98-$T98-$U98-$V98,"") | X98: =IF(AND(ISNUMBER($S98),$S98>0),$W98/$S98,"") | Y98: 06/10
A99: =IF(Produtos!$A99="","",Produtos!$A99) -> P4070 | B99: =IF(Produtos!$A99="","",Produtos!$B99) -> Lixeira c/Tampa Pedal 40x70 80L | C99: =IF(Produtos!$A99="","",Produtos!$C99) -> Lixeiras com pedal | D99: =IF(Produtos!$A99="","",IF(Produtos!$D99="","",Produtos!$D99)) -> 416.62 | E99: 91.95 | F99: =IF($A99="","",IF($C99="","⚠ categoria",IFERROR(INDEX(Parâmetros!$B$13:$B$22,MATCH($C99,Parâmetros!$A$13:$A$22,0)),"⚠ categoria"))) -> 0.13 | H99: =IF($A99="","",IF(ISNUMBER($G99),$G99,IF(ISNUMBER($F99),$F99,""))) -> 0.13 | I99: =IF(OR($A99="",NOT(ISNUMBER($D99)),NOT(ISNUMBER($H99))),"",IF((1-$H99-Parâmetros!$B$4-Parâmetros!$C$4-Parâmetros!$D$4)<=0,"INVALIDO",($D99+IF(ISNUMBER($E99),$E99,0)+IF(ISNUMBER(Parâmetros!$E$4),Parâmetros!$E$4,0))/(1-$H99-Parâmetros!$B$4-Parâmetros!$C$4-Parâmetros!$D$4))) -> 941.7963 | J99: 944.10548 | K99: =IF(OR($A99="",NOT(ISNUMBER($D99)),NOT(ISNUMBER($H99))),"",IF(AND(ISNUMBER($J99),$J99>0),$J99,IF(ISNUMBER($I99),$I99,""))) -> 944.10548 | L99: =IF(ISNUMBER($K99),$K99*$H99,"") -> 122.73371 | M99: =IF(ISNUMBER($K99),$K99*Parâmetros!$B$4,"") -> 94.410548 | N99: =IF(ISNUMBER($K99),$K99*Parâmetros!$C$4,"") -> 28.323164 | O99: =IF(ISNUMBER($K99),IF(ISNUMBER(Parâmetros!$E$4),Parâmetros!$E$4,0),"") -> 0 | P99: =IF(ISNUMBER($K99),$K99-$D99-IF(ISNUMBER($E99),$E99,0)-$L99-$M99-$N99-$O99,"") -> 190.06805 | Q99: =IF(AND(ISNUMBER($K99),$K99>0),$P99/$K99,"") -> 0.20132078 | S99: =IF(OR(NOT(ISNUMBER($R99)),$R99=0,NOT(ISNUMBER($K99))),"",$K99*(1-$R99)) | T99: =IF(ISNUMBER($S99),$S99*$H99,"") | U99: =IF(ISNUMBER($S99),$S99*Parâmetros!$B$4,"") | V99: =IF(ISNUMBER($S99),$S99*Parâmetros!$C$4,"") | W99: =IF(ISNUMBER($S99),$S99-$D99-IF(ISNUMBER($E99),$E99,0)-$O99-$T99-$U99-$V99,"") | X99: =IF(AND(ISNUMBER($S99),$S99>0),$W99/$S99,"") | Y99: 06/10
A100: =IF(Produtos!$A100="","",Produtos!$A100) -> P4075 | B100: =IF(Produtos!$A100="","",Produtos!$B100) -> Lixeira c/Tampa Pedal 40x75 95L | C100: =IF(Produtos!$A100="","",Produtos!$C100) -> Lixeiras com pedal | D100: =IF(Produtos!$A100="","",IF(Produtos!$D100="","",Produtos!$D100)) -> 478.21 | E100: 91.95 | F100: =IF($A100="","",IF($C100="","⚠ categoria",IFERROR(INDEX(Parâmetros!$B$13:$B$22,MATCH($C100,Parâmetros!$A$13:$A$22,0)),"⚠ categoria"))) -> 0.13 | H100: =IF($A100="","",IF(ISNUMBER($G100),$G100,IF(ISNUMBER($F100),$F100,""))) -> 0.13 | I100: =IF(OR($A100="",NOT(ISNUMBER($D100)),NOT(ISNUMBER($H100))),"",IF((1-$H100-Parâmetros!$B$4-Parâmetros!$C$4-Parâmetros!$D$4)<=0,"INVALIDO",($D100+IF(ISNUMBER($E100),$E100,0)+IF(ISNUMBER(Parâmetros!$E$4),Parâmetros!$E$4,0))/(1-$H100-Parâmetros!$B$4-Parâmetros!$C$4-Parâmetros!$D$4))) -> 1055.8519 | J100: 1055.95 | K100: =IF(OR($A100="",NOT(ISNUMBER($D100)),NOT(ISNUMBER($H100))),"",IF(AND(ISNUMBER($J100),$J100>0),$J100,IF(ISNUMBER($I100),$I100,""))) -> 1055.95 | L100: =IF(ISNUMBER($K100),$K100*$H100,"") -> 137.2735 | M100: =IF(ISNUMBER($K100),$K100*Parâmetros!$B$4,"") -> 105.595 | N100: =IF(ISNUMBER($K100),$K100*Parâmetros!$C$4,"") -> 31.6785 | O100: =IF(ISNUMBER($K100),IF(ISNUMBER(Parâmetros!$E$4),Parâmetros!$E$4,0),"") -> 0 | P100: =IF(ISNUMBER($K100),$K100-$D100-IF(ISNUMBER($E100),$E100,0)-$L100-$M100-$N100-$O100,"") -> 211.243 | Q100: =IF(AND(ISNUMBER($K100),$K100>0),$P100/$K100,"") -> 0.20005019 | S100: =IF(OR(NOT(ISNUMBER($R100)),$R100=0,NOT(ISNUMBER($K100))),"",$K100*(1-$R100)) | T100: =IF(ISNUMBER($S100),$S100*$H100,"") | U100: =IF(ISNUMBER($S100),$S100*Parâmetros!$B$4,"") | V100: =IF(ISNUMBER($S100),$S100*Parâmetros!$C$4,"") | W100: =IF(ISNUMBER($S100),$S100-$D100-IF(ISNUMBER($E100),$E100,0)-$O100-$T100-$U100-$V100,"") | X100: =IF(AND(ISNUMBER($S100),$S100>0),$W100/$S100,"") | Y100: 06/10
A101: =IF(Produtos!$A101="","",Produtos!$A101) -> P4080 | B101: =IF(Produtos!$A101="","",Produtos!$B101) -> Lixeira c/Tampa Pedal 40x80 100L | C101: =IF(Produtos!$A101="","",Produtos!$C101) -> Lixeiras com pedal | D101: =IF(Produtos!$A101="","",IF(Produtos!$D101="","",Produtos!$D101)) -> 553.79 | F101: =IF($A101="","",IF($C101="","⚠ categoria",IFERROR(INDEX(Parâmetros!$B$13:$B$22,MATCH($C101,Parâmetros!$A$13:$A$22,0)),"⚠ categoria"))) -> 0.13 | H101: =IF($A101="","",IF(ISNUMBER($G101),$G101,IF(ISNUMBER($F101),$F101,""))) -> 0.13 | I101: =IF(OR($A101="",NOT(ISNUMBER($D101)),NOT(ISNUMBER($H101))),"",IF((1-$H101-Parâmetros!$B$4-Parâmetros!$C$4-Parâmetros!$D$4)<=0,"INVALIDO",($D101+IF(ISNUMBER($E101),$E101,0)+IF(ISNUMBER(Parâmetros!$E$4),Parâmetros!$E$4,0))/(1-$H101-Parâmetros!$B$4-Parâmetros!$C$4-Parâmetros!$D$4))) -> 1025.537 | K101: =IF(OR($A101="",NOT(ISNUMBER($D101)),NOT(ISNUMBER($H101))),"",IF(AND(ISNUMBER($J101),$J101>0),$J101,IF(ISNUMBER($I101),$I101,""))) -> 1025.537 | L101: =IF(ISNUMBER($K101),$K101*$H101,"") -> 133.31981 | M101: =IF(ISNUMBER($K101),$K101*Parâmetros!$B$4,"") -> 102.5537 | N101: =IF(ISNUMBER($K101),$K101*Parâmetros!$C$4,"") -> 30.766111 | O101: =IF(ISNUMBER($K101),IF(ISNUMBER(Parâmetros!$E$4),Parâmetros!$E$4,0),"") -> 0 | P101: =IF(ISNUMBER($K101),$K101-$D101-IF(ISNUMBER($E101),$E101,0)-$L101-$M101-$N101-$O101,"") -> 205.10741 | Q101: =IF(AND(ISNUMBER($K101),$K101>0),$P101/$K101,"") -> 0.2 | S101: =IF(OR(NOT(ISNUMBER($R101)),$R101=0,NOT(ISNUMBER($K101))),"",$K101*(1-$R101)) | T101: =IF(ISNUMBER($S101),$S101*$H101,"") | U101: =IF(ISNUMBER($S101),$S101*Parâmetros!$B$4,"") | V101: =IF(ISNUMBER($S101),$S101*Parâmetros!$C$4,"") | W101: =IF(ISNUMBER($S101),$S101-$D101-IF(ISNUMBER($E101),$E101,0)-$O101-$T101-$U101-$V101,"") | X101: =IF(AND(ISNUMBER($S101),$S101>0),$W101/$S101,"")
A102: =IF(Produtos!$A102="","",Produtos!$A102) -> P4090 | B102: =IF(Produtos!$A102="","",Produtos!$B102) -> Lixeira c/Tampa Pedal 40x90 120L | C102: =IF(Produtos!$A102="","",Produtos!$C102) -> Lixeiras com pedal | D102: =IF(Produtos!$A102="","",IF(Produtos!$D102="","",Produtos!$D102)) -> 771.68 | E102: 106.85 | F102: =IF($A102="","",IF($C102="","⚠ categoria",IFERROR(INDEX(Parâmetros!$B$13:$B$22,MATCH($C102,Parâmetros!$A$13:$A$22,0)),"⚠ categoria"))) -> 0.13 | H102: =IF($A102="","",IF(ISNUMBER($G102),$G102,IF(ISNUMBER($F102),$F102,""))) -> 0.13 | I102: =IF(OR($A102="",NOT(ISNUMBER($D102)),NOT(ISNUMBER($H102))),"",IF((1-$H102-Parâmetros!$B$4-Parâmetros!$C$4-Parâmetros!$D$4)<=0,"INVALIDO",($D102+IF(ISNUMBER($E102),$E102,0)+IF(ISNUMBER(Parâmetros!$E$4),Parâmetros!$E$4,0))/(1-$H102-Parâmetros!$B$4-Parâmetros!$C$4-Parâmetros!$D$4))) -> 1626.9074 | J102: 1551.5069 | K102: =IF(OR($A102="",NOT(ISNUMBER($D102)),NOT(ISNUMBER($H102))),"",IF(AND(ISNUMBER($J102),$J102>0),$J102,IF(ISNUMBER($I102),$I102,""))) -> 1551.5069 | L102: =IF(ISNUMBER($K102),$K102*$H102,"") -> 201.6959 | M102: =IF(ISNUMBER($K102),$K102*Parâmetros!$B$4,"") -> 155.15069 | N102: =IF(ISNUMBER($K102),$K102*Parâmetros!$C$4,"") -> 46.545207 | O102: =IF(ISNUMBER($K102),IF(ISNUMBER(Parâmetros!$E$4),Parâmetros!$E$4,0),"") -> 0 | P102: =IF(ISNUMBER($K102),$K102-$D102-IF(ISNUMBER($E102),$E102,0)-$L102-$M102-$N102-$O102,"") -> 269.58511 | Q102: =IF(AND(ISNUMBER($K102),$K102>0),$P102/$K102,"") -> 0.17375695 | S102: =IF(OR(NOT(ISNUMBER($R102)),$R102=0,NOT(ISNUMBER($K102))),"",$K102*(1-$R102)) | T102: =IF(ISNUMBER($S102),$S102*$H102,"") | U102: =IF(ISNUMBER($S102),$S102*Parâmetros!$B$4,"") | V102: =IF(ISNUMBER($S102),$S102*Parâmetros!$C$4,"") | W102: =IF(ISNUMBER($S102),$S102-$D102-IF(ISNUMBER($E102),$E102,0)-$O102-$T102-$U102-$V102,"") | X102: =IF(AND(ISNUMBER($S102),$S102>0),$W102/$S102,"") | Y102: 06/10
A103: =IF(Produtos!$A103="","",Produtos!$A103) -> L2425-BC | B103: =IF(Produtos!$A103="","",Produtos!$B103) -> Lixeira de Aço inox 24x25 13L c/Aro basculante colorido | C103: =IF(Produtos!$A103="","",Produtos!$C103) -> Lixeiras em inox | D103: =IF(Produtos!$A103="","",IF(Produtos!$D103="","",Produtos!$D103)) -> 110.45 | E103: 29.25 | F103: =IF($A103="","",IF($C103="","⚠ categoria",IFERROR(INDEX(Parâmetros!$B$13:$B$22,MATCH($C103,Parâmetros!$A$13:$A$22,0)),"⚠ categoria"))) -> 0.13 | G103: 0.12 | H103: =IF($A103="","",IF(ISNUMBER($G103),$G103,IF(ISNUMBER($F103),$F103,""))) -> 0.12 | I103: =IF(OR($A103="",NOT(ISNUMBER($D103)),NOT(ISNUMBER($H103))),"",IF((1-$H103-Parâmetros!$B$4-Parâmetros!$C$4-Parâmetros!$D$4)<=0,"INVALIDO",($D103+IF(ISNUMBER($E103),$E103,0)+IF(ISNUMBER(Parâmetros!$E$4),Parâmetros!$E$4,0))/(1-$H103-Parâmetros!$B$4-Parâmetros!$C$4-Parâmetros!$D$4))) -> 254 | J103: 260.43255 | K103: =IF(OR($A103="",NOT(ISNUMBER($D103)),NOT(ISNUMBER($H103))),"",IF(AND(ISNUMBER($J103),$J103>0),$J103,IF(ISNUMBER($I103),$I103,""))) -> 260.43255 | L103: =IF(ISNUMBER($K103),$K103*$H103,"") -> 31.251906 | M103: =IF(ISNUMBER($K103),$K103*Parâmetros!$B$4,"") -> 26.043255 | N103: =IF(ISNUMBER($K103),$K103*Parâmetros!$C$4,"") -> 7.8129765 | O103: =IF(ISNUMBER($K103),IF(ISNUMBER(Parâmetros!$E$4),Parâmetros!$E$4,0),"") -> 0 | P103: =IF(ISNUMBER($K103),$K103-$D103-IF(ISNUMBER($E103),$E103,0)-$L103-$M103-$N103-$O103,"") -> 55.624412 | Q103: =IF(AND(ISNUMBER($K103),$K103>0),$P103/$K103,"") -> 0.21358472 | S103: =IF(OR(NOT(ISNUMBER($R103)),$R103=0,NOT(ISNUMBER($K103))),"",$K103*(1-$R103)) | T103: =IF(ISNUMBER($S103),$S103*$H103,"") | U103: =IF(ISNUMBER($S103),$S103*Parâmetros!$B$4,"") | V103: =IF(ISNUMBER($S103),$S103*Parâmetros!$C$4,"") | W103: =IF(ISNUMBER($S103),$S103-$D103-IF(ISNUMBER($E103),$E103,0)-$O103-$T103-$U103-$V103,"") | X103: =IF(AND(ISNUMBER($S103),$S103>0),$W103/$S103,"") | Y103: 04/09
A104: =IF(Produtos!$A104="","",Produtos!$A104) -> L2430-BC | B104: =IF(Produtos!$A104="","",Produtos!$B104) -> Lixeira de Aço inox 24x30 15L c/Aro basculante colorido | C104: =IF(Produtos!$A104="","",Produtos!$C104) -> Lixeiras em inox | D104: =IF(Produtos!$A104="","",IF(Produtos!$D104="","",Produtos!$D104)) -> 120.38 | E104: 29.25 | F104: =IF($A104="","",IF($C104="","⚠ categoria",IFERROR(INDEX(Parâmetros!$B$13:$B$22,MATCH($C104,Parâmetros!$A$13:$A$22,0)),"⚠ categoria"))) -> 0.13 | G104: 0.12 | H104: =IF($A104="","",IF(ISNUMBER($G104),$G104,IF(ISNUMBER($F104),$F104,""))) -> 0.12 | I104: =IF(OR($A104="",NOT(ISNUMBER($D104)),NOT(ISNUMBER($H104))),"",IF((1-$H104-Parâmetros!$B$4-Parâmetros!$C$4-Parâmetros!$D$4)<=0,"INVALIDO",($D104+IF(ISNUMBER($E104),$E104,0)+IF(ISNUMBER(Parâmetros!$E$4),Parâmetros!$E$4,0))/(1-$H104-Parâmetros!$B$4-Parâmetros!$C$4-Parâmetros!$D$4))) -> 272.05455 | J104: 273.9 | K104: =IF(OR($A104="",NOT(ISNUMBER($D104)),NOT(ISNUMBER($H104))),"",IF(AND(ISNUMBER($J104),$J104>0),$J104,IF(ISNUMBER($I104),$I104,""))) -> 273.9 | L104: =IF(ISNUMBER($K104),$K104*$H104,"") -> 32.868 | M104: =IF(ISNUMBER($K104),$K104*Parâmetros!$B$4,"") -> 27.39 | N104: =IF(ISNUMBER($K104),$K104*Parâmetros!$C$4,"") -> 8.217 | O104: =IF(ISNUMBER($K104),IF(ISNUMBER(Parâmetros!$E$4),Parâmetros!$E$4,0),"") -> 0 | P104: =IF(ISNUMBER($K104),$K104-$D104-IF(ISNUMBER($E104),$E104,0)-$L104-$M104-$N104-$O104,"") -> 55.795 | Q104: =IF(AND(ISNUMBER($K104),$K104>0),$P104/$K104,"") -> 0.20370573 | S104: =IF(OR(NOT(ISNUMBER($R104)),$R104=0,NOT(ISNUMBER($K104))),"",$K104*(1-$R104)) | T104: =IF(ISNUMBER($S104),$S104*$H104,"") | U104: =IF(ISNUMBER($S104),$S104*Parâmetros!$B$4,"") | V104: =IF(ISNUMBER($S104),$S104*Parâmetros!$C$4,"") | W104: =IF(ISNUMBER($S104),$S104-$D104-IF(ISNUMBER($E104),$E104,0)-$O104-$T104-$U104-$V104,"") | X104: =IF(AND(ISNUMBER($S104),$S104>0),$W104/$S104,"") | Y104: 06/10
A105: =IF(Produtos!$A105="","",Produtos!$A105) -> L2440-BC | B105: =IF(Produtos!$A105="","",Produtos!$B105) -> Lixeira de Aço inox 24x40 20L c/Aro basculante colorido | C105: =IF(Produtos!$A105="","",Produtos!$C105) -> Lixeiras em inox | D105: =IF(Produtos!$A105="","",IF(Produtos!$D105="","",Produtos!$D105)) -> 137.47 | E105: 29.25 | F105: =IF($A105="","",IF($C105="","⚠ categoria",IFERROR(INDEX(Parâmetros!$B$13:$B$22,MATCH($C105,Parâmetros!$A$13:$A$22,0)),"⚠ categoria"))) -> 0.13 | G105: 0.12 | H105: =IF($A105="","",IF(ISNUMBER($G105),$G105,IF(ISNUMBER($F105),$F105,""))) -> 0.12 | I105: =IF(OR($A105="",NOT(ISNUMBER($D105)),NOT(ISNUMBER($H105))),"",IF((1-$H105-Parâmetros!$B$4-Parâmetros!$C$4-Parâmetros!$D$4)<=0,"INVALIDO",($D105+IF(ISNUMBER($E105),$E105,0)+IF(ISNUMBER(Parâmetros!$E$4),Parâmetros!$E$4,0))/(1-$H105-Parâmetros!$B$4-Parâmetros!$C$4-Parâmetros!$D$4))) -> 303.12727 | J105: 304.41127 | K105: =IF(OR($A105="",NOT(ISNUMBER($D105)),NOT(ISNUMBER($H105))),"",IF(AND(ISNUMBER($J105),$J105>0),$J105,IF(ISNUMBER($I105),$I105,""))) -> 304.41127 | L105: =IF(ISNUMBER($K105),$K105*$H105,"") -> 36.529353 | M105: =IF(ISNUMBER($K105),$K105*Parâmetros!$B$4,"") -> 30.441128 | N105: =IF(ISNUMBER($K105),$K105*Parâmetros!$C$4,"") -> 9.1323383 | O105: =IF(ISNUMBER($K105),IF(ISNUMBER(Parâmetros!$E$4),Parâmetros!$E$4,0),"") -> 0 | P105: =IF(ISNUMBER($K105),$K105-$D105-IF(ISNUMBER($E105),$E105,0)-$L105-$M105-$N105-$O105,"") -> 61.588456 | Q105: =IF(AND(ISNUMBER($K105),$K105>0),$P105/$K105,"") -> 0.20231989 | S105: =IF(OR(NOT(ISNUMBER($R105)),$R105=0,NOT(ISNUMBER($K105))),"",$K105*(1-$R105)) | T105: =IF(ISNUMBER($S105),$S105*$H105,"") | U105: =IF(ISNUMBER($S105),$S105*Parâmetros!$B$4,"") | V105: =IF(ISNUMBER($S105),$S105*Parâmetros!$C$4,"") | W105: =IF(ISNUMBER($S105),$S105-$D105-IF(ISNUMBER($E105),$E105,0)-$O105-$T105-$U105-$V105,"") | X105: =IF(AND(ISNUMBER($S105),$S105>0),$W105/$S105,"") | Y105: 24/09
...

Sheet ML Premium
A1: ="MERCADO LIVRE — PREMIUM | Comissão por categoria (aba Parâmetros) ou manual por linha | Imposto "&TEXT(Parâmetros!$B$5,"0%")&" | ADS "&TEXT(Parâmetros!$C$5,"0.0%")&" | Margem mín. "&TEXT(Parâmetros!$D$5,"0%")&" | Custo fixo/un. R$ "&TEXT(Parâmetros!$E$5,"0.00") -> MERCADO LIVRE — PREMIUM | Comissão por categoria (aba Parâmetros) ou manual por linha | Imposto 10% | ADS 3.0% | Margem mín. 20% | Custo fixo/un. R$ 0.00
A2: PRODUTO | D2: ENTRADAS | F2: COMISSÃO | I2: PREÇO SUGERIDO | J2: PREÇO MANUAL | K2: PREÇO USADO | L2: COMPOSIÇÃO DO PREÇO | R2: PROMOÇÃO | Y2: CONTROLE
A3: Código | B3: Produto | C3: Categoria | D3: Vl. Revenda 6% = Custo (R$) | E3: Frete (R$) | F3: Comissão categoria (%) | G3: ✏ Comissão manual (%) | H3: ✅ Comissão usada (%) | I3: ⚙ Preço Sugerido | J3: ✏ Preço Manual | K3: ✅ Preço Usado | L3: Comissão (R$) | M3: Imposto (R$) | N3: ADS (R$) | O3: Custo fixo (R$) | P3: Lucro Líq (R$) | Q3: Margem (%) | R3: % Desc. Promo | S3: Preço Promo (R$) | T3: Comissão Promo (R$) | U3: Imposto Promo (R$) | V3: ADS Promo (R$) | W3: Lucro Promo (R$) | X3: Margem Promo (%) | Y3: Atualizado em | Z3: Observação
A4: =IF(Produtos!$A4="","",Produtos!$A4) -> L1618 | B4: =IF(Produtos!$A4="","",Produtos!$B4) -> Lixeira Aço Inox s/Tampa 16x18 03L | C4: =IF(Produtos!$A4="","",Produtos!$C4) -> Lixeiras em inox | D4: =IF(Produtos!$A4="","",IF(Produtos!$D4="","",Produtos!$D4)) -> 39.8 | E4: 14.15 | F4: =IF($A4="","",IF($C4="","⚠ categoria",IFERROR(INDEX(Parâmetros!$C$13:$C$22,MATCH($C4,Parâmetros!$A$13:$A$22,0)),"⚠ categoria"))) -> 0.18 | H4: =IF($A4="","",IF(ISNUMBER($G4),$G4,IF(ISNUMBER($F4),$F4,""))) -> 0.18 | I4: =IF(OR($A4="",NOT(ISNUMBER($D4)),NOT(ISNUMBER($H4))),"",IF((1-$H4-Parâmetros!$B$5-Parâmetros!$C$5-Parâmetros!$D$5)<=0,"INVALIDO",($D4+IF(ISNUMBER($E4),$E4,0)+IF(ISNUMBER(Parâmetros!$E$5),Parâmetros!$E$5,0))/(1-$H4-Parâmetros!$B$5-Parâmetros!$C$5-Parâmetros!$D$5))) -> 110.10204 | J4: 89.18 | K4: =IF(OR($A4="",NOT(ISNUMBER($D4)),NOT(ISNUMBER($H4))),"",IF(AND(ISNUMBER($J4),$J4>0),$J4,IF(ISNUMBER($I4),$I4,""))) -> 89.18 | L4: =IF(ISNUMBER($K4),$K4*$H4,"") -> 16.0524 | M4: =IF(ISNUMBER($K4),$K4*Parâmetros!$B$5,"") -> 8.918 | N4: =IF(ISNUMBER($K4),$K4*Parâmetros!$C$5,"") -> 2.6754 | O4: =IF(ISNUMBER($K4),IF(ISNUMBER(Parâmetros!$E$5),Parâmetros!$E$5,0),"") -> 0 | P4: =IF(ISNUMBER($K4),$K4-$D4-IF(ISNUMBER($E4),$E4,0)-$L4-$M4-$N4-$O4,"") -> 7.5842 | Q4: =IF(AND(ISNUMBER($K4),$K4>0),$P4/$K4,"") -> 0.085043732 | S4: =IF(OR(NOT(ISNUMBER($R4)),$R4=0,NOT(ISNUMBER($K4))),"",$K4*(1-$R4)) | T4: =IF(ISNUMBER($S4),$S4*$H4,"") | U4: =IF(ISNUMBER($S4),$S4*Parâmetros!$B$5,"") | V4: =IF(ISNUMBER($S4),$S4*Parâmetros!$C$5,"") | W4: =IF(ISNUMBER($S4),$S4-$D4-IF(ISNUMBER($E4),$E4,0)-$O4-$T4-$U4-$V4,"") | X4: =IF(AND(ISNUMBER($S4),$S4>0),$W4/$S4,"")
A5: =IF(Produtos!$A5="","",Produtos!$A5) -> L1623 | B5: =IF(Produtos!$A5="","",Produtos!$B5) -> Lixeira Aço Inox s/Tampa 16x23 05L | C5: =IF(Produtos!$A5="","",Produtos!$C5) -> Lixeiras em inox | D5: =IF(Produtos!$A5="","",IF(Produtos!$D5="","",Produtos!$D5)) -> 49.15 | E5: 16.45 | F5: =IF($A5="","",IF($C5="","⚠ categoria",IFERROR(INDEX(Parâmetros!$C$13:$C$22,MATCH($C5,Parâmetros!$A$13:$A$22,0)),"⚠ categoria"))) -> 0.18 | H5: =IF($A5="","",IF(ISNUMBER($G5),$G5,IF(ISNUMBER($F5),$F5,""))) -> 0.18 | I5: =IF(OR($A5="",NOT(ISNUMBER($D5)),NOT(ISNUMBER($H5))),"",IF((1-$H5-Parâmetros!$B$5-Parâmetros!$C$5-Parâmetros!$D$5)<=0,"INVALIDO",($D5+IF(ISNUMBER($E5),$E5,0)+IF(ISNUMBER(Parâmetros!$E$5),Parâmetros!$E$5,0))/(1-$H5-Parâmetros!$B$5-Parâmetros!$C$5-Parâmetros!$D$5))) -> 133.87755 | J5: 104.75 | K5: =IF(OR($A5="",NOT(ISNUMBER($D5)),NOT(ISNUMBER($H5))),"",IF(AND(ISNUMBER($J5),$J5>0),$J5,IF(ISNUMBER($I5),$I5,""))) -> 104.75 | L5: =IF(ISNUMBER($K5),$K5*$H5,"") -> 18.855 | M5: =IF(ISNUMBER($K5),$K5*Parâmetros!$B$5,"") -> 10.475 | N5: =IF(ISNUMBER($K5),$K5*Parâmetros!$C$5,"") -> 3.1425 | O5: =IF(ISNUMBER($K5),IF(ISNUMBER(Parâmetros!$E$5),Parâmetros!$E$5,0),"") -> 0 | P5: =IF(ISNUMBER($K5),$K5-$D5-IF(ISNUMBER($E5),$E5,0)-$L5-$M5-$N5-$O5,"") -> 6.6775 | Q5: =IF(AND(ISNUMBER($K5),$K5>0),$P5/$K5,"") -> 0.063747017 | S5: =IF(OR(NOT(ISNUMBER($R5)),$R5=0,NOT(ISNUMBER($K5))),"",$K5*(1-$R5)) | T5: =IF(ISNUMBER($S5),$S5*$H5,"") | U5: =IF(ISNUMBER($S5),$S5*Parâmetros!$B$5,"") | V5: =IF(ISNUMBER($S5),$S5*Parâmetros!$C$5,"") | W5: =IF(ISNUMBER($S5),$S5-$D5-IF(ISNUMBER($E5),$E5,0)-$O5-$T5-$U5-$V5,"") | X5: =IF(AND(ISNUMBER($S5),$S5>0),$W5/$S5,"")
A6: =IF(Produtos!$A6="","",Produtos!$A6) -> L2025 | B6: =IF(Produtos!$A6="","",Produtos!$B6) -> Lixeira Aço Inox s/Tampa 20x25 07L | C6: =IF(Produtos!$A6="","",Produtos!$C6) -> Lixeiras em inox | D6: =IF(Produtos!$A6="","",IF(Produtos!$D6="","",Produtos!$D6)) -> 51.82 | E6: 16.85 | F6: =IF($A6="","",IF($C6="","⚠ categoria",IFERROR(INDEX(Parâmetros!$C$13:$C$22,MATCH($C6,Parâmetros!$A$13:$A$22,0)),"⚠ categoria"))) -> 0.18 | H6: =IF($A6="","",IF(ISNUMBER($G6),$G6,IF(ISNUMBER($F6),$F6,""))) -> 0.18 | I6: =IF(OR($A6="",NOT(ISNUMBER($D6)),NOT(ISNUMBER($H6))),"",IF((1-$H6-Parâmetros!$B$5-Parâmetros!$C$5-Parâmetros!$D$5)<=0,"INVALIDO",($D6+IF(ISNUMBER($E6),$E6,0)+IF(ISNUMBER(Parâmetros!$E$5),Parâmetros!$E$5,0))/(1-$H6-Parâmetros!$B$5-Parâmetros!$C$5-Parâmetros!$D$5))) -> 140.14286 | J6: 113.11 | K6: =IF(OR($A6="",NOT(ISNUMBER($D6)),NOT(ISNUMBER($H6))),"",IF(AND(ISNUMBER($J6),$J6>0),$J6,IF(ISNUMBER($I6),$I6,""))) -> 113.11 | L6: =IF(ISNUMBER($K6),$K6*$H6,"") -> 20.3598 | M6: =IF(ISNUMBER($K6),$K6*Parâmetros!$B$5,"") -> 11.311 | N6: =IF(ISNUMBER($K6),$K6*Parâmetros!$C$5,"") -> 3.3933 | O6: =IF(ISNUMBER($K6),IF(ISNUMBER(Parâmetros!$E$5),Parâmetros!$E$5,0),"") -> 0 | P6: =IF(ISNUMBER($K6),$K6-$D6-IF(ISNUMBER($E6),$E6,0)-$L6-$M6-$N6-$O6,"") -> 9.3759 | Q6: =IF(AND(ISNUMBER($K6),$K6>0),$P6/$K6,"") -> 0.082891875 | S6: =IF(OR(NOT(ISNUMBER($R6)),$R6=0,NOT(ISNUMBER($K6))),"",$K6*(1-$R6)) | T6: =IF(ISNUMBER($S6),$S6*$H6,"") | U6: =IF(ISNUMBER($S6),$S6*Parâmetros!$B$5,"") | V6: =IF(ISNUMBER($S6),$S6*Parâmetros!$C$5,"") | W6: =IF(ISNUMBER($S6),$S6-$D6-IF(ISNUMBER($E6),$E6,0)-$O6-$T6-$U6-$V6,"") | X6: =IF(AND(ISNUMBER($S6),$S6>0),$W6/$S6,"")
A7: =IF(Produtos!$A7="","",Produtos!$A7) -> L2030 | B7: =IF(Produtos!$A7="","",Produtos!$B7) -> Lixeira Aço Inox s/Tampa 20x30 10L | C7: =IF(Produtos!$A7="","",Produtos!$C7) -> Lixeiras em inox | D7: =IF(Produtos!$A7="","",IF(Produtos!$D7="","",Produtos!$D7)) -> 55.49 | E7: 16.85 | F7: =IF($A7="","",IF($C7="","⚠ categoria",IFERROR(INDEX(Parâmetros!$C$13:$C$22,MATCH($C7,Parâmetros!$A$13:$A$22,0)),"⚠ categoria"))) -> 0.18 | H7: =IF($A7="","",IF(ISNUMBER($G7),$G7,IF(ISNUMBER($F7),$F7,""))) -> 0.18 | I7: =IF(OR($A7="",NOT(ISNUMBER($D7)),NOT(ISNUMBER($H7))),"",IF((1-$H7-Parâmetros!$B$5-Parâmetros!$C$5-Parâmetros!$D$5)<=0,"INVALIDO",($D7+IF(ISNUMBER($E7),$E7,0)+IF(ISNUMBER(Parâmetros!$E$5),Parâmetros!$E$5,0))/(1-$H7-Parâmetros!$B$5-Parâmetros!$C$5-Parâmetros!$D$5))) -> 147.63265 | J7: 119.22 | K7: =IF(OR($A7="",NOT(ISNUMBER($D7)),NOT(ISNUMBER($H7))),"",IF(AND(ISNUMBER($J7),$J7>0),$J7,IF(ISNUMBER($I7),$I7,""))) -> 119.22 | L7: =IF(ISNUMBER($K7),$K7*$H7,"") -> 21.4596 | M7: =IF(ISNUMBER($K7),$K7*Parâmetros!$B$5,"") -> 11.922 | N7: =IF(ISNUMBER($K7),$K7*Parâmetros!$C$5,"") -> 3.5766 | O7: =IF(ISNUMBER($K7),IF(ISNUMBER(Parâmetros!$E$5),Parâmetros!$E$5,0),"") -> 0 | P7: =IF(ISNUMBER($K7),$K7-$D7-IF(ISNUMBER($E7),$E7,0)-$L7-$M7-$N7-$O7,"") -> 9.9218 | Q7: =IF(AND(ISNUMBER($K7),$K7>0),$P7/$K7,"") -> 0.083222614 | S7: =IF(OR(NOT(ISNUMBER($R7)),$R7=0,NOT(ISNUMBER($K7))),"",$K7*(1-$R7)) | T7: =IF(ISNUMBER($S7),$S7*$H7,"") | U7: =IF(ISNUMBER($S7),$S7*Parâmetros!$B$5,"") | V7: =IF(ISNUMBER($S7),$S7*Parâmetros!$C$5,"") | W7: =IF(ISNUMBER($S7),$S7-$D7-IF(ISNUMBER($E7),$E7,0)-$O7-$T7-$U7-$V7,"") | X7: =IF(AND(ISNUMBER($S7),$S7>0),$W7/$S7,"")
A8: =IF(Produtos!$A8="","",Produtos!$A8) -> L2425 | B8: =IF(Produtos!$A8="","",Produtos!$B8) -> Lixeira Aço Inox s/Tampa 24x25 13L | C8: =IF(Produtos!$A8="","",Produtos!$C8) -> Lixeiras em inox | D8: =IF(Produtos!$A8="","",IF(Produtos!$D8="","",Produtos!$D8)) -> 62.2 | F8: =IF($A8="","",IF($C8="","⚠ categoria",IFERROR(INDEX(Parâmetros!$C$13:$C$22,MATCH($C8,Parâmetros!$A$13:$A$22,0)),"⚠ categoria"))) -> 0.18 | H8: =IF($A8="","",IF(ISNUMBER($G8),$G8,IF(ISNUMBER($F8),$F8,""))) -> 0.18 | I8: =IF(OR($A8="",NOT(ISNUMBER($D8)),NOT(ISNUMBER($H8))),"",IF((1-$H8-Parâmetros!$B$5-Parâmetros!$C$5-Parâmetros!$D$5)<=0,"INVALIDO",($D8+IF(ISNUMBER($E8),$E8,0)+IF(ISNUMBER(Parâmetros!$E$5),Parâmetros!$E$5,0))/(1-$H8-Parâmetros!$B$5-Parâmetros!$C$5-Parâmetros!$D$5))) -> 126.93878 | K8: =IF(OR($A8="",NOT(ISNUMBER($D8)),NOT(ISNUMBER($H8))),"",IF(AND(ISNUMBER($J8),$J8>0),$J8,IF(ISNUMBER($I8),$I8,""))) -> 126.93878 | L8: =IF(ISNUMBER($K8),$K8*$H8,"") -> 22.84898 | M8: =IF(ISNUMBER($K8),$K8*Parâmetros!$B$5,"") -> 12.693878 | N8: =IF(ISNUMBER($K8),$K8*Parâmetros!$C$5,"") -> 3.8081633 | O8: =IF(ISNUMBER($K8),IF(ISNUMBER(Parâmetros!$E$5),Parâmetros!$E$5,0),"") -> 0 | P8: =IF(ISNUMBER($K8),$K8-$D8-IF(ISNUMBER($E8),$E8,0)-$L8-$M8-$N8-$O8,"") -> 25.387755 | Q8: =IF(AND(ISNUMBER($K8),$K8>0),$P8/$K8,"") -> 0.2 | S8: =IF(OR(NOT(ISNUMBER($R8)),$R8=0,NOT(ISNUMBER($K8))),"",$K8*(1-$R8)) | T8: =IF(ISNUMBER($S8),$S8*$H8,"") | U8: =IF(ISNUMBER($S8),$S8*Parâmetros!$B$5,"") | V8: =IF(ISNUMBER($S8),$S8*Parâmetros!$C$5,"") | W8: =IF(ISNUMBER($S8),$S8-$D8-IF(ISNUMBER($E8),$E8,0)-$O8-$T8-$U8-$V8,"") | X8: =IF(AND(ISNUMBER($S8),$S8>0),$W8/$S8,"")
